Workbook
Name Fronteras: 'Rangos'!$H$5:$H$11
Name Productores: 'Rangos'!$J$5:$J$39
Name Status: 'Rangos'!$B$5:$B$14
Name Transporte: 'Rangos'!$D$5:$D$44

Sheet Cargas
B2: PROGRAMA DE CARGAS EN BRASIL
A4: Carga Sem.# | B4: Status | C4: Factura Export. | D4: Productor | E4: Fecha de Carga | F4: Carpeta Import. | G4: AFIDI | H4: Transportista | I4: Fecha Frontera | J4: Frontera | K4: Insp. MGAP | L4: Fecha Descarga | M4: TT | N4: Cajas MIC | O4: Código de viaje | P4: Cajas Desc | Q4: MIC | R4: PLACAS T | S4: PLACAS R | T4: Observaciones
A5: 14 | B5: Cancelado | C5: xx | D5: Papa | F5: =VLOOKUP($C5,CARPETAS!$C$5:$L$2388,2,FALSE) -> BRB | G5: =VLOOKUP($C5,CARPETAS!$C$5:$L$2388,9,FALSE) -> xx | H5: =VLOOKUP($C5,CARPETAS!$C$5:$L$2388,5,FALSE) -> xx | I5: =E5+2 -> 2 | J5: =VLOOKUP($C5,CARPETAS!$C$5:$L$2388,4,FALSE) -> xx | L5: =I5+1 -> 3 | M5: =IF(E5<>"",L5-E5,"-") -> - | N5: 1000
A6: 2 | B6: Cancelado | C6: XX | D6: Claudia | E6: 43112 | F6: =VLOOKUP($C6,CARPETAS!$C$5:$L$2388,2,FALSE) -> BRB | G6: =VLOOKUP($C6,CARPETAS!$C$5:$L$2388,9,FALSE) -> xx | H6: =VLOOKUP($C6,CARPETAS!$C$5:$L$2388,5,FALSE) -> xx | I6: =E6+2 -> 43114 | J6: =VLOOKUP($C6,CARPETAS!$C$5:$L$2388,4,FALSE) -> xx | L6: =I6+1 -> 43115 | M6: =IF(E6<>"",L6-E6,"-") -> 3 | N6: 936
A7: 7 | B7: Cancelado | C7: xx | D7: Claudia | E7: 43143 | F7: =VLOOKUP($C7,CARPETAS!$C$5:$L$2388,2,FALSE) -> BRB | G7: =VLOOKUP($C7,CARPETAS!$C$5:$L$2388,9,FALSE) -> xx | H7: =VLOOKUP($C7,CARPETAS!$C$5:$L$2388,5,FALSE) -> xx | I7: =E7+2 -> 43145 | J7: =VLOOKUP($C7,CARPETAS!$C$5:$L$2388,4,FALSE) -> xx | L7: =I7+1 -> 43146 | M7: =IF(E7<>"",L7-E7,"-") -> 3 | N7: 936
A8: 7 | B8: Cancelado | C8: xx | D8: Jaime | E8: 43147 | F8: =VLOOKUP($C8,CARPETAS!$C$5:$L$2388,2,FALSE) -> BRB | G8: =VLOOKUP($C8,CARPETAS!$C$5:$L$2388,9,FALSE) -> xx | H8: =VLOOKUP($C8,CARPETAS!$C$5:$L$2388,5,FALSE) -> xx | I8: =E8+2 -> 43149 | J8: =VLOOKUP($C8,CARPETAS!$C$5:$L$2388,4,FALSE) -> xx | L8: =I8+1 -> 43150 | M8: =IF(E8<>"",L8-E8,"-") -> 3 | N8: 936
A9: 7 | B9: Cancelado | C9: xx | D9: Sidnei | E9: 43147 | F9: =VLOOKUP($C9,CARPETAS!$C$5:$L$2388,2,FALSE) -> BRB | G9: =VLOOKUP($C9,CARPETAS!$C$5:$L$2388,9,FALSE) -> xx | H9: =VLOOKUP($C9,CARPETAS!$C$5:$L$2388,5,FALSE) -> xx | I9: =E9+2 -> 43149 | J9: =VLOOKUP($C9,CARPETAS!$C$5:$L$2388,4,FALSE) -> xx | L9: =I9+1 -> 43150 | M9: =IF(E9<>"",L9-E9,"-") -> 3 | N9: 936
A10: 7 | B10: Cancelado | C10: xx | D10: Sidnei | E10: 43147 | F10: =VLOOKUP($C10,CARPETAS!$C$5:$L$2388,2,FALSE) -> BRB | G10: =VLOOKUP($C10,CARPETAS!$C$5:$L$2388,9,FALSE) -> xx | H10: =VLOOKUP($C10,CARPETAS!$C$5:$L$2388,5,FALSE) -> xx | I10: =E10+2 -> 43149 | J10: =VLOOKUP($C10,CARPETAS!$C$5:$L$2388,4,FALSE) -> xx | L10: =I10+1 -> 43150 | M10: =IF(E10<>"",L10-E10,"-") -> 3 | N10: 936
A11: 7 | B11: Cancelado | C11: xx | D11: Ulgo | E11: 43147 | F11: =VLOOKUP($C11,CARPETAS!$C$5:$L$2388,2,FALSE) -> BRB | G11: =VLOOKUP($C11,CARPETAS!$C$5:$L$2388,9,FALSE) -> xx | H11: =VLOOKUP($C11,CARPETAS!$C$5:$L$2388,5,FALSE) -> xx | I11: =E11+2 -> 43149 | J11: =VLOOKUP($C11,CARPETAS!$C$5:$L$2388,4,FALSE) -> xx | L11: =I11+1 -> 43150 | M11: =IF(E11<>"",L11-E11,"-") -> 3 | N11: 936
A12: 7 | B12: Cancelado | C12: xx | D12: Claudia | E12: 43147 | F12: =VLOOKUP($C12,CARPETAS!$C$5:$L$2388,2,FALSE) -> BRB | G12: =VLOOKUP($C12,CARPETAS!$C$5:$L$2388,9,FALSE) -> xx | H12: =VLOOKUP($C12,CARPETAS!$C$5:$L$2388,5,FALSE) -> xx | I12: =E12+2 -> 43149 | J12: =VLOOKUP($C12,CARPETAS!$C$5:$L$2388,4,FALSE) -> xx | L12: =I12+1 -> 43150 | M12: =IF(E12<>"",L12-E12,"-") -> 3 | N12: 936
A13: 9 | B13: Cancelado | C13: xx | D13: Sidnei | E13: 43161 | F13: =VLOOKUP($C13,CARPETAS!$C$5:$L$2388,2,FALSE) -> BRB | G13: =VLOOKUP($C13,CARPETAS!$C$5:$L$2388,9,FALSE) -> xx | H13: =VLOOKUP($C13,CARPETAS!$C$5:$L$2388,5,FALSE) -> xx | I13: =E13+2 -> 43163 | J13: =VLOOKUP($C13,CARPETAS!$C$5:$L$2388,4,FALSE) -> xx | L13: =I13+1 -> 43164 | M13: =IF(E13<>"",L13-E13,"-") -> 3 | N13: 936
A14: 11 | B14: Cancelado | C14: XX | D14: Jaime | E14: 43175 | F14: =VLOOKUP($C14,CARPETAS!$C$5:$L$2388,2,FALSE) -> BRB | G14: =VLOOKUP($C14,CARPETAS!$C$5:$L$2388,9,FALSE) -> xx | H14: =VLOOKUP($C14,CARPETAS!$C$5:$L$2388,5,FALSE) -> xx | I14: 43174 | J14: =VLOOKUP($C14,CARPETAS!$C$5:$L$2388,4,FALSE) -> xx | L14: =I14+1 -> 43175 | M14: =IF(E14<>"",L14-E14,"-") -> 0 | N14: 936
A15: 11 | B15: Cancelado | C15: xx | D15: Ulgo | E15: 43175 | F15: =VLOOKUP($C15,CARPETAS!$C$5:$L$2388,2,FALSE) -> BRB | G15: =VLOOKUP($C15,CARPETAS!$C$5:$L$2388,9,FALSE) -> xx | H15: =VLOOKUP($C15,CARPETAS!$C$5:$L$2388,5,FALSE) -> xx | I15: 43174 | J15: =VLOOKUP($C15,CARPETAS!$C$5:$L$2388,4,FALSE) -> xx | L15: =I15+1 -> 43175 | M15: =IF(E15<>"",L15-E15,"-") -> 0 | N15: 936
A16: 13 | B16: Destruida | C16: 308/2018 | D16: Corupá | E16: 43185 | F16: =VLOOKUP($C16,CARPETAS!$C$5:$L$2388,2,FALSE) -> #N/A | G16: =VLOOKUP($C16,CARPETAS!$C$5:$L$2388,9,FALSE) -> #N/A | H16: =VLOOKUP($C16,CARPETAS!$C$5:$L$2388,5,FALSE) -> #N/A | I16: =E16+2 -> 43187 | J16: =VLOOKUP($C16,CARPETAS!$C$5:$L$2388,4,FALSE) -> #N/A | L16: =I16+1+4 -> 43192 | M16: =IF(E16<>"",L16-E16,"-") -> 7 | N16: 936 | Q16: 2935 | R16: MKB 0869 | S16: MGK 7801 | T16: P.C.DESCARGA MIERCOLES EN R. DE COREA 02/04/18 /*//TZ: caminhão se encontrava com temperatura de -6º NEGATIVOS, mirar a fruta,
A17: 13 | B17: Cancelado | C17: xx | D17: Claudia | E17: 43186 | F17: =VLOOKUP($C17,CARPETAS!$C$5:$L$2388,2,FALSE) -> BRB | G17: =VLOOKUP($C17,CARPETAS!$C$5:$L$2388,9,FALSE) -> xx | H17: =VLOOKUP($C17,CARPETAS!$C$5:$L$2388,5,FALSE) -> xx | I17: =E17+2 -> 43188 | J17: =VLOOKUP($C17,CARPETAS!$C$5:$L$2388,4,FALSE) -> xx | L17: =I17+1 -> 43189 | M17: =IF(E17<>"",L17-E17,"-") -> 3 | N17: 936
A18: 21 | B18: Cancelado | C18: xx | D18: Claudia | E18: 43245 | F18: =VLOOKUP($C18,CARPETAS!$C$5:$L$2388,2,FALSE) -> BRB | G18: =VLOOKUP($C18,CARPETAS!$C$5:$L$2388,9,FALSE) -> xx | H18: =VLOOKUP($C18,CARPETAS!$C$5:$L$2388,5,FALSE) -> xx | I18: =E18+2 -> 43247 | J18: =VLOOKUP($C18,CARPETAS!$C$5:$L$2388,4,FALSE) -> xx | L18: =I18+1 -> 43248 | M18: =IF(E18<>"",L18-E18,"-") -> 3 | N18: 936
A19: 21 | B19: Cancelado | C19: xx | D19: Jaime | E19: 43245 | F19: =VLOOKUP($C19,CARPETAS!$C$5:$L$2388,2,FALSE) -> BRB | G19: =VLOOKUP($C19,CARPETAS!$C$5:$L$2388,9,FALSE) -> xx | H19: =VLOOKUP($C19,CARPETAS!$C$5:$L$2388,5,FALSE) -> xx | I19: =E19+2 -> 43247 | J19: =VLOOKUP($C19,CARPETAS!$C$5:$L$2388,4,FALSE) -> xx | L19: =I19+1 -> 43248 | M19: =IF(E19<>"",L19-E19,"-") -> 3 | N19: 936
A20: 22 | B20: Cancelado | C20: xx | D20: Claudia | E20: 43248 | F20: =VLOOKUP($C20,CARPETAS!$C$5:$L$2388,2,FALSE) -> BRB | G20: =VLOOKUP($C20,CARPETAS!$C$5:$L$2388,9,FALSE) -> xx | H20: =VLOOKUP($C20,CARPETAS!$C$5:$L$2388,5,FALSE) -> xx | I20: =E20+2 -> 43250 | J20: =VLOOKUP($C20,CARPETAS!$C$5:$L$2388,4,FALSE) -> xx | L20: =I20+1 -> 43251 | M20: =IF(E20<>"",L20-E20,"-") -> 3 | N20: 936
A21: 22 | B21: Cancelado | C21: xx | D21: Claudia | E21: 43248 | F21: =VLOOKUP($C21,CARPETAS!$C$5:$L$2388,2,FALSE) -> BRB | G21: =VLOOKUP($C21,CARPETAS!$C$5:$L$2388,9,FALSE) -> xx | H21: =VLOOKUP($C21,CARPETAS!$C$5:$L$2388,5,FALSE) -> xx | I21: =E21+2 -> 43250 | J21: =VLOOKUP($C21,CARPETAS!$C$5:$L$2388,4,FALSE) -> xx | L21: =I21+1 -> 43251 | M21: =IF(E21<>"",L21-E21,"-") -> 3 | N21: 936
A22: 22 | B22: Cancelado | C22: xx | D22: Jaime | E22: 43248 | F22: =VLOOKUP($C22,CARPETAS!$C$5:$L$2388,2,FALSE) -> BRB | G22: =VLOOKUP($C22,CARPETAS!$C$5:$L$2388,9,FALSE) -> xx | H22: =VLOOKUP($C22,CARPETAS!$C$5:$L$2388,5,FALSE) -> xx | I22: =E22+2 -> 43250 | J22: =VLOOKUP($C22,CARPETAS!$C$5:$L$2388,4,FALSE) -> xx | L22: =I22+1 -> 43251 | M22: =IF(E22<>"",L22-E22,"-") -> 3 | N22: 936
A23: 22 | B23: Cancelado | C23: xx | D23: Gilson | E23: 43248 | F23: =VLOOKUP($C23,CARPETAS!$C$5:$L$2388,2,FALSE) -> BRB | G23: =VLOOKUP($C23,CARPETAS!$C$5:$L$2388,9,FALSE) -> xx | H23: =VLOOKUP($C23,CARPETAS!$C$5:$L$2388,5,FALSE) -> xx | I23: =E23+2 -> 43250 | J23: =VLOOKUP($C23,CARPETAS!$C$5:$L$2388,4,FALSE) -> xx | L23: =I23+1 -> 43251 | M23: =IF(E23<>"",L23-E23,"-") -> 3 | N23: 936
A24: 22 | B24: Cancelado | C24: xx | D24: Corupá | E24: 43248 | F24: =VLOOKUP($C24,CARPETAS!$C$5:$L$2388,2,FALSE) -> BRB | G24: =VLOOKUP($C24,CARPETAS!$C$5:$L$2388,9,FALSE) -> xx | H24: =VLOOKUP($C24,CARPETAS!$C$5:$L$2388,5,FALSE) -> xx | I24: =E24+2 -> 43250 | J24: =VLOOKUP($C24,CARPETAS!$C$5:$L$2388,4,FALSE) -> xx | L24: =I24+1 -> 43251 | M24: =IF(E24<>"",L24-E24,"-") -> 3 | N24: 936
A25: 22 | B25: Cancelado | C25: xx | D25: Sidnei | E25: 43248 | F25: =VLOOKUP($C25,CARPETAS!$C$5:$L$2388,2,FALSE) -> BRB | G25: =VLOOKUP($C25,CARPETAS!$C$5:$L$2388,9,FALSE) -> xx | H25: =VLOOKUP($C25,CARPETAS!$C$5:$L$2388,5,FALSE) -> xx | I25: =E25+2 -> 43250 | J25: =VLOOKUP($C25,CARPETAS!$C$5:$L$2388,4,FALSE) -> xx | L25: =I25+1 -> 43251 | M25: =IF(E25<>"",L25-E25,"-") -> 3 | N25: 936
A26: 22 | B26: Cancelado | C26: xx | D26: Claudia | E26: 43252 | F26: =VLOOKUP($C26,CARPETAS!$C$5:$L$2388,2,FALSE) -> BRB | G26: =VLOOKUP($C26,CARPETAS!$C$5:$L$2388,9,FALSE) -> xx | H26: =VLOOKUP($C26,CARPETAS!$C$5:$L$2388,5,FALSE) -> xx | I26: =E26+2 -> 43254 | J26: =VLOOKUP($C26,CARPETAS!$C$5:$L$2388,4,FALSE) -> xx | L26: =I26+1 -> 43255 | M26: =IF(E26<>"",L26-E26,"-") -> 3 | N26: 936
A27: 22 | B27: Cancelado | C27: xx | D27: Claudia | E27: 43252 | F27: =VLOOKUP($C27,CARPETAS!$C$5:$L$2388,2,FALSE) -> BRB | G27: =VLOOKUP($C27,CARPETAS!$C$5:$L$2388,9,FALSE) -> xx | H27: =VLOOKUP($C27,CARPETAS!$C$5:$L$2388,5,FALSE) -> xx | I27: =E27+2 -> 43254 | J27: =VLOOKUP($C27,CARPETAS!$C$5:$L$2388,4,FALSE) -> xx | L27: =I27+1 -> 43255 | M27: =IF(E27<>"",L27-E27,"-") -> 3 | N27: 936
A28: 22 | B28: Cancelado | C28: xx | D28: Jaime | E28: 43252 | F28: =VLOOKUP($C28,CARPETAS!$C$5:$L$2388,2,FALSE) -> BRB | G28: =VLOOKUP($C28,CARPETAS!$C$5:$L$2388,9,FALSE) -> xx | H28: =VLOOKUP($C28,CARPETAS!$C$5:$L$2388,5,FALSE) -> xx | I28: =E28+2 -> 43254 | J28: =VLOOKUP($C28,CARPETAS!$C$5:$L$2388,4,FALSE) -> xx | L28: =I28+1 -> 43255 | M28: =IF(E28<>"",L28-E28,"-") -> 3 | N28: 936
... A34: 26 | B34: Cancelado | C34: xx | D34: Corupá | E34: 43278 | F34: =VLOOKUP($C34,CARPETAS!$C$5:$L$2388,2,FALSE) -> BRB | G34: =VLOOKUP($C34,CARPETAS!$C$5:$L$2388,9,FALSE) -> xx | H34: =VLOOKUP($C34,CARPETAS!$C$5:$L$2388,5,FALSE) -> xx | I34: =E34+2 -> 43280 | J34: =VLOOKUP($C34,CARPETAS!$C$5:$L$2388,4,FALSE) -> xx | L34: =I34+1 -> 43281 | M34: =IF(E34<>"",L34-E34,"-") -> 3 | N34: 936
A35: 36 | B35: Cancelado | C35: xx | D35: Sidnei | E35: 43349 | F35: =VLOOKUP($C35,CARPETAS!$C$5:$L$2388,2,FALSE) -> BRB | G35: =VLOOKUP($C35,CARPETAS!$C$5:$L$2388,9,FALSE) -> xx | H35: =VLOOKUP($C35,CARPETAS!$C$5:$L$2388,5,FALSE) -> xx | I35: 43322 | J35: =VLOOKUP($C35,CARPETAS!$C$5:$L$2388,4,FALSE) -> xx | L35: =I35+1 -> 43323 | M35: =IF(E35<>"",L35-E35,"-") -> -26 | N35: 936
A36: 42 | B36: Cancelado | C36: xx | D36: Nordeste | E36: 43391 | F36: =VLOOKUP($C36,CARPETAS!$C$5:$L$2388,2,FALSE) -> BRB | G36: =VLOOKUP($C36,CARPETAS!$C$5:$L$2388,9,FALSE) -> xx | H36: =VLOOKUP($C36,CARPETAS!$C$5:$L$2388,5,FALSE) -> xx | I36: =E36+3 -> 43394 | J36: =VLOOKUP($C36,CARPETAS!$C$5:$L$2388,4,FALSE) -> xx | L36: =I36+1 -> 43395 | M36: =IF(E36<>"",L36-E36,"-") -> 4 | N36: 936 | O36: N/A
A37: 43 | B37: Cancelado | C37: xx | D37: Nordeste | E37: 43395 | F37: =VLOOKUP($C37,CARPETAS!$C$5:$L$2388,2,FALSE) -> BRB | G37: =VLOOKUP($C37,CARPETAS!$C$5:$L$2388,9,FALSE) -> xx | H37: =VLOOKUP($C37,CARPETAS!$C$5:$L$2388,5,FALSE) -> xx | I37: =E37+3 -> 43398 | J37: =VLOOKUP($C37,CARPETAS!$C$5:$L$2388,4,FALSE) -> xx | L37: =I37+1 -> 43399 | M37: =IF(E37<>"",L37-E37,"-") -> 4 | N37: 936
A38: 43 | B38: Cancelado | C38: xx | D38: Nordeste | E38: 43395 | F38: =VLOOKUP($C38,CARPETAS!$C$5:$L$2388,2,FALSE) -> BRB | G38: =VLOOKUP($C38,CARPETAS!$C$5:$L$2388,9,FALSE) -> xx | H38: =VLOOKUP($C38,CARPETAS!$C$5:$L$2388,5,FALSE) -> xx | I38: =E38+3 -> 43398 | J38: =VLOOKUP($C38,CARPETAS!$C$5:$L$2388,4,FALSE) -> xx | L38: =I38+1 -> 43399 | M38: =IF(E38<>"",L38-E38,"-") -> 4 | N38: 936
A39: 47 | B39: Cancelado | C39: xx | D39: Valdemar | E39: 43425 | F39: =VLOOKUP($C39,CARPETAS!$C$5:$L$2388,2,FALSE) -> BRB | G39: =VLOOKUP($C39,CARPETAS!$C$5:$L$2388,9,FALSE) -> xx | H39: =VLOOKUP($C39,CARPETAS!$C$5:$L$2388,5,FALSE) -> xx | I39: =E39+2 -> 43427 | J39: =VLOOKUP($C39,CARPETAS!$C$5:$L$2388,4,FALSE) -> xx | L39: =I39+1 -> 43428 | M39: =IF(E39<>"",L39-E39,"-") -> 3 | N39: 936
A40: 47 | B40: Cancelado | C40: xx | D40: Valdemar | E40: 43426 | F40: =VLOOKUP($C40,CARPETAS!$C$5:$L$2388,2,FALSE) -> BRB | G40: =VLOOKUP($C40,CARPETAS!$C$5:$L$2388,9,FALSE) -> xx | H40: =VLOOKUP($C40,CARPETAS!$C$5:$L$2388,5,FALSE) -> xx | I40: =E40+2 -> 43428 | J40: =VLOOKUP($C40,CARPETAS!$C$5:$L$2388,4,FALSE) -> xx | L40: =I40+1 -> 43429 | M40: =IF(E40<>"",L40-E40,"-") -> 3 | N40: 936
A41: 48 | B41: Cancelado | C41: xx | D41: Nordeste | E41: 43430 | F41: =VLOOKUP($C41,CARPETAS!$C$5:$L$2388,2,FALSE) -> BRB | G41: =VLOOKUP($C41,CARPETAS!$C$5:$L$2388,9,FALSE) -> xx | H41: =VLOOKUP($C41,CARPETAS!$C$5:$L$2388,5,FALSE) -> xx | I41: =E41+2 -> 43432 | J41: =VLOOKUP($C41,CARPETAS!$C$5:$L$2388,4,FALSE) -> xx | L41: =I41+1 -> 43433 | M41: =IF(E41<>"",L41-E41,"-") -> 3 | N41: 936
A42: 1 | B42: Descargado | C42: 403/2018 | D42: Gilson | E42: 43468 | F42: =VLOOKUP($C42,CARPETAS!$C$5:$L$2388,2,FALSE) -> #N/A | G42: =VLOOKUP($C42,CARPETAS!$C$5:$L$2388,9,FALSE) -> #N/A | H42: =VLOOKUP($C42,CARPETAS!$C$5:$L$2388,5,FALSE) -> #N/A | I42: 43469 | J42: =VLOOKUP($C42,CARPETAS!$C$5:$L$2388,4,FALSE) -> #N/A | L42: =I42+1 -> 43470 | M42: =IF(E42<>"",L42-E42,"-") -> 2 | N42: 900 | O42: GT 001 | P42: 902 | Q42: 536 | R42: QIW 6450 | S42: QHT8275 | T42: P.C. DESCARGO EN R. NATURAL 05/01/19 ///R.D 05/01 - DESCARGA EN REP DE COREA.
A43: 1 | B43: Descargado | C43: 405/2019 | D43: Valdemar | E43: 43468 | F43: =VLOOKUP($C43,CARPETAS!$C$5:$L$2388,2,FALSE) -> BRB001 | G43: =VLOOKUP($C43,CARPETAS!$C$5:$L$2388,9,FALSE) -> 134.03.89 | H43: =VLOOKUP($C43,CARPETAS!$C$5:$L$2388,5,FALSE) -> Transzanini | I43: 43469 | J43: =VLOOKUP($C43,CARPETAS!$C$5:$L$2388,4,FALSE) -> Rivera | L43: =I43+4 -> 43473 | M43: =IF(E43<>"",L43-E43,"-") -> 5 | N43: 900 | O43: VH 004 | P43: 900 | Q43: 537 | R43: FJX 1877 | S43: EOE 2359 | T43: R.D 09/01 - DESCARGO EN MERCADO MODELO. /// R.D 08/01 - QUEDA PARA DESCARAR EL DIA 09/01
A44: 1 | B44: Descargado | C44: 404/2018 | D44: Corupá | E44: 43468 | F44: =VLOOKUP($C44,CARPETAS!$C$5:$L$2388,2,FALSE) -> #N/A | G44: =VLOOKUP($C44,CARPETAS!$C$5:$L$2388,9,FALSE) -> #N/A | H44: =VLOOKUP($C44,CARPETAS!$C$5:$L$2388,5,FALSE) -> #N/A | I44: 43472 | J44: =VLOOKUP($C44,CARPETAS!$C$5:$L$2388,4,FALSE) -> #N/A | L44: =I44+1 -> 43473 | M44: =IF(E44<>"",L44-E44,"-") -> 5 | N44: 900 | O44: CP 002 | P44: 901 | Q44: 3371 | R44: MLP 4888 | S44: MKT 2555 | T44: P.C. DESCARGO EN LARRAVIDE 08/01/19 ///R.D 08/01 - DESCARGA EN LARRAVIDE /// TZ 07/01 - DESCARGA 08/1
A45: 1 | B45: Descargado | C45: 404/2018 | D45: Claudia | E45: 43468 | F45: =VLOOKUP($C45,CARPETAS!$C$5:$L$2388,2,FALSE) -> #N/A | G45: =VLOOKUP($C45,CARPETAS!$C$5:$L$2388,9,FALSE) -> #N/A | H45: =VLOOKUP($C45,CARPETAS!$C$5:$L$2388,5,FALSE) -> #N/A | I45: 43472 | J45: =VLOOKUP($C45,CARPETAS!$C$5:$L$2388,4,FALSE) -> #N/A | L45: =I45+1 -> 43473 | M45: =IF(E45<>"",L45-E45,"-") -> 5 | N45: 900 | O45: CH 003 | P45: 901 | Q45: 3374 | R45: MGK 2404 | S45: MIB 3710 | T45: R.D 08/01 - DESCARGA EN MERCADO MODELO /// TZ 07/01 - DESCARGA 08/1
A46: 1 | B46: Descargado | C46: 405/2019 | D46: Claudia | E46: 43469 | F46: =VLOOKUP($C46,CARPETAS!$C$5:$L$2388,2,FALSE) -> BRB001 | G46: =VLOOKUP($C46,CARPETAS!$C$5:$L$2388,9,FALSE) -> 134.03.89 | H46: =VLOOKUP($C46,CARPETAS!$C$5:$L$2388,5,FALSE) -> Transzanini | I46: 43472 | J46: =VLOOKUP($C46,CARPETAS!$C$5:$L$2388,4,FALSE) -> Rivera | L46: =I46+1 -> 43473 | M46: =IF(E46<>"",L46-E46,"-") -> 4 | N46: 900 | O46: CH 004 | P46: 901 | Q46: 539 | R46: EOE 2475 | S46: MJY 7644 | T46: R.D 08/01 - DESCARGA EN MERCADO MODELO /// TZ 07/01 - DESCARGA 08/1
A47: 2 | B47: Descargado | C47: 405/2019 | D47: Valdemar | E47: 43471 | F47: =VLOOKUP($C47,CARPETAS!$C$5:$L$2388,2,FALSE) -> BRB001 | G47: =VLOOKUP($C47,CARPETAS!$C$5:$L$2388,9,FALSE) -> 134.03.89 | H47: =VLOOKUP($C47,CARPETAS!$C$5:$L$2388,5,FALSE) -> Transzanini | I47: 43472 | J47: =VLOOKUP($C47,CARPETAS!$C$5:$L$2388,4,FALSE) -> Rivera | L47: =I47+1 -> 43473 | M47: =IF(E47<>"",L47-E47,"-") -> 2 | N47: 900 | O47: VH 005 | P47: 900 | Q47: 538 | R47: QJQ 3510 | S47: MLX 3048 | T47: P.C. DESCARGO EN LARRAVIDE 08/01/19 ////R.D 08/01 - DESCARGA EN LARRAVIDE /// TZ 07/01 - DESCARGA 08/1
A48: 2 | B48: Descargado | C48: 405/2019 | D48: Claudia | E48: 43471 | F48: =VLOOKUP($C48,CARPETAS!$C$5:$L$2388,2,FALSE) -> BRB001 | G48: =VLOOKUP($C48,CARPETAS!$C$5:$L$2388,9,FALSE) -> 134.03.89 | H48: =VLOOKUP($C48,CARPETAS!$C$5:$L$2388,5,FALSE) -> Transzanini | I48: 43472 | J48: =VLOOKUP($C48,CARPETAS!$C$5:$L$2388,4,FALSE) -> Rivera | L48: =I48+1 -> 43473 | M48: =IF(E48<>"",L48-E48,"-") -> 2 | N48: 900 | O48: CH 005 | P48: 901 | Q48: 540 | R48: MMH 8790 | S48: MHW 7826 | T48: R.D 09/01 - DESCARGO EN MERCADO MODELO, TRAJO PALLETS CAIDOS Y CAJAS DESTACADAS. /// R.D 08/01 - QUEDA PARA DESCARAR EL DIA 09/01
A49: 1 | B49: Descargado | C49: 406/2019 | D49: Jaime | E49: 43469 | F49: =VLOOKUP($C49,CARPETAS!$C$5:$L$2388,2,FALSE) -> BRB002 | G49: =VLOOKUP($C49,CARPETAS!$C$5:$L$2388,9,FALSE) -> 134.03.90 | H49: =VLOOKUP($C49,CARPETAS!$C$5:$L$2388,5,FALSE) -> Silvio | I49: 43472 | J49: =VLOOKUP($C49,CARPETAS!$C$5:$L$2388,4,FALSE) -> Rivera | L49: =I49+1+1 -> 43474 | M49: =IF(E49<>"",L49-E49,"-") -> 5 | N49: 900 | O49: JM 002 | P49: 900 | Q49: 3373 | R49: MKF 4284 | S49: MKN 1857 | T49: p.c. descarga en riqueza 9/01/19 ////
A50: 1 | B50: Descargado | C50: 406/2019 | D50: Ulgo | E50: 43470 | F50: =VLOOKUP($C50,CARPETAS!$C$5:$L$2388,2,FALSE) -> BRB002 | G50: =VLOOKUP($C50,CARPETAS!$C$5:$L$2388,9,FALSE) -> 134.03.90 | H50: =VLOOKUP($C50,CARPETAS!$C$5:$L$2388,5,FALSE) -> Silvio | I50: 43472 | J50: =VLOOKUP($C50,CARPETAS!$C$5:$L$2388,4,FALSE) -> Rivera | L50: 43475 | M50: =IF(E50<>"",L50-E50,"-") -> 5 | N50: 900 | O50: UB 002 | P50: 900 | Q50: 3377 | R50: MIA 7610 | S50: MKI 2771 | T50: R.D 10/01 - DESCARGO EN MERCADO MODELO /// R.D 09/01 - NO DESCARGO, DESCARGARIA EL DIA 10/01.
A51: 1 | B51: Descargado | C51: 406/2019 | D51: Sidnei | E51: 43469 | F51: =VLOOKUP($C51,CARPETAS!$C$5:$L$2388,2,FALSE) -> BRB002 | G51: =VLOOKUP($C51,CARPETAS!$C$5:$L$2388,9,FALSE) -> 134.03.90 | H51: =VLOOKUP($C51,CARPETAS!$C$5:$L$2388,5,FALSE) -> Silvio | I51: 43472 | J51: =VLOOKUP($C51,CARPETAS!$C$5:$L$2388,4,FALSE) -> Rivera | L51: 43475 | M51: =IF(E51<>"",L51-E51,"-") -> 6 | N51: 900 | O51: SR 001 | P51: 900 | Q51: 3372 | R51: QHM 2913 | S51: QHO 8784 | T51: p.c. descargo en r. de corea 10/01/19 ////R.D 09/01 - NO DESCARGO, DESCARGARIA EL DIA 10/01.
A52: 1 | B52: Descargado | C52: 406/2019 | D52: Corupá | E52: 43469 | F52: =VLOOKUP($C52,CARPETAS!$C$5:$L$2388,2,FALSE) -> BRB002 | G52: =VLOOKUP($C52,CARPETAS!$C$5:$L$2388,9,FALSE) -> 134.03.90 | H52: =VLOOKUP($C52,CARPETAS!$C$5:$L$2388,5,FALSE) -> Silvio | I52: 43473 | J52: =VLOOKUP($C52,CARPETAS!$C$5:$L$2388,4,FALSE) -> Rivera | L52: 43475 | M52: =IF(E52<>"",L52-E52,"-") -> 6 | N52: 900 | O52: CP 003 | P52: 901 | Q52: 3376 | R52: MIA 0291 | S52: MJD 4506 | T52: R.D 10/01 - DESCARGO EN MERCADO MODELO /// R.D 09/01 - NO DESCARGO, DESCARGARIA EL DIA 10/01.
A53: 2 | B53: Descargado | C53: 406/2019 | D53: Jaime | E53: 43472 | F53: =VLOOKUP($C53,CARPETAS!$C$5:$L$2388,2,FALSE) -> BRB002 | G53: =VLOOKUP($C53,CARPETAS!$C$5:$L$2388,9,FALSE) -> 134.03.90 | H53: =VLOOKUP($C53,CARPETAS!$C$5:$L$2388,5,FALSE) -> Silvio | I53: 43473 | J53: =VLOOKUP($C53,CARPETAS!$C$5:$L$2388,4,FALSE) -> Rivera | L53: 43475 | M53: =IF(E53<>"",L53-E53,"-") -> 3 | N53: 900 | O53: JM 003 | P53: 901 | Q53: 3378 | R53: FXA 1048 | S53: HRS 5249 | T53: P.C. DESCARGO EN R. NATURAL 10/01/19 ////R.D 10/01 - DESCARGA EN CRNL RAIZ. /// R.D 09/01 - NO DESCARGO, DESCARGARIA EL DIA 10/01.
A54: 2 | B54: Descargado | C54: 406/2019 | D54: Corupá | E54: 43474 | F54: =VLOOKUP($C54,CARPETAS!$C$5:$L$2388,2,FALSE) -> BRB002 | G54: =VLOOKUP($C54,CARPETAS!$C$5:$L$2388,9,FALSE) -> 134.03.90 | H54: SILVIO | I54: =E54+2 -> 43476 | J54: =VLOOKUP($C54,CARPETAS!$C$5:$L$2388,4,FALSE) -> Rivera | L54: =I54+1 -> 43477 | M54: =IF(E54<>"",L54-E54,"-") -> 3 | N54: 900 | O54: CP 004 | P54: 900 | Q54: 3380 | R54: MKO 7300 | S54: MKQ 7464 | T54: PC. DESCARGO EN LARRAVIDE 12/01/19 ////DM descarga larravide 12/1
A55: 2 | B55: Descargado | C55: 405/2019 | D55: Sidnei | E55: 43474 | F55: =VLOOKUP($C55,CARPETAS!$C$5:$L$2388,2,FALSE) -> BRB001 | G55: =VLOOKUP($C55,CARPETAS!$C$5:$L$2388,9,FALSE) -> 134.03.89 | H55: =VLOOKUP($C55,CARPETAS!$C$5:$L$2388,5,FALSE) -> Transzanini | I55: =E55+2 -> 43476 | J55: =VLOOKUP($C55,CARPETAS!$C$5:$L$2388,4,FALSE) -> Rivera | L55: =I55+1 -> 43477 | M55: =IF(E55<>"",L55-E55,"-") -> 3 | N55: 900 | O55: SR 002 | P55: 900 | Q55: 546 | R55: QJV 4800 | S55: QJM 1037 | T55: PC. DESCARGO EN LARRAVIDE 12/01/19 ////DM descarga larravide 12/1
A56: 2 | B56: Descargado | C56: 407/2019 | D56: Claudia | E56: 43474 | F56: =VLOOKUP($C56,CARPETAS!$C$5:$L$2388,2,FALSE) -> BRB003 | G56: =VLOOKUP($C56,CARPETAS!$C$5:$L$2388,9,FALSE) -> 134.06.39 | H56: Cmcn | I56: 43476 | J56: =VLOOKUP($C56,CARPETAS!$C$5:$L$2388,4,FALSE) -> Rivera | L56: 43479 | M56: =IF(E56<>"",L56-E56,"-") -> 5 | N56: 900 | O56: CH 006 | P56: 900 | Q56: 520 | R56: DPF 9633 | S56: HRS 8321 | T56: M.A DESCARGO EN LARRAVIDE 14/01/19 ////
A57: 2 | B57: Descargado | C57: 406/2019 | D57: Corupá | E57: 43476 | F57: =VLOOKUP($C57,CARPETAS!$C$5:$L$2388,2,FALSE) -> BRB002 | G57: =VLOOKUP($C57,CARPETAS!$C$5:$L$2388,9,FALSE) -> 134.03.90 | H57: SILVIO | I57: 43479 | J57: =VLOOKUP($C57,CARPETAS!$C$5:$L$2388,4,FALSE) -> Rivera | L57: =I57+1 -> 43480 | M57: =IF(E57<>"",L57-E57,"-") -> 4 | N57: 900 | O57: CP 005 | P57: 901 | Q57: 3383 | R57: MKV 0568 | S57: MJV 2237 | T57: DM descarga Mercado Modelo 15/1
A58: 2 | B58: Descargado | C58: 405/2019 | D58: Gilson | E58: 43475 | F58: =VLOOKUP($C58,CARPETAS!$C$5:$L$2388,2,FALSE) -> BRB001 | G58: =VLOOKUP($C58,CARPETAS!$C$5:$L$2388,9,FALSE) -> 134.03.89 | H58: =VLOOKUP($C58,CARPETAS!$C$5:$L$2388,5,FALSE) -> Transzanini | I58: 43479 | J58: =VLOOKUP($C58,CARPETAS!$C$5:$L$2388,4,FALSE) -> Rivera | L58: 43480 | M58: =IF(E58<>"",L58-E58,"-") -> 5 | N58: 900 | O58: GT 002 | P58: 904 | Q58: 548 | R58: EOE 2510 | S58: MHW 7856 | T58: R.D 15/01 - DESCARGO EN MERCADO MODELO, TRAJO 2 CAJAS DE MUESTRA. /// DM descarga Mercado Modelo 15/1
A59: 3 | B59: Descargado | C59: 405/2019 | D59: Jaime | E59: 43478 | F59: =VLOOKUP($C59,CARPETAS!$C$5:$L$2388,2,FALSE) -> BRB001 | G59: =VLOOKUP($C59,CARPETAS!$C$5:$L$2388,9,FALSE) -> 134.03.89 | H59: =VLOOKUP($C59,CARPETAS!$C$5:$L$2388,5,FALSE) -> Transzanini | I59: 43479 | J59: =VLOOKUP($C59,CARPETAS!$C$5:$L$2388,4,FALSE) -> Rivera | L59: =I59+1 -> 43480 | M59: =IF(E59<>"",L59-E59,"-") -> 2 | N59: 900 | O59: JM 004 | P59: 901 | Q59: 550 | R59: FEJ 8244 | S59: QHT 8875 | T59: DM descarga Mercado Modelo 15/1
A60: 3 | B60: Descargado | C60: 408/2019 | D60: Claudia | E60: 43478 | F60: =VLOOKUP($C60,CARPETAS!$C$5:$L$2388,2,FALSE) -> BRB004 | G60: =VLOOKUP($C60,CARPETAS!$C$5:$L$2388,9,FALSE) -> 134.08.44 | H60: =VLOOKUP($C60,CARPETAS!$C$5:$L$2388,5,FALSE) -> Silvio | I60: 43479 | J60: =VLOOKUP($C60,CARPETAS!$C$5:$L$2388,4,FALSE) -> Rivera | L60: 43481 | M60: =IF(E60<>"",L60-E60,"-") -> 3 | N60: 900 | O60: CH 007 | P60: 901 | Q60: 3387 | R60: QID 0890 | S60: QHA 9965 | T60: M.A DESCARGA LARRAVIDE 16/01
A61: 3 | B61: Descargado | C61: 408/2019 | D61: Claudia | E61: 43478 | F61: =VLOOKUP($C61,CARPETAS!$C$5:$L$2388,2,FALSE) -> BRB004 | G61: =VLOOKUP($C61,CARPETAS!$C$5:$L$2388,9,FALSE) -> 134.08.44 | H61: =VLOOKUP($C61,CARPETAS!$C$5:$L$2388,5,FALSE) -> Silvio | I61: 43479 | J61: =VLOOKUP($C61,CARPETAS!$C$5:$L$2388,4,FALSE) -> Rivera | L61: 43481 | M61: =IF(E61<>"",L61-E61,"-") -> 3 | N61: 900 | O61: CH 008 | P61: 901 | Q61: 3388 | R61: AWA 3514 | S61: MLD 7421 | T61: M.A DESCARGA LARRAVIDE 16/01
A62: 2 | B62: Descargado | C62: 406/2019 | D62: Ulgo | E62: 43476 | F62: =VLOOKUP($C62,CARPETAS!$C$5:$L$2388,2,FALSE) -> BRB002 | G62: =VLOOKUP($C62,CARPETAS!$C$5:$L$2388,9,FALSE) -> 134.03.90 | H62: =VLOOKUP($C62,CARPETAS!$C$5:$L$2388,5,FALSE) -> Silvio | I62: 43480 | J62: =VLOOKUP($C62,CARPETAS!$C$5:$L$2388,4,FALSE) -> Rivera | L62: 43481 | M62: =IF(E62<>"",L62-E62,"-") -> 5 | N62: 900 | O62: UB 003 | P62: 900 | Q62: 3382 | R62: IXY 3608 | S62: MLT 5777 | T62: P.C. DESCARGA EN R. NATURAL 16/01/19 ////
A63: 3 | B63: Descargado | C63: 408/2019 | D63: Valdemar | E63: 43479 | F63: =VLOOKUP($C63,CARPETAS!$C$5:$L$2388,2,FALSE) -> BRB004 | G63: =VLOOKUP($C63,CARPETAS!$C$5:$L$2388,9,FALSE) -> 134.08.44 | H63: =VLOOKUP($C63,CARPETAS!$C$5:$L$2388,5,FALSE) -> Silvio | I63: 43480 | J63: =VLOOKUP($C63,CARPETAS!$C$5:$L$2388,4,FALSE) -> Rivera | L63: =I63+1 -> 43481 | M63: =IF(E63<>"",L63-E63,"-") -> 2 | N63: 900 | O63: VH 006 | P63: 900 | Q63: 3390 | R63: QHN 9892 | S63: QIR 3943 | T63: P.C. DESCARGA EN R. NATURAL 17/01/19 ////P.C. ARRIBO 11:45 ///16/01/19 P.C. DESCARGA 17/01/19 ////
A64: 2 | B64: Descargado | C64: 408/2019 | D64: Gilson | E64: 43476 | F64: =VLOOKUP($C64,CARPETAS!$C$5:$L$2388,2,FALSE) -> BRB004 | G64: =VLOOKUP($C64,CARPETAS!$C$5:$L$2388,9,FALSE) -> 134.08.44 | H64: =VLOOKUP($C64,CARPETAS!$C$5:$L$2388,5,FALSE) -> Silvio | I64: 43481 | J64: =VLOOKUP($C64,CARPETAS!$C$5:$L$2388,4,FALSE) -> Rivera | L64: =I64+1 -> 43482 | M64: =IF(E64<>"",L64-E64,"-") -> 6 | N64: 900 | O64: GT 003 | P64: 901 | Q64: 3389 | R64: MMF 8555 | S64: QJR 7555
A65: 3 | B65: Descargado | C65: 408/2019 | D65: Claudia | E65: 43479 | F65: =VLOOKUP($C65,CARPETAS!$C$5:$L$2388,2,FALSE) -> BRB004 | G65: =VLOOKUP($C65,CARPETAS!$C$5:$L$2388,9,FALSE) -> 134.08.44 | H65: =VLOOKUP($C65,CARPETAS!$C$5:$L$2388,5,FALSE) -> Silvio | I65: =E65+2 -> 43481 | J65: =VLOOKUP($C65,CARPETAS!$C$5:$L$2388,4,FALSE) -> Rivera | L65: =I65+1 -> 43482 | M65: =IF(E65<>"",L65-E65,"-") -> 3 | N65: 900 | O65: CH 009 | P65: 900 | Q65: 3392 | R65: QII 4230 | S65: QIW 2160
A66: 3 | B66: Descargado | C66: 408/2019 | D66: Corupá | E66: 43480 | F66: =VLOOKUP($C66,CARPETAS!$C$5:$L$2388,2,FALSE) -> BRB004 | G66: =VLOOKUP($C66,CARPETAS!$C$5:$L$2388,9,FALSE) -> 134.08.44 | H66: =VLOOKUP($C66,CARPETAS!$C$5:$L$2388,5,FALSE) -> Silvio | I66: 43482 | J66: =VLOOKUP($C66,CARPETAS!$C$5:$L$2388,4,FALSE) -> Rivera | L66: =I66+1 -> 43483 | M66: =IF(E66<>"",L66-E66,"-") -> 3 | N66: 900 | O66: CP 006 | P66: 901 | Q66: 3391 | R66: QIX 6840 | S66: QIW6120
A67: 3 | B67: Descargado | C67: 410/2019 | D67: Sidnei | E67: 43481 | F67: =VLOOKUP($C67,CARPETAS!$C$5:$L$2388,2,FALSE) -> BRB006 | G67: =VLOOKUP($C67,CARPETAS!$C$5:$L$2388,9,FALSE) -> 134.10.38 | H67: =VLOOKUP($C67,CARPETAS!$C$5:$L$2388,5,FALSE) -> Silvio | I67: =E67+2 -> 43483 | J67: =VLOOKUP($C67,CARPETAS!$C$5:$L$2388,4,FALSE) -> Rivera | L67: =I67+1 -> 43484 | M67: =IF(E67<>"",L67-E67,"-") -> 3 | N67: 900 | O67: SR 003 | P67: 900 | Q67: 3393 | R67: MKT 4555 | S67: QIR 4668 | T67: DM camion vino con varios palet torzidos y un palet volcado // M.A LLEGA 19/01 // DESCARGA 21/01 // STATUS ERA FRONTERA
A68: 3 | B68: Descargado | C68: 410/2019 | D68: Ulgo | E68: 43481 | F68: =VLOOKUP($C68,CARPETAS!$C$5:$L$2388,2,FALSE) -> BRB006 | G68: =VLOOKUP($C68,CARPETAS!$C$5:$L$2388,9,FALSE) -> 134.10.38 | H68: =VLOOKUP($C68,CARPETAS!$C$5:$L$2388,5,FALSE) -> Silvio | I68: =E68+2 -> 43483 | J68: =VLOOKUP($C68,CARPETAS!$C$5:$L$2388,4,FALSE) -> Rivera | L68: =I68+1 -> 43484 | M68: =IF(E68<>"",L68-E68,"-") -> 3 | N68: 900 | O68: UB 004 | P68: 899 | Q68: 3396 | R68: MLB 5744 | S68: MKN 4574 | T68: M.A LLEGA 19/01 // DESCARGA 21/01 // STATUS ERA FRONTERA
A69: 3 | B69: Descargado | C69: 409/2019 | D69: Corupá | E69: 43482 | F69: =VLOOKUP($C69,CARPETAS!$C$5:$L$2388,2,FALSE) -> BRB005 | G69: =VLOOKUP($C69,CARPETAS!$C$5:$L$2388,9,FALSE) -> 134.08.43 | H69: =VLOOKUP($C69,CARPETAS!$C$5:$L$2388,5,FALSE) -> Transzanini | I69: 43486 | J69: =VLOOKUP($C69,CARPETAS!$C$5:$L$2388,4,FALSE) -> Rivera | L69: =I69+1 -> 43487 | M69: =IF(E69<>"",L69-E69,"-") -> 5 | N69: 900 | O69: CP 007 | P69: 900 | Q69: 558 | R69: MGK 9855 | S69: MHX 0195 | T69: M.A CAMION CON PALLETS EN MAL ESTADO Y FRUTA CON COLOR EN VARIOS PALLETS // M.A LLEGA A LAS 5HS STATUS ERA FRONTERA
A70: 3 | B70: Descargado | C70: 409/2019 | D70: Corupá | E70: 43483 | F70: =VLOOKUP($C70,CARPETAS!$C$5:$L$2388,2,FALSE) -> BRB005 | G70: =VLOOKUP($C70,CARPETAS!$C$5:$L$2388,9,FALSE) -> 134.08.43 | H70: =VLOOKUP($C70,CARPETAS!$C$5:$L$2388,5,FALSE) -> Transzanini | I70: 43486 | J70: =VLOOKUP($C70,CARPETAS!$C$5:$L$2388,4,FALSE) -> Rivera | L70: =I70+1+1 -> 43488 | M70: =IF(E70<>"",L70-E70,"-") -> 5 | N70: 900 | O70: CP 008 | P70: 901 | Q70: 560 | R70: EOE 2456 | S70: EOE 2444 | T70: P.C. DESCARGO 23/01/19 ////
A71: 3 | B71: Descargado | C71: 409/2019 | D71: Gilson | E71: 43482 | F71: =VLOOKUP($C71,CARPETAS!$C$5:$L$2388,2,FALSE) -> BRB005 | G71: =VLOOKUP($C71,CARPETAS!$C$5:$L$2388,9,FALSE) -> 134.08.43 | H71: =VLOOKUP($C71,CARPETAS!$C$5:$L$2388,5,FALSE) -> Transzanini | I71: 43486 | J71: =VLOOKUP($C71,CARPETAS!$C$5:$L$2388,4,FALSE) -> Rivera | L71: =I71+1 -> 43487 | M71: =IF(E71<>"",L71-E71,"-") -> 5 | N71: 900 | O71: GT 004 | P71: 900 | Q71: 552 | R71: FFW 3459 | S71: MKM 3904 | T71: M.A LLEGA A LAS 5HS STATUS ERA FRONTERA
A72: 4 | B72: Descargado | C72: 409/2019 | D72: Claudia | E72: 43487 | F72: =VLOOKUP($C72,CARPETAS!$C$5:$L$2388,2,FALSE) -> BRB005 | G72: =VLOOKUP($C72,CARPETAS!$C$5:$L$2388,9,FALSE) -> 134.08.43 | H72: =VLOOKUP($C72,CARPETAS!$C$5:$L$2388,5,FALSE) -> Transzanini | I72: 43489 | J72: =VLOOKUP($C72,CARPETAS!$C$5:$L$2388,4,FALSE) -> Rivera | L72: 43490 | M72: =IF(E72<>"",L72-E72,"-") -> 3 | N72: 900 | O72: CH 010 | P72: 900 | Q72: 566 | R72: MMH 8790 | S72: MHW 7826
A73: 4 | B73: Descargado | C73: 410/2019 | D73: Claudia | E73: 43488 | F73: =VLOOKUP($C73,CARPETAS!$C$5:$L$2388,2,FALSE) -> BRB006 | G73: =VLOOKUP($C73,CARPETAS!$C$5:$L$2388,9,FALSE) -> 134.10.38 | H73: =VLOOKUP($C73,CARPETAS!$C$5:$L$2388,5,FALSE) -> Silvio | I73: 43489 | J73: =VLOOKUP($C73,CARPETAS!$C$5:$L$2388,4,FALSE) -> Rivera | L73: =I73+1 -> 43490 | M73: =IF(E73<>"",L73-E73,"-") -> 2 | N73: 900 | O73: CH 011 | P73: 901 | Q73: 3401 | R73: FXA 1048 | S73: HRS 5249 | T73: M.A FRUTA CON TEMPERATURA VARIADA
A74: 4 | B74: Descargado | C74: 407/2019 | D74: Corupá | E74: 43488 | F74: =VLOOKUP($C74,CARPETAS!$C$5:$L$2388,2,FALSE) -> BRB003 | G74: =VLOOKUP($C74,CARPETAS!$C$5:$L$2388,9,FALSE) -> 134.06.39 | H74: =VLOOKUP($C74,CARPETAS!$C$5:$L$2388,5,FALSE) -> Cmcn | I74: 43490 | J74: =VLOOKUP($C74,CARPETAS!$C$5:$L$2388,4,FALSE) -> Rivera | L74: =I74+1 -> 43491 | M74: =IF(E74<>"",L74-E74,"-") -> 3 | N74: 900 | O74: CP 009 | P74: 901 | Q74: 530 | R74: MKJ 5565 | S74: MCG 3843
A75: 4 | B75: Descargado | C75: 409/2019 | D75: Claudia | E75: 43489 | F75: =VLOOKUP($C75,CARPETAS!$C$5:$L$2388,2,FALSE) -> BRB005 | G75: =VLOOKUP($C75,CARPETAS!$C$5:$L$2388,9,FALSE) -> 134.08.43 | H75: =VLOOKUP($C75,CARPETAS!$C$5:$L$2388,5,FALSE) -> Transzanini | I75: 43490 | J75: =VLOOKUP($C75,CARPETAS!$C$5:$L$2388,4,FALSE) -> Rivera | L75: =I75+1 -> 43491 | M75: =IF(E75<>"",L75-E75,"-") -> 2 | N75: 900 | O75: CH 012 | P75: 901 | Q75: 570 | R75: EOE 2331 | S75: ARI 8929
A76: 4 | B76: Descargado | C76: 409/2019 | D76: Corupá | E76: 43487 | F76: =VLOOKUP($C76,CARPETAS!$C$5:$L$2388,2,FALSE) -> BRB005 | G76: =VLOOKUP($C76,CARPETAS!$C$5:$L$2388,9,FALSE) -> 134.08.43 | H76: =VLOOKUP($C76,CARPETAS!$C$5:$L$2388,5,FALSE) -> Transzanini | I76: 43493 | J76: =VLOOKUP($C76,CARPETAS!$C$5:$L$2388,4,FALSE) -> Rivera | L76: =I76+1 -> 43494 | M76: =IF(E76<>"",L76-E76,"-") -> 7 | N76: 900 | O76: CP010 | P76: 901 | Q76: 567 | R76: OKG 6076 | S76: MLO 8857 | T76: TZ 28/01- camara desligada
A77: 4 | B77: Descargado | C77: 410/2019 | D77: Corupá | E77: 43490 | F77: =VLOOKUP($C77,CARPETAS!$C$5:$L$2388,2,FALSE) -> BRB006 | G77: =VLOOKUP($C77,CARPETAS!$C$5:$L$2388,9,FALSE) -> 134.10.38 | H77: =VLOOKUP($C77,CARPETAS!$C$5:$L$2388,5,FALSE) -> Silvio | I77: 43493 | J77: =VLOOKUP($C77,CARPETAS!$C$5:$L$2388,4,FALSE) -> Rivera | L77: =I77+1+1 -> 43495 | M77: =IF(E77<>"",L77-E77,"-") -> 5 | N77: 900 | O77: CP 011 | P77: 900 | Q77: 3405 | R77: ASN 3591 | S77: ASA 4580 | T77: M.A DESCARGA EN M.MODELO 30/01 // M.A LLEGO 29/01 DESCARGA 30/01
A78: 4 | B78: Descargado | C78: 411/2019 | D78: Gilson | E78: 43489 | F78: =VLOOKUP($C78,CARPETAS!$C$5:$L$2388,2,FALSE) -> BRB007 | G78: =VLOOKUP($C78,CARPETAS!$C$5:$L$2388,9,FALSE) -> 134.16.99 | H78: =VLOOKUP($C78,CARPETAS!$C$5:$L$2388,5,FALSE) -> Zanini | I78: 43493 | J78: =VLOOKUP($C78,CARPETAS!$C$5:$L$2388,4,FALSE) -> Rivera | L78: =I78+1 -> 43494 | M78: =IF(E78<>"",L78-E78,"-") -> 5 | N78: 936 | O78: GT 005 | P78: 936 | Q78: 572 | R78: FEJ 8190 | S78: FEJ 8236 | T78: TZ 28/01- camara desligada
A79: 4 | B79: Descargado | C79: 411/2019 | D79: Gilson | E79: 43490 | F79: =VLOOKUP($C79,CARPETAS!$C$5:$L$2388,2,FALSE) -> BRB007 | G79: =VLOOKUP($C79,CARPETAS!$C$5:$L$2388,9,FALSE) -> 134.16.99 | H79: =VLOOKUP($C79,CARPETAS!$C$5:$L$2388,5,FALSE) -> Zanini | I79: 43493 | J79: =VLOOKUP($C79,CARPETAS!$C$5:$L$2388,4,FALSE) -> Rivera | L79: =I79+1 -> 43494 | M79: =IF(E79<>"",L79-E79,"-") -> 4 | N79: 936 | O79: GT 006 | P79: 936 | Q79: 573 | R79: MIJ 9299 | S79: MLX 3078 | T79: TZ 28/01- camara desligada
A80: 4 | B80: Descargado | C80: 410/2019 | D80: Claudia | E80: 43490 | F80: =VLOOKUP($C80,CARPETAS!$C$5:$L$2388,2,FALSE) -> BRB006 | G80: =VLOOKUP($C80,CARPETAS!$C$5:$L$2388,9,FALSE) -> 134.10.38 | H80: =VLOOKUP($C80,CARPETAS!$C$5:$L$2388,5,FALSE) -> Silvio | I80: 43493 | J80: =VLOOKUP($C80,CARPETAS!$C$5:$L$2388,4,FALSE) -> Rivera | L80: =I80+1 -> 43494 | M80: =IF(E80<>"",L80-E80,"-") -> 4 | N80: 900 | O80: CH013 | P80: 900 | Q80: 3407 | R80: QJO 1359 | S80: QJM 9087 | T80: TZ 28/01- camara desligada
A81: 4 | B81: Descargado | C81: 410/2019 | D81: Jaime | E81: 43489 | F81: =VLOOKUP($C81,CARPETAS!$C$5:$L$2388,2,FALSE) -> BRB006 | G81: =VLOOKUP($C81,CARPETAS!$C$5:$L$2388,9,FALSE) -> 134.10.38 | H81: =VLOOKUP($C81,CARPETAS!$C$5:$L$2388,5,FALSE) -> Silvio | I81: 43493 | J81: =VLOOKUP($C81,CARPETAS!$C$5:$L$2388,4,FALSE) -> Rivera | L81: =I81+1+1 -> 43495 | M81: =IF(E81<>"",L81-E81,"-") -> 6 | N81: 900 | O81: JM 005 | P81: 900 | Q81: 3403 | R81: QIZ 5300 | S81: MHM 6777 | T81: P.C. DESCARGO EN R. NATURAL 30/01/19 ////M.A DESCARGA EN R.NATURAL 30/01 // M.A LLEGO 29/01 DESCARGA 30/01
A82: 4 | B82: Descargado | C82: 410/2019 | D82: Valdemar | E82: 43488 | F82: =VLOOKUP($C82,CARPETAS!$C$5:$L$2388,2,FALSE) -> BRB006 | G82: =VLOOKUP($C82,CARPETAS!$C$5:$L$2388,9,FALSE) -> 134.10.38 | H82: =VLOOKUP($C82,CARPETAS!$C$5:$L$2388,5,FALSE) -> Silvio | I82: 43493 | J82: =VLOOKUP($C82,CARPETAS!$C$5:$L$2388,4,FALSE) -> Rivera | L82: =I82+1+1 -> 43495 | M82: =IF(E82<>"",L82-E82,"-") -> 7 | N82: 900 | O82: VH 007 | P82: 900 | Q82: 3402 | R82: MMD 2437 | S82: MMH 1697 | T82: P.C. DESCARGO EN R. NATURAL 30/01/19 ////M.A DESCARGA EN R.NATURAL 30/01 // M.A LLEGO 29/01 DESCARGA 30/01
A83: 5 | B83: Descargado | C83: 411/2019 | D83: Valdemar | E83: 43492 | F83: =VLOOKUP($C83,CARPETAS!$C$5:$L$2388,2,FALSE) -> BRB007 | G83: =VLOOKUP($C83,CARPETAS!$C$5:$L$2388,9,FALSE) -> 134.16.99 | H83: =VLOOKUP($C83,CARPETAS!$C$5:$L$2388,5,FALSE) -> Zanini | I83: =E83+2 -> 43494 | J83: =VLOOKUP($C83,CARPETAS!$C$5:$L$2388,4,FALSE) -> Rivera | L83: =I83+1 -> 43495 | M83: =IF(E83<>"",L83-E83,"-") -> 3 | N83: 936 | O83: VH 008 | P83: 936 | Q83: 574 | R83: OKG 6086 | S83: MLP 8427 | T83: P.C. DESCARGO EN R. NATURAL 30/01/19 ////M.A DESCARGA EN R.NATURAL 30/01 // M.A LLEGO 29/01 DESCARGA 30/01
A84: 5 | B84: Descargado | C84: 413/2019 | D84: Claudia | E84: 43493 | F84: =VLOOKUP($C84,CARPETAS!$C$5:$L$2388,2,FALSE) -> BRB009 | G84: =VLOOKUP($C84,CARPETAS!$C$5:$L$2388,9,FALSE) -> 134.18.86 | H84: =VLOOKUP($C84,CARPETAS!$C$5:$L$2388,5,FALSE) -> CMCN | I84: =E84+2 -> 43495 | J84: =VLOOKUP($C84,CARPETAS!$C$5:$L$2388,4,FALSE) -> Rivera | L84: =I84+1+1 -> 43497 | M84: =IF(E84<>"",L84-E84,"-") -> 4 | N84: 936 | O84: CH 014 | P84: 936 | Q84: 531 | R84: DPF 9633 | S84: HRS 8321
A85: 5 | B85: Descargado | C85: 412/2019 | D85: Jaime | E85: 43494 | F85: =VLOOKUP($C85,CARPETAS!$C$5:$L$2388,2,FALSE) -> BRB008 | G85: =VLOOKUP($C85,CARPETAS!$C$5:$L$2388,9,FALSE) -> 134.18.85 | H85: =VLOOKUP($C85,CARPETAS!$C$5:$L$2388,5,FALSE) -> Silvio | I85: 43495 | J85: =VLOOKUP($C85,CARPETAS!$C$5:$L$2388,4,FALSE) -> Rivera | L85: =I85+1+1 -> 43497 | M85: =IF(E85<>"",L85-E85,"-") -> 3 | N85: 936 | O85: JM 006 | P85: 937 | Q85: 3410 | R85: QIU 6129 | S85: MJI 6107
A86: 5 | B86: Descargado | C86: 412/2019 | D86: Valdemar | E86: 43493 | F86: =VLOOKUP($C86,CARPETAS!$C$5:$L$2388,2,FALSE) -> BRB008 | G86: =VLOOKUP($C86,CARPETAS!$C$5:$L$2388,9,FALSE) -> 134.18.85 | H86: =VLOOKUP($C86,CARPETAS!$C$5:$L$2388,5,FALSE) -> Silvio | I86: =E86+2 -> 43495 | J86: =VLOOKUP($C86,CARPETAS!$C$5:$L$2388,4,FALSE) -> Rivera | L86: =I86+1+1 -> 43497 | M86: =IF(E86<>"",L86-E86,"-") -> 4 | N86: 936 | O86: VH 009 | P86: 936 | Q86: 3408 | R86: AWA 3514 | S86: MLD 7421 | T86: DM camion vino con pencas color 2.3.4.5.6 y de pintitas con palet a mas de 20 grados de pulpa y un pale caido
A87: 5 | B87: Descargado | C87: 412/2019 | D87: Claudia | E87: 43496 | F87: =VLOOKUP($C87,CARPETAS!$C$5:$L$2388,2,FALSE) -> BRB008 | G87: =VLOOKUP($C87,CARPETAS!$C$5:$L$2388,9,FALSE) -> 134.18.85 | H87: =VLOOKUP($C87,CARPETAS!$C$5:$L$2388,5,FALSE) -> Silvio | I87: 43497 | J87: =VLOOKUP($C87,CARPETAS!$C$5:$L$2388,4,FALSE) -> Rivera | L87: =I87+1 -> 43498 | M87: =IF(E87<>"",L87-E87,"-") -> 2 | N87: 936 | O87: CH 015 | P87: 936 | Q87: 3411 | R87: MJG 6640 | S87: MBM 4192
A88: 5 | B88: Descargado | C88: 412/2019 | D88: Corupá | E88: 43495 | F88: =VLOOKUP($C88,CARPETAS!$C$5:$L$2388,2,FALSE) -> BRB008 | G88: =VLOOKUP($C88,CARPETAS!$C$5:$L$2388,9,FALSE) -> 134.18.85 | H88: =VLOOKUP($C88,CARPETAS!$C$5:$L$2388,5,FALSE) -> Silvio | I88: 43500 | J88: =VLOOKUP($C88,CARPETAS!$C$5:$L$2388,4,FALSE) -> Rivera | L88: =I88+1 -> 43501 | M88: =IF(E88<>"",L88-E88,"-") -> 6 | N88: 936 | O88: CP 012 | P88: 937 | Q88: 3409 | R88: MKV 0568 | S88: MJV 2237 | T88: DM camion vino con pencas color 4 y 5 en varios palets se sacaron fotos y se le mostro al chofer
A89: 5 | B89: Descargado | C89: 414/2019 | D89: Corupá | E89: 43496 | F89: =VLOOKUP($C89,CARPETAS!$C$5:$L$2388,2,FALSE) -> BRB010 | G89: =VLOOKUP($C89,CARPETAS!$C$5:$L$2388,9,FALSE) -> 134.21.41 | H89: =VLOOKUP($C89,CARPETAS!$C$5:$L$2388,5,FALSE) -> Silvio | I89: 43500 | J89: =VLOOKUP($C89,CARPETAS!$C$5:$L$2388,4,FALSE) -> Rivera | L89: =I89+1 -> 43501 | M89: =IF(E89<>"",L89-E89,"-") -> 5 | N89: 936 | O89: CP 013 | P89: 937 | Q89: 3418 | R89: MGB 5290 | S89: QHN 3333 | T89: DM camion vino con pencas color 4 y 5 en varios palets se sacaron fotos y se le mostro al chofer
A90: 5 | B90: Descargado | C90: 411/2019 | D90: Claudia | E90: 43495 | F90: =VLOOKUP($C90,CARPETAS!$C$5:$L$2388,2,FALSE) -> BRB007 | G90: =VLOOKUP($C90,CARPETAS!$C$5:$L$2388,9,FALSE) -> 134.16.99 | H90: =VLOOKUP($C90,CARPETAS!$C$5:$L$2388,5,FALSE) -> Zanini | I90: 43500 | J90: =VLOOKUP($C90,CARPETAS!$C$5:$L$2388,4,FALSE) -> Rivera | L90: =I90+1 -> 43501 | M90: =IF(E90<>"",L90-E90,"-") -> 6 | N90: 936 | O90: CH 016 | P90: 936 | Q90: 575 | R90: MHJ 4178 | S90: MIH 5927 | T90: TZ 01/02 - problema mecanico
A91: 5 | B91: Descargado | C91: 416/2019 | D91: Gilson | E91: 43497 | F91: =VLOOKUP($C91,CARPETAS!$C$5:$L$2388,2,FALSE) -> BRB012 | G91: =VLOOKUP($C91,CARPETAS!$C$5:$L$2388,9,FALSE) -> 134.21.43 | H91: =VLOOKUP($C91,CARPETAS!$C$5:$L$2388,5,FALSE) -> Zanini | I91: 43500 | J91: =VLOOKUP($C91,CARPETAS!$C$5:$L$2388,4,FALSE) -> Rivera | L91: =I91+1 -> 43501 | M91: =IF(E91<>"",L91-E91,"-") -> 4 | N91: 936 | O91: GT 007 | Q91: 582 | R91: EOE 2476 | S91: FFW 3337 | T91: M.A camion vino sentido y casi todo el camion con fruta madura
A92: 6 | B92: Descargado | C92: 414/2019 | D92: Claudia | E92: 43500 | F92: =VLOOKUP($C92,CARPETAS!$C$5:$L$2388,2,FALSE) -> BRB010 | G92: =VLOOKUP($C92,CARPETAS!$C$5:$L$2388,9,FALSE) -> 134.21.41 | H92: =VLOOKUP($C92,CARPETAS!$C$5:$L$2388,5,FALSE) -> Silvio | I92: 43500 | J92: =VLOOKUP($C92,CARPETAS!$C$5:$L$2388,4,FALSE) -> Rivera | L92: =I92+1 -> 43501 | M92: =IF(E92<>"",L92-E92,"-") -> 1 | N92: 936 | O92: CH 017 | Q92: 3417 | R92: MKO 7300 | S92: MKQ 7464
A93: 5 | B93: Descargado | C93: 416/2019 | D93: Gilson | E93: 43496 | F93: =VLOOKUP($C93,CARPETAS!$C$5:$L$2388,2,FALSE) -> BRB012 | G93: =VLOOKUP($C93,CARPETAS!$C$5:$L$2388,9,FALSE) -> 134.21.43 | H93: =VLOOKUP($C93,CARPETAS!$C$5:$L$2388,5,FALSE) -> Zanini | I93: 43501 | J93: =VLOOKUP($C93,CARPETAS!$C$5:$L$2388,4,FALSE) -> Rivera | L93: =I93+1 -> 43502 | M93: =IF(E93<>"",L93-E93,"-") -> 6 | N93: 936 | O93: GT 008 | P93: 938 | Q93: 578 | R93: MIQ 4650 | S93: QHK 7670 | T93: P.C. DESCARGO EN R. NATURAL 06/02/19 ////DM descarga r natural 6/2
A94: 5 | B94: Descargado | C94: 414/2019 | D94: Jaime | E94: 43496 | F94: =VLOOKUP($C94,CARPETAS!$C$5:$L$2388,2,FALSE) -> BRB010 | G94: =VLOOKUP($C94,CARPETAS!$C$5:$L$2388,9,FALSE) -> 134.21.41 | H94: =VLOOKUP($C94,CARPETAS!$C$5:$L$2388,5,FALSE) -> Silvio | I94: 43501 | J94: =VLOOKUP($C94,CARPETAS!$C$5:$L$2388,4,FALSE) -> Rivera | L94: =I94+1 -> 43502 | M94: =IF(E94<>"",L94-E94,"-") -> 6 | N94: 936 | O94: JM 007 | P94: 937 | Q94: 3415 | R94: IXY 3608 | S94: MLT 5777 | T94: P.C. DESCARGO EN R. NATURAL 06/02/19 ////DM descarga r natural 6/2
A95: 6 | B95: Descargado | C95: 416/2019 | D95: Valdemar | E95: 43500 | F95: =VLOOKUP($C95,CARPETAS!$C$5:$L$2388,2,FALSE) -> BRB012 | G95: =VLOOKUP($C95,CARPETAS!$C$5:$L$2388,9,FALSE) -> 134.21.43 | H95: =VLOOKUP($C95,CARPETAS!$C$5:$L$2388,5,FALSE) -> Zanini | I95: 43501 | J95: =VLOOKUP($C95,CARPETAS!$C$5:$L$2388,4,FALSE) -> Rivera | L95: =I95+1 -> 43502 | M95: =IF(E95<>"",L95-E95,"-") -> 2 | N95: 936 | O95: VH 010 | P95: 936 | Q95: 583 | R95: FFW 3459 | S95: MKM 3904 | T95: M.A camion con fruta color (3,4,5) se le saco foto correspondiente y se le mostro al motorista
A96: 6 | B96: Descargado | C96: 416/2019 | D96: Jaime | E96: 43500 | F96: =VLOOKUP($C96,CARPETAS!$C$5:$L$2388,2,FALSE) -> BRB012 | G96: =VLOOKUP($C96,CARPETAS!$C$5:$L$2388,9,FALSE) -> 134.21.43 | H96: =VLOOKUP($C96,CARPETAS!$C$5:$L$2388,5,FALSE) -> Zanini | I96: =E96+2 -> 43502 | J96: =VLOOKUP($C96,CARPETAS!$C$5:$L$2388,4,FALSE) -> Rivera | L96: =I96+1 -> 43503 | M96: =IF(E96<>"",L96-E96,"-") -> 3 | N96: 936 | O96: JM 008 | P96: 936 | Q96: 584 | R96: EOE2321 | S96: MHQ 1661
A97: 6 | B97: Descargado | C97: 414/2019 | D97: Corupá | E97: 43501 | F97: =VLOOKUP($C97,CARPETAS!$C$5:$L$2388,2,FALSE) -> BRB010 | G97: =VLOOKUP($C97,CARPETAS!$C$5:$L$2388,9,FALSE) -> 134.21.41 | H97: =VLOOKUP($C97,CARPETAS!$C$5:$L$2388,5,FALSE) -> Silvio | I97: =E97+2 -> 43503 | J97: =VLOOKUP($C97,CARPETAS!$C$5:$L$2388,4,FALSE) -> Rivera | L97: =I97+1 -> 43504 | M97: =IF(E97<>"",L97-E97,"-") -> 3 | N97: 936 | O97: CP 014 | P97: 936 | Q97: 3419 | R97: MKT 4555 | S97: QIR 4668 | T97: M.A. DESCARGO EN SOTANO 08/02/19 ////
A98: 6 | B98: Descargado | C98: 416/2019 | D98: Corupá | E98: 43502 | F98: =VLOOKUP($C98,CARPETAS!$C$5:$L$2388,2,FALSE) -> BRB012 | G98: =VLOOKUP($C98,CARPETAS!$C$5:$L$2388,9,FALSE) -> 134.21.43 | H98: =VLOOKUP($C98,CARPETAS!$C$5:$L$2388,5,FALSE) -> Zanini | I98: 43503 | J98: =VLOOKUP($C98,CARPETAS!$C$5:$L$2388,4,FALSE) -> Rivera | L98: =I98+1 -> 43504 | M98: =IF(E98<>"",L98-E98,"-") -> 2 | N98: 936 | O98: CP 015 | P98: 937 | Q98: 585 | R98: QJV 4800 | S98: QJM 1036 | T98: M.A. DESCARGO EN SOTANO 08/02/19 ////
A99: 6 | B99: Descargado | C99: 415/2019 | D99: Claudia | E99: 43501 | F99: =VLOOKUP($C99,CARPETAS!$C$5:$L$2388,2,FALSE) -> BRB011 | G99: =VLOOKUP($C99,CARPETAS!$C$5:$L$2388,9,FALSE) -> 134.21.42 | H99: =VLOOKUP($C99,CARPETAS!$C$5:$L$2388,5,FALSE) -> Osveli | I99: =E99+2 -> 43503 | J99: =VLOOKUP($C99,CARPETAS!$C$5:$L$2388,4,FALSE) -> Rivera | L99: =I99+1 -> 43504 | M99: =IF(E99<>"",L99-E99,"-") -> 3 | N99: 936 | O99: CH 018 | P99: 937 | Q99: 20 | R99: MAN 4773 | S99: IIT 9127 | T99: M.A. DESCARGO EN SOTANO 08/02/19 ////
A100: 6 | B100: Descargado | C100: 413/2019 | D100: Gilson | E100: 43501 | F100: =VLOOKUP($C100,CARPETAS!$C$5:$L$2388,2,FALSE) -> BRB009 | G100: =VLOOKUP($C100,CARPETAS!$C$5:$L$2388,9,FALSE) -> 134.18.86 | H100: =VLOOKUP($C100,CARPETAS!$C$5:$L$2388,5,FALSE) -> CMCN | I100: =E100+2 -> 43503 | J100: =VLOOKUP($C100,CARPETAS!$C$5:$L$2388,4,FALSE) -> Rivera | L100: =I100+1 -> 43504 | M100: =IF(E100<>"",L100-E100,"-") -> 3 | N100: 936 | O100: GT 009 | P100: 937 | Q100: 577 | R100: MIU 8665 | S100: ILO 1318 | T100: M.A. DESCARGO EN SOTANO 08/02/19 ////
A101: 6 | B101: Descargado | C101: 416/2019 | D101: Corupá | E101: 43503 | F101: =VLOOKUP($C101,CARPETAS!$C$5:$L$2388,2,FALSE) -> BRB012 | G101: =VLOOKUP($C101,CARPETAS!$C$5:$L$2388,9,FALSE) -> 134.21.43 | H101: =VLOOKUP($C101,CARPETAS!$C$5:$L$2388,5,FALSE) -> Zanini | I101: 43504 | J101: =VLOOKUP($C101,CARPETAS!$C$5:$L$2388,4,FALSE) -> Rivera | L101: =I101+1 -> 43505 | M101: =IF(E101<>"",L101-E101,"-") -> 2 | N101: 936 | O101: CP 016 | P101: 937 | Q101: 588 | R101: MJO 4528 | S101: QHF 0778
A102: 6 | B102: Descargado | C102: 414/2019 | D102: Claudia | E102: 43502 | F102: =VLOOKUP($C102,CARPETAS!$C$5:$L$2388,2,FALSE) -> BRB010 | G102: =VLOOKUP($C102,CARPETAS!$C$5:$L$2388,9,FALSE) -> 134.21.41 | H102: =VLOOKUP($C102,CARPETAS!$C$5:$L$2388,5,FALSE) -> Silvio | I102: =E102+2 -> 43504 | J102: =VLOOKUP($C102,CARPETAS!$C$5:$L$2388,4,FALSE) -> Rivera | L102: =I102+1 -> 43505 | M102: =IF(E102<>"",L102-E102,"-") -> 3 | N102: 936 | O102: CH 019 | P102: 936 | Q102: 3422 | R102: FXA 1048 | S102: HRS 5249
A103: 6 | B103: Descargado | C103: 414/2019 | D103: Corupá | E103: 43504 | F103: =VLOOKUP($C103,CARPETAS!$C$5:$L$2388,2,FALSE) -> BRB010 | G103: =VLOOKUP($C103,CARPETAS!$C$5:$L$2388,9,FALSE) -> 134.21.41 | H103: =VLOOKUP($C103,CARPETAS!$C$5:$L$2388,5,FALSE) -> Silvio | I103: 43507 | J103: =VLOOKUP($C103,CARPETAS!$C$5:$L$2388,4,FALSE) -> Rivera | L103: =I103+1 -> 43508 | M103: =IF(E103<>"",L103-E103,"-") -> 4 | N103: 936 | O103: CP 017 | P103: 937 | Q103: 3427 | R103: QJR 9666 | S103: QJO 8666
A104: 6 | B104: Descargado | C104: 419/2019 | D104: Claudia | E104: 43504 | F104: =VLOOKUP($C104,CARPETAS!$C$5:$L$2388,2,FALSE) -> BRB015 | G104: =VLOOKUP($C104,CARPETAS!$C$5:$L$2388,9,FALSE) -> 134.21.03 | H104: =VLOOKUP($C104,CARPETAS!$C$5:$L$2388,5,FALSE) -> Zanini | I104: 43507 | J104: =VLOOKUP($C104,CARPETAS!$C$5:$L$2388,4,FALSE) -> Rivera | L104: =I104+1 -> 43508 | M104: =IF(E104<>"",L104-E104,"-") -> 4 | N104: 936 | O104: CH 020 | P104: 937 | Q104: 591 | R104: FJX 1877 | S104: EOE 2359
A105: 6 | B105: Descargado | C105: 416/2019 | D105: Jaime | E105: 43503 | F105: =VLOOKUP($C105,CARPETAS!$C$5:$L$2388,2,FALSE) -> BRB012 | G105: =VLOOKUP($C105,CARPETAS!$C$5:$L$2388,9,FALSE) -> 134.21.43 | H105: =VLOOKUP($C105,CARPETAS!$C$5:$L$2388,5,FALSE) -> Zanini | I105: 43507 | J105: =VLOOKUP($C105,CARPETAS!$C$5:$L$2388,4,FALSE) -> Rivera | L105: =I105+1 -> 43508 | M105: =IF(E105<>"",L105-E105,"-") -> 5 | N105: 936 | O105: JM 009 | P105: 937 | Q105: 589 | R105: FFW 3347 | S105: MLA 7853 | T105: M.A descarga 13/02 vino con muchos pallets torcidos
A106: 6 | B106: Descargado | C106: 417/2019 | D106: Gilson | E106: 43503 | F106: =VLOOKUP($C106,CARPETAS!$C$5:$L$2388,2,FALSE) -> BRB013 | G106: =VLOOKUP($C106,CARPETAS!$C$5:$L$2388,9,FALSE) -> 134.21.01 | H106: =VLOOKUP($C106,CARPETAS!$C$5:$L$2388,5,FALSE) -> CMCN | I106: 43507 | J106: =VLOOKUP($C106,CARPETAS!$C$5:$L$2388,4,FALSE) -> Rivera | L106: =I106+1 -> 43508 | M106: =IF(E106<>"",L106-E106,"-") -> 5 | N106: 936 | O106: GT 010 | P106: 936 | Q106: 579 | R106: MKJ 5565 | S106: MCG 3843
A107: 6 | B107: Descargado | C107: 416/2019 | D107: Claudia | E107: 43503 | F107: =VLOOKUP($C107,CARPETAS!$C$5:$L$2388,2,FALSE) -> BRB012 | G107: =VLOOKUP($C107,CARPETAS!$C$5:$L$2388,9,FALSE) -> 134.21.43 | H107: =VLOOKUP($C107,CARPETAS!$C$5:$L$2388,5,FALSE) -> Zanini | I107: 43508 | J107: =VLOOKUP($C107,CARPETAS!$C$5:$L$2388,4,FALSE) -> Rivera | L107: =I107+1 -> 43509 | M107: =IF(E107<>"",L107-E107,"-") -> 6 | N107: 936 | O107: CH 021 | P107: 937 | Q107: 587 | R107: EOE 2475 | S107: MJY 7644
...

Sheet Carpetas
B2: CARPETAS DE IMPORTACIÓN - CONTROL DE CARGAS y SALDOS
B4: Fecha | C4: Fatura | D4: Carpeta | E4: Export | F4: Frontera | G4: Transp. | H4: Qtde | I4: Cargado | J4: Saldo | K4: Afidi | L4: DUA
B5: 43838 | C5: 006/2020 | D5: BRB004 | E5: Etimex | F5: Rio Branco | G5: Silvio | H5: 4680 | I5: =SUMIF(Cargas!$C$5:$C$1652,C5,Cargas!$N$5:$N$1652) -> 4680 | J5: =IF(ABS(H5-I5)<20,0,H5-I5) -> 0 | K5: 136.37.80 | L5: 6527
B6: 43845 | C6: 008/2020 | D6: BRB007 | E6: Etimex | F6: Rio Branco | G6: Silvio | H6: 4680 | I6: =SUMIF(Cargas!$C$5:$C$1652,C6,Cargas!$N$5:$N$1652) -> 4680 | J6: =IF(ABS(H6-I6)<20,0,H6-I6) -> 0 | K6: 136.42.77 | L6: 11510
B7: 43859 | C7: 013/2020 | D7: BRB011 | E7: Etimex | F7: Rio Branco | G7: Silvio | H7: 5616 | I7: =SUMIF(Cargas!$C$5:$C$1652,C7,Cargas!$N$5:$N$1652) -> 5616 | J7: =IF(ABS(H7-I7)<20,0,H7-I7) -> 0 | K7: 136.51.05 | L7: 22600
B8: 43467 | C8: 405/2019 | D8: BRB001 | E8: Joana | F8: Rivera | G8: Transzanini | H8: 6300 | I8: =SUMIF(Cargas!$C$5:$C$1652,C8,Cargas!$N$5:$N$1652) -> 6300 | J8: =IF(ABS(H8-I8)<20,0,H8-I8) -> 0 | K8: 134.03.89 | L8: 1843
B9: 43497 | C9: 406/2019 | D9: BRB002 | E9: Joana | F9: Rivera | G9: Silvio | H9: 7200 | I9: =SUMIF(Cargas!$C$5:$C$1652,C9,Cargas!$N$5:$N$1652) -> 7200 | J9: =IF(ABS(H9-I9)<20,0,H9-I9) -> 0 | K9: 134.03.90 | L9: 3609
B10: 43472 | C10: 407/2019 | D10: BRB003 | E10: Joana | F10: Rivera | G10: Cmcn | H10: 1800 | I10: =SUMIF(Cargas!$C$5:$C$1652,C10,Cargas!$N$5:$N$1652) -> 1800 | J10: =IF(ABS(H10-I10)<20,0,H10-I10) -> 0 | K10: 134.06.39 | L10: 6078
B11: 43475 | C11: 408/2019 | D11: BRB004 | E11: Joana | F11: Rivera | G11: Silvio | H11: 5400 | I11: =SUMIF(Cargas!$C$5:$C$1652,C11,Cargas!$N$5:$N$1652) -> 5400 | J11: =IF(ABS(H11-I11)<20,0,H11-I11) -> 0 | K11: 134.08.44 | L11: 7741
B12: 43475 | C12: 409/2019 | D12: BRB005 | E12: Joana | F12: Rivera | G12: Transzanini | H12: 5400 | I12: =SUMIF(Cargas!$C$5:$C$1652,C12,Cargas!$N$5:$N$1652) -> 5400 | J12: =IF(ABS(H12-I12)<20,0,H12-I12) -> 0 | K12: 134.08.43 | L12: 110005
B13: 43480 | C13: 410/2019 | D13: BRB006 | E13: Joana | F13: Rivera | G13: Silvio | H13: 7200 | I13: =SUMIF(Cargas!$C$5:$C$1652,C13,Cargas!$N$5:$N$1652) -> 7200 | J13: =IF(ABS(H13-I13)<20,0,H13-I13) -> 0 | K13: 134.10.38 | L13: 10395
B14: 43488 | C14: 411/2019 | D14: BRB007 | E14: Joana | F14: Rivera | G14: Zanini | H14: 3744 | I14: =SUMIF(Cargas!$C$5:$C$1652,C14,Cargas!$N$5:$N$1652) -> 3744 | J14: =IF(ABS(H14-I14)<20,0,H14-I14) -> 0 | K14: 134.16.99 | L14: 15329
B15: 43493 | C15: 412/2019 | D15: BRB008 | E15: Joana | F15: Rivera | G15: Silvio | H15: 3744 | I15: =SUMIF(Cargas!$C$5:$C$1652,C15,Cargas!$N$5:$N$1652) -> 3744 | J15: =IF(ABS(H15-I15)<20,0,H15-I15) -> 0 | K15: 134.18.85 | L15: 18261
B16: 43493 | C16: 413/2019 | D16: BRB009 | E16: Joana | F16: Rivera | G16: CMCN | H16: 1872 | I16: =SUMIF(Cargas!$C$5:$C$1652,C16,Cargas!$N$5:$N$1652) -> 1872 | J16: =IF(ABS(H16-I16)<20,0,H16-I16) -> 0 | K16: 134.18.86 | L16: 18226
... B104: 43781 | C104: 490/2019 | D104: BRE002 | E104: Joana | F104: Rivera | G104: Silvio | H104: 1250 | I104: =SUMIF(Cargas!$C$5:$C$1652,C104,Cargas!$N$5:$N$1652) -> 1250 | J104: =IF(ABS(H104-I104)<20,0,H104-I104) -> 0 | K104: 135.92.62 | L104: 202355
B105: 43904 | C105: 049/20 | D105: BRP007 | E105: Etimex | F105: Rio Branco | G105: Silvio | H105: 1000 | I105: =SUMIF(Cargas!$C$5:$C$1652,C105,Cargas!$N$5:$N$1652) -> 1000 | J105: =IF(ABS(H105-I105)<20,0,H105-I105) -> 0 | K105: 136.62.83 | L105: xx
B106: 43903 | C106: 050/20 | D106: BRB021 | E106: Etimex | F106: Rio Branco | G106: Silvio | H106: 7488 | I106: =SUMIF(Cargas!$C$5:$C$1652,C106,Cargas!$N$5:$N$1652) -> 7488 | J106: =IF(ABS(H106-I106)<20,0,H106-I106) -> 0 | K106: 1367846 | L106: 42973
B107: 43907 | C107: 055/20 | D107: BRB022 | E107: Etimex | F107: Rio Branco | G107: Silvio | H107: 7488 | I107: =SUMIF(Cargas!$C$5:$C$1652,C107,Cargas!$N$5:$N$1652) -> 7488 | J107: =IF(ABS(H107-I107)<20,0,H107-I107) -> 0 | K107: 136.80.95 | L107: 46164
B108: 43907 | C108: 056/20 | D108: BRB023 | E108: Etimex | F108: Rio Branco | G108: Zanini | H108: 3744 | I108: =SUMIF(Cargas!$C$5:$C$1652,C108,Cargas!$N$5:$N$1652) -> 3744 | J108: =IF(ABS(H108-I108)<20,0,H108-I108) -> 0 | K108: 136.80.96 | L108: 45581
B109: 43914 | C109: 060/20 | D109: BRP008 | E109: Etimex | F109: Rio Branco | G109: Silvio | H109: 1000 | I109: =SUMIF(Cargas!$C$5:$C$1652,C109,Cargas!$N$5:$N$1652) -> 1000 | J109: =IF(ABS(H109-I109)<20,0,H109-I109) -> 0 | K109: 136.62.83 | L109: xx
B110: 43915 | C110: 063/20 | D110: BRP009 | E110: Etimex | F110: Rio Branco | G110: Silvio | H110: 1000 | I110: =SUMIF(Cargas!$C$5:$C$1652,C110,Cargas!$N$5:$N$1652) -> 1000 | J110: =IF(ABS(H110-I110)<20,0,H110-I110) -> 0 | K110: 136.54.60 | L110: xx
B111: 43915 | C111: 064/20 | D111: BRB024 | E111: Etimex | F111: Rio Branco | G111: Silvio | H111: 7488 | I111: =SUMIF(Cargas!$C$5:$C$1652,C111,Cargas!$N$5:$N$1652) -> 7488 | J111: =IF(ABS(H111-I111)<20,0,H111-I111) -> 0 | K111: 136.85.90 | L111: 48621
B112: 43917 | C112: 065/20 | D112: BRB025 | E112: Etimex | F112: Rio Branco | G112: Zanini | H112: 5616 | I112: =SUMIF(Cargas!$C$5:$C$1652,C112,Cargas!$N$5:$N$1652) -> 5616 | J112: =IF(ABS(H112-I112)<20,0,H112-I112) -> 0 | K112: 136.85.91 | L112: 49751
B113: 43918 | C113: 069/20 | D113: BRP010 | E113: Etimex | F113: Rio Branco | G113: Silvio | H113: 1000 | I113: =SUMIF(Cargas!$C$5:$C$1652,C113,Cargas!$N$5:$N$1652) -> 1000 | J113: =IF(ABS(H113-I113)<20,0,H113-I113) -> 0 | K113: 136.78.87 | L113: 49710
B114: 43920 | C114: 071/20 | D114: BRB027 | E114: Etimex | F114: Rio Branco | G114: Silvio | H114: 7488 | I114: =SUMIF(Cargas!$C$5:$C$1652,C114,Cargas!$N$5:$N$1652) -> 7488 | J114: =IF(ABS(H114-I114)<20,0,H114-I114) -> 0 | K114: 136.87.60 | L114: 50964
B115: 43921 | C115: 072/20 | D115: BRP011 | E115: Etimex | F115: Rio Branco | G115: Silvio | H115: 1000 | I115: =SUMIF(Cargas!$C$5:$C$1652,C115,Cargas!$N$5:$N$1652) -> 1000 | J115: =IF(ABS(H115-I115)<20,0,H115-I115) -> 0 | K115: 136.75.81 | L115: xx
B116: 43922 | C116: 074/20 | D116: BRP012 | E116: Etimex | F116: Rio Branco | G116: Silvio | H116: 1000 | I116: =SUMIF(Cargas!$C$5:$C$1652,C116,Cargas!$N$5:$N$1652) -> 1000 | J116: =IF(ABS(H116-I116)<20,0,H116-I116) -> 0 | K116: 136.78.88 | L116: xx
B117: 43920 | C117: 075/20 | D117: BRB028 | E117: Etimex | F117: Rio Branco | G117: Zanini | H117: 5616 | I117: =SUMIF(Cargas!$C$5:$C$1652,C117,Cargas!$N$5:$N$1652) -> 5616 | J117: =IF(ABS(H117-I117)<20,0,H117-I117) -> 0 | K117: 136.89.74 | L117: 52547
B118: 44048 | C118: 083/ | D118: BRB057 | E118: Agricola Famosa | F118: Rio Branco | G118: Silvio | H118: 1152 | I118: =SUMIF(Cargas!$C$5:$C$1652,C118,Cargas!$N$5:$N$1652) -> 1152 | J118: =IF(ABS(H118-I118)<20,0,H118-I118) -> 0 | K118: 137.80.10 | L118: 121946
B119: 43928 | C119: 086/20 | D119: BRP014 | E119: Etimex | F119: Rio Branco | G119: Silvio | H119: 1000 | I119: =SUMIF(Cargas!$C$5:$C$1652,C119,Cargas!$N$5:$N$1652) -> 1000 | J119: =IF(ABS(H119-I119)<20,0,H119-I119) -> 0 | K119: 136.86.99 | L119: 53668
B120: 43929 | C120: 087/20 | D120: BRB030 | E120: Etimex | F120: Rio Branco | G120: Silvio | H120: 9360 | I120: =SUMIF(Cargas!$C$5:$C$1652,C120,Cargas!$N$5:$N$1652) -> 9360 | J120: =IF(ABS(H120-I120)<20,0,H120-I120) -> 0 | K120: 136.95.65 | L120: 54013
B121: 44048 | C121: 088/ | D121: BRB057 | E121: Agricola Famosa | F121: Rio Branco | G121: Silvio | H121: 1152 | I121: =SUMIF(Cargas!$C$5:$C$1652,C121,Cargas!$N$5:$N$1652) -> 1152 | J121: =IF(ABS(H121-I121)<20,0,H121-I121) -> 0 | K121: 137.80.10 | L121: 121946
B122: 43929 | C122: 088/20 | D122: BRB031 | E122: Etimex | F122: Rio Branco | G122: Zanini | H122: 5616 | I122: =SUMIF(Cargas!$C$5:$C$1652,C122,Cargas!$N$5:$N$1652) -> 5616 | J122: =IF(ABS(H122-I122)<20,0,H122-I122) -> 0 | K122: 136.95.66 | L122: 54930
B123: 43930 | C123: 089/20 | D123: BRP015 | E123: Etimex | F123: Rio Branco | G123: Silvio | H123: 2000 | I123: =SUMIF(Cargas!$C$5:$C$1652,C123,Cargas!$N$5:$N$1652) -> 2000 | J123: =IF(ABS(H123-I123)<20,0,H123-I123) -> 0 | K123: 139.96.27 | L123: 53933
B124: 43937 | C124: 095/20 | D124: BRB029 | E124: Etimex | F124: Rio Branco | G124: ATX | H124: 1872 | I124: =SUMIF(Cargas!$C$5:$C$1652,C124,Cargas!$N$5:$N$1652) -> 1872 | J124: =IF(ABS(H124-I124)<20,0,H124-I124) -> 0 | K124: 136.95.67 | L124: 56917
B125: 43939 | C125: 096/20 | D125: BRP016 | E125: Etimex | F125: Rio Branco | G125: Silvio | H125: 1000 | I125: =SUMIF(Cargas!$C$5:$C$1652,C125,Cargas!$N$5:$N$1652) -> 1000 | J125: =IF(ABS(H125-I125)<20,0,H125-I125) -> 0 | K125: 137.01.81 | L125: 57401
B126: 43941 | C126: 100/20 | D126: BRB032 | E126: Etimex | F126: Rio Branco | G126: Silvio | H126: 5616 | I126: =SUMIF(Cargas!$C$5:$C$1652,C126,Cargas!$N$5:$N$1652) -> 5616 | J126: =IF(ABS(H126-I126)<20,0,H126-I126) -> 0 | K126: 137.02.11 | L126: 59793
B127: 43941 | C127: 101/20 | D127: BRB033 | E127: Etimex | F127: Rio Branco | G127: Zanini | H127: 5616 | I127: =SUMIF(Cargas!$C$5:$C$1652,C127,Cargas!$N$5:$N$1652) -> 5616 | J127: =IF(ABS(H127-I127)<20,0,H127-I127) -> 0 | K127: 137.02.12 | L127: 60087
B128: 44055 | C128: 102 | D128: BRB060 | E128: Agricola Famosa | F128: Rio Branco | G128: Silvio | H128: 1152 | I128: =SUMIF(Cargas!$C$5:$C$1652,C128,Cargas!$N$5:$N$1652) -> 1152 | J128: =IF(ABS(H128-I128)<20,0,H128-I128) -> 0 | K128: 137.86.68 | L128: 127453
... B150: 44041 | C150: 1435/ | D150: PYB004 | E150: Misionero | F150: Salto | G150: Transur | H150: 990 | I150: =SUMIF(Cargas!$C$5:$C$1652,C150,Cargas!$N$5:$N$1652) -> 990 | J150: =IF(ABS(H150-I150)<20,0,H150-I150) -> 0 | K150: 137.80.74 | L150: 119445
B151: 44041 | C151: 1438/ | D151: PYB003 | E151: Misionero | F151: Salto | G151: Transur | H151: =990*2 -> 1980 | I151: =SUMIF(Cargas!$C$5:$C$1652,C151,Cargas!$N$5:$N$1652) -> 1980 | J151: =IF(ABS(H151-I151)<20,0,H151-I151) -> 0 | K151: 137.77.37 | L151: 115014
B152: 44037 | C152: 1439/ | D152: PYB002 | E152: Misionero | F152: Salto | G152: Transur | H152: 990 | I152: =SUMIF(Cargas!$C$5:$C$1652,C152,Cargas!$N$5:$N$1652) -> 990 | J152: =IF(ABS(H152-I152)<20,0,H152-I152) -> 0 | K152: 137.75.18 | L152: 113854
B153: 44047 | C153: 1445/ | D153: PYB005 | E153: Misionero | F153: Salto | G153: Agrologistica | H153: 1980 | I153: =SUMIF(Cargas!$C$5:$C$1652,C153,Cargas!$N$5:$N$1652) -> 1980 | J153: =IF(ABS(H153-I153)<20,0,H153-I153) -> 0 | K153: 137.80.56 | L153: 119557
B154: 44013 | C154: 145/20 | D154: BRB048 | E154: Etimex | F154: Rio Branco | G154: Silvio | H154: 7488 | I154: =SUMIF(Cargas!$C$5:$C$1652,C154,Cargas!$N$5:$N$1652) -> 7488 | J154: =IF(ABS(H154-I154)<20,0,H154-I154) -> 0 | K154: 137.56.99 | L154: 98527
B155: 44117 | C155: 256/20 | D155: BRB084 | E155: Etimex | F155: Rio Branco | G155: Zanini | H155: 3744 | I155: =SUMIF(Cargas!$C$5:$C$1652,C155,Cargas!$N$5:$N$1652) -> 3744 | J155: =IF(ABS(H155-I155)<20,0,H155-I155) -> 0 | K155: 138.52.31 | L155: 162232
B156: 44013 | C156: 146/20 | D156: BRB049 | E156: Etimex | F156: Rio Branco | G156: Zanini | H156: 7488 | I156: =SUMIF(Cargas!$C$5:$C$1652,C156,Cargas!$N$5:$N$1652) -> 7488 | J156: =IF(ABS(H156-I156)<20,0,H156-I156) -> 0 | K156: 137.57.00 | L156: 98557
B157: 44015 | C157: 149/20 | D157: BRB050 | E157: Etimex | F157: Rio Branco | G157: Silvio | H157: 7488 | I157: =SUMIF(Cargas!$C$5:$C$1652,C157,Cargas!$N$5:$N$1652) -> 7488 | J157: =IF(ABS(H157-I157)<20,0,H157-I157) -> 0 | K157: 137.60.77 | L157: 102788
B158: 44015 | C158: 150/20 | D158: BRB051 | E158: Etimex | F158: Rio Branco | G158: Zanini | H158: 7488 | I158: =SUMIF(Cargas!$C$5:$C$1652,C158,Cargas!$N$5:$N$1652) -> 7488 | J158: =IF(ABS(H158-I158)<20,0,H158-I158) -> 0 | K158: 137.60.76 | L158: 101950
B159: 44015 | C159: 151/20 | D159: BRB052 | E159: Etimex | F159: Rio Branco | G159: Gral | H159: 1872 | I159: =SUMIF(Cargas!$C$5:$C$1652,C159,Cargas!$N$5:$N$1652) -> 1872 | J159: =IF(ABS(H159-I159)<20,0,H159-I159) -> 0 | K159: 1376075 | L159: 102047
B160: 44063 | C160: 157/20 | D160: BRB062 | E160: Agricola Famosa | F160: Rio Branco | G160: Silvio | H160: 1152 | I160: =SUMIF(Cargas!$C$5:$C$1652,C160,Cargas!$N$5:$N$1652) -> 1152 | J160: =IF(ABS(H160-I160)<20,0,H160-I160) -> 0 | K160: 137.93.95 | L160: 130901
B161: 44117 | C161: 260/20 | D161: BRB085 | E161: Etimex | F161: Rio Branco | G161: Silvio | H161: 3744 | I161: =SUMIF(Cargas!$C$5:$C$1652,C161,Cargas!$N$5:$N$1652) -> 3744 | J161: =IF(ABS(H161-I161)<20,0,H161-I161) -> 0 | K161: 138.52.32 | L161: 163674
B162: 44120 | C162: 1301/ | D162: BRB086 | E162: Agricola Famosa | F162: Rio Branco | G162: Silvio | H162: 1152 | I162: =SUMIF(Cargas!$C$5:$C$1652,C162,Cargas!$N$5:$N$1652) -> 1152 | J162: =IF(ABS(H162-I162)<20,0,H162-I162) -> 0 | K162: 138.51.08 | L162: 169069
B163: 44026 | C163: 164/20 | D163: BRB053 | E163: Etimex | F163: Rio Branco | G163: Silvio | H163: 7488 | I163: =SUMIF(Cargas!$C$5:$C$1652,C163,Cargas!$N$5:$N$1652) -> 7488 | J163: =IF(ABS(H163-I163)<20,0,H163-I163) -> 0 | K163: 137.69.44 | L163: 110250
B164: 44120 | C164: 1302/ | D164: BRB086 | E164: Agricola Famosa | F164: Rio Branco | G164: Silvio | H164: 1152 | I164: =SUMIF(Cargas!$C$5:$C$1652,C164,Cargas!$N$5:$N$1652) -> 1152 | J164: =IF(ABS(H164-I164)<20,0,H164-I164) -> 0 | K164: 138.51.07 | L164: 169069
B165: 44026 | C165: 165/20 | D165: BRB054 | E165: Etimex | F165: Rio Branco | G165: Zanini | H165: 7488 | I165: =SUMIF(Cargas!$C$5:$C$1652,C165,Cargas!$N$5:$N$1652) -> 7488 | J165: =IF(ABS(H165-I165)<20,0,H165-I165) -> 0 | K165: 137.67.08 | L165: 106053
B166: 44030 | C166: 167/20 | D166: BRE001 | E166: Etimex | F166: Rio Branco | G166: Zanini | H166: 2560 | I166: =SUMIF(Cargas!$C$5:$C$1652,C166,Cargas!$N$5:$N$1652) -> 2560 | J166: =IF(ABS(H166-I166)<20,0,H166-I166) -> 0 | K166: 137.61.18 | L166: 108435
B167: 44063 | C167: 171/20 | D167: BRB062 | E167: Agricola Famosa | F167: Rio Branco | G167: Silvio | H167: 1152 | I167: =SUMIF(Cargas!$C$5:$C$1652,C167,Cargas!$N$5:$N$1652) -> 1152 | J167: =IF(ABS(H167-I167)<20,0,H167-I167) -> 0 | K167: 137.93.96 | L167: 130901
B168: 44040 | C168: 172/20 | D168: BRB056 | E168: Etimex | F168: Rio Branco | G168: Gral | H168: =936*2 -> 1872 | I168: =SUMIF(Cargas!$C$5:$C$1652,C168,Cargas!$N$5:$N$1652) -> 1872 | J168: =IF(ABS(H168-I168)<20,0,H168-I168) -> 0 | K168: 137.79.28 | L168: 115792
B169: 44043 | C169: 174/20 | D169: BRE002 | E169: Etimex | F169: Rio Branco | G169: Zanini | H169: 2560 | I169: =SUMIF(Cargas!$C$5:$C$1652,C169,Cargas!$N$5:$N$1652) -> 2560 | J169: =IF(ABS(H169-I169)<20,0,H169-I169) -> 0 | K169: 137.70.96 | L169: 117441
B170: 44046 | C170: 177/20 | D170: BRB058 | E170: Etimex | F170: Rio Branco | G170: Silvio | H170: 3744 | I170: =SUMIF(Cargas!$C$5:$C$1652,C170,Cargas!$N$5:$N$1652) -> 3744 | J170: =IF(ABS(H170-I170)<20,0,H170-I170) -> 0 | K170: 137.84.32 | L170: 118479
B171: 44046 | C171: 178/20 | D171: BRB059 | E171: Etimex | F171: Rio Branco | G171: Zanini | H171: 3744 | I171: =SUMIF(Cargas!$C$5:$C$1652,C171,Cargas!$N$5:$N$1652) -> 3744 | J171: =IF(ABS(H171-I171)<20,0,H171-I171) -> 0 | K171: 137.84.33 | L171: 119271
B172: 44127 | C172: 1459/ | D172: BRB087 | E172: Agricola Famosa | F172: Rio Branco | G172: Silvio | H172: 1152 | I172: =SUMIF(Cargas!$C$5:$C$1652,C172,Cargas!$N$5:$N$1652) -> 1152 | J172: =IF(ABS(H172-I172)<20,0,H172-I172) -> 0 | K172: 138.56.98 | L172: 172991
B173: 44124 | C173: 274/20 | D173: BRB088 | E173: Etimex | F173: Rio Branco | G173: Zanini | H173: 3744 | I173: =SUMIF(Cargas!$C$5:$C$1652,C173,Cargas!$N$5:$N$1652) -> 3744 | J173: =IF(ABS(H173-I173)<20,0,H173-I173) -> 0 | K173: 138.59.35 | L173: 167249
B174: 44133 | C174: 1630/ | D174: BRB089 | E174: Agricola Famosa | F174: Rio Branco | G174: Silvio | H174: 1152 | I174: =SUMIF(Cargas!$C$5:$C$1652,C174,Cargas!$N$5:$N$1652) -> 1152 | J174: =IF(ABS(H174-I174)<20,0,H174-I174) -> 0 | K174: 138.59.35 | L174: 176061
B175: 44053 | C175: 185//20 | D175: BRE003 | E175: Etimex | F175: Rio Branco | G175: Zanini | H175: 2560 | I175: =SUMIF(Cargas!$C$5:$C$1652,C175,Cargas!$N$5:$N$1652) -> 2560 | J175: =IF(ABS(H175-I175)<20,0,H175-I175) -> 0 | K175: 137.54.45 | L175: 124487
B176: 44055 | C176: 188/20 | D176: BRB061 | E176: Etimex | F176: Rio Branco | G176: Silvio | H176: 3744 | I176: =SUMIF(Cargas!$C$5:$C$1652,C176,Cargas!$N$5:$N$1652) -> 3744 | J176: =IF(ABS(H176-I176)<20,0,H176-I176) -> 0 | K176: 137.93.33 | L176: 123817
B177: 44060 | C177: 189/20 | D177: BRB063 | E177: Etimex | F177: Rio Branco | G177: Silvio | H177: 4680 | I177: =SUMIF(Cargas!$C$5:$C$1652,C177,Cargas!$N$5:$N$1652) -> 4680 | J177: =IF(ABS(H177-I177)<20,0,H177-I177) -> 0 | K177: 137.96.17 | L177: 127602
B178: 44060 | C178: 190/20 | D178: BRB064 | E178: Etimex | F178: Rio Branco | G178: Zanini | H178: 4680 | I178: =SUMIF(Cargas!$C$5:$C$1652,C178,Cargas!$N$5:$N$1652) -> 4680 | J178: =IF(ABS(H178-I178)<20,0,H178-I178) -> 0 | K178: 137.96.18 | L178: 128601
B179: 44060 | C179: 191/20 | D179: BRB065 | E179: Etimex | F179: Rio Branco | G179: Gral | H179: =936*2 -> 1872 | I179: =SUMIF(Cargas!$C$5:$C$1652,C179,Cargas!$N$5:$N$1652) -> 1872 | J179: =IF(ABS(H179-I179)<20,0,H179-I179) -> 0 | K179: 137.96.19 | L179: 127628
B180: 44061 | C180: 192/20 | D180: BRE004 | E180: Etimex | F180: Rio Branco | G180: Zanini | H180: 2560 | I180: =SUMIF(Cargas!$C$5:$C$1652,C180,Cargas!$N$5:$N$1652) -> 2560 | J180: =IF(ABS(H180-I180)<20,0,H180-I180) -> 0 | K180: 137.42.30/137.42.31 | L180: 127927
B181: 44064 | C181: 194/20 | D181: BRE005 | E181: Etimex | F181: Rio Branco | G181: Zanini | H181: 2560 | I181: =SUMIF(Cargas!$C$5:$C$1652,C181,Cargas!$N$5:$N$1652) -> 2560 | J181: =IF(ABS(H181-I181)<20,0,H181-I181) -> 0 | K181: 1375761/1375766 | L181: 129544
B182: 44133 | C182: 1636/ | D182: BRB089 | E182: Agricola Famosa | F182: Rio Branco | G182: Silvio | H182: 1152 | I182: =SUMIF(Cargas!$C$5:$C$1652,C182,Cargas!$N$5:$N$1652) -> 1152 | J182: =IF(ABS(H182-I182)<20,0,H182-I182) -> 0 | K182: 138.59.35 | L182: 176061
B183: 44074 | C183: 197/20 | D183: BRB068 | E183: Etimex | F183: Rio Branco | G183: Silvio | H183: 4680 | I183: =SUMIF(Cargas!$C$5:$C$1652,C183,Cargas!$N$5:$N$1652) -> 4680 | J183: =IF(ABS(H183-I183)<20,0,H183-I183) -> 0 | K183: 138.07.84 | L183: 135432
B184: 44074 | C184: 198/20 | D184: BRB069 | E184: Etimex | F184: Rio Branco | G184: Zanini | H184: 4680 | I184: =SUMIF(Cargas!$C$5:$C$1652,C184,Cargas!$N$5:$N$1652) -> 4680 | J184: =IF(ABS(H184-I184)<20,0,H184-I184) -> 0 | K184: 138.07.85 | L184: 136229
B185: 44074 | C185: 199/20 | D185: BRB070 | E185: Etimex | F185: Rio Branco | G185: Gral | H185: =936*2 -> 1872 | I185: =SUMIF(Cargas!$C$5:$C$1652,C185,Cargas!$N$5:$N$1652) -> 1872 | J185: =IF(ABS(H185-I185)<20,0,H185-I185) -> 0 | K185: 138.07.86 | L185: 135518
B186: 44133 | C186: 1642/ | D186: BRB089 | E186: Agricola Famosa | F186: Rio Branco | G186: Silvio | H186: 1152 | I186: =SUMIF(Cargas!$C$5:$C$1652,C186,Cargas!$N$5:$N$1652) -> 1152 | J186: =IF(ABS(H186-I186)<20,0,H186-I186) -> 0 | K186: 138.59.35 | L186: 176061
B187: 44130 | C187: 285/20 | D187: BRB090 | E187: Etimex | F187: Rio Branco | G187: Zanini | H187: 3744 | I187: =SUMIF(Cargas!$C$5:$C$1652,C187,Cargas!$N$5:$N$1652) -> 3744 | J187: =IF(ABS(H187-I187)<20,0,H187-I187) -> 0 | K187: 138.65.05 | L187: 173910
B188: 44082 | C188: 208/20 | D188: BRB071 | E188: Etimex | F188: Rio Branco | G188: Silvio | H188: 4680 | I188: =SUMIF(Cargas!$C$5:$C$1652,C188,Cargas!$N$5:$N$1652) -> 4680 | J188: =IF(ABS(H188-I188)<20,0,H188-I188) -> 0 | K188: 138.16.52 | L188: 144690
B189: 44130 | C189: 286/20 | D189: BRB091 | E189: Etimex | F189: Rio Branco | G189: Silvio | H189: 3744 | I189: =SUMIF(Cargas!$C$5:$C$1652,C189,Cargas!$N$5:$N$1652) -> 3744 | J189: =IF(ABS(H189-I189)<20,0,H189-I189) -> 0 | K189: 138.65.06 | L189: 172920
B190: 44138 | C190: 297/20 | D190: BRB092 | E190: Etimex | F190: Rio Branco | G190: Silvio | H190: 3744 | I190: =SUMIF(Cargas!$C$5:$C$1652,C190,Cargas!$N$5:$N$1652) -> 3744 | J190: =IF(ABS(H190-I190)<20,0,H190-I190) -> 0 | K190: 138.69.97 | L190: 176959
B191: 44082 | C191: 209/20 | D191: BRB072 | E191: Etimex | F191: Rio Branco | G191: Zanini | H191: 4680 | I191: =SUMIF(Cargas!$C$5:$C$1652,C191,Cargas!$N$5:$N$1652) -> 4680 | J191: =IF(ABS(H191-I191)<20,0,H191-I191) -> 0 | K191: 138.16.53 | L191: 139814
B192: 44140 | C192: 298/20 | D192: BRB093 | E192: Etimex | F192: Rio Branco | G192: Zanini | H192: 4680 | I192: =SUMIF(Cargas!$C$5:$C$1652,C192,Cargas!$N$5:$N$1652) -> 4680 | J192: =IF(ABS(H192-I192)<20,0,H192-I192) -> 0 | K192: 138.69.99 | L192: 179096
B193: 44208 | C193: 2994/ | D193: BRA001 | E193: Agricola Famosa | F193: Rio Branco | G193: Silvio | H193: 1152 | I193: =SUMIF(Cargas!$C$5:$C$1652,C193,Cargas!$N$5:$N$1652) -> 1152 | J193: =IF(ABS(H193-I193)<20,0,H193-I193) -> 0 | K193: 139.16.59 | L193: 6588
B194: 44082 | C194: 210/20 | D194: BRE006 | E194: Etimex | F194: Rio Branco | G194: Zanini | H194: 1280 | I194: =SUMIF(Cargas!$C$5:$C$1652,C194,Cargas!$N$5:$N$1652) -> 1280 | J194: =IF(ABS(H194-I194)<20,0,H194-I194) -> 0 | K194: 138.15.87 | L194: 142417
B195: 44083 | C195: 214/20 | D195: BRE007 | E195: Etimex | F195: Rio Branco | G195: Zanini | H195: 1140 | I195: =SUMIF(Cargas!$C$5:$C$1652,C195,Cargas!$N$5:$N$1652) -> 1140 | J195: =IF(ABS(H195-I195)<20,0,H195-I195) -> 0 | K195: 138.16.09 | L195: 142486
B196: 44070 | C196: 220/20 | D196: BRB066 | E196: Agricola Famosa | F196: Rio Branco | G196: Silvio | H196: 1152 | I196: =SUMIF(Cargas!$C$5:$C$1652,C196,Cargas!$N$5:$N$1652) -> 1152 | J196: =IF(ABS(H196-I196)<20,0,H196-I196) -> 0 | K196: 138.02.00 | L196: 135671
B197: 44142 | C197: 1805/ | D197: BRB094 | E197: Agricola Famosa | F197: Rio Branco | G197: Silvio | H197: 1152 | I197: =SUMIF(Cargas!$C$5:$C$1652,C197,Cargas!$N$5:$N$1652) -> 1152 | J197: =IF(ABS(H197-I197)<20,0,H197-I197) -> 0 | K197: 138.71.40 | L197: 182684
... B265: 44238 | C265: 3385/ | D265: BRA005 | E265: Agricola Famosa | F265: Rio Branco | G265: Silvio | H265: 1152 | I265: =SUMIF(Cargas!$C$5:$C$1652,C265,Cargas!$N$5:$N$1652) -> 1152 | J265: =IF(ABS(H265-I265)<20,0,H265-I265) -> 0 | K265: 139.28.29 | L265: 19843
B266: 44232 | C266: 3494/ | D266: BRA006 | E266: Agricola Famosa | F266: Rio Branco | G266: Silvio | H266: 1152 | I266: 1152 | J266: =IF(ABS(H266-I266)<20,0,H266-I266) -> 0 | K266: 139.31.58 | L266: 23337
B267: 44232 | C267: 3495/ | D267: BRA006 | E267: Agricola Famosa | F267: Rio Branco | G267: Silvio | H267: 1152 | I267: 1152 | J267: =IF(ABS(H267-I267)<20,0,H267-I267) -> 0 | K267: 139.31.58 | L267: 23337
B268: 44169 | C268: 365/20 | D268: BRE026 | E268: Etimex | F268: Rio Branco | G268: Miro | H268: 1300 | I268: =SUMIF(Cargas!$C$5:$C$1652,C268,Cargas!$N$5:$N$1652) -> 1300 | J268: =IF(ABS(H268-I268)<20,0,H268-I268) -> 0 | K268: 1359530/1389531 | L268: 199608
B269: 44112 | C269: 250/20 | D269: BRP017 | E269: Etimex | F269: Rio Branco | G269: Kaipper | H269: 1000 | I269: =SUMIF(Cargas!$C$5:$C$1652,C269,Cargas!$N$5:$N$1652) -> 1000 | J269: =IF(ABS(H269-I269)<20,0,H269-I269) -> 0 | K269: 138.40.36 | L269: 160882
B270: 44118 | C270: 263/ | D270: BRP018 | E270: Etimex | F270: Rio Branco | G270: Silvio | H270: 1000 | I270: =SUMIF(Cargas!$C$5:$C$1652,C270,Cargas!$N$5:$N$1652) -> 1000 | J270: =IF(ABS(H270-I270)<20,0,H270-I270) -> 0 | K270: 138.42.87 | L270: 164006
B271: 44118 | C271: 267/20 | D271: BRP019 | E271: Etimex | F271: Rio Branco | G271: Silvio | H271: 1000 | I271: =SUMIF(Cargas!$C$5:$C$1652,C271,Cargas!$N$5:$N$1652) -> 1000 | J271: =IF(ABS(H271-I271)<20,0,H271-I271) -> 0 | K271: 138.42.15 | L271: xx
B272: 44118 | C272: 266/20 | D272: BRP020 | E272: Etimex | F272: Rio Branco | G272: Silvio | H272: 1000 | I272: =SUMIF(Cargas!$C$5:$C$1652,C272,Cargas!$N$5:$N$1652) -> 1000 | J272: =IF(ABS(H272-I272)<20,0,H272-I272) -> 0 | K272: 138.41.89 | L272: xx
B273: 44141 | C273: 299/20 | D273: BRP021 | E273: Etimex | F273: Rio Branco | G273: Silvio | H273: 1000 | I273: =SUMIF(Cargas!$C$5:$C$1652,C273,Cargas!$N$5:$N$1652) -> 1000 | J273: =IF(ABS(H273-I273)<20,0,H273-I273) -> 0 | K273: 138.40.36
B274: 44141 | C274: 302/20 | D274: BRP022 | E274: Etimex | F274: Rio Branco | G274: Silvio | H274: 1000 | I274: =SUMIF(Cargas!$C$5:$C$1652,C274,Cargas!$N$5:$N$1652) -> 1000 | J274: =IF(ABS(H274-I274)<20,0,H274-I274) -> 0 | K274: 138.68.58
B275: 44148 | C275: 320/20 | D275: BRP023 | E275: Etimex | F275: Rio Branco | G275: Zanini | H275: 1000 | I275: =SUMIF(Cargas!$C$5:$C$1652,C275,Cargas!$N$5:$N$1652) -> 1000 | J275: =IF(ABS(H275-I275)<20,0,H275-I275) -> 0 | K275: 138.77.57 | L275: 183985
B276: 44148 | C276: 321/20 | D276: BRP024 | E276: Etimex | F276: Rio Branco | G276: Miro | H276: 1000 | I276: =SUMIF(Cargas!$C$5:$C$1652,C276,Cargas!$N$5:$N$1652) -> 1000 | J276: =IF(ABS(H276-I276)<20,0,H276-I276) -> 0 | K276: 138.77.58 | L276: 183986
B277: 44148 | C277: 322/20 | D277: BRP025 | E277: Etimex | F277: Rio Branco | G277: Zanini | H277: 1000 | I277: =SUMIF(Cargas!$C$5:$C$1652,C277,Cargas!$N$5:$N$1652) -> 1000 | J277: =IF(ABS(H277-I277)<20,0,H277-I277) -> 0 | K277: 138.77.59 | L277: 183987
...

Sheet Rangos
B2: Listas para validación de datos
B4: Status List | D4: Transporte | E4: Cajas x Viaje | F4: INCOTERMS | H4: Fronteras | J4: Productores | K4: Iniciales
B5: Solicitado | J5: Ulgo | K5: HG
B6: Destruida | D6: CMCN | E6: 936 | F6: DAP | H6: Montevideo | J6: Sergio | K6: SR
B7: Confirmado | D7: Amaro | E7: 1008 | F7: DAP | H7: Salto | J7: Claudia | K7: CH
B8: Cancelado | D8: Balbiani | E8: 1040 | F8: FCA | H8: Chuy | J8: Gilson | K8: GT
B9: Cargado | D9: Cigliuti | E9: 936 | F9: FCA | H9: Río Branco | J9: Jaime | K9: JM
B10: Frontera | D10: Cordenonsi | E10: 936 | F10: DAP | H10: Rivera | J10: Papa | K10: PA
B11: Liberado | D11: El Palomar | E11: 1000 | F11: DAP | H11: xx | J11: Boniato | K11: BO
B12: Arribado | D12: Pradera | E12: 918 | F12: FCA | J12: Sidnei | K12: SR
B13: Puerto | D13: Transzanini | E13: 918 | J13: Benini | K13: BN
B14: Descargado | D14: Gral | E14: 918 | F14: DAP | J14: Valdemar | K14: VH
D15: Aotrans | J15: Valdemar Ita
D16: Sergio Nava | E16: 918 | J16: Varios | K16: VA
D17: Marvel | J17: Nordeste | K17: ND
D18: K2 | E18: 918 | F18: DAP | J18: Corupá | K18: CP
D19: Costa Rica | E19: 918 | F19: DAP | J19: Jhony Viera | K19: JV
D20: Schwanck | E20: 918 | F20: DAP | J20: Muller | K20: MU
J21: Sergio | K21: SG
J22: Vitor | K22: VM
J23: Paraguay | K23: PY
J24: Paraguay EC | K24: PYE
J25: Paraguay OP | K25: PYO
J26: Paraguay MS | K26: PYM
J27: Paraguay GM | K27: GM
D28: Silvio | E28: 918 | F28: DAP | J28: Paraguay DF | K28: DF
D29: Tottal Brasil | E29: 918 | F29: DAP | J29: Paraguay HF | K29: HF
J30: Paraguay SF | K30: SF
D31: Trans America | E31: 918 | F31: DAP | J31: Bolivia Tuli | K31: BT
J32: Cebolla | K32: CE
J33: Abacaxi | K33: AB
J34: AgroBianvirc | K34: BRSP
D35: Transitex | E35: 1008 | F35: DAP | J35: Varios | K35: VA
D36: Ruiz | E36: 1008 | F36: FCA | J36: Cobalchini | K36: CB
D37: Viana | E37: 1008 | F37: FCA | J37: Junkes | K37: JS
D38: Realeza | E38: 918 | F38: FCA | J38: BAHIA | K38: BA
D39: Azzolini | E39: 918 | F39: DAP | J39: xx | K39: xx
D40: VI-MA | E40: 918 | F40: DAP
D41: Coopecarga | E41: 918 | F41: DAP
D42: Chabat | E42: 918
D43: Transporte Carneiro | E43: 918
D44: xx | E44: 1000
