Workbook
Name AtrasoDias: Parametros!$B$10
Name CajasBO: Parametros!$D$15
Name CajasBR: Parametros!$B$15
Name CajasOrigen: Parametros!$B$15:$D$15
Name CajasProm: Parametros!$B$11
Name CajasPY: Parametros!$C$15
Name CapFisica: Parametros!$B$59
Name CapMadurar: Parametros!$B$58
Name CepeaKg: Parametros!$B$21
Name CgCajas: Cargas!$H$5:$H$300
Name CgCarga: Cargas!$B$5:$B$300
Name CgCosto: Cargas!$P$5:$P$300
Name CgCuenta: Cargas!$N$5:$N$300
Name CgEstado: Cargas!$I$5:$I$300
Name CgOrigen: Cargas!$D$5:$D$300
Name CgOTIF: Cargas!$U$5:$U$300
Name CgPipeline: Cargas!$T$5:$T$300
Name CgProductor: Cargas!$E$5:$E$300
Name CgSemana: Cargas!$M$5:$M$300
Name CgSemanaP90: Cargas!$S$5:$S$300
Name CoberturaObjetivo: Parametros!$B$6
Name ConteoBO: Parametros!$D$16
Name ConteoBR: Parametros!$B$16
Name ConteoPY: Parametros!$C$16
Name ConteoTotal: Parametros!$E$16
Name CostoBO: Parametros!$D$33
Name CostoBR: Parametros!$B$33
Name CostoOrigen: Parametros!$B$33:$D$33
Name CostoPY: Parametros!$C$33
Name DemSemana: Demanda!$A$6:$A$18
Name DemVenta: Demanda!$H$6:$H$18
Name DiasMadurar: Parametros!$B$46
Name DiasVenta: Parametros!$B$7
Name EstacTabla: Parametros!$A$36:$B$40
Name FactorEscenario: Parametros!$B$9
Name FechaConteo: Parametros!$B$3
Name FechaHoy: Parametros!$B$4
Name HistSemana: Demanda!$A$22:$A$33
Name HistTotal: Demanda!$G$22:$G$33
Name KgCaja: Parametros!$B$22
Name LagBO: Parametros!$D$14
Name LagBR: Parametros!$B$14
Name LagPY: Parametros!$C$14
Name Lags: Parametros!$B$14:$D$14
Name LagsP90: Parametros!$B$45:$D$45
Name MinimoSabado: Parametros!$B$5
Name MinSugerido: Parametros!$B$52
Name Origenes: Parametros!$B$13:$D$13
Name PrACargar: Proyeccion!$K$6:$K$18
Name PrBO: Proyeccion!$S$6:$S$18
Name PrBOd: Proyeccion!$T$6:$T$18
Name PrBR: Proyeccion!$O$6:$O$18
Name PrBRd: Proyeccion!$P$6:$P$18
Name PrCamiones: Proyeccion!$D$6:$D$18
Name PrCobertura: Proyeccion!$M$6:$M$18
Name PrecioBR_BRL: Parametros!$B$25
Name PrEstado: Proyeccion!$N$6:$N$18
Name PrLimite: Proyeccion!$J$6:$J$18
Name PrProy: Proyeccion!$I$6:$I$18
Name PrPY: Proyeccion!$Q$6:$Q$18

Sheet Inicio
A1: PLAN DE COMPRAS SIMULADO - Almar S.R.L. (banana Brasil + Paraguay + Bolivia)
A2: Generado el 29/09/2026 11:36 a partir de plan_compras.json (conteo del 26/09/2026). Planilla de trabajo: se edita a mano, no la pisa el script.
A4: PARA QUE SIRVE
B5: Proyectar el stock de banana al cierre de cada sabado, saber cuantos camiones cargar y hasta que dia, y probar escenarios (venta distinta a comienzo/fin de mes, atraso en frontera, camiones de mas o de menos).
B6: Sigue las reglas de Almar: el sabado cierra la semana; lo que descarga el lunes suma a la semana siguiente; Paraguay carga domingo-lunes-martes y entra en la semana; los pedidos a Paraguay cierran el miercoles y a Brasil el jueves; minimo 22.500 cajas al cierre del sabado (Bolivia incluida).
B7: Y la practica de las multinacionales de fruta (S&OP semanal): un solo plan de demanda, proyeccion de inventario por semana con dias de cobertura, stock minimo explicito, recomendacion de pedido con fecha limite por lead time, escenarios, KPIs y tablero de proveedores.
A8: COMO SE USA
A9: 1 | B9: Parametros: fecha del conteo, conteo por origen, minimo, lead times, cajas por camion, escenario. Las celdas AMARILLAS son las que se tocan; las blancas son formulas.
A10: 2 | B10: Demanda: venta plan por semana (viene de la hoja ventas_plan), factor por semana del mes (1a, 2a, 3a, 4a/5a) y una columna "Venta manual" que pisa todo. Anota la venta real del ERP cuando cierre la semana: la planilla calcula el desvio.
A11: 3 | B11: Cargas: una fila por camion (Aloha, dictado, supuesto). Para simular, agrega filas: fecha de carga, origen, productor, cajas. La descarga, la semana a la que suma y el costo salen solos.
A12: 4 | B12: Proyeccion: stock al sabado semana por semana, total y por origen, dias de cobertura, camiones a cargar y fecha limite. Los faltantes se arrastran a la semana siguiente (como el simulador web).
A13: 5 | B13: Que cargar: la recomendacion en limpio, con el origen que queda mas justo y el dia en que cierra el pedido.
A14: 6 | B14: Escenarios: la misma proyeccion con venta -10% / base / +10% lado a lado. El atraso en frontera se prueba desde Parametros.
A15: 7 | B15: KPIs: cobertura, semanas bajo minimo, camiones por semana, mix por origen, costo estimado, exactitud del pronostico, y una tabla de referencia de como lo miden las multinacionales.
A16: 8 | B16: Proveedores: capacidad y comportamiento real de cada productor (camiones por semana, lead time real, transportista, dias de carga, precio 2026).
A17: 9 | B17: Glosario: terminos y buenas practicas, con las fuentes consultadas.
A18: 10 | B18: Calendario: la rutina S&OP de la semana (que se mira cada dia, quien decide, con que hoja). Semaforo: una pantalla con el estado por origen para esta semana, la proxima y la siguiente, mas los riesgos abiertos.
A19: 11 | B19: Capacidad: cajas a madurar por semana contra lo que las camaras pueden madurar, y stock contra la capacidad fisica (hay que completar camaras y cajas en Parametros). MercadoPY: exportadores de Paraguay con volumen, como alternativas si falla un proveedor habitual.
A20: CONVENCION | B20: Amarillo = entrada. Blanco = formula (no tocar). Rojo = falta / bajo minimo. Verde = ok. Las fechas van en dd/mm/aaaa.
A21: ORIGEN DE LOS DATOS | B21: plan_compras.json (paso 5j de actualizar_precios.ps1): Plan de Cargas de Aloha, cargas dictadas por Gonzalo (plan_compras.xlsx), supuestos PY, ventas_plan, conteo por camara. Precios: precios_cepea.json (Cepea + cargas 2026).
B22: Para refrescar los datos: volver a correr el script que arma esta planilla (plan_compras\generar_plan_xlsx.ps1) o pegar a mano las cargas nuevas en la hoja Cargas.
A23: QUIEN LA ARMO | B23: Pedido de Gonzalo del 28/09/2026 ("una planilla de plan de compras simulado a medida de mis necesidades y de una empresa multinacional"). La armaron dos sesiones de Claude: una investigo la practica S&OP de las multinacionales de fruta y aporto lead times reales, proveedores, precios de aduana y el mercado exportador de Paraguay; la otra armo las hojas y las formulas sobre los datos del pipeline.

Sheet Calendario
A1: Calendario S&OP semanal de Almar
A2: Rutina fija: que se mira, quien decide y con que hoja, cada dia. Es lo que hacen las multinacionales de fruta (Dole: metricas diarias y semanales de volumen, precio, flete, merma, servicio y capital de trabajo), a escala de 16-17 mil cajas por semana.
A4: Dia | B4: Momento | C4: Que se hace | D4: Decide / carga | E4: Hoja / herramienta
A5: Lunes | B5: manana | C5: Venta real de la semana pasada (ERP) y desvio contra el plan. Si hubo conteo por camara el sabado, actualizar el conteo. Revisar que descargo el fin de semana y el lunes (Aloha). | D5: Gonzalo / administracion | E5: Demanda (col. Venta real ERP), Parametros (conteo), Cargas (descarga real)
A6: Martes | B6: manana | C6: Abastecimiento: bajar el Plan de Cargas de Aloha, marcar camiones en frontera o atrasados, cargar en Cargas lo nuevo, mirar la calidad de lo que llego. | D6: Gonzalo / recepcion | E6: Cargas, Proveedores (lead time real), index_calidad
A7: Miercoles | B7: 12:00 | C7: Llega el WhatsApp del servidor (Cepea, clima, plan de compras). Decision de la semana: cuantos camiones faltan para el sabado siguiente y de que origen. CIERRE DE PEDIDOS PARAGUAY. | D7: Gonzalo | E7: QueCargar, Semaforo, Proveedores (cupos PY)
A8: Jueves | B8: manana | C8: CIERRE DE PEDIDOS BRASIL: confirmar productores, transportistas y dias de carga; dictar las cargas (plan_compras.xlsx) para que entren al plan. | D8: Gonzalo | E8: QueCargar, Proveedores (cupos BR), plan_compras.xlsx hoja cargas_programadas
A9: Viernes | B9: 19:00 | C9: WhatsApp de cierre. Riesgos de la semana que viene: frontera lenta (escenario P90), calidad, Bolivia sin carga, venta distinta a la esperada. Ajustar venta manual si cambio. | D9: Gonzalo | E9: Escenarios, Semaforo, Demanda (venta manual)
A10: Sabado | B10: cierre | C10: Cierre semanal: el stock del sabado es la referencia. Comparar stock real contra el proyectado y anotar la diferencia (merma, conteo, camiones que no llegaron). | D10: Deposito | E10: Parametros (conteo), KPIs
A11: Mensual | B11: primer lunes | C11: Revisar factores de estacionalidad por semana del mes, desvio estandar de la venta, precios de compra por origen, capacidad de camaras, concentracion de proveedores. | D11: Gonzalo | E11: Parametros, Demanda, KPIs, MercadoPY
A13: Reglas fijas: el sabado cierra la semana; lo que descarga el lunes suma a la siguiente; Paraguay carga domingo-lunes-martes (entra en la semana); Brasil cierra pedidos jueves y Paraguay miercoles; minimo 22.500 cajas al sabado, Bolivia incluida.

Sheet Parametros
A1: Parametros
A2: Celdas amarillas: se editan. Todo lo demas de la planilla depende de estas.
A3: Fecha del conteo por camara | B3: 46291 | C3: El stock arranca de aca. Solo cuentan los camiones que descargan DESPUES de esta fecha.
A4: Hoy (FechaHoy) | B4: =TODAY() -> 46294 | C4: Se puede pisar con una fecha fija para revisar un plan viejo.
A5: Minimo al cierre del sabado (cajas) | B5: 22500 | C5: Gonzalo 27/09/2026: "de una semana a otra unas 22/23 mil cajas cerrando el sabado", Bolivia incluida. Equivale a ~7-8 dias de venta (fruta que todavia no maduro: gas + camara).
A6: Cobertura objetivo (dias de venta) | B6: 7 | C6: Referencia para pintar la cobertura: menos que esto = amarillo, menos de 2 = rojo.
A7: Dias de venta por semana | B7: 6 | C7: Lunes a sabado.
A8: Escenario de venta | B8: Base | C8: Multiplica la venta de todas las semanas (salvo las que tengan venta manual). La hoja Escenarios muestra -10% / base / +10% juntos.
A9: Factor de venta del escenario | B9: =IF(B8="Venta +10%",1.1,IF(B8="Venta -10%",0.9,IF(B8="Venta +20%",1.2,IF(B8="Venta -20%",0.8,1)))) -> 1
A10: Atraso extra en frontera (dias) | B10: 0 | C10: Se suma al lead time de todos los camiones sin descarga real. Probar 1 o 2 para ver que pasa si la frontera se traba.
A11: Cajas por camion para los que FALTAN | B11: 1000 | C11: Los camiones reales llevan sus cajas; este promedio se usa para calcular cuantos faltan.
A13: POR ORIGEN | B13: BR | C13: PY | D13: BO | E13: Nota
A14: Dias de carga a descarga (lead time) | B14: 3 | C14: 4 | D14: 6 | E14: Brasil 3: regla de Gonzalo (lo que carga lunes a miercoles entra en la semana; viernes y sabado entra lunes o martes). Paraguay 4: mediana observada en Aloha, decidido por Gonzalo el 28/09/2026 ("paraguay vamos a 4 dias"): un camion PY cargado el martes descarga el sabado y entra en la semana; el del miercoles ya no. Bolivia 6. Los tres valores vienen de plan_compras.json y son los mismos del simulador web y del WhatsApp.
A15: Cajas por camion (tipico) | B15: 1008 | C15: 980 | D15: 1050 | E15: Se usa cuando una fila de Cargas no tiene cajas. 936 los chicos de AXT.
A16: Conteo por camara a la fecha del conteo | B16: 11653 | C16: 13673 | D16: 1646 | E16: =SUM(B16:D16) -> 26972
A17: Cierre de pedidos (dia de la semana anterior) | B17: jueves | C17: miercoles | D17: segun disponibilidad | E17: Gonzalo 27/09: "Brasil cierra los pedidos de la semana siguiente los jueves, Paraguay los miercoles". Por eso el numero tiene que estar el miercoles.
A18: Ultima carga en Aloha | B18: 2026-09-25 | C18: 2026-09-23 | D18: 2026-09-25 | E18: Export de Aloha: Plan - Cargas (export Aloha 2026-09-24).xlsx (2026-09-24 15:51). En el servidor se baja solo en cada corrida.
A20: COSTOS DE REFERENCIA (para el KPI de costo)
A21: Cepea Nanica 1a SC (R$/kg) | B21: 1.18 | C21: semana 2026-09-25
A22: Kg netos por caja | B22: 22
A23: Servicios por caja Brasil (R$: envalado, paletizado, flete interno) | B23: 18 | C23: Gonzalo 27/09: "estoy pagando 18 mas precio na roca". Solo Brasil.
A24: Caja equivalente Cepea (R$) = kg x 22 + servicios | B24: =CepeaKg*KgCaja+ServiciosCaja -> 43.96
A25: Precio promedio pagado Almar Brasil (R$/caja, ponderado 4 semanas) | B25: 36.87 | C25: Gonzalo 28/09: 'Brasil tenes el promedio de la compra semanal que sale en el WhatsApp'. Semanas 05/09 R$ 36.3 (10) · 12/09 R$ 36.5 (14) · 19/09 R$ 38.67 (3) · 26/09 R$ 38.67 (3). Lo regenera el pipeline en precios_cepea.json > almar.semanas.
A26: Tipo de cambio BRL por USD | B26: 5.2
A27: Paraguay: precio por caja (PYG, Carape SIMA) | B27: 60000 | C27: Referencia de mercado, no lo que paga Almar: cambiar por el precio real de compra si se conoce.
A28: Tipo de cambio PYG por USD | B28: 7500
A29: Bolivia: precio de compra | B29: ver fila 32 | C29: Gonzalo lo pasa despues; mientras, la referencia de aduana (fila 31).
A30: COSTO POR CAJA EN USD (lo usan Cargas, KPIs y el valor del stock) | B30: BR | C30: PY | D30: BO | E30: Nota
A31: Referencia: valor declarado en aduana 2026 (VNA, USD/caja) | B31: 11.6 | C31: 11.5 | D31: 10.8 | E31: Penta (aduana UY, ene-ago 2026), USD/kg neto x kg por caja: BR 0,527 x 22 · PY 0,522 x 22 · BO 0,539 x 20. Es CIF-aduana, no precio productor. 2025: 12,7 / 14,9 / 13,8.
A32: Precio de compra real (USD/caja; vacio = referencia) | B32: =ROUND(PrecioBR_BRL/TC_BRL,2) -> 7.09 | C32: 7 | E32: ="Gonzalo 28/09/2026: Paraguay USD 7 por caja; Brasil = promedio ponderado pagado ("&FIXED(PrecioBR_BRL,2)&" R$) / TC "&FIXED(TC_BRL,2)&" (sin los R$ "&ServiciosCaja&" de servicios: puesto en Uruguay serian "&FIXED((PrecioBR_BRL+ServiciosCaja)/TC_BRL,2)&" USD); Bolivia pendiente (queda la referencia de aduana). Carape "&FIXED(PYG_Caja/TC_PYG,2)&" USD es mercado local, no compra." -> Gonzalo 28/09/2026: Paraguay USD 7 por caja; Brasil = promedio ponderado pagado (36,87 R$) / TC 5,20 (sin los R$ 18 de servicios: puesto en Uruguay serian 10,55 USD); Bolivia pendiente (queda la referencia de aduana). Carape 8,00 USD es mercado local, no compra.
A33: USD/caja usado | B33: =IF(B32<>"",B32,B31) -> 7.09 | C33: =IF(C32<>"",C32,C31) -> 7 | D33: =IF(D32<>"",D32,D31) -> 10.8
A34: ESTACIONALIDAD DENTRO DEL MES (factor sobre la venta plan)
A35: Semana del mes | B35: Factor | C35: Nota
A36: 1 | B36: 1 | C36: 1a semana (arranque de mes: sueldos, mas venta)
A37: 2 | B37: 1 | C37: 2a semana
A38: 3 | B38: 1 | C38: 3a semana
A39: 4 | B39: 1 | C39: 4a semana (fin de mes: menos venta)
A40: 5 | B40: 1 | C40: 5a semana (cuando el mes tiene 5 lunes)
A41: Todos en 1,00 hasta que Gonzalo los ajuste con su experiencia (28/09/2026: "las ventas conforme a si es comienzo de mes o final de mes"). Ej: 1,05 / 1,00 / 0,98 / 0,95.
A43: LEAD TIME REAL Y RIESGO (Plan de Cargas Aloha 2024-2026) | B43: BR | C43: PY | D43: BO | E43: Nota
A44: TT mediana carga a descarga (dias) | B44: 3 | C44: 4 | D44: 6 | E44: Mediana observada en Aloha. Para planificar se usa la regla de Gonzalo (fila 14); esta es la referencia real.
A45: TT P90: frontera lenta (dias) | B45: 6 | C45: 5 | D45: 8 | E45: 9 de cada 10 camiones descargan antes de esto. Cargas usa esta fila para la "descarga pesimista" y Escenarios para "frontera a P90".
A46: Dias de maduracion (gas + camara) antes de vender | B46: 7 | E46: Lead time total carga a venta: BR ~10 dias, PY ~11, BO ~13.
A47: Vida util maxima en verde (dias) = alerta de EXCESO | B47: 16 | E47: SUPUESTO editable (no tiene fuente medida en Almar): la banana verde aguanta del orden de 2 semanas en camara a 13-14 C antes de perder calidad (referencia estandar: UC Davis Postharvest, "Banana: recommendations for maintaining postharvest quality", que da 2-4 semanas segun variedad y madurez). Mas cobertura que esto es merma, no seguridad. Ajustar con lo que se observe en index_calidad.
A48: Nivel de servicio objetivo | B48: 0.95
A49: z (factor del nivel de servicio) | B49: =NORMSINV(B48) -> 1.6448536
A50: Desvio estandar de la venta semanal (cajas) | B50: =IFERROR(ROUND(STDEV(HistTotal),0),1700) -> 1282 | E50: REAL: desvio estandar del total BR+PY+BO de las 12 semanas de venta ERP que estan en Demanda (historial). Se puede pisar con un numero.
A51: Stock de seguridad sugerido (cajas) | B51: =ROUND(Zserv*SigmaVenta*SQRT((LagBR+DiasMadurar)/7+1),0) -> 3286 | E51: z x sigma x raiz(lead time en semanas + 1 semana de revision). Cubre la variabilidad de la venta durante el tiempo en que no se puede reaccionar.
A52: Minimo sugerido = seguridad + dias de maduracion de venta | B52: =SSsugerido+ROUND(INDEX(DemVenta,MATCH(FechaHoy-WEEKDAY(FechaHoy,2)+1+7,DemSemana,0))/DiasVenta*DiasMadurar,0) -> 23119 | E52: ="Contra el minimo de Gonzalo ("&FIXED(MinimoSabado,0)&"): "&IF(MinSugerido>MinimoSabado,"la formula pide "&FIXED(MinSugerido-MinimoSabado,0)&" cajas mas","la formula pide "&FIXED(MinimoSabado-MinSugerido,0)&" cajas menos")&". El que manda en la planilla es el de la fila 5." -> Contra el minimo de Gonzalo (22.500): la formula pide 619 cajas mas. El que manda en la planilla es el de la fila 5.
A54: CAPACIDAD DE MADURACION Y CAMARAS (completar: no lo tenemos)
A55: Camaras de gas (cantidad) | E55: Multinacionales: minimo 4 camaras para escalonar entrada, gaseo y despacho sin cuellos de botella.
A56: Cajas por camara
A57: Ciclo de maduracion (dias) | B57: 5 | E57: Ciclo de 4 a 6 dias; el de 5 es el mas usado, el de 6 da mejor sabor y vida (Produce News). Etileno 100-150 ppm las primeras 24 h.
A58: Cajas maximas a madurar por semana | B58: =IF(OR(B55="",B56=""),"",B55*B56/B57*7) | E58: camaras x cajas / ciclo x 7. La hoja Capacidad compara la venta de cada semana contra esto.
A59: Capacidad fisica total en camaras (cajas) | E59: ZAC + Coronel Raiz, banana. La hoja Capacidad muestra la ocupacion al sabado.
A61: SUPUESTOS DE CARGA (1 = se cuentan, 0 = no)
A62: Contar los supuestos de Paraguay (5 camiones/semana, dom-lun-mar) | B62: 1 | E62: Gonzalo 27/09: "la PY siempre se carga domingo, lunes y martes; por lo general estoy cargando 5/6". Son los camiones con Estado = Supuesto en Cargas.
A63: Contar los supuestos de Brasil (8 camiones/semana los viernes, mas alla de lo dictado) | B63: 1 | E63: Estado = "Supuesto BR" en Cargas, solo en las semanas posteriores a la ultima dictada. Con 0, "Camiones a cargar" muestra TODA la necesidad (como el WhatsApp); con 1 muestra lo que falta ademas del ritmo habitual. El WhatsApp y el simulador web no usan este supuesto.

Sheet Demanda
A1: Demanda: venta por semana (cajas)
A2: Venta usada = venta manual si hay; si no, venta plan x factor de la semana del mes x factor del escenario. El mix por origen viene de cada fila de la hoja ventas_plan (por eso la semana del 28/09 tiene 54/39/7 y las siguientes 53/38/9: Bolivia 1 carga esa semana); es editable. Anota la venta real del ERP cuando cierre la semana.
A5: Semana (lunes) | B5: Sabado (cierre) | C5: Mes | D5: Semana del mes | E5: Venta plan (cajas) | F5: Factor semana del mes | G5: Venta manual (pisa todo) | H5: VENTA USADA | I5: Mix BR % | J5: Mix PY % | K5: Mix BO % | L5: Venta BR | M5: Venta PY | N5: Venta BO | O5: Venta real ERP (cajas) | P5: Desvio real vs usada | Q5: Fuente / nota
A6: 46286 | B6: =A6+5 -> 46291 | C6: =TEXT(A6,"mmm") -> set | D6: =INT((DAY(A6)-1)/7)+1 -> 3 | E6: 14845 | F6: =IFERROR(VLOOKUP(D6,EstacTabla,2,FALSE),1) -> 1 | H6: =IF(G6<>"",G6,ROUND(E6*F6*FactorEscenario,0)) -> 14845 | I6: 0.533 | J6: 0.419 | K6: =1-I6-J6 -> 0.048 | L6: =ROUND(H6*I6,0) -> 7912 | M6: =ROUND(H6*J6,0) -> 6220 | N6: =H6-L6-M6 -> 713 | O6: 14845 | P6: =IF(O6="","",O6/H6-1) -> 0 | Q6: REAL ERP (captura 29/09/2026)
A7: 46293 | B7: =A7+5 -> 46298 | C7: =TEXT(A7,"mmm") -> set | D7: =INT((DAY(A7)-1)/7)+1 -> 4 | E7: 16000 | F7: =IFERROR(VLOOKUP(D7,EstacTabla,2,FALSE),1) -> 1 | H7: =IF(G7<>"",G7,ROUND(E7*F7*FactorEscenario,0)) -> 16000 | I7: 0.54 | J7: 0.394 | K7: =1-I7-J7 -> 0.066 | L7: =ROUND(H7*I7,0) -> 8640 | M7: =ROUND(H7*J7,0) -> 6304 | N7: =H7-L7-M7 -> 1056 | P7: =IF(O7="","",O7/H7-1) | Q7: Gonzalo 27/09: se pide vender 16.000; Bolivia 1 carga, el resto PY y BR
A8: 46300 | B8: =A8+5 -> 46305 | C8: =TEXT(A8,"mmm") -> Oct | D8: =INT((DAY(A8)-1)/7)+1 -> 1 | E8: 17000 | F8: =IFERROR(VLOOKUP(D8,EstacTabla,2,FALSE),1) -> 1 | H8: =IF(G8<>"",G8,ROUND(E8*F8*FactorEscenario,0)) -> 17000 | I8: 0.617 | J8: 0.312 | K8: =1-I8-J8 -> 0.071 | L8: =ROUND(H8*I8,0) -> 10489 | M8: =ROUND(H8*J8,0) -> 5304 | N8: =H8-L8-M8 -> 1207 | P8: =IF(O8="","",O8/H8-1) | Q8: SUPUESTO = semana anterior (confirmar)
A9: 46307 | B9: =A9+5 -> 46312 | C9: =TEXT(A9,"mmm") -> Oct | D9: =INT((DAY(A9)-1)/7)+1 -> 2 | E9: 17000 | F9: =IFERROR(VLOOKUP(D9,EstacTabla,2,FALSE),1) -> 1 | H9: =IF(G9<>"",G9,ROUND(E9*F9*FactorEscenario,0)) -> 17000 | I9: 0.617 | J9: 0.312 | K9: =1-I9-J9 -> 0.071 | L9: =ROUND(H9*I9,0) -> 10489 | M9: =ROUND(H9*J9,0) -> 5304 | N9: =H9-L9-M9 -> 1207 | P9: =IF(O9="","",O9/H9-1) | Q9: SUPUESTO = semana anterior (confirmar)
A10: 46314 | B10: =A10+5 -> 46319 | C10: =TEXT(A10,"mmm") -> Oct | D10: =INT((DAY(A10)-1)/7)+1 -> 3 | E10: 17000 | F10: =IFERROR(VLOOKUP(D10,EstacTabla,2,FALSE),1) -> 1 | H10: =IF(G10<>"",G10,ROUND(E10*F10*FactorEscenario,0)) -> 17000 | I10: 0.617 | J10: 0.312 | K10: =1-I10-J10 -> 0.071 | L10: =ROUND(H10*I10,0) -> 10489 | M10: =ROUND(H10*J10,0) -> 5304 | N10: =H10-L10-M10 -> 1207 | P10: =IF(O10="","",O10/H10-1) | Q10: SUPUESTO = semana anterior (confirmar)
A11: 46321 | B11: =A11+5 -> 46326 | C11: =TEXT(A11,"mmm") -> Oct | D11: =INT((DAY(A11)-1)/7)+1 -> 4 | E11: 17000 | F11: =IFERROR(VLOOKUP(D11,EstacTabla,2,FALSE),1) -> 1 | H11: =IF(G11<>"",G11,ROUND(E11*F11*FactorEscenario,0)) -> 17000 | I11: 0.617 | J11: 0.312 | K11: =1-I11-J11 -> 0.071 | L11: =ROUND(H11*I11,0) -> 10489 | M11: =ROUND(H11*J11,0) -> 5304 | N11: =H11-L11-M11 -> 1207 | P11: =IF(O11="","",O11/H11-1) | Q11: sin fila en ventas_plan: copia de la semana del 19/10 (SUPUESTO)
A12: 46328 | B12: =A12+5 -> 46333 | C12: =TEXT(A12,"mmm") -> Nov | D12: =INT((DAY(A12)-1)/7)+1 -> 1 | E12: 17000 | F12: =IFERROR(VLOOKUP(D12,EstacTabla,2,FALSE),1) -> 1 | H12: =IF(G12<>"",G12,ROUND(E12*F12*FactorEscenario,0)) -> 17000 | I12: 0.617 | J12: 0.312 | K12: =1-I12-J12 -> 0.071 | L12: =ROUND(H12*I12,0) -> 10489 | M12: =ROUND(H12*J12,0) -> 5304 | N12: =H12-L12-M12 -> 1207 | P12: =IF(O12="","",O12/H12-1) | Q12: sin fila en ventas_plan: copia de la semana del 19/10 (SUPUESTO)
A13: 46335 | B13: =A13+5 -> 46340 | C13: =TEXT(A13,"mmm") -> Nov | D13: =INT((DAY(A13)-1)/7)+1 -> 2 | E13: 17000 | F13: =IFERROR(VLOOKUP(D13,EstacTabla,2,FALSE),1) -> 1 | H13: =IF(G13<>"",G13,ROUND(E13*F13*FactorEscenario,0)) -> 17000 | I13: 0.617 | J13: 0.312 | K13: =1-I13-J13 -> 0.071 | L13: =ROUND(H13*I13,0) -> 10489 | M13: =ROUND(H13*J13,0) -> 5304 | N13: =H13-L13-M13 -> 1207 | P13: =IF(O13="","",O13/H13-1) | Q13: sin fila en ventas_plan: copia de la semana del 19/10 (SUPUESTO)
A14: 46342 | B14: =A14+5 -> 46347 | C14: =TEXT(A14,"mmm") -> Nov | D14: =INT((DAY(A14)-1)/7)+1 -> 3 | E14: 17000 | F14: =IFERROR(VLOOKUP(D14,EstacTabla,2,FALSE),1) -> 1 | H14: =IF(G14<>"",G14,ROUND(E14*F14*FactorEscenario,0)) -> 17000 | I14: 0.617 | J14: 0.312 | K14: =1-I14-J14 -> 0.071 | L14: =ROUND(H14*I14,0) -> 10489 | M14: =ROUND(H14*J14,0) -> 5304 | N14: =H14-L14-M14 -> 1207 | P14: =IF(O14="","",O14/H14-1) | Q14: sin fila en ventas_plan: copia de la semana del 19/10 (SUPUESTO)
A15: 46349 | B15: =A15+5 -> 46354 | C15: =TEXT(A15,"mmm") -> Nov | D15: =INT((DAY(A15)-1)/7)+1 -> 4 | E15: 17000 | F15: =IFERROR(VLOOKUP(D15,EstacTabla,2,FALSE),1) -> 1 | H15: =IF(G15<>"",G15,ROUND(E15*F15*FactorEscenario,0)) -> 17000 | I15: 0.617 | J15: 0.312 | K15: =1-I15-J15 -> 0.071 | L15: =ROUND(H15*I15,0) -> 10489 | M15: =ROUND(H15*J15,0) -> 5304 | N15: =H15-L15-M15 -> 1207 | P15: =IF(O15="","",O15/H15-1) | Q15: sin fila en ventas_plan: copia de la semana del 19/10 (SUPUESTO)
A16: 46356 | B16: =A16+5 -> 46361 | C16: =TEXT(A16,"mmm") -> Nov | D16: =INT((DAY(A16)-1)/7)+1 -> 5 | E16: 17000 | F16: =IFERROR(VLOOKUP(D16,EstacTabla,2,FALSE),1) -> 1 | H16: =IF(G16<>"",G16,ROUND(E16*F16*FactorEscenario,0)) -> 17000 | I16: 0.617 | J16: 0.312 | K16: =1-I16-J16 -> 0.071 | L16: =ROUND(H16*I16,0) -> 10489 | M16: =ROUND(H16*J16,0) -> 5304 | N16: =H16-L16-M16 -> 1207 | P16: =IF(O16="","",O16/H16-1) | Q16: sin fila en ventas_plan: copia de la semana del 19/10 (SUPUESTO)
A17: 46363 | B17: =A17+5 -> 46368 | C17: =TEXT(A17,"mmm") -> Dic | D17: =INT((DAY(A17)-1)/7)+1 -> 1 | E17: 17000 | F17: =IFERROR(VLOOKUP(D17,EstacTabla,2,FALSE),1) -> 1 | H17: =IF(G17<>"",G17,ROUND(E17*F17*FactorEscenario,0)) -> 17000 | I17: 0.617 | J17: 0.312 | K17: =1-I17-J17 -> 0.071 | L17: =ROUND(H17*I17,0) -> 10489 | M17: =ROUND(H17*J17,0) -> 5304 | N17: =H17-L17-M17 -> 1207 | P17: =IF(O17="","",O17/H17-1) | Q17: sin fila en ventas_plan: copia de la semana del 19/10 (SUPUESTO)
A18: 46370 | B18: =A18+5 -> 46375 | C18: =TEXT(A18,"mmm") -> Dic | D18: =INT((DAY(A18)-1)/7)+1 -> 2 | E18: 17000 | F18: =IFERROR(VLOOKUP(D18,EstacTabla,2,FALSE),1) -> 1 | H18: =IF(G18<>"",G18,ROUND(E18*F18*FactorEscenario,0)) -> 17000 | I18: 0.617 | J18: 0.312 | K18: =1-I18-J18 -> 0.071 | L18: =ROUND(H18*I18,0) -> 10489 | M18: =ROUND(H18*J18,0) -> 5304 | N18: =H18-L18-M18 -> 1207 | P18: =IF(O18="","",O18/H18-1) | Q18: sin fila en ventas_plan: copia de la semana del 19/10 (SUPUESTO)
A20: HISTORIAL DE VENTA REAL (ERP, cajas por semana lunes-sabado). Agregar semanas en plan_compras.xlsx > ventas_semanales.
A21: Semana (lunes) | B21: Sabado | C21: BR | D21: PY | E21: BO | F21: Ecuador (otro canal) | G21: TOTAL banana (BR+PY+BO) | H21: Semana del mes
A22: 46209 | B22: 46214 | C22: 8884 | D22: 4896 | E22: 713 | F22: 7277 | G22: =C22+D22+E22 -> 14493 | H22: =INT((DAY(A22)-1)/7)+1 -> 1
A23: 46216 | B23: 46221 | C23: 8547 | D23: 3607 | E23: 344 | F23: 6900 | G23: =C23+D23+E23 -> 12498 | H23: =INT((DAY(A23)-1)/7)+1 -> 2
A24: 46223 | B24: 46228 | C24: 11589 | D24: 2140 | E24: 1025 | F24: 7601 | G24: =C24+D24+E24 -> 14754 | H24: =INT((DAY(A24)-1)/7)+1 -> 3
A25: 46230 | B25: 46235 | C25: 9196 | D25: 4748 | E25: 0 | F25: 7884 | G25: =C25+D25+E25 -> 13944 | H25: =INT((DAY(A25)-1)/7)+1 -> 4
A26: 46237 | B26: 46242 | C26: 9880 | D26: 5192 | E26: 866 | F26: 7601 | G26: =C26+D26+E26 -> 15938 | H26: =INT((DAY(A26)-1)/7)+1 -> 1
A27: 46244 | B27: 46249 | C27: 6972 | D27: 6201 | E27: 1816 | F27: 6647 | G27: =C27+D27+E27 -> 14989 | H27: =INT((DAY(A27)-1)/7)+1 -> 2
A28: 46251 | B28: 46256 | C28: 8041 | D28: 5861 | E28: 34 | F28: 6290 | G28: =C28+D28+E28 -> 13936 | H28: =INT((DAY(A28)-1)/7)+1 -> 3
A29: 46258 | B29: 46263 | C29: 6633 | D29: 7058 | E29: 1051 | F29: 4669 | G29: =C29+D29+E29 -> 14742 | H29: =INT((DAY(A29)-1)/7)+1 -> 4
A30: 46265 | B30: 46270 | C30: 11032 | D30: 5369 | E30: 873 | F30: 7102 | G30: =C30+D30+E30 -> 17274 | H30: =INT((DAY(A30)-1)/7)+1 -> 5
A31: 46272 | B31: 46277 | C31: 12293 | D31: 2770 | E31: 1486 | F31: 6924 | G31: =C31+D31+E31 -> 16549 | H31: =INT((DAY(A31)-1)/7)+1 -> 1
A32: 46279 | B32: 46284 | C32: 8590 | D32: 5769 | E32: 1492 | F32: 6673 | G32: =C32+D32+E32 -> 15851 | H32: =INT((DAY(A32)-1)/7)+1 -> 2
A33: 46286 | B33: 46291 | C33: 7919 | D33: 6221 | E33: 705 | F33: 6718 | G33: =C33+D33+E33 -> 14845 | H33: =INT((DAY(A33)-1)/7)+1 -> 3
A35: Promedio de todas las semanas | C35: =ROUND(AVERAGE(C22:C33),0) -> 9131 | D35: =ROUND(AVERAGE(D22:D33),0) -> 4986 | E35: =ROUND(AVERAGE(E22:E33),0) -> 867 | F35: =ROUND(AVERAGE(F22:F33),0) -> 6857 | G35: =ROUND(AVERAGE(G22:G33),0) -> 14984
A36: Promedio ultimas 4 semanas | C36: =ROUND(AVERAGE(C30:C33),0) -> 9959 | D36: =ROUND(AVERAGE(D30:D33),0) -> 5032 | E36: =ROUND(AVERAGE(E30:E33),0) -> 1139 | F36: =ROUND(AVERAGE(F30:F33),0) -> 6854 | G36: =ROUND(AVERAGE(G30:G33),0) -> 16130
A37: Desvio estandar (todas) | C37: =ROUND(STDEV(C22:C33),0) -> 1770 | D37: =ROUND(STDEV(D22:D33),0) -> 1472 | E37: =ROUND(STDEV(E22:E33),0) -> 564 | F37: =ROUND(STDEV(F22:F33),0) -> 832 | G37: =ROUND(STDEV(G22:G33),0) -> 1282
A38: Mix ultimas 4 semanas (sobre banana) | C38: =SUM(C30:C33)/SUM(G30:G33) -> 0.61739953 | D38: =SUM(D30:D33)/SUM(G30:G33) -> 0.31198562 | E38: =SUM(E30:E33)/SUM(G30:G33) -> 0.070614858 | F38: ="" | G38: =1 -> 1
A39: Lectura: el plan usa 16.000 (sem 28/09) y 17.000 (despues) contra un promedio real de las ultimas 4 semanas que se ve arriba; el mix real de esas 4 semanas es el que reparte los SUPUESTOS de ventas_plan desde el 29/09. El desvio estandar del total alimenta el stock de seguridad de Parametros.

Sheet Cargas
A1: Cargas: un camion por fila
A2: Amarillo = se carga a mano. Descarga = fecha real si la hay; si no, carga + lead time del origen + atraso del escenario. Solo suman los que descargan despues del conteo (Cuenta = 1). Para simular: agregar filas abajo con Estado = Simulado.
A4: N | B4: Fecha carga | C4: Dia | D4: Origen | E4: Productor | F4: Transportista | G4: Cajas (vacio = tipico) | H4: Cajas usadas | I4: Estado | J4: Descarga real | K4: Lead time (dias) | L4: Fecha descarga | M4: Semana de venta (lunes) | N4: Cuenta | O4: USD/caja | P4: Costo USD | Q4: Nota | R4: Descarga pesimista (P90) | S4: Semana de venta P90 | T4: Pipeline (cargado, sin descargar) | U4: OTIF (1 = descargo a tiempo)
A5: =IF(B5="","",ROW()-4) -> 1 | B5: 46288 | C5: =IF(B5="","",TEXT(B5,"ddd")) -> mié | D5: PY | E5: Paraguay AS | F5: MARSO EMPRENDIMIENTOS S.R.L. | G5: 980 | H5: =IF(B5="","",IF(G5<>"",G5,IFERROR(INDEX(CajasOrigen,MATCH(D5,Origenes,0)),CajasProm))) -> 980 | I5: Aloha | J5: 46292 | K5: =IF(B5="","",IFERROR(INDEX(Lags,MATCH(D5,Origenes,0)),LagBR)+IF(J5<>"",0,AtrasoDias)) -> 4 | L5: =IF(B5="","",IF(J5<>"",J5,B5+K5)) -> 46292 | M5: =IF(L5="","",L5-WEEKDAY(L5,2)+1) -> 46286 | N5: =IF(L5="","",IF(L5>FechaConteo,1,0)*IF(I5="Supuesto",SupPY,IF(I5="Supuesto BR",SupBR,1))) -> 1 | O5: =IF(D5="","",IFERROR(INDEX(CostoOrigen,MATCH(D5,Origenes,0)),0)) -> 7 | P5: =IF(H5="","",H5*O5) -> 6860 | Q5: descarga real confirmada por Gonzalo 28/09/2026 ("domingo 27/09 si descarga"): despues del conteo del sabado 26, suma a la semana del 28/09 | R5: =IF(B5="","",IF(J5<>"",J5,B5+IFERROR(INDEX(LagsP90,MATCH(D5,Origenes,0)),K5))) -> 46292 | S5: =IF(R5="","",R5-WEEKDAY(R5,2)+1) -> 46286 | T5: =IF(B5="","",IF(AND(B5<=FechaHoy,J5="",I5<>"Supuesto",I5<>"Simulado"),H5,0)) -> 0 | U5: =IF(J5="","",IF(J5-B5<=K5+1,1,0)) -> 1
A6: =IF(B6="","",ROW()-4) -> 2 | B6: 46290 | C6: =IF(B6="","",TEXT(B6,"ddd")) -> vie | D6: BO | E6: Bolivia | G6: 1050 | H6: =IF(B6="","",IF(G6<>"",G6,IFERROR(INDEX(CajasOrigen,MATCH(D6,Origenes,0)),CajasProm))) -> 1050 | I6: Aloha | K6: =IF(B6="","",IFERROR(INDEX(Lags,MATCH(D6,Origenes,0)),LagBR)+IF(J6<>"",0,AtrasoDias)) -> 6 | L6: =IF(B6="","",IF(J6<>"",J6,B6+K6)) -> 46296 | M6: =IF(L6="","",L6-WEEKDAY(L6,2)+1) -> 46293 | N6: =IF(L6="","",IF(L6>FechaConteo,1,0)*IF(I6="Supuesto",SupPY,IF(I6="Supuesto BR",SupBR,1))) -> 1 | O6: =IF(D6="","",IFERROR(INDEX(CostoOrigen,MATCH(D6,Origenes,0)),0)) -> 10.8 | P6: =IF(H6="","",H6*O6) -> 11340 | Q6: Aloha: Solicitado | R6: =IF(B6="","",IF(J6<>"",J6,B6+IFERROR(INDEX(LagsP90,MATCH(D6,Origenes,0)),K6))) -> 46298 | S6: =IF(R6="","",R6-WEEKDAY(R6,2)+1) -> 46293 | T6: =IF(B6="","",IF(AND(B6<=FechaHoy,J6="",I6<>"Supuesto",I6<>"Simulado"),H6,0)) -> 1050 | U6: =IF(J6="","",IF(J6-B6<=K6+1,1,0))
A7: =IF(B7="","",ROW()-4) -> 3 | B7: 46290 | C7: =IF(B7="","",TEXT(B7,"ddd")) -> vie | D7: BR | E7: Cassio Hauck | G7: 936 | H7: =IF(B7="","",IF(G7<>"",G7,IFERROR(INDEX(CajasOrigen,MATCH(D7,Origenes,0)),CajasProm))) -> 936 | I7: Aloha | K7: =IF(B7="","",IFERROR(INDEX(Lags,MATCH(D7,Origenes,0)),LagBR)+IF(J7<>"",0,AtrasoDias)) -> 3 | L7: =IF(B7="","",IF(J7<>"",J7,B7+K7)) -> 46293 | M7: =IF(L7="","",L7-WEEKDAY(L7,2)+1) -> 46293 | N7: =IF(L7="","",IF(L7>FechaConteo,1,0)*IF(I7="Supuesto",SupPY,IF(I7="Supuesto BR",SupBR,1))) -> 1 | O7: =IF(D7="","",IFERROR(INDEX(CostoOrigen,MATCH(D7,Origenes,0)),0)) -> 7.09 | P7: =IF(H7="","",H7*O7) -> 6636.24 | Q7: Aloha: Solicitado | R7: =IF(B7="","",IF(J7<>"",J7,B7+IFERROR(INDEX(LagsP90,MATCH(D7,Origenes,0)),K7))) -> 46296 | S7: =IF(R7="","",R7-WEEKDAY(R7,2)+1) -> 46293 | T7: =IF(B7="","",IF(AND(B7<=FechaHoy,J7="",I7<>"Supuesto",I7<>"Simulado"),H7,0)) -> 936 | U7: =IF(J7="","",IF(J7-B7<=K7+1,1,0))
A8: =IF(B8="","",ROW()-4) -> 4 | B8: 46290 | C8: =IF(B8="","",TEXT(B8,"ddd")) -> vie | D8: BR | E8: Corupá | F8: FG | G8: 1008 | H8: =IF(B8="","",IF(G8<>"",G8,IFERROR(INDEX(CajasOrigen,MATCH(D8,Origenes,0)),CajasProm))) -> 1008 | I8: Aloha | K8: =IF(B8="","",IFERROR(INDEX(Lags,MATCH(D8,Origenes,0)),LagBR)+IF(J8<>"",0,AtrasoDias)) -> 3 | L8: =IF(B8="","",IF(J8<>"",J8,B8+K8)) -> 46293 | M8: =IF(L8="","",L8-WEEKDAY(L8,2)+1) -> 46293 | N8: =IF(L8="","",IF(L8>FechaConteo,1,0)*IF(I8="Supuesto",SupPY,IF(I8="Supuesto BR",SupBR,1))) -> 1 | O8: =IF(D8="","",IFERROR(INDEX(CostoOrigen,MATCH(D8,Origenes,0)),0)) -> 7.09 | P8: =IF(H8="","",H8*O8) -> 7146.72 | Q8: Aloha: Solicitado | R8: =IF(B8="","",IF(J8<>"",J8,B8+IFERROR(INDEX(LagsP90,MATCH(D8,Origenes,0)),K8))) -> 46296 | S8: =IF(R8="","",R8-WEEKDAY(R8,2)+1) -> 46293 | T8: =IF(B8="","",IF(AND(B8<=FechaHoy,J8="",I8<>"Supuesto",I8<>"Simulado"),H8,0)) -> 1008 | U8: =IF(J8="","",IF(J8-B8<=K8+1,1,0))
A9: =IF(B9="","",ROW()-4) -> 5 | B9: 46293 | C9: =IF(B9="","",TEXT(B9,"ddd")) -> lun | D9: PY | E9: Paraguay AS | G9: 980 | H9: =IF(B9="","",IF(G9<>"",G9,IFERROR(INDEX(CajasOrigen,MATCH(D9,Origenes,0)),CajasProm))) -> 980 | I9: Dictado | K9: =IF(B9="","",IFERROR(INDEX(Lags,MATCH(D9,Origenes,0)),LagBR)+IF(J9<>"",0,AtrasoDias)) -> 4 | L9: =IF(B9="","",IF(J9<>"",J9,B9+K9)) -> 46297 | M9: =IF(L9="","",L9-WEEKDAY(L9,2)+1) -> 46293 | N9: =IF(L9="","",IF(L9>FechaConteo,1,0)*IF(I9="Supuesto",SupPY,IF(I9="Supuesto BR",SupBR,1))) -> 1 | O9: =IF(D9="","",IFERROR(INDEX(CostoOrigen,MATCH(D9,Origenes,0)),0)) -> 7 | P9: =IF(H9="","",H9*O9) -> 6860 | Q9: nota 25/09: Alvarito 1, nota completa 25/09: lunes confirmado | R9: =IF(B9="","",IF(J9<>"",J9,B9+IFERROR(INDEX(LagsP90,MATCH(D9,Origenes,0)),K9))) -> 46298 | S9: =IF(R9="","",R9-WEEKDAY(R9,2)+1) -> 46293 | T9: =IF(B9="","",IF(AND(B9<=FechaHoy,J9="",I9<>"Supuesto",I9<>"Simulado"),H9,0)) -> 980 | U9: =IF(J9="","",IF(J9-B9<=K9+1,1,0))
A10: =IF(B10="","",ROW()-4) -> 6 | B10: 46293 | C10: =IF(B10="","",TEXT(B10,"ddd")) -> lun | D10: PY | E10: Paraguay DF | G10: 980 | H10: =IF(B10="","",IF(G10<>"",G10,IFERROR(INDEX(CajasOrigen,MATCH(D10,Origenes,0)),CajasProm))) -> 980 | I10: Dictado | K10: =IF(B10="","",IFERROR(INDEX(Lags,MATCH(D10,Origenes,0)),LagBR)+IF(J10<>"",0,AtrasoDias)) -> 4 | L10: =IF(B10="","",IF(J10<>"",J10,B10+K10)) -> 46297 | M10: =IF(L10="","",L10-WEEKDAY(L10,2)+1) -> 46293 | N10: =IF(L10="","",IF(L10>FechaConteo,1,0)*IF(I10="Supuesto",SupPY,IF(I10="Supuesto BR",SupBR,1))) -> 1 | O10: =IF(D10="","",IFERROR(INDEX(CostoOrigen,MATCH(D10,Origenes,0)),0)) -> 7 | P10: =IF(H10="","",H10*O10) -> 6860 | Q10: nota 25/09: Diego 2, nota completa 25/09: lunes confirmado | R10: =IF(B10="","",IF(J10<>"",J10,B10+IFERROR(INDEX(LagsP90,MATCH(D10,Origenes,0)),K10))) -> 46298 | S10: =IF(R10="","",R10-WEEKDAY(R10,2)+1) -> 46293 | T10: =IF(B10="","",IF(AND(B10<=FechaHoy,J10="",I10<>"Supuesto",I10<>"Simulado"),H10,0)) -> 980 | U10: =IF(J10="","",IF(J10-B10<=K10+1,1,0))
A11: =IF(B11="","",ROW()-4) -> 7 | B11: 46293 | C11: =IF(B11="","",TEXT(B11,"ddd")) -> lun | D11: PY | E11: Paraguay MS | G11: 980 | H11: =IF(B11="","",IF(G11<>"",G11,IFERROR(INDEX(CajasOrigen,MATCH(D11,Origenes,0)),CajasProm))) -> 980 | I11: Dictado | K11: =IF(B11="","",IFERROR(INDEX(Lags,MATCH(D11,Origenes,0)),LagBR)+IF(J11<>"",0,AtrasoDias)) -> 4 | L11: =IF(B11="","",IF(J11<>"",J11,B11+K11)) -> 46297 | M11: =IF(L11="","",L11-WEEKDAY(L11,2)+1) -> 46293 | N11: =IF(L11="","",IF(L11>FechaConteo,1,0)*IF(I11="Supuesto",SupPY,IF(I11="Supuesto BR",SupBR,1))) -> 1 | O11: =IF(D11="","",IFERROR(INDEX(CostoOrigen,MATCH(D11,Origenes,0)),0)) -> 7 | P11: =IF(H11="","",H11*O11) -> 6860 | Q11: nota 25/09: Milciades 1, nota completa 25/09: lunes confirmado | R11: =IF(B11="","",IF(J11<>"",J11,B11+IFERROR(INDEX(LagsP90,MATCH(D11,Origenes,0)),K11))) -> 46298 | S11: =IF(R11="","",R11-WEEKDAY(R11,2)+1) -> 46293 | T11: =IF(B11="","",IF(AND(B11<=FechaHoy,J11="",I11<>"Supuesto",I11<>"Simulado"),H11,0)) -> 980 | U11: =IF(J11="","",IF(J11-B11<=K11+1,1,0))
A12: =IF(B12="","",ROW()-4) -> 8 | B12: 46294 | C12: =IF(B12="","",TEXT(B12,"ddd")) -> mar | D12: BR | E12: Ivo zimer | F12: Chabat | G12: 1008 | H12: =IF(B12="","",IF(G12<>"",G12,IFERROR(INDEX(CajasOrigen,MATCH(D12,Origenes,0)),CajasProm))) -> 1008 | I12: Dictado | K12: =IF(B12="","",IFERROR(INDEX(Lags,MATCH(D12,Origenes,0)),LagBR)+IF(J12<>"",0,AtrasoDias)) -> 3 | L12: =IF(B12="","",IF(J12<>"",J12,B12+K12)) -> 46297 | M12: =IF(L12="","",L12-WEEKDAY(L12,2)+1) -> 46293 | N12: =IF(L12="","",IF(L12>FechaConteo,1,0)*IF(I12="Supuesto",SupPY,IF(I12="Supuesto BR",SupBR,1))) -> 1 | O12: =IF(D12="","",IFERROR(INDEX(CostoOrigen,MATCH(D12,Origenes,0)),0)) -> 7.09 | P12: =IF(H12="","",H12*O12) -> 7146.72 | Q12: nota 25/09: tersa | R12: =IF(B12="","",IF(J12<>"",J12,B12+IFERROR(INDEX(LagsP90,MATCH(D12,Origenes,0)),K12))) -> 46300 | S12: =IF(R12="","",R12-WEEKDAY(R12,2)+1) -> 46300 | T12: =IF(B12="","",IF(AND(B12<=FechaHoy,J12="",I12<>"Supuesto",I12<>"Simulado"),H12,0)) -> 1008 | U12: =IF(J12="","",IF(J12-B12<=K12+1,1,0))
A13: =IF(B13="","",ROW()-4) -> 9 | B13: 46294 | C13: =IF(B13="","",TEXT(B13,"ddd")) -> mar | D13: PY | E13: Paraguay DF | G13: 980 | H13: =IF(B13="","",IF(G13<>"",G13,IFERROR(INDEX(CajasOrigen,MATCH(D13,Origenes,0)),CajasProm))) -> 980 | I13: Dictado | K13: =IF(B13="","",IFERROR(INDEX(Lags,MATCH(D13,Origenes,0)),LagBR)+IF(J13<>"",0,AtrasoDias)) -> 4 | L13: =IF(B13="","",IF(J13<>"",J13,B13+K13)) -> 46298 | M13: =IF(L13="","",L13-WEEKDAY(L13,2)+1) -> 46293 | N13: =IF(L13="","",IF(L13>FechaConteo,1,0)*IF(I13="Supuesto",SupPY,IF(I13="Supuesto BR",SupBR,1))) -> 1 | O13: =IF(D13="","",IFERROR(INDEX(CostoOrigen,MATCH(D13,Origenes,0)),0)) -> 7 | P13: =IF(H13="","",H13*O13) -> 6860 | Q13: nota 25/09: Diego 2, nota completa 25/09: martes confirmado | R13: =IF(B13="","",IF(J13<>"",J13,B13+IFERROR(INDEX(LagsP90,MATCH(D13,Origenes,0)),K13))) -> 46299 | S13: =IF(R13="","",R13-WEEKDAY(R13,2)+1) -> 46293 | T13: =IF(B13="","",IF(AND(B13<=FechaHoy,J13="",I13<>"Supuesto",I13<>"Simulado"),H13,0)) -> 980 | U13: =IF(J13="","",IF(J13-B13<=K13+1,1,0))
A14: =IF(B14="","",ROW()-4) -> 10 | B14: 46295 | C14: =IF(B14="","",TEXT(B14,"ddd")) -> mié | D14: BR | E14: Agrocurupa | F14: Nilton | G14: 1008 | H14: =IF(B14="","",IF(G14<>"",G14,IFERROR(INDEX(CajasOrigen,MATCH(D14,Origenes,0)),CajasProm))) -> 1008 | I14: Dictado | K14: =IF(B14="","",IFERROR(INDEX(Lags,MATCH(D14,Origenes,0)),LagBR)+IF(J14<>"",0,AtrasoDias)) -> 3 | L14: =IF(B14="","",IF(J14<>"",J14,B14+K14)) -> 46298 | M14: =IF(L14="","",L14-WEEKDAY(L14,2)+1) -> 46293 | N14: =IF(L14="","",IF(L14>FechaConteo,1,0)*IF(I14="Supuesto",SupPY,IF(I14="Supuesto BR",SupBR,1))) -> 1 | O14: =IF(D14="","",IFERROR(INDEX(CostoOrigen,MATCH(D14,Origenes,0)),0)) -> 7.09 | P14: =IF(H14="","",H14*O14) -> 7146.72 | Q14: nota 25/09: cuarta | R14: =IF(B14="","",IF(J14<>"",J14,B14+IFERROR(INDEX(LagsP90,MATCH(D14,Origenes,0)),K14))) -> 46301 | S14: =IF(R14="","",R14-WEEKDAY(R14,2)+1) -> 46300 | T14: =IF(B14="","",IF(AND(B14<=FechaHoy,J14="",I14<>"Supuesto",I14<>"Simulado"),H14,0)) -> 0 | U14: =IF(J14="","",IF(J14-B14<=K14+1,1,0))
A15: =IF(B15="","",ROW()-4) -> 11 | B15: 46295 | C15: =IF(B15="","",TEXT(B15,"ddd")) -> mié | D15: BR | E15: Fisher | F15: Amaro | G15: 1008 | H15: =IF(B15="","",IF(G15<>"",G15,IFERROR(INDEX(CajasOrigen,MATCH(D15,Origenes,0)),CajasProm))) -> 1008 | I15: Dictado | K15: =IF(B15="","",IFERROR(INDEX(Lags,MATCH(D15,Origenes,0)),LagBR)+IF(J15<>"",0,AtrasoDias)) -> 3 | L15: =IF(B15="","",IF(J15<>"",J15,B15+K15)) -> 46298 | M15: =IF(L15="","",L15-WEEKDAY(L15,2)+1) -> 46293 | N15: =IF(L15="","",IF(L15>FechaConteo,1,0)*IF(I15="Supuesto",SupPY,IF(I15="Supuesto BR",SupBR,1))) -> 1 | O15: =IF(D15="","",IFERROR(INDEX(CostoOrigen,MATCH(D15,Origenes,0)),0)) -> 7.09 | P15: =IF(H15="","",H15*O15) -> 7146.72 | Q15: nota 25/09: cuarta | R15: =IF(B15="","",IF(J15<>"",J15,B15+IFERROR(INDEX(LagsP90,MATCH(D15,Origenes,0)),K15))) -> 46301 | S15: =IF(R15="","",R15-WEEKDAY(R15,2)+1) -> 46300 | T15: =IF(B15="","",IF(AND(B15<=FechaHoy,J15="",I15<>"Supuesto",I15<>"Simulado"),H15,0)) -> 0 | U15: =IF(J15="","",IF(J15-B15<=K15+1,1,0))
A16: =IF(B16="","",ROW()-4) -> 12 | B16: 46295 | C16: =IF(B16="","",TEXT(B16,"ddd")) -> mié | D16: BR | E16: Stein | F16: Nilton | G16: 1008 | H16: =IF(B16="","",IF(G16<>"",G16,IFERROR(INDEX(CajasOrigen,MATCH(D16,Origenes,0)),CajasProm))) -> 1008 | I16: Dictado | K16: =IF(B16="","",IFERROR(INDEX(Lags,MATCH(D16,Origenes,0)),LagBR)+IF(J16<>"",0,AtrasoDias)) -> 3 | L16: =IF(B16="","",IF(J16<>"",J16,B16+K16)) -> 46298 | M16: =IF(L16="","",L16-WEEKDAY(L16,2)+1) -> 46293 | N16: =IF(L16="","",IF(L16>FechaConteo,1,0)*IF(I16="Supuesto",SupPY,IF(I16="Supuesto BR",SupBR,1))) -> 1 | O16: =IF(D16="","",IFERROR(INDEX(CostoOrigen,MATCH(D16,Origenes,0)),0)) -> 7.09 | P16: =IF(H16="","",H16*O16) -> 7146.72 | Q16: carga extra: "asi cierro mejor pensando en futuro" (ademas de la sexta ya dictada) | R16: =IF(B16="","",IF(J16<>"",J16,B16+IFERROR(INDEX(LagsP90,MATCH(D16,Origenes,0)),K16))) -> 46301 | S16: =IF(R16="","",R16-WEEKDAY(R16,2)+1) -> 46300 | T16: =IF(B16="","",IF(AND(B16<=FechaHoy,J16="",I16<>"Supuesto",I16<>"Simulado"),H16,0)) -> 0 | U16: =IF(J16="","",IF(J16-B16<=K16+1,1,0))
A17: =IF(B17="","",ROW()-4) -> 13 | B17: 46297 | C17: =IF(B17="","",TEXT(B17,"ddd")) -> vie | D17: BR | E17: Agrocurupa | F17: Nilton | G17: 1008 | H17: =IF(B17="","",IF(G17<>"",G17,IFERROR(INDEX(CajasOrigen,MATCH(D17,Origenes,0)),CajasProm))) -> 1008 | I17: Dictado | K17: =IF(B17="","",IFERROR(INDEX(Lags,MATCH(D17,Origenes,0)),LagBR)+IF(J17<>"",0,AtrasoDias)) -> 3 | L17: =IF(B17="","",IF(J17<>"",J17,B17+K17)) -> 46300 | M17: =IF(L17="","",L17-WEEKDAY(L17,2)+1) -> 46300 | N17: =IF(L17="","",IF(L17>FechaConteo,1,0)*IF(I17="Supuesto",SupPY,IF(I17="Supuesto BR",SupBR,1))) -> 1 | O17: =IF(D17="","",IFERROR(INDEX(CostoOrigen,MATCH(D17,Origenes,0)),0)) -> 7.09 | P17: =IF(H17="","",H17*O17) -> 7146.72 | Q17: nota 25/09: sexta | R17: =IF(B17="","",IF(J17<>"",J17,B17+IFERROR(INDEX(LagsP90,MATCH(D17,Origenes,0)),K17))) -> 46303 | S17: =IF(R17="","",R17-WEEKDAY(R17,2)+1) -> 46300 | T17: =IF(B17="","",IF(AND(B17<=FechaHoy,J17="",I17<>"Supuesto",I17<>"Simulado"),H17,0)) -> 0 | U17: =IF(J17="","",IF(J17-B17<=K17+1,1,0))
A18: =IF(B18="","",ROW()-4) -> 14 | B18: 46297 | C18: =IF(B18="","",TEXT(B18,"ddd")) -> vie | D18: BR | E18: Cassio | F18: Axt | G18: 936 | H18: =IF(B18="","",IF(G18<>"",G18,IFERROR(INDEX(CajasOrigen,MATCH(D18,Origenes,0)),CajasProm))) -> 936 | I18: Dictado | K18: =IF(B18="","",IFERROR(INDEX(Lags,MATCH(D18,Origenes,0)),LagBR)+IF(J18<>"",0,AtrasoDias)) -> 3 | L18: =IF(B18="","",IF(J18<>"",J18,B18+K18)) -> 46300 | M18: =IF(L18="","",L18-WEEKDAY(L18,2)+1) -> 46300 | N18: =IF(L18="","",IF(L18>FechaConteo,1,0)*IF(I18="Supuesto",SupPY,IF(I18="Supuesto BR",SupBR,1))) -> 1 | O18: =IF(D18="","",IFERROR(INDEX(CostoOrigen,MATCH(D18,Origenes,0)),0)) -> 7.09 | P18: =IF(H18="","",H18*O18) -> 6636.24 | Q18: nota 25/09: sexta | R18: =IF(B18="","",IF(J18<>"",J18,B18+IFERROR(INDEX(LagsP90,MATCH(D18,Origenes,0)),K18))) -> 46303 | S18: =IF(R18="","",R18-WEEKDAY(R18,2)+1) -> 46300 | T18: =IF(B18="","",IF(AND(B18<=FechaHoy,J18="",I18<>"Supuesto",I18<>"Simulado"),H18,0)) -> 0 | U18: =IF(J18="","",IF(J18-B18<=K18+1,1,0))
A19: =IF(B19="","",ROW()-4) -> 15 | B19: 46297 | C19: =IF(B19="","",TEXT(B19,"ddd")) -> vie | D19: BR | E19: Fisher | F19: Amaro | G19: 1008 | H19: =IF(B19="","",IF(G19<>"",G19,IFERROR(INDEX(CajasOrigen,MATCH(D19,Origenes,0)),CajasProm))) -> 1008 | I19: Dictado | K19: =IF(B19="","",IFERROR(INDEX(Lags,MATCH(D19,Origenes,0)),LagBR)+IF(J19<>"",0,AtrasoDias)) -> 3 | L19: =IF(B19="","",IF(J19<>"",J19,B19+K19)) -> 46300 | M19: =IF(L19="","",L19-WEEKDAY(L19,2)+1) -> 46300 | N19: =IF(L19="","",IF(L19>FechaConteo,1,0)*IF(I19="Supuesto",SupPY,IF(I19="Supuesto BR",SupBR,1))) -> 1 | O19: =IF(D19="","",IFERROR(INDEX(CostoOrigen,MATCH(D19,Origenes,0)),0)) -> 7.09 | P19: =IF(H19="","",H19*O19) -> 7146.72 | Q19: nota 25/09: sexta | R19: =IF(B19="","",IF(J19<>"",J19,B19+IFERROR(INDEX(LagsP90,MATCH(D19,Origenes,0)),K19))) -> 46303 | S19: =IF(R19="","",R19-WEEKDAY(R19,2)+1) -> 46300 | T19: =IF(B19="","",IF(AND(B19<=FechaHoy,J19="",I19<>"Supuesto",I19<>"Simulado"),H19,0)) -> 0 | U19: =IF(J19="","",IF(J19-B19<=K19+1,1,0))
A20: =IF(B20="","",ROW()-4) -> 16 | B20: 46297 | C20: =IF(B20="","",TEXT(B20,"ddd")) -> vie | D20: BR | E20: Gilson | F20: Nilton | G20: 1008 | H20: =IF(B20="","",IF(G20<>"",G20,IFERROR(INDEX(CajasOrigen,MATCH(D20,Origenes,0)),CajasProm))) -> 1008 | I20: Dictado | K20: =IF(B20="","",IFERROR(INDEX(Lags,MATCH(D20,Origenes,0)),LagBR)+IF(J20<>"",0,AtrasoDias)) -> 3 | L20: =IF(B20="","",IF(J20<>"",J20,B20+K20)) -> 46300 | M20: =IF(L20="","",L20-WEEKDAY(L20,2)+1) -> 46300 | N20: =IF(L20="","",IF(L20>FechaConteo,1,0)*IF(I20="Supuesto",SupPY,IF(I20="Supuesto BR",SupBR,1))) -> 1 | O20: =IF(D20="","",IFERROR(INDEX(CostoOrigen,MATCH(D20,Origenes,0)),0)) -> 7.09 | P20: =IF(H20="","",H20*O20) -> 7146.72 | Q20: nota 25/09: sexta | R20: =IF(B20="","",IF(J20<>"",J20,B20+IFERROR(INDEX(LagsP90,MATCH(D20,Origenes,0)),K20))) -> 46303 | S20: =IF(R20="","",R20-WEEKDAY(R20,2)+1) -> 46300 | T20: =IF(B20="","",IF(AND(B20<=FechaHoy,J20="",I20<>"Supuesto",I20<>"Simulado"),H20,0)) -> 0 | U20: =IF(J20="","",IF(J20-B20<=K20+1,1,0))
A21: =IF(B21="","",ROW()-4) -> 17 | B21: 46297 | C21: =IF(B21="","",TEXT(B21,"ddd")) -> vie | D21: BR | E21: Ivo zimer | F21: Chabat | G21: 1008 | H21: =IF(B21="","",IF(G21<>"",G21,IFERROR(INDEX(CajasOrigen,MATCH(D21,Origenes,0)),CajasProm))) -> 1008 | I21: Dictado | K21: =IF(B21="","",IFERROR(INDEX(Lags,MATCH(D21,Origenes,0)),LagBR)+IF(J21<>"",0,AtrasoDias)) -> 3 | L21: =IF(B21="","",IF(J21<>"",J21,B21+K21)) -> 46300 | M21: =IF(L21="","",L21-WEEKDAY(L21,2)+1) -> 46300 | N21: =IF(L21="","",IF(L21>FechaConteo,1,0)*IF(I21="Supuesto",SupPY,IF(I21="Supuesto BR",SupBR,1))) -> 1 | O21: =IF(D21="","",IFERROR(INDEX(CostoOrigen,MATCH(D21,Origenes,0)),0)) -> 7.09 | P21: =IF(H21="","",H21*O21) -> 7146.72 | Q21: nota 25/09: sexta | R21: =IF(B21="","",IF(J21<>"",J21,B21+IFERROR(INDEX(LagsP90,MATCH(D21,Origenes,0)),K21))) -> 46303 | S21: =IF(R21="","",R21-WEEKDAY(R21,2)+1) -> 46300 | T21: =IF(B21="","",IF(AND(B21<=FechaHoy,J21="",I21<>"Supuesto",I21<>"Simulado"),H21,0)) -> 0 | U21: =IF(J21="","",IF(J21-B21<=K21+1,1,0))
A22: =IF(B22="","",ROW()-4) -> 18 | B22: 46297 | C22: =IF(B22="","",TEXT(B22,"ddd")) -> vie | D22: BR | E22: Josemar | F22: Nilton | G22: 1008 | H22: =IF(B22="","",IF(G22<>"",G22,IFERROR(INDEX(CajasOrigen,MATCH(D22,Origenes,0)),CajasProm))) -> 1008 | I22: Dictado | K22: =IF(B22="","",IFERROR(INDEX(Lags,MATCH(D22,Origenes,0)),LagBR)+IF(J22<>"",0,AtrasoDias)) -> 3 | L22: =IF(B22="","",IF(J22<>"",J22,B22+K22)) -> 46300 | M22: =IF(L22="","",L22-WEEKDAY(L22,2)+1) -> 46300 | N22: =IF(L22="","",IF(L22>FechaConteo,1,0)*IF(I22="Supuesto",SupPY,IF(I22="Supuesto BR",SupBR,1))) -> 1 | O22: =IF(D22="","",IFERROR(INDEX(CostoOrigen,MATCH(D22,Origenes,0)),0)) -> 7.09 | P22: =IF(H22="","",H22*O22) -> 7146.72 | Q22: nota 25/09: sexta | R22: =IF(B22="","",IF(J22<>"",J22,B22+IFERROR(INDEX(LagsP90,MATCH(D22,Origenes,0)),K22))) -> 46303 | S22: =IF(R22="","",R22-WEEKDAY(R22,2)+1) -> 46300 | T22: =IF(B22="","",IF(AND(B22<=FechaHoy,J22="",I22<>"Supuesto",I22<>"Simulado"),H22,0)) -> 0 | U22: =IF(J22="","",IF(J22-B22<=K22+1,1,0))
A23: =IF(B23="","",ROW()-4) -> 19 | B23: 46297 | C23: =IF(B23="","",TEXT(B23,"ddd")) -> vie | D23: BR | E23: Marconi | F23: Chabat | G23: 1008 | H23: =IF(B23="","",IF(G23<>"",G23,IFERROR(INDEX(CajasOrigen,MATCH(D23,Origenes,0)),CajasProm))) -> 1008 | I23: Dictado | K23: =IF(B23="","",IFERROR(INDEX(Lags,MATCH(D23,Origenes,0)),LagBR)+IF(J23<>"",0,AtrasoDias)) -> 3 | L23: =IF(B23="","",IF(J23<>"",J23,B23+K23)) -> 46300 | M23: =IF(L23="","",L23-WEEKDAY(L23,2)+1) -> 46300 | N23: =IF(L23="","",IF(L23>FechaConteo,1,0)*IF(I23="Supuesto",SupPY,IF(I23="Supuesto BR",SupBR,1))) -> 1 | O23: =IF(D23="","",IFERROR(INDEX(CostoOrigen,MATCH(D23,Origenes,0)),0)) -> 7.09 | P23: =IF(H23="","",H23*O23) -> 7146.72 | Q23: nota 25/09: sexta | R23: =IF(B23="","",IF(J23<>"",J23,B23+IFERROR(INDEX(LagsP90,MATCH(D23,Origenes,0)),K23))) -> 46303 | S23: =IF(R23="","",R23-WEEKDAY(R23,2)+1) -> 46300 | T23: =IF(B23="","",IF(AND(B23<=FechaHoy,J23="",I23<>"Supuesto",I23<>"Simulado"),H23,0)) -> 0 | U23: =IF(J23="","",IF(J23-B23<=K23+1,1,0))
A24: =IF(B24="","",ROW()-4) -> 20 | B24: 46297 | C24: =IF(B24="","",TEXT(B24,"ddd")) -> vie | D24: BR | E24: Stein | F24: Nilton | G24: 1008 | H24: =IF(B24="","",IF(G24<>"",G24,IFERROR(INDEX(CajasOrigen,MATCH(D24,Origenes,0)),CajasProm))) -> 1008 | I24: Dictado | K24: =IF(B24="","",IFERROR(INDEX(Lags,MATCH(D24,Origenes,0)),LagBR)+IF(J24<>"",0,AtrasoDias)) -> 3 | L24: =IF(B24="","",IF(J24<>"",J24,B24+K24)) -> 46300 | M24: =IF(L24="","",L24-WEEKDAY(L24,2)+1) -> 46300 | N24: =IF(L24="","",IF(L24>FechaConteo,1,0)*IF(I24="Supuesto",SupPY,IF(I24="Supuesto BR",SupBR,1))) -> 1 | O24: =IF(D24="","",IFERROR(INDEX(CostoOrigen,MATCH(D24,Origenes,0)),0)) -> 7.09 | P24: =IF(H24="","",H24*O24) -> 7146.72 | Q24: nota 25/09: sexta | R24: =IF(B24="","",IF(J24<>"",J24,B24+IFERROR(INDEX(LagsP90,MATCH(D24,Origenes,0)),K24))) -> 46303 | S24: =IF(R24="","",R24-WEEKDAY(R24,2)+1) -> 46300 | T24: =IF(B24="","",IF(AND(B24<=FechaHoy,J24="",I24<>"Supuesto",I24<>"Simulado"),H24,0)) -> 0 | U24: =IF(J24="","",IF(J24-B24<=K24+1,1,0))
A25: =IF(B25="","",ROW()-4) -> 21 | B25: 46300 | C25: =IF(B25="","",TEXT(B25,"ddd")) -> lun | D25: PY | E25: Paraguay (supuesto) | G25: 980 | H25: =IF(B25="","",IF(G25<>"",G25,IFERROR(INDEX(CajasOrigen,MATCH(D25,Origenes,0)),CajasProm))) -> 980 | I25: Supuesto | K25: =IF(B25="","",IFERROR(INDEX(Lags,MATCH(D25,Origenes,0)),LagBR)+IF(J25<>"",0,AtrasoDias)) -> 4 | L25: =IF(B25="","",IF(J25<>"",J25,B25+K25)) -> 46304 | M25: =IF(L25="","",L25-WEEKDAY(L25,2)+1) -> 46300 | N25: =IF(L25="","",IF(L25>FechaConteo,1,0)*IF(I25="Supuesto",SupPY,IF(I25="Supuesto BR",SupBR,1))) -> 1 | O25: =IF(D25="","",IFERROR(INDEX(CostoOrigen,MATCH(D25,Origenes,0)),0)) -> 7 | P25: =IF(H25="","",H25*O25) -> 6860 | Q25: supuesto: 5 camiones PY por semana, cargan dom-lun-mar (Gonzalo 27/09) | R25: =IF(B25="","",IF(J25<>"",J25,B25+IFERROR(INDEX(LagsP90,MATCH(D25,Origenes,0)),K25))) -> 46305 | S25: =IF(R25="","",R25-WEEKDAY(R25,2)+1) -> 46300 | T25: =IF(B25="","",IF(AND(B25<=FechaHoy,J25="",I25<>"Supuesto",I25<>"Simulado"),H25,0)) -> 0 | U25: =IF(J25="","",IF(J25-B25<=K25+1,1,0))
A26: =IF(B26="","",ROW()-4) -> 22 | B26: 46300 | C26: =IF(B26="","",TEXT(B26,"ddd")) -> lun | D26: PY | E26: Paraguay (supuesto) | G26: 980 | H26: =IF(B26="","",IF(G26<>"",G26,IFERROR(INDEX(CajasOrigen,MATCH(D26,Origenes,0)),CajasProm))) -> 980 | I26: Supuesto | K26: =IF(B26="","",IFERROR(INDEX(Lags,MATCH(D26,Origenes,0)),LagBR)+IF(J26<>"",0,AtrasoDias)) -> 4 | L26: =IF(B26="","",IF(J26<>"",J26,B26+K26)) -> 46304 | M26: =IF(L26="","",L26-WEEKDAY(L26,2)+1) -> 46300 | N26: =IF(L26="","",IF(L26>FechaConteo,1,0)*IF(I26="Supuesto",SupPY,IF(I26="Supuesto BR",SupBR,1))) -> 1 | O26: =IF(D26="","",IFERROR(INDEX(CostoOrigen,MATCH(D26,Origenes,0)),0)) -> 7 | P26: =IF(H26="","",H26*O26) -> 6860 | Q26: supuesto: 5 camiones PY por semana, cargan dom-lun-mar (Gonzalo 27/09) | R26: =IF(B26="","",IF(J26<>"",J26,B26+IFERROR(INDEX(LagsP90,MATCH(D26,Origenes,0)),K26))) -> 46305 | S26: =IF(R26="","",R26-WEEKDAY(R26,2)+1) -> 46300 | T26: =IF(B26="","",IF(AND(B26<=FechaHoy,J26="",I26<>"Supuesto",I26<>"Simulado"),H26,0)) -> 0 | U26: =IF(J26="","",IF(J26-B26<=K26+1,1,0))
A27: =IF(B27="","",ROW()-4) -> 23 | B27: 46300 | C27: =IF(B27="","",TEXT(B27,"ddd")) -> lun | D27: PY | E27: Paraguay (supuesto) | G27: 980 | H27: =IF(B27="","",IF(G27<>"",G27,IFERROR(INDEX(CajasOrigen,MATCH(D27,Origenes,0)),CajasProm))) -> 980 | I27: Supuesto | K27: =IF(B27="","",IFERROR(INDEX(Lags,MATCH(D27,Origenes,0)),LagBR)+IF(J27<>"",0,AtrasoDias)) -> 4 | L27: =IF(B27="","",IF(J27<>"",J27,B27+K27)) -> 46304 | M27: =IF(L27="","",L27-WEEKDAY(L27,2)+1) -> 46300 | N27: =IF(L27="","",IF(L27>FechaConteo,1,0)*IF(I27="Supuesto",SupPY,IF(I27="Supuesto BR",SupBR,1))) -> 1 | O27: =IF(D27="","",IFERROR(INDEX(CostoOrigen,MATCH(D27,Origenes,0)),0)) -> 7 | P27: =IF(H27="","",H27*O27) -> 6860 | Q27: supuesto: 5 camiones PY por semana, cargan dom-lun-mar (Gonzalo 27/09) | R27: =IF(B27="","",IF(J27<>"",J27,B27+IFERROR(INDEX(LagsP90,MATCH(D27,Origenes,0)),K27))) -> 46305 | S27: =IF(R27="","",R27-WEEKDAY(R27,2)+1) -> 46300 | T27: =IF(B27="","",IF(AND(B27<=FechaHoy,J27="",I27<>"Supuesto",I27<>"Simulado"),H27,0)) -> 0 | U27: =IF(J27="","",IF(J27-B27<=K27+1,1,0))
A28: =IF(B28="","",ROW()-4) -> 24 | B28: 46300 | C28: =IF(B28="","",TEXT(B28,"ddd")) -> lun | D28: PY | E28: Paraguay (supuesto) | G28: 980 | H28: =IF(B28="","",IF(G28<>"",G28,IFERROR(INDEX(CajasOrigen,MATCH(D28,Origenes,0)),CajasProm))) -> 980 | I28: Supuesto | K28: =IF(B28="","",IFERROR(INDEX(Lags,MATCH(D28,Origenes,0)),LagBR)+IF(J28<>"",0,AtrasoDias)) -> 4 | L28: =IF(B28="","",IF(J28<>"",J28,B28+K28)) -> 46304 | M28: =IF(L28="","",L28-WEEKDAY(L28,2)+1) -> 46300 | N28: =IF(L28="","",IF(L28>FechaConteo,1,0)*IF(I28="Supuesto",SupPY,IF(I28="Supuesto BR",SupBR,1))) -> 1 | O28: =IF(D28="","",IFERROR(INDEX(CostoOrigen,MATCH(D28,Origenes,0)),0)) -> 7 | P28: =IF(H28="","",H28*O28) -> 6860 | Q28: supuesto: 5 camiones PY por semana, cargan dom-lun-mar (Gonzalo 27/09) | R28: =IF(B28="","",IF(J28<>"",J28,B28+IFERROR(INDEX(LagsP90,MATCH(D28,Origenes,0)),K28))) -> 46305 | S28: =IF(R28="","",R28-WEEKDAY(R28,2)+1) -> 46300 | T28: =IF(B28="","",IF(AND(B28<=FechaHoy,J28="",I28<>"Supuesto",I28<>"Simulado"),H28,0)) -> 0 | U28: =IF(J28="","",IF(J28-B28<=K28+1,1,0))
A29: =IF(B29="","",ROW()-4) -> 25 | B29: 46300 | C29: =IF(B29="","",TEXT(B29,"ddd")) -> lun | D29: PY | E29: Paraguay (supuesto) | G29: 980 | H29: =IF(B29="","",IF(G29<>"",G29,IFERROR(INDEX(CajasOrigen,MATCH(D29,Origenes,0)),CajasProm))) -> 980 | I29: Supuesto | K29: =IF(B29="","",IFERROR(INDEX(Lags,MATCH(D29,Origenes,0)),LagBR)+IF(J29<>"",0,AtrasoDias)) -> 4 | L29: =IF(B29="","",IF(J29<>"",J29,B29+K29)) -> 46304 | M29: =IF(L29="","",L29-WEEKDAY(L29,2)+1) -> 46300 | N29: =IF(L29="","",IF(L29>FechaConteo,1,0)*IF(I29="Supuesto",SupPY,IF(I29="Supuesto BR",SupBR,1))) -> 1 | O29: =IF(D29="","",IFERROR(INDEX(CostoOrigen,MATCH(D29,Origenes,0)),0)) -> 7 | P29: =IF(H29="","",H29*O29) -> 6860 | Q29: supuesto: 5 camiones PY por semana, cargan dom-lun-mar (Gonzalo 27/09) | R29: =IF(B29="","",IF(J29<>"",J29,B29+IFERROR(INDEX(LagsP90,MATCH(D29,Origenes,0)),K29))) -> 46305 | S29: =IF(R29="","",R29-WEEKDAY(R29,2)+1) -> 46300 | T29: =IF(B29="","",IF(AND(B29<=FechaHoy,J29="",I29<>"Supuesto",I29<>"Simulado"),H29,0)) -> 0 | U29: =IF(J29="","",IF(J29-B29<=K29+1,1,0))
A30: =IF(B30="","",ROW()-4) -> 26 | B30: 46304 | C30: =IF(B30="","",TEXT(B30,"ddd")) -> vie | D30: BR | E30: Brasil (supuesto) | G30: 1008 | H30: =IF(B30="","",IF(G30<>"",G30,IFERROR(INDEX(CajasOrigen,MATCH(D30,Origenes,0)),CajasProm))) -> 1008 | I30: Supuesto BR | K30: =IF(B30="","",IFERROR(INDEX(Lags,MATCH(D30,Origenes,0)),LagBR)+IF(J30<>"",0,AtrasoDias)) -> 3 | L30: =IF(B30="","",IF(J30<>"",J30,B30+K30)) -> 46307 | M30: =IF(L30="","",L30-WEEKDAY(L30,2)+1) -> 46307 | N30: =IF(L30="","",IF(L30>FechaConteo,1,0)*IF(I30="Supuesto",SupPY,IF(I30="Supuesto BR",SupBR,1))) -> 1 | O30: =IF(D30="","",IFERROR(INDEX(CostoOrigen,MATCH(D30,Origenes,0)),0)) -> 7.09 | P30: =IF(H30="","",H30*O30) -> 7146.72 | Q30: supuesto: 8 camiones BR los viernes, ritmo habitual (Gonzalo 28/09); se apaga en Parametros > SupBR | R30: =IF(B30="","",IF(J30<>"",J30,B30+IFERROR(INDEX(LagsP90,MATCH(D30,Origenes,0)),K30))) -> 46310 | S30: =IF(R30="","",R30-WEEKDAY(R30,2)+1) -> 46307 | T30: =IF(B30="","",IF(AND(B30<=FechaHoy,J30="",I30<>"Supuesto",I30<>"Simulado"),H30,0)) -> 0 | U30: =IF(J30="","",IF(J30-B30<=K30+1,1,0))
A31: =IF(B31="","",ROW()-4) -> 27 | B31: 46304 | C31: =IF(B31="","",TEXT(B31,"ddd")) -> vie | D31: BR | E31: Brasil (supuesto) | G31: 1008 | H31: =IF(B31="","",IF(G31<>"",G31,IFERROR(INDEX(CajasOrigen,MATCH(D31,Origenes,0)),CajasProm))) -> 1008 | I31: Supuesto BR | K31: =IF(B31="","",IFERROR(INDEX(Lags,MATCH(D31,Origenes,0)),LagBR)+IF(J31<>"",0,AtrasoDias)) -> 3 | L31: =IF(B31="","",IF(J31<>"",J31,B31+K31)) -> 46307 | M31: =IF(L31="","",L31-WEEKDAY(L31,2)+1) -> 46307 | N31: =IF(L31="","",IF(L31>FechaConteo,1,0)*IF(I31="Supuesto",SupPY,IF(I31="Supuesto BR",SupBR,1))) -> 1 | O31: =IF(D31="","",IFERROR(INDEX(CostoOrigen,MATCH(D31,Origenes,0)),0)) -> 7.09 | P31: =IF(H31="","",H31*O31) -> 7146.72 | Q31: supuesto: 8 camiones BR los viernes, ritmo habitual (Gonzalo 28/09); se apaga en Parametros > SupBR | R31: =IF(B31="","",IF(J31<>"",J31,B31+IFERROR(INDEX(LagsP90,MATCH(D31,Origenes,0)),K31))) -> 46310 | S31: =IF(R31="","",R31-WEEKDAY(R31,2)+1) -> 46307 | T31: =IF(B31="","",IF(AND(B31<=FechaHoy,J31="",I31<>"Supuesto",I31<>"Simulado"),H31,0)) -> 0 | U31: =IF(J31="","",IF(J31-B31<=K31+1,1,0))
A32: =IF(B32="","",ROW()-4) -> 28 | B32: 46304 | C32: =IF(B32="","",TEXT(B32,"ddd")) -> vie | D32: BR | E32: Brasil (supuesto) | G32: 1008 | H32: =IF(B32="","",IF(G32<>"",G32,IFERROR(INDEX(CajasOrigen,MATCH(D32,Origenes,0)),CajasProm))) -> 1008 | I32: Supuesto BR | K32: =IF(B32="","",IFERROR(INDEX(Lags,MATCH(D32,Origenes,0)),LagBR)+IF(J32<>"",0,AtrasoDias)) -> 3 | L32: =IF(B32="","",IF(J32<>"",J32,B32+K32)) -> 46307 | M32: =IF(L32="","",L32-WEEKDAY(L32,2)+1) -> 46307 | N32: =IF(L32="","",IF(L32>FechaConteo,1,0)*IF(I32="Supuesto",SupPY,IF(I32="Supuesto BR",SupBR,1))) -> 1 | O32: =IF(D32="","",IFERROR(INDEX(CostoOrigen,MATCH(D32,Origenes,0)),0)) -> 7.09 | P32: =IF(H32="","",H32*O32) -> 7146.72 | Q32: supuesto: 8 camiones BR los viernes, ritmo habitual (Gonzalo 28/09); se apaga en Parametros > SupBR | R32: =IF(B32="","",IF(J32<>"",J32,B32+IFERROR(INDEX(LagsP90,MATCH(D32,Origenes,0)),K32))) -> 46310 | S32: =IF(R32="","",R32-WEEKDAY(R32,2)+1) -> 46307 | T32: =IF(B32="","",IF(AND(B32<=FechaHoy,J32="",I32<>"Supuesto",I32<>"Simulado"),H32,0)) -> 0 | U32: =IF(J32="","",IF(J32-B32<=K32+1,1,0))
A33: =IF(B33="","",ROW()-4) -> 29 | B33: 46304 | C33: =IF(B33="","",TEXT(B33,"ddd")) -> vie | D33: BR | E33: Brasil (supuesto) | G33: 1008 | H33: =IF(B33="","",IF(G33<>"",G33,IFERROR(INDEX(CajasOrigen,MATCH(D33,Origenes,0)),CajasProm))) -> 1008 | I33: Supuesto BR | K33: =IF(B33="","",IFERROR(INDEX(Lags,MATCH(D33,Origenes,0)),LagBR)+IF(J33<>"",0,AtrasoDias)) -> 3 | L33: =IF(B33="","",IF(J33<>"",J33,B33+K33)) -> 46307 | M33: =IF(L33="","",L33-WEEKDAY(L33,2)+1) -> 46307 | N33: =IF(L33="","",IF(L33>FechaConteo,1,0)*IF(I33="Supuesto",SupPY,IF(I33="Supuesto BR",SupBR,1))) -> 1 | O33: =IF(D33="","",IFERROR(INDEX(CostoOrigen,MATCH(D33,Origenes,0)),0)) -> 7.09 | P33: =IF(H33="","",H33*O33) -> 7146.72 | Q33: supuesto: 8 camiones BR los viernes, ritmo habitual (Gonzalo 28/09); se apaga en Parametros > SupBR | R33: =IF(B33="","",IF(J33<>"",J33,B33+IFERROR(INDEX(LagsP90,MATCH(D33,Origenes,0)),K33))) -> 46310 | S33: =IF(R33="","",R33-WEEKDAY(R33,2)+1) -> 46307 | T33: =IF(B33="","",IF(AND(B33<=FechaHoy,J33="",I33<>"Supuesto",I33<>"Simulado"),H33,0)) -> 0 | U33: =IF(J33="","",IF(J33-B33<=K33+1,1,0))
A34: =IF(B34="","",ROW()-4) -> 30 | B34: 46304 | C34: =IF(B34="","",TEXT(B34,"ddd")) -> vie | D34: BR | E34: Brasil (supuesto) | G34: 1008 | H34: =IF(B34="","",IF(G34<>"",G34,IFERROR(INDEX(CajasOrigen,MATCH(D34,Origenes,0)),CajasProm))) -> 1008 | I34: Supuesto BR | K34: =IF(B34="","",IFERROR(INDEX(Lags,MATCH(D34,Origenes,0)),LagBR)+IF(J34<>"",0,AtrasoDias)) -> 3 | L34: =IF(B34="","",IF(J34<>"",J34,B34+K34)) -> 46307 | M34: =IF(L34="","",L34-WEEKDAY(L34,2)+1) -> 46307 | N34: =IF(L34="","",IF(L34>FechaConteo,1,0)*IF(I34="Supuesto",SupPY,IF(I34="Supuesto BR",SupBR,1))) -> 1 | O34: =IF(D34="","",IFERROR(INDEX(CostoOrigen,MATCH(D34,Origenes,0)),0)) -> 7.09 | P34: =IF(H34="","",H34*O34) -> 7146.72 | Q34: supuesto: 8 camiones BR los viernes, ritmo habitual (Gonzalo 28/09); se apaga en Parametros > SupBR | R34: =IF(B34="","",IF(J34<>"",J34,B34+IFERROR(INDEX(LagsP90,MATCH(D34,Origenes,0)),K34))) -> 46310 | S34: =IF(R34="","",R34-WEEKDAY(R34,2)+1) -> 46307 | T34: =IF(B34="","",IF(AND(B34<=FechaHoy,J34="",I34<>"Supuesto",I34<>"Simulado"),H34,0)) -> 0 | U34: =IF(J34="","",IF(J34-B34<=K34+1,1,0))
A35: =IF(B35="","",ROW()-4) -> 31 | B35: 46304 | C35: =IF(B35="","",TEXT(B35,"ddd")) -> vie | D35: BR | E35: Brasil (supuesto) | G35: 1008 | H35: =IF(B35="","",IF(G35<>"",G35,IFERROR(INDEX(CajasOrigen,MATCH(D35,Origenes,0)),CajasProm))) -> 1008 | I35: Supuesto BR | K35: =IF(B35="","",IFERROR(INDEX(Lags,MATCH(D35,Origenes,0)),LagBR)+IF(J35<>"",0,AtrasoDias)) -> 3 | L35: =IF(B35="","",IF(J35<>"",J35,B35+K35)) -> 46307 | M35: =IF(L35="","",L35-WEEKDAY(L35,2)+1) -> 46307 | N35: =IF(L35="","",IF(L35>FechaConteo,1,0)*IF(I35="Supuesto",SupPY,IF(I35="Supuesto BR",SupBR,1))) -> 1 | O35: =IF(D35="","",IFERROR(INDEX(CostoOrigen,MATCH(D35,Origenes,0)),0)) -> 7.09 | P35: =IF(H35="","",H35*O35) -> 7146.72 | Q35: supuesto: 8 camiones BR los viernes, ritmo habitual (Gonzalo 28/09); se apaga en Parametros > SupBR | R35: =IF(B35="","",IF(J35<>"",J35,B35+IFERROR(INDEX(LagsP90,MATCH(D35,Origenes,0)),K35))) -> 46310 | S35: =IF(R35="","",R35-WEEKDAY(R35,2)+1) -> 46307 | T35: =IF(B35="","",IF(AND(B35<=FechaHoy,J35="",I35<>"Supuesto",I35<>"Simulado"),H35,0)) -> 0 | U35: =IF(J35="","",IF(J35-B35<=K35+1,1,0))
A36: =IF(B36="","",ROW()-4) -> 32 | B36: 46304 | C36: =IF(B36="","",TEXT(B36,"ddd")) -> vie | D36: BR | E36: Brasil (supuesto) | G36: 1008 | H36: =IF(B36="","",IF(G36<>"",G36,IFERROR(INDEX(CajasOrigen,MATCH(D36,Origenes,0)),CajasProm))) -> 1008 | I36: Supuesto BR | K36: =IF(B36="","",IFERROR(INDEX(Lags,MATCH(D36,Origenes,0)),LagBR)+IF(J36<>"",0,AtrasoDias)) -> 3 | L36: =IF(B36="","",IF(J36<>"",J36,B36+K36)) -> 46307 | M36: =IF(L36="","",L36-WEEKDAY(L36,2)+1) -> 46307 | N36: =IF(L36="","",IF(L36>FechaConteo,1,0)*IF(I36="Supuesto",SupPY,IF(I36="Supuesto BR",SupBR,1))) -> 1 | O36: =IF(D36="","",IFERROR(INDEX(CostoOrigen,MATCH(D36,Origenes,0)),0)) -> 7.09 | P36: =IF(H36="","",H36*O36) -> 7146.72 | Q36: supuesto: 8 camiones BR los viernes, ritmo habitual (Gonzalo 28/09); se apaga en Parametros > SupBR | R36: =IF(B36="","",IF(J36<>"",J36,B36+IFERROR(INDEX(LagsP90,MATCH(D36,Origenes,0)),K36))) -> 46310 | S36: =IF(R36="","",R36-WEEKDAY(R36,2)+1) -> 46307 | T36: =IF(B36="","",IF(AND(B36<=FechaHoy,J36="",I36<>"Supuesto",I36<>"Simulado"),H36,0)) -> 0 | U36: =IF(J36="","",IF(J36-B36<=K36+1,1,0))
... A127: =IF(B127="","",ROW()-4) -> 123 | B127: 46374 | C127: =IF(B127="","",TEXT(B127,"ddd")) -> vie | D127: BR | E127: Brasil (supuesto) | G127: 1008 | H127: =IF(B127="","",IF(G127<>"",G127,IFERROR(INDEX(CajasOrigen,MATCH(D127,Origenes,0)),CajasProm))) -> 1008 | I127: Supuesto BR | K127: =IF(B127="","",IFERROR(INDEX(Lags,MATCH(D127,Origenes,0)),LagBR)+IF(J127<>"",0,AtrasoDias)) -> 3 | L127: =IF(B127="","",IF(J127<>"",J127,B127+K127)) -> 46377 | M127: =IF(L127="","",L127-WEEKDAY(L127,2)+1) -> 46377 | N127: =IF(L127="","",IF(L127>FechaConteo,1,0)*IF(I127="Supuesto",SupPY,IF(I127="Supuesto BR",SupBR,1))) -> 1 | O127: =IF(D127="","",IFERROR(INDEX(CostoOrigen,MATCH(D127,Origenes,0)),0)) -> 7.09 | P127: =IF(H127="","",H127*O127) -> 7146.72 | Q127: supuesto: 8 camiones BR los viernes, ritmo habitual (Gonzalo 28/09); se apaga en Parametros > SupBR | R127: =IF(B127="","",IF(J127<>"",J127,B127+IFERROR(INDEX(LagsP90,MATCH(D127,Origenes,0)),K127))) -> 46380 | S127: =IF(R127="","",R127-WEEKDAY(R127,2)+1) -> 46377 | T127: =IF(B127="","",IF(AND(B127<=FechaHoy,J127="",I127<>"Supuesto",I127<>"Simulado"),H127,0)) -> 0 | U127: =IF(J127="","",IF(J127-B127<=K127+1,1,0))
A128: =IF(B128="","",ROW()-4) | C128: =IF(B128="","",TEXT(B128,"ddd")) | H128: =IF(B128="","",IF(G128<>"",G128,IFERROR(INDEX(CajasOrigen,MATCH(D128,Origenes,0)),CajasProm))) | K128: =IF(B128="","",IFERROR(INDEX(Lags,MATCH(D128,Origenes,0)),LagBR)+IF(J128<>"",0,AtrasoDias)) | L128: =IF(B128="","",IF(J128<>"",J128,B128+K128)) | M128: =IF(L128="","",L128-WEEKDAY(L128,2)+1) | N128: =IF(L128="","",IF(L128>FechaConteo,1,0)*IF(I128="Supuesto",SupPY,IF(I128="Supuesto BR",SupBR,1))) | O128: =IF(D128="","",IFERROR(INDEX(CostoOrigen,MATCH(D128,Origenes,0)),0)) | P128: =IF(H128="","",H128*O128) | R128: =IF(B128="","",IF(J128<>"",J128,B128+IFERROR(INDEX(LagsP90,MATCH(D128,Origenes,0)),K128))) | S128: =IF(R128="","",R128-WEEKDAY(R128,2)+1) | T128: =IF(B128="","",IF(AND(B128<=FechaHoy,J128="",I128<>"Supuesto",I128<>"Simulado"),H128,0)) | U128: =IF(J128="","",IF(J128-B128<=K128+1,1,0))
A129: =IF(B129="","",ROW()-4) | C129: =IF(B129="","",TEXT(B129,"ddd")) | H129: =IF(B129="","",IF(G129<>"",G129,IFERROR(INDEX(CajasOrigen,MATCH(D129,Origenes,0)),CajasProm))) | K129: =IF(B129="","",IFERROR(INDEX(Lags,MATCH(D129,Origenes,0)),LagBR)+IF(J129<>"",0,AtrasoDias)) | L129: =IF(B129="","",IF(J129<>"",J129,B129+K129)) | M129: =IF(L129="","",L129-WEEKDAY(L129,2)+1) | N129: =IF(L129="","",IF(L129>FechaConteo,1,0)*IF(I129="Supuesto",SupPY,IF(I129="Supuesto BR",SupBR,1))) | O129: =IF(D129="","",IFERROR(INDEX(CostoOrigen,MATCH(D129,Origenes,0)),0)) | P129: =IF(H129="","",H129*O129) | R129: =IF(B129="","",IF(J129<>"",J129,B129+IFERROR(INDEX(LagsP90,MATCH(D129,Origenes,0)),K129))) | S129: =IF(R129="","",R129-WEEKDAY(R129,2)+1) | T129: =IF(B129="","",IF(AND(B129<=FechaHoy,J129="",I129<>"Supuesto",I129<>"Simulado"),H129,0)) | U129: =IF(J129="","",IF(J129-B129<=K129+1,1,0))
A130: =IF(B130="","",ROW()-4) | C130: =IF(B130="","",TEXT(B130,"ddd")) | H130: =IF(B130="","",IF(G130<>"",G130,IFERROR(INDEX(CajasOrigen,MATCH(D130,Origenes,0)),CajasProm))) | K130: =IF(B130="","",IFERROR(INDEX(Lags,MATCH(D130,Origenes,0)),LagBR)+IF(J130<>"",0,AtrasoDias)) | L130: =IF(B130="","",IF(J130<>"",J130,B130+K130)) | M130: =IF(L130="","",L130-WEEKDAY(L130,2)+1) | N130: =IF(L130="","",IF(L130>FechaConteo,1,0)*IF(I130="Supuesto",SupPY,IF(I130="Supuesto BR",SupBR,1))) | O130: =IF(D130="","",IFERROR(INDEX(CostoOrigen,MATCH(D130,Origenes,0)),0)) | P130: =IF(H130="","",H130*O130) | R130: =IF(B130="","",IF(J130<>"",J130,B130+IFERROR(INDEX(LagsP90,MATCH(D130,Origenes,0)),K130))) | S130: =IF(R130="","",R130-WEEKDAY(R130,2)+1) | T130: =IF(B130="","",IF(AND(B130<=FechaHoy,J130="",I130<>"Supuesto",I130<>"Simulado"),H130,0)) | U130: =IF(J130="","",IF(J130-B130<=K130+1,1,0))
A131: =IF(B131="","",ROW()-4) | C131: =IF(B131="","",TEXT(B131,"ddd")) | H131: =IF(B131="","",IF(G131<>"",G131,IFERROR(INDEX(CajasOrigen,MATCH(D131,Origenes,0)),CajasProm))) | K131: =IF(B131="","",IFERROR(INDEX(Lags,MATCH(D131,Origenes,0)),LagBR)+IF(J131<>"",0,AtrasoDias)) | L131: =IF(B131="","",IF(J131<>"",J131,B131+K131)) | M131: =IF(L131="","",L131-WEEKDAY(L131,2)+1) | N131: =IF(L131="","",IF(L131>FechaConteo,1,0)*IF(I131="Supuesto",SupPY,IF(I131="Supuesto BR",SupBR,1))) | O131: =IF(D131="","",IFERROR(INDEX(CostoOrigen,MATCH(D131,Origenes,0)),0)) | P131: =IF(H131="","",H131*O131) | R131: =IF(B131="","",IF(J131<>"",J131,B131+IFERROR(INDEX(LagsP90,MATCH(D131,Origenes,0)),K131))) | S131: =IF(R131="","",R131-WEEKDAY(R131,2)+1) | T131: =IF(B131="","",IF(AND(B131<=FechaHoy,J131="",I131<>"Supuesto",I131<>"Simulado"),H131,0)) | U131: =IF(J131="","",IF(J131-B131<=K131+1,1,0))
A132: =IF(B132="","",ROW()-4) | C132: =IF(B132="","",TEXT(B132,"ddd")) | H132: =IF(B132="","",IF(G132<>"",G132,IFERROR(INDEX(CajasOrigen,MATCH(D132,Origenes,0)),CajasProm))) | K132: =IF(B132="","",IFERROR(INDEX(Lags,MATCH(D132,Origenes,0)),LagBR)+IF(J132<>"",0,AtrasoDias)) | L132: =IF(B132="","",IF(J132<>"",J132,B132+K132)) | M132: =IF(L132="","",L132-WEEKDAY(L132,2)+1) | N132: =IF(L132="","",IF(L132>FechaConteo,1,0)*IF(I132="Supuesto",SupPY,IF(I132="Supuesto BR",SupBR,1))) | O132: =IF(D132="","",IFERROR(INDEX(CostoOrigen,MATCH(D132,Origenes,0)),0)) | P132: =IF(H132="","",H132*O132) | R132: =IF(B132="","",IF(J132<>"",J132,B132+IFERROR(INDEX(LagsP90,MATCH(D132,Origenes,0)),K132))) | S132: =IF(R132="","",R132-WEEKDAY(R132,2)+1) | T132: =IF(B132="","",IF(AND(B132<=FechaHoy,J132="",I132<>"Supuesto",I132<>"Simulado"),H132,0)) | U132: =IF(J132="","",IF(J132-B132<=K132+1,1,0))
A133: =IF(B133="","",ROW()-4) | C133: =IF(B133="","",TEXT(B133,"ddd")) | H133: =IF(B133="","",IF(G133<>"",G133,IFERROR(INDEX(CajasOrigen,MATCH(D133,Origenes,0)),CajasProm))) | K133: =IF(B133="","",IFERROR(INDEX(Lags,MATCH(D133,Origenes,0)),LagBR)+IF(J133<>"",0,AtrasoDias)) | L133: =IF(B133="","",IF(J133<>"",J133,B133+K133)) | M133: =IF(L133="","",L133-WEEKDAY(L133,2)+1) | N133: =IF(L133="","",IF(L133>FechaConteo,1,0)*IF(I133="Supuesto",SupPY,IF(I133="Supuesto BR",SupBR,1))) | O133: =IF(D133="","",IFERROR(INDEX(CostoOrigen,MATCH(D133,Origenes,0)),0)) | P133: =IF(H133="","",H133*O133) | R133: =IF(B133="","",IF(J133<>"",J133,B133+IFERROR(INDEX(LagsP90,MATCH(D133,Origenes,0)),K133))) | S133: =IF(R133="","",R133-WEEKDAY(R133,2)+1) | T133: =IF(B133="","",IF(AND(B133<=FechaHoy,J133="",I133<>"Supuesto",I133<>"Simulado"),H133,0)) | U133: =IF(J133="","",IF(J133-B133<=K133+1,1,0))
A134: =IF(B134="","",ROW()-4) | C134: =IF(B134="","",TEXT(B134,"ddd")) | H134: =IF(B134="","",IF(G134<>"",G134,IFERROR(INDEX(CajasOrigen,MATCH(D134,Origenes,0)),CajasProm))) | K134: =IF(B134="","",IFERROR(INDEX(Lags,MATCH(D134,Origenes,0)),LagBR)+IF(J134<>"",0,AtrasoDias)) | L134: =IF(B134="","",IF(J134<>"",J134,B134+K134)) | M134: =IF(L134="","",L134-WEEKDAY(L134,2)+1) | N134: =IF(L134="","",IF(L134>FechaConteo,1,0)*IF(I134="Supuesto",SupPY,IF(I134="Supuesto BR",SupBR,1))) | O134: =IF(D134="","",IFERROR(INDEX(CostoOrigen,MATCH(D134,Origenes,0)),0)) | P134: =IF(H134="","",H134*O134) | R134: =IF(B134="","",IF(J134<>"",J134,B134+IFERROR(INDEX(LagsP90,MATCH(D134,Origenes,0)),K134))) | S134: =IF(R134="","",R134-WEEKDAY(R134,2)+1) | T134: =IF(B134="","",IF(AND(B134<=FechaHoy,J134="",I134<>"Supuesto",I134<>"Simulado"),H134,0)) | U134: =IF(J134="","",IF(J134-B134<=K134+1,1,0))
A135: =IF(B135="","",ROW()-4) | C135: =IF(B135="","",TEXT(B135,"ddd")) | H135: =IF(B135="","",IF(G135<>"",G135,IFERROR(INDEX(CajasOrigen,MATCH(D135,Origenes,0)),CajasProm))) | K135: =IF(B135="","",IFERROR(INDEX(Lags,MATCH(D135,Origenes,0)),LagBR)+IF(J135<>"",0,AtrasoDias)) | L135: =IF(B135="","",IF(J135<>"",J135,B135+K135)) | M135: =IF(L135="","",L135-WEEKDAY(L135,2)+1) | N135: =IF(L135="","",IF(L135>FechaConteo,1,0)*IF(I135="Supuesto",SupPY,IF(I135="Supuesto BR",SupBR,1))) | O135: =IF(D135="","",IFERROR(INDEX(CostoOrigen,MATCH(D135,Origenes,0)),0)) | P135: =IF(H135="","",H135*O135) | R135: =IF(B135="","",IF(J135<>"",J135,B135+IFERROR(INDEX(LagsP90,MATCH(D135,Origenes,0)),K135))) | S135: =IF(R135="","",R135-WEEKDAY(R135,2)+1) | T135: =IF(B135="","",IF(AND(B135<=FechaHoy,J135="",I135<>"Supuesto",I135<>"Simulado"),H135,0)) | U135: =IF(J135="","",IF(J135-B135<=K135+1,1,0))
A136: =IF(B136="","",ROW()-4) | C136: =IF(B136="","",TEXT(B136,"ddd")) | H136: =IF(B136="","",IF(G136<>"",G136,IFERROR(INDEX(CajasOrigen,MATCH(D136,Origenes,0)),CajasProm))) | K136: =IF(B136="","",IFERROR(INDEX(Lags,MATCH(D136,Origenes,0)),LagBR)+IF(J136<>"",0,AtrasoDias)) | L136: =IF(B136="","",IF(J136<>"",J136,B136+K136)) | M136: =IF(L136="","",L136-WEEKDAY(L136,2)+1) | N136: =IF(L136="","",IF(L136>FechaConteo,1,0)*IF(I136="Supuesto",SupPY,IF(I136="Supuesto BR",SupBR,1))) | O136: =IF(D136="","",IFERROR(INDEX(CostoOrigen,MATCH(D136,Origenes,0)),0)) | P136: =IF(H136="","",H136*O136) | R136: =IF(B136="","",IF(J136<>"",J136,B136+IFERROR(INDEX(LagsP90,MATCH(D136,Origenes,0)),K136))) | S136: =IF(R136="","",R136-WEEKDAY(R136,2)+1) | T136: =IF(B136="","",IF(AND(B136<=FechaHoy,J136="",I136<>"Supuesto",I136<>"Simulado"),H136,0)) | U136: =IF(J136="","",IF(J136-B136<=K136+1,1,0))
A137: =IF(B137="","",ROW()-4) | C137: =IF(B137="","",TEXT(B137,"ddd")) | H137: =IF(B137="","",IF(G137<>"",G137,IFERROR(INDEX(CajasOrigen,MATCH(D137,Origenes,0)),CajasProm))) | K137: =IF(B137="","",IFERROR(INDEX(Lags,MATCH(D137,Origenes,0)),LagBR)+IF(J137<>"",0,AtrasoDias)) | L137: =IF(B137="","",IF(J137<>"",J137,B137+K137)) | M137: =IF(L137="","",L137-WEEKDAY(L137,2)+1) | N137: =IF(L137="","",IF(L137>FechaConteo,1,0)*IF(I137="Supuesto",SupPY,IF(I137="Supuesto BR",SupBR,1))) | O137: =IF(D137="","",IFERROR(INDEX(CostoOrigen,MATCH(D137,Origenes,0)),0)) | P137: =IF(H137="","",H137*O137) | R137: =IF(B137="","",IF(J137<>"",J137,B137+IFERROR(INDEX(LagsP90,MATCH(D137,Origenes,0)),K137))) | S137: =IF(R137="","",R137-WEEKDAY(R137,2)+1) | T137: =IF(B137="","",IF(AND(B137<=FechaHoy,J137="",I137<>"Supuesto",I137<>"Simulado"),H137,0)) | U137: =IF(J137="","",IF(J137-B137<=K137+1,1,0))
A138: =IF(B138="","",ROW()-4) | C138: =IF(B138="","",TEXT(B138,"ddd")) | H138: =IF(B138="","",IF(G138<>"",G138,IFERROR(INDEX(CajasOrigen,MATCH(D138,Origenes,0)),CajasProm))) | K138: =IF(B138="","",IFERROR(INDEX(Lags,MATCH(D138,Origenes,0)),LagBR)+IF(J138<>"",0,AtrasoDias)) | L138: =IF(B138="","",IF(J138<>"",J138,B138+K138)) | M138: =IF(L138="","",L138-WEEKDAY(L138,2)+1) | N138: =IF(L138="","",IF(L138>FechaConteo,1,0)*IF(I138="Supuesto",SupPY,IF(I138="Supuesto BR",SupBR,1))) | O138: =IF(D138="","",IFERROR(INDEX(CostoOrigen,MATCH(D138,Origenes,0)),0)) | P138: =IF(H138="","",H138*O138) | R138: =IF(B138="","",IF(J138<>"",J138,B138+IFERROR(INDEX(LagsP90,MATCH(D138,Origenes,0)),K138))) | S138: =IF(R138="","",R138-WEEKDAY(R138,2)+1) | T138: =IF(B138="","",IF(AND(B138<=FechaHoy,J138="",I138<>"Supuesto",I138<>"Simulado"),H138,0)) | U138: =IF(J138="","",IF(J138-B138<=K138+1,1,0))
A139: =IF(B139="","",ROW()-4) | C139: =IF(B139="","",TEXT(B139,"ddd")) | H139: =IF(B139="","",IF(G139<>"",G139,IFERROR(INDEX(CajasOrigen,MATCH(D139,Origenes,0)),CajasProm))) | K139: =IF(B139="","",IFERROR(INDEX(Lags,MATCH(D139,Origenes,0)),LagBR)+IF(J139<>"",0,AtrasoDias)) | L139: =IF(B139="","",IF(J139<>"",J139,B139+K139)) | M139: =IF(L139="","",L139-WEEKDAY(L139,2)+1) | N139: =IF(L139="","",IF(L139>FechaConteo,1,0)*IF(I139="Supuesto",SupPY,IF(I139="Supuesto BR",SupBR,1))) | O139: =IF(D139="","",IFERROR(INDEX(CostoOrigen,MATCH(D139,Origenes,0)),0)) | P139: =IF(H139="","",H139*O139) | R139: =IF(B139="","",IF(J139<>"",J139,B139+IFERROR(INDEX(LagsP90,MATCH(D139,Origenes,0)),K139))) | S139: =IF(R139="","",R139-WEEKDAY(R139,2)+1) | T139: =IF(B139="","",IF(AND(B139<=FechaHoy,J139="",I139<>"Supuesto",I139<>"Simulado"),H139,0)) | U139: =IF(J139="","",IF(J139-B139<=K139+1,1,0))
... A300: =IF(B300="","",ROW()-4) | C300: =IF(B300="","",TEXT(B300,"ddd")) | H300: =IF(B300="","",IF(G300<>"",G300,IFERROR(INDEX(CajasOrigen,MATCH(D300,Origenes,0)),CajasProm))) | K300: =IF(B300="","",IFERROR(INDEX(Lags,MATCH(D300,Origenes,0)),LagBR)+IF(J300<>"",0,AtrasoDias)) | L300: =IF(B300="","",IF(J300<>"",J300,B300+K300)) | M300: =IF(L300="","",L300-WEEKDAY(L300,2)+1) | N300: =IF(L300="","",IF(L300>FechaConteo,1,0)*IF(I300="Supuesto",SupPY,IF(I300="Supuesto BR",SupBR,1))) | O300: =IF(D300="","",IFERROR(INDEX(CostoOrigen,MATCH(D300,Origenes,0)),0)) | P300: =IF(H300="","",H300*O300) | R300: =IF(B300="","",IF(J300<>"",J300,B300+IFERROR(INDEX(LagsP90,MATCH(D300,Origenes,0)),K300))) | S300: =IF(R300="","",R300-WEEKDAY(R300,2)+1) | T300: =IF(B300="","",IF(AND(B300<=FechaHoy,J300="",I300<>"Supuesto",I300<>"Simulado"),H300,0)) | U300: =IF(J300="","",IF(J300-B300<=K300+1,1,0))

Sheet Proyeccion
A1: Proyeccion de stock al cierre de cada sabado
A2: Stock final = stock inicial + cajas que descargan en la semana - venta. Los camiones a cargar se arrastran: "Stock proyectado" ya incluye los pedidos de las semanas anteriores. La primera semana (la del conteo) va prorrateada por los dias que quedan.
A5: Semana (lunes) | B5: Sabado | C5: Stock inicial | D5: Camiones que descargan | E5: Cajas que descargan | F5: Venta | G5: Stock final (sin pedidos) | H5: Pedidos anteriores (cajas) | I5: STOCK PROYECTADO | J5: Fecha limite de carga (el lead time mas largo BR/PY) | K5: CAMIONES A CARGAR | L5: Stock con pedido | M5: Dias de cobertura | N5: Estado | O5: BR stock | P5: BR dias | Q5: PY stock | R5: PY dias | S5: BO stock | T5: BO dias | U5: Origen mas justo
A6: =Demanda!A6 -> 46286 | B6: =A6+5 -> 46291 | C6: =ConteoTotal -> 26972 | D6: =COUNTIFS(CgSemana,A6,CgCuenta,1) -> 1 | E6: =SUMIFS(CgCajas,CgSemana,A6,CgCuenta,1) -> 980 | F6: =ROUND(Demanda!H6*MAX(0,MIN(DiasVenta,B6-FechaConteo))/DiasVenta,0) -> 0 | G6: =C6+E6-F6 -> 27952 | H6: =0 -> 0 | I6: =G6+H6 -> 27952 | J6: =B6-MAX(LagBR,LagPY)-AtrasoDias -> 46287 | K6: =IF(AND(I6<MinimoSabado,J6>=FechaHoy),ROUNDUP((MinimoSabado-I6)/CajasProm,0),0) -> 0 | L6: =I6+K6*CajasProm -> 27952 | M6: =IF(Demanda!H7=0,"",L6/(Demanda!H7/DiasVenta)) -> 10.482 | N6: =IF(I6<0,"FALTA",IF(K6>0,"CARGAR "&K6,IF(I6<MinimoSabado,"BAJO MINIMO (limite pasado)",IF(AND(M6<>"",M6>VidaVerde),"EXCESO (merma)","OK")))) -> OK | O6: =ConteoBR+SUMIFS(CgCajas,CgSemana,A6,CgCuenta,1,CgOrigen,"BR")-ROUND(Demanda!L6*MAX(0,MIN(DiasVenta,B6-FechaConteo))/DiasVenta,0) -> 11653 | P6: =IF(Demanda!L7=0,"",O6/(Demanda!L7/DiasVenta)) -> 8.0923611 | Q6: =ConteoPY+SUMIFS(CgCajas,CgSemana,A6,CgCuenta,1,CgOrigen,"PY")-ROUND(Demanda!M6*MAX(0,MIN(DiasVenta,B6-FechaConteo))/DiasVenta,0) -> 14653 | R6: =IF(Demanda!M7=0,"",Q6/(Demanda!M7/DiasVenta)) -> 13.946383 | S6: =ConteoBO+SUMIFS(CgCajas,CgSemana,A6,CgCuenta,1,CgOrigen,"BO")-ROUND(Demanda!N6*MAX(0,MIN(DiasVenta,B6-FechaConteo))/DiasVenta,0) -> 1646 | T6: =IF(Demanda!N7=0,"",S6/(Demanda!N7/DiasVenta)) -> 9.3522727 | U6: =IF(P6=MIN(P6,R6,T6),"Brasil",IF(R6=MIN(P6,R6,T6),"Paraguay","Bolivia")) -> Brasil
A7: =Demanda!A7 -> 46293 | B7: =A7+5 -> 46298 | C7: =G6 -> 27952 | D7: =COUNTIFS(CgSemana,A7,CgCuenta,1) -> 11 | E7: =SUMIFS(CgCajas,CgSemana,A7,CgCuenta,1) -> 10946 | F7: =ROUND(Demanda!H7,0) -> 16000 | G7: =C7+E7-F7 -> 22898 | H7: =SUM($K$6:K6)*CajasProm -> 0 | I7: =G7+H7 -> 22898 | J7: =B7-MAX(LagBR,LagPY)-AtrasoDias -> 46294 | K7: =IF(AND(I7<MinimoSabado,J7>=FechaHoy),ROUNDUP((MinimoSabado-I7)/CajasProm,0),0) -> 0 | L7: =I7+K7*CajasProm -> 22898 | M7: =IF(Demanda!H8=0,"",L7/(Demanda!H8/DiasVenta)) -> 8.0816471 | N7: =IF(I7<0,"FALTA",IF(K7>0,"CARGAR "&K7,IF(I7<MinimoSabado,"BAJO MINIMO (limite pasado)",IF(AND(M7<>"",M7>VidaVerde),"EXCESO (merma)","OK")))) -> OK | O7: =O6+SUMIFS(CgCajas,CgSemana,A7,CgCuenta,1,CgOrigen,"BR")-ROUND(Demanda!L7,0) -> 8989 | P7: =IF(Demanda!L8=0,"",O7/(Demanda!L8/DiasVenta)) -> 5.1419582 | Q7: =Q6+SUMIFS(CgCajas,CgSemana,A7,CgCuenta,1,CgOrigen,"PY")-ROUND(Demanda!M7,0) -> 12269 | R7: =IF(Demanda!M8=0,"",Q7/(Demanda!M8/DiasVenta)) -> 13.878959 | S7: =S6+SUMIFS(CgCajas,CgSemana,A7,CgCuenta,1,CgOrigen,"BO")-ROUND(Demanda!N7,0) -> 1640 | T7: =IF(Demanda!N8=0,"",S7/(Demanda!N8/DiasVenta)) -> 8.1524441 | U7: =IF(P7=MIN(P7,R7,T7),"Brasil",IF(R7=MIN(P7,R7,T7),"Paraguay","Bolivia")) -> Brasil
A8: =Demanda!A8 -> 46300 | B8: =A8+5 -> 46305 | C8: =G7 -> 22898 | D8: =COUNTIFS(CgSemana,A8,CgCuenta,1) -> 13 | E8: =SUMIFS(CgCajas,CgSemana,A8,CgCuenta,1) -> 12892 | F8: =ROUND(Demanda!H8,0) -> 17000 | G8: =C8+E8-F8 -> 18790 | H8: =SUM($K$6:K7)*CajasProm -> 0 | I8: =G8+H8 -> 18790 | J8: =B8-MAX(LagBR,LagPY)-AtrasoDias -> 46301 | K8: =IF(AND(I8<MinimoSabado,J8>=FechaHoy),ROUNDUP((MinimoSabado-I8)/CajasProm,0),0) -> 4 | L8: =I8+K8*CajasProm -> 22790 | M8: =IF(Demanda!H9=0,"",L8/(Demanda!H9/DiasVenta)) -> 8.0435294 | N8: =IF(I8<0,"FALTA",IF(K8>0,"CARGAR "&K8,IF(I8<MinimoSabado,"BAJO MINIMO (limite pasado)",IF(AND(M8<>"",M8>VidaVerde),"EXCESO (merma)","OK")))) -> CARGAR 4 | O8: =O7+SUMIFS(CgCajas,CgSemana,A8,CgCuenta,1,CgOrigen,"BR")-ROUND(Demanda!L8,0) -> 6492 | P8: =IF(Demanda!L9=0,"",O8/(Demanda!L9/DiasVenta)) -> 3.7136047 | Q8: =Q7+SUMIFS(CgCajas,CgSemana,A8,CgCuenta,1,CgOrigen,"PY")-ROUND(Demanda!M8,0) -> 11865 | R8: =IF(Demanda!M9=0,"",Q8/(Demanda!M9/DiasVenta)) -> 13.421946 | S8: =S7+SUMIFS(CgCajas,CgSemana,A8,CgCuenta,1,CgOrigen,"BO")-ROUND(Demanda!N8,0) -> 433 | T8: =IF(Demanda!N9=0,"",S8/(Demanda!N9/DiasVenta)) -> 2.1524441 | U8: =IF(P8=MIN(P8,R8,T8),"Brasil",IF(R8=MIN(P8,R8,T8),"Paraguay","Bolivia")) -> Bolivia
A9: =Demanda!A9 -> 46307 | B9: =A9+5 -> 46312 | C9: =G8 -> 18790 | D9: =COUNTIFS(CgSemana,A9,CgCuenta,1) -> 13 | E9: =SUMIFS(CgCajas,CgSemana,A9,CgCuenta,1) -> 12964 | F9: =ROUND(Demanda!H9,0) -> 17000 | G9: =C9+E9-F9 -> 14754 | H9: =SUM($K$6:K8)*CajasProm -> 4000 | I9: =G9+H9 -> 18754 | J9: =B9-MAX(LagBR,LagPY)-AtrasoDias -> 46308 | K9: =IF(AND(I9<MinimoSabado,J9>=FechaHoy),ROUNDUP((MinimoSabado-I9)/CajasProm,0),0) -> 4 | L9: =I9+K9*CajasProm -> 22754 | M9: =IF(Demanda!H10=0,"",L9/(Demanda!H10/DiasVenta)) -> 8.0308235 | N9: =IF(I9<0,"FALTA",IF(K9>0,"CARGAR "&K9,IF(I9<MinimoSabado,"BAJO MINIMO (limite pasado)",IF(AND(M9<>"",M9>VidaVerde),"EXCESO (merma)","OK")))) -> CARGAR 4 | O9: =O8+SUMIFS(CgCajas,CgSemana,A9,CgCuenta,1,CgOrigen,"BR")-ROUND(Demanda!L9,0) -> 4067 | P9: =IF(Demanda!L10=0,"",O9/(Demanda!L10/DiasVenta)) -> 2.3264372 | Q9: =Q8+SUMIFS(CgCajas,CgSemana,A9,CgCuenta,1,CgOrigen,"PY")-ROUND(Demanda!M9,0) -> 11461 | R9: =IF(Demanda!M10=0,"",Q9/(Demanda!M10/DiasVenta)) -> 12.964932 | S9: =S8+SUMIFS(CgCajas,CgSemana,A9,CgCuenta,1,CgOrigen,"BO")-ROUND(Demanda!N9,0) -> -774 | T9: =IF(Demanda!N10=0,"",S9/(Demanda!N10/DiasVenta)) -> -3.8475559 | U9: =IF(P9=MIN(P9,R9,T9),"Brasil",IF(R9=MIN(P9,R9,T9),"Paraguay","Bolivia")) -> Bolivia
A10: =Demanda!A10 -> 46314 | B10: =A10+5 -> 46319 | C10: =G9 -> 14754 | D10: =COUNTIFS(CgSemana,A10,CgCuenta,1) -> 13 | E10: =SUMIFS(CgCajas,CgSemana,A10,CgCuenta,1) -> 12964 | F10: =ROUND(Demanda!H10,0) -> 17000 | G10: =C10+E10-F10 -> 10718 | H10: =SUM($K$6:K9)*CajasProm -> 8000 | I10: =G10+H10 -> 18718 | J10: =B10-MAX(LagBR,LagPY)-AtrasoDias -> 46315 | K10: =IF(AND(I10<MinimoSabado,J10>=FechaHoy),ROUNDUP((MinimoSabado-I10)/CajasProm,0),0) -> 4 | L10: =I10+K10*CajasProm -> 22718 | M10: =IF(Demanda!H11=0,"",L10/(Demanda!H11/DiasVenta)) -> 8.0181176 | N10: =IF(I10<0,"FALTA",IF(K10>0,"CARGAR "&K10,IF(I10<MinimoSabado,"BAJO MINIMO (limite pasado)",IF(AND(M10<>"",M10>VidaVerde),"EXCESO (merma)","OK")))) -> CARGAR 4 | O10: =O9+SUMIFS(CgCajas,CgSemana,A10,CgCuenta,1,CgOrigen,"BR")-ROUND(Demanda!L10,0) -> 1642 | P10: =IF(Demanda!L11=0,"",O10/(Demanda!L11/DiasVenta)) -> 0.93926971 | Q10: =Q9+SUMIFS(CgCajas,CgSemana,A10,CgCuenta,1,CgOrigen,"PY")-ROUND(Demanda!M10,0) -> 11057 | R10: =IF(Demanda!M11=0,"",Q10/(Demanda!M11/DiasVenta)) -> 12.507919 | S10: =S9+SUMIFS(CgCajas,CgSemana,A10,CgCuenta,1,CgOrigen,"BO")-ROUND(Demanda!N10,0) -> -1981 | T10: =IF(Demanda!N11=0,"",S10/(Demanda!N11/DiasVenta)) -> -9.8475559 | U10: =IF(P10=MIN(P10,R10,T10),"Brasil",IF(R10=MIN(P10,R10,T10),"Paraguay","Bolivia")) -> Bolivia
A11: =Demanda!A11 -> 46321 | B11: =A11+5 -> 46326 | C11: =G10 -> 10718 | D11: =COUNTIFS(CgSemana,A11,CgCuenta,1) -> 8 | E11: =SUMIFS(CgCajas,CgSemana,A11,CgCuenta,1) -> 8064 | F11: =ROUND(Demanda!H11,0) -> 17000 | G11: =C11+E11-F11 -> 1782 | H11: =SUM($K$6:K10)*CajasProm -> 12000 | I11: =G11+H11 -> 13782 | J11: =B11-MAX(LagBR,LagPY)-AtrasoDias -> 46322 | K11: =IF(AND(I11<MinimoSabado,J11>=FechaHoy),ROUNDUP((MinimoSabado-I11)/CajasProm,0),0) -> 9 | L11: =I11+K11*CajasProm -> 22782 | M11: =IF(Demanda!H12=0,"",L11/(Demanda!H12/DiasVenta)) -> 8.0407059 | N11: =IF(I11<0,"FALTA",IF(K11>0,"CARGAR "&K11,IF(I11<MinimoSabado,"BAJO MINIMO (limite pasado)",IF(AND(M11<>"",M11>VidaVerde),"EXCESO (merma)","OK")))) -> CARGAR 9 | O11: =O10+SUMIFS(CgCajas,CgSemana,A11,CgCuenta,1,CgOrigen,"BR")-ROUND(Demanda!L11,0) -> -783 | P11: =IF(Demanda!L12=0,"",O11/(Demanda!L12/DiasVenta)) -> -0.4478978 | Q11: =Q10+SUMIFS(CgCajas,CgSemana,A11,CgCuenta,1,CgOrigen,"PY")-ROUND(Demanda!M11,0) -> 5753 | R11: =IF(Demanda!M12=0,"",Q11/(Demanda!M12/DiasVenta)) -> 6.5079186 | S11: =S10+SUMIFS(CgCajas,CgSemana,A11,CgCuenta,1,CgOrigen,"BO")-ROUND(Demanda!N11,0) -> -3188 | T11: =IF(Demanda!N12=0,"",S11/(Demanda!N12/DiasVenta)) -> -15.847556 | U11: =IF(P11=MIN(P11,R11,T11),"Brasil",IF(R11=MIN(P11,R11,T11),"Paraguay","Bolivia")) -> Bolivia
A12: =Demanda!A12 -> 46328 | B12: =A12+5 -> 46333 | C12: =G11 -> 1782 | D12: =COUNTIFS(CgSemana,A12,CgCuenta,1) -> 8 | E12: =SUMIFS(CgCajas,CgSemana,A12,CgCuenta,1) -> 8064 | F12: =ROUND(Demanda!H12,0) -> 17000 | G12: =C12+E12-F12 -> -7154 | H12: =SUM($K$6:K11)*CajasProm -> 21000 | I12: =G12+H12 -> 13846 | J12: =B12-MAX(LagBR,LagPY)-AtrasoDias -> 46329 | K12: =IF(AND(I12<MinimoSabado,J12>=FechaHoy),ROUNDUP((MinimoSabado-I12)/CajasProm,0),0) -> 9 | L12: =I12+K12*CajasProm -> 22846 | M12: =IF(Demanda!H13=0,"",L12/(Demanda!H13/DiasVenta)) -> 8.0632941 | N12: =IF(I12<0,"FALTA",IF(K12>0,"CARGAR "&K12,IF(I12<MinimoSabado,"BAJO MINIMO (limite pasado)",IF(AND(M12<>"",M12>VidaVerde),"EXCESO (merma)","OK")))) -> CARGAR 9 | O12: =O11+SUMIFS(CgCajas,CgSemana,A12,CgCuenta,1,CgOrigen,"BR")-ROUND(Demanda!L12,0) -> -3208 | P12: =IF(Demanda!L13=0,"",O12/(Demanda!L13/DiasVenta)) -> -1.8350653 | Q12: =Q11+SUMIFS(CgCajas,CgSemana,A12,CgCuenta,1,CgOrigen,"PY")-ROUND(Demanda!M12,0) -> 449 | R12: =IF(Demanda!M13=0,"",Q12/(Demanda!M13/DiasVenta)) -> 0.50791855 | S12: =S11+SUMIFS(CgCajas,CgSemana,A12,CgCuenta,1,CgOrigen,"BO")-ROUND(Demanda!N12,0) -> -4395 | T12: =IF(Demanda!N13=0,"",S12/(Demanda!N13/DiasVenta)) -> -21.847556 | U12: =IF(P12=MIN(P12,R12,T12),"Brasil",IF(R12=MIN(P12,R12,T12),"Paraguay","Bolivia")) -> Bolivia
A13: =Demanda!A13 -> 46335 | B13: =A13+5 -> 46340 | C13: =G12 -> -7154 | D13: =COUNTIFS(CgSemana,A13,CgCuenta,1) -> 8 | E13: =SUMIFS(CgCajas,CgSemana,A13,CgCuenta,1) -> 8064 | F13: =ROUND(Demanda!H13,0) -> 17000 | G13: =C13+E13-F13 -> -16090 | H13: =SUM($K$6:K12)*CajasProm -> 30000 | I13: =G13+H13 -> 13910 | J13: =B13-MAX(LagBR,LagPY)-AtrasoDias -> 46336 | K13: =IF(AND(I13<MinimoSabado,J13>=FechaHoy),ROUNDUP((MinimoSabado-I13)/CajasProm,0),0) -> 9 | L13: =I13+K13*CajasProm -> 22910 | M13: =IF(Demanda!H14=0,"",L13/(Demanda!H14/DiasVenta)) -> 8.0858824 | N13: =IF(I13<0,"FALTA",IF(K13>0,"CARGAR "&K13,IF(I13<MinimoSabado,"BAJO MINIMO (limite pasado)",IF(AND(M13<>"",M13>VidaVerde),"EXCESO (merma)","OK")))) -> CARGAR 9 | O13: =O12+SUMIFS(CgCajas,CgSemana,A13,CgCuenta,1,CgOrigen,"BR")-ROUND(Demanda!L13,0) -> -5633 | P13: =IF(Demanda!L14=0,"",O13/(Demanda!L14/DiasVenta)) -> -3.2222328 | Q13: =Q12+SUMIFS(CgCajas,CgSemana,A13,CgCuenta,1,CgOrigen,"PY")-ROUND(Demanda!M13,0) -> -4855 | R13: =IF(Demanda!M14=0,"",Q13/(Demanda!M14/DiasVenta)) -> -5.4920814 | S13: =S12+SUMIFS(CgCajas,CgSemana,A13,CgCuenta,1,CgOrigen,"BO")-ROUND(Demanda!N13,0) -> -5602 | T13: =IF(Demanda!N14=0,"",S13/(Demanda!N14/DiasVenta)) -> -27.847556 | U13: =IF(P13=MIN(P13,R13,T13),"Brasil",IF(R13=MIN(P13,R13,T13),"Paraguay","Bolivia")) -> Bolivia
A14: =Demanda!A14 -> 46342 | B14: =A14+5 -> 46347 | C14: =G13 -> -16090 | D14: =COUNTIFS(CgSemana,A14,CgCuenta,1) -> 8 | E14: =SUMIFS(CgCajas,CgSemana,A14,CgCuenta,1) -> 8064 | F14: =ROUND(Demanda!H14,0) -> 17000 | G14: =C14+E14-F14 -> -25026 | H14: =SUM($K$6:K13)*CajasProm -> 39000 | I14: =G14+H14 -> 13974 | J14: =B14-MAX(LagBR,LagPY)-AtrasoDias -> 46343 | K14: =IF(AND(I14<MinimoSabado,J14>=FechaHoy),ROUNDUP((MinimoSabado-I14)/CajasProm,0),0) -> 9 | L14: =I14+K14*CajasProm -> 22974 | M14: =IF(Demanda!H15=0,"",L14/(Demanda!H15/DiasVenta)) -> 8.1084706 | N14: =IF(I14<0,"FALTA",IF(K14>0,"CARGAR "&K14,IF(I14<MinimoSabado,"BAJO MINIMO (limite pasado)",IF(AND(M14<>"",M14>VidaVerde),"EXCESO (merma)","OK")))) -> CARGAR 9 | O14: =O13+SUMIFS(CgCajas,CgSemana,A14,CgCuenta,1,CgOrigen,"BR")-ROUND(Demanda!L14,0) -> -8058 | P14: =IF(Demanda!L15=0,"",O14/(Demanda!L15/DiasVenta)) -> -4.6094003 | Q14: =Q13+SUMIFS(CgCajas,CgSemana,A14,CgCuenta,1,CgOrigen,"PY")-ROUND(Demanda!M14,0) -> -10159 | R14: =IF(Demanda!M15=0,"",Q14/(Demanda!M15/DiasVenta)) -> -11.492081 | S14: =S13+SUMIFS(CgCajas,CgSemana,A14,CgCuenta,1,CgOrigen,"BO")-ROUND(Demanda!N14,0) -> -6809 | T14: =IF(Demanda!N15=0,"",S14/(Demanda!N15/DiasVenta)) -> -33.847556 | U14: =IF(P14=MIN(P14,R14,T14),"Brasil",IF(R14=MIN(P14,R14,T14),"Paraguay","Bolivia")) -> Bolivia
A15: =Demanda!A15 -> 46349 | B15: =A15+5 -> 46354 | C15: =G14 -> -25026 | D15: =COUNTIFS(CgSemana,A15,CgCuenta,1) -> 8 | E15: =SUMIFS(CgCajas,CgSemana,A15,CgCuenta,1) -> 8064 | F15: =ROUND(Demanda!H15,0) -> 17000 | G15: =C15+E15-F15 -> -33962 | H15: =SUM($K$6:K14)*CajasProm -> 48000 | I15: =G15+H15 -> 14038 | J15: =B15-MAX(LagBR,LagPY)-AtrasoDias -> 46350 | K15: =IF(AND(I15<MinimoSabado,J15>=FechaHoy),ROUNDUP((MinimoSabado-I15)/CajasProm,0),0) -> 9 | L15: =I15+K15*CajasProm -> 23038 | M15: =IF(Demanda!H16=0,"",L15/(Demanda!H16/DiasVenta)) -> 8.1310588 | N15: =IF(I15<0,"FALTA",IF(K15>0,"CARGAR "&K15,IF(I15<MinimoSabado,"BAJO MINIMO (limite pasado)",IF(AND(M15<>"",M15>VidaVerde),"EXCESO (merma)","OK")))) -> CARGAR 9 | O15: =O14+SUMIFS(CgCajas,CgSemana,A15,CgCuenta,1,CgOrigen,"BR")-ROUND(Demanda!L15,0) -> -10483 | P15: =IF(Demanda!L16=0,"",O15/(Demanda!L16/DiasVenta)) -> -5.9965678 | Q15: =Q14+SUMIFS(CgCajas,CgSemana,A15,CgCuenta,1,CgOrigen,"PY")-ROUND(Demanda!M15,0) -> -15463 | R15: =IF(Demanda!M16=0,"",Q15/(Demanda!M16/DiasVenta)) -> -17.492081 | S15: =S14+SUMIFS(CgCajas,CgSemana,A15,CgCuenta,1,CgOrigen,"BO")-ROUND(Demanda!N15,0) -> -8016 | T15: =IF(Demanda!N16=0,"",S15/(Demanda!N16/DiasVenta)) -> -39.847556 | U15: =IF(P15=MIN(P15,R15,T15),"Brasil",IF(R15=MIN(P15,R15,T15),"Paraguay","Bolivia")) -> Bolivia
A16: =Demanda!A16 -> 46356 | B16: =A16+5 -> 46361 | C16: =G15 -> -33962 | D16: =COUNTIFS(CgSemana,A16,CgCuenta,1) -> 8 | E16: =SUMIFS(CgCajas,CgSemana,A16,CgCuenta,1) -> 8064 | F16: =ROUND(Demanda!H16,0) -> 17000 | G16: =C16+E16-F16 -> -42898 | H16: =SUM($K$6:K15)*CajasProm -> 57000 | I16: =G16+H16 -> 14102 | J16: =B16-MAX(LagBR,LagPY)-AtrasoDias -> 46357 | K16: =IF(AND(I16<MinimoSabado,J16>=FechaHoy),ROUNDUP((MinimoSabado-I16)/CajasProm,0),0) -> 9 | L16: =I16+K16*CajasProm -> 23102 | M16: =IF(Demanda!H17=0,"",L16/(Demanda!H17/DiasVenta)) -> 8.1536471 | N16: =IF(I16<0,"FALTA",IF(K16>0,"CARGAR "&K16,IF(I16<MinimoSabado,"BAJO MINIMO (limite pasado)",IF(AND(M16<>"",M16>VidaVerde),"EXCESO (merma)","OK")))) -> CARGAR 9 | O16: =O15+SUMIFS(CgCajas,CgSemana,A16,CgCuenta,1,CgOrigen,"BR")-ROUND(Demanda!L16,0) -> -12908 | P16: =IF(Demanda!L17=0,"",O16/(Demanda!L17/DiasVenta)) -> -7.3837353 | Q16: =Q15+SUMIFS(CgCajas,CgSemana,A16,CgCuenta,1,CgOrigen,"PY")-ROUND(Demanda!M16,0) -> -20767 | R16: =IF(Demanda!M17=0,"",Q16/(Demanda!M17/DiasVenta)) -> -23.492081 | S16: =S15+SUMIFS(CgCajas,CgSemana,A16,CgCuenta,1,CgOrigen,"BO")-ROUND(Demanda!N16,0) -> -9223 | T16: =IF(Demanda!N17=0,"",S16/(Demanda!N17/DiasVenta)) -> -45.847556 | U16: =IF(P16=MIN(P16,R16,T16),"Brasil",IF(R16=MIN(P16,R16,T16),"Paraguay","Bolivia")) -> Bolivia
A17: =Demanda!A17 -> 46363 | B17: =A17+5 -> 46368 | C17: =G16 -> -42898 | D17: =COUNTIFS(CgSemana,A17,CgCuenta,1) -> 8 | E17: =SUMIFS(CgCajas,CgSemana,A17,CgCuenta,1) -> 8064 | F17: =ROUND(Demanda!H17,0) -> 17000 | G17: =C17+E17-F17 -> -51834 | H17: =SUM($K$6:K16)*CajasProm -> 66000 | I17: =G17+H17 -> 14166 | J17: =B17-MAX(LagBR,LagPY)-AtrasoDias -> 46364 | K17: =IF(AND(I17<MinimoSabado,J17>=FechaHoy),ROUNDUP((MinimoSabado-I17)/CajasProm,0),0) -> 9 | L17: =I17+K17*CajasProm -> 23166 | M17: =IF(Demanda!H18=0,"",L17/(Demanda!H18/DiasVenta)) -> 8.1762353 | N17: =IF(I17<0,"FALTA",IF(K17>0,"CARGAR "&K17,IF(I17<MinimoSabado,"BAJO MINIMO (limite pasado)",IF(AND(M17<>"",M17>VidaVerde),"EXCESO (merma)","OK")))) -> CARGAR 9 | O17: =O16+SUMIFS(CgCajas,CgSemana,A17,CgCuenta,1,CgOrigen,"BR")-ROUND(Demanda!L17,0) -> -15333 | P17: =IF(Demanda!L18=0,"",O17/(Demanda!L18/DiasVenta)) -> -8.7709029 | Q17: =Q16+SUMIFS(CgCajas,CgSemana,A17,CgCuenta,1,CgOrigen,"PY")-ROUND(Demanda!M17,0) -> -26071 | R17: =IF(Demanda!M18=0,"",Q17/(Demanda!M18/DiasVenta)) -> -29.492081 | S17: =S16+SUMIFS(CgCajas,CgSemana,A17,CgCuenta,1,CgOrigen,"BO")-ROUND(Demanda!N17,0) -> -10430 | T17: =IF(Demanda!N18=0,"",S17/(Demanda!N18/DiasVenta)) -> -51.847556 | U17: =IF(P17=MIN(P17,R17,T17),"Brasil",IF(R17=MIN(P17,R17,T17),"Paraguay","Bolivia")) -> Bolivia
A18: =Demanda!A18 -> 46370 | B18: =A18+5 -> 46375 | C18: =G17 -> -51834 | D18: =COUNTIFS(CgSemana,A18,CgCuenta,1) -> 8 | E18: =SUMIFS(CgCajas,CgSemana,A18,CgCuenta,1) -> 8064 | F18: =ROUND(Demanda!H18,0) -> 17000 | G18: =C18+E18-F18 -> -60770 | H18: =SUM($K$6:K17)*CajasProm -> 75000 | I18: =G18+H18 -> 14230 | J18: =B18-MAX(LagBR,LagPY)-AtrasoDias -> 46371 | K18: =IF(AND(I18<MinimoSabado,J18>=FechaHoy),ROUNDUP((MinimoSabado-I18)/CajasProm,0),0) -> 9 | L18: =I18+K18*CajasProm -> 23230 | M18: =IF(Demanda!H18=0,"",L18/(Demanda!H18/DiasVenta)) -> 8.1988235 | N18: =IF(I18<0,"FALTA",IF(K18>0,"CARGAR "&K18,IF(I18<MinimoSabado,"BAJO MINIMO (limite pasado)",IF(AND(M18<>"",M18>VidaVerde),"EXCESO (merma)","OK")))) -> CARGAR 9 | O18: =O17+SUMIFS(CgCajas,CgSemana,A18,CgCuenta,1,CgOrigen,"BR")-ROUND(Demanda!L18,0) -> -17758 | P18: =IF(Demanda!L18=0,"",O18/(Demanda!L18/DiasVenta)) -> -10.15807 | Q18: =Q17+SUMIFS(CgCajas,CgSemana,A18,CgCuenta,1,CgOrigen,"PY")-ROUND(Demanda!M18,0) -> -31375 | R18: =IF(Demanda!M18=0,"",Q18/(Demanda!M18/DiasVenta)) -> -35.492081 | S18: =S17+SUMIFS(CgCajas,CgSemana,A18,CgCuenta,1,CgOrigen,"BO")-ROUND(Demanda!N18,0) -> -11637 | T18: =IF(Demanda!N18=0,"",S18/(Demanda!N18/DiasVenta)) -> -57.847556 | U18: =IF(P18=MIN(P18,R18,T18),"Brasil",IF(R18=MIN(P18,R18,T18),"Paraguay","Bolivia")) -> Bolivia

Sheet QueCargar
A1: Que cargar
A2: Solo las semanas cuyo limite de carga todavia no paso. Camiones ADEMAS de lo dictado y de los supuestos. El origen sugerido es el que queda con menos dias de venta al cierre (Proyeccion).
A5: Sabado de cierre | B5: Stock proyectado (con pedidos anteriores) | C5: Camiones a cargar | D5: Cargar hasta (por origen) | E5: Origen sugerido | F5: Pedido cierra (PY mie / BR jue) | G5: Cobertura al cierre (dias) | H5: Estado | I5: Renglon para WhatsApp
A6: =IF(Proyeccion!J6<FechaHoy,"",Proyeccion!B6) | B6: =IF(A6="","",Proyeccion!I6) | C6: =IF(A6="","",Proyeccion!K6) | D6: =IF(A6="","","BR "&TEXT(Proyeccion!B6-LagBR-AtrasoDias,"ddd dd/mm")&" · PY "&TEXT(Proyeccion!B6-LagPY-AtrasoDias,"ddd dd/mm")&" · BO "&TEXT(Proyeccion!B6-LagBO-AtrasoDias,"ddd dd/mm")) | E6: =IF(A6="","",IF(C6>0,Proyeccion!U6,"-")) | F6: =IF(A6="","","PY mie "&TEXT(Proyeccion!A6-5,"dd/mm")&" / BR jue "&TEXT(Proyeccion!A6-4,"dd/mm")) | G6: =IF(A6="","",Proyeccion!M6) | H6: =IF(A6="","",Proyeccion!N6) | I6: =IF(A6="","","Sab "&TEXT(A6,"dd/mm")&": "&FIXED(B6,0)&" cajas - descargan "&Proyeccion!D6&" - vende "&FIXED(Proyeccion!F6,0)&IF(C6>0," -> cargar "&C6&" mas hasta el "&TEXT(Proyeccion!J6,"dd/mm")&" ("&E6&"; BR hasta el "&TEXT(Proyeccion!B6-LagBR-AtrasoDias,"dd/mm")&")"," -> ok"))
A7: =IF(Proyeccion!J7<FechaHoy,"",Proyeccion!B7) -> 46298 | B7: =IF(A7="","",Proyeccion!I7) -> 22898 | C7: =IF(A7="","",Proyeccion!K7) -> 0 | D7: =IF(A7="","","BR "&TEXT(Proyeccion!B7-LagBR-AtrasoDias,"ddd dd/mm")&" · PY "&TEXT(Proyeccion!B7-LagPY-AtrasoDias,"ddd dd/mm")&" · BO "&TEXT(Proyeccion!B7-LagBO-AtrasoDias,"ddd dd/mm")) -> BR mié 30/09 · PY mar 29/09 · BO dom 27/09 | E7: =IF(A7="","",IF(C7>0,Proyeccion!U7,"-")) -> - | F7: =IF(A7="","","PY mie "&TEXT(Proyeccion!A7-5,"dd/mm")&" / BR jue "&TEXT(Proyeccion!A7-4,"dd/mm")) -> PY mie 23/09 / BR jue 24/09 | G7: =IF(A7="","",Proyeccion!M7) -> 8.0816471 | H7: =IF(A7="","",Proyeccion!N7) -> OK | I7: =IF(A7="","","Sab "&TEXT(A7,"dd/mm")&": "&FIXED(B7,0)&" cajas - descargan "&Proyeccion!D7&" - vende "&FIXED(Proyeccion!F7,0)&IF(C7>0," -> cargar "&C7&" mas hasta el "&TEXT(Proyeccion!J7,"dd/mm")&" ("&E7&"; BR hasta el "&TEXT(Proyeccion!B7-LagBR-AtrasoDias,"dd/mm")&")"," -> ok")) -> Sab 03/10: 22.898 cajas - descargan 11 - vende 16.000 -> ok
A8: =IF(Proyeccion!J8<FechaHoy,"",Proyeccion!B8) -> 46305 | B8: =IF(A8="","",Proyeccion!I8) -> 18790 | C8: =IF(A8="","",Proyeccion!K8) -> 4 | D8: =IF(A8="","","BR "&TEXT(Proyeccion!B8-LagBR-AtrasoDias,"ddd dd/mm")&" · PY "&TEXT(Proyeccion!B8-LagPY-AtrasoDias,"ddd dd/mm")&" · BO "&TEXT(Proyeccion!B8-LagBO-AtrasoDias,"ddd dd/mm")) -> BR mié 07/10 · PY mar 06/10 · BO dom 04/10 | E8: =IF(A8="","",IF(C8>0,Proyeccion!U8,"-")) -> Bolivia | F8: =IF(A8="","","PY mie "&TEXT(Proyeccion!A8-5,"dd/mm")&" / BR jue "&TEXT(Proyeccion!A8-4,"dd/mm")) -> PY mie 30/09 / BR jue 01/10 | G8: =IF(A8="","",Proyeccion!M8) -> 8.0435294 | H8: =IF(A8="","",Proyeccion!N8) -> CARGAR 4 | I8: =IF(A8="","","Sab "&TEXT(A8,"dd/mm")&": "&FIXED(B8,0)&" cajas - descargan "&Proyeccion!D8&" - vende "&FIXED(Proyeccion!F8,0)&IF(C8>0," -> cargar "&C8&" mas hasta el "&TEXT(Proyeccion!J8,"dd/mm")&" ("&E8&"; BR hasta el "&TEXT(Proyeccion!B8-LagBR-AtrasoDias,"dd/mm")&")"," -> ok")) -> Sab 10/10: 18.790 cajas - descargan 13 - vende 17.000 -> cargar 4 mas hasta el 06/10 (Bolivia; BR hasta el 07/10)
A9: =IF(Proyeccion!J9<FechaHoy,"",Proyeccion!B9) -> 46312 | B9: =IF(A9="","",Proyeccion!I9) -> 18754 | C9: =IF(A9="","",Proyeccion!K9) -> 4 | D9: =IF(A9="","","BR "&TEXT(Proyeccion!B9-LagBR-AtrasoDias,"ddd dd/mm")&" · PY "&TEXT(Proyeccion!B9-LagPY-AtrasoDias,"ddd dd/mm")&" · BO "&TEXT(Proyeccion!B9-LagBO-AtrasoDias,"ddd dd/mm")) -> BR mié 14/10 · PY mar 13/10 · BO dom 11/10 | E9: =IF(A9="","",IF(C9>0,Proyeccion!U9,"-")) -> Bolivia | F9: =IF(A9="","","PY mie "&TEXT(Proyeccion!A9-5,"dd/mm")&" / BR jue "&TEXT(Proyeccion!A9-4,"dd/mm")) -> PY mie 07/10 / BR jue 08/10 | G9: =IF(A9="","",Proyeccion!M9) -> 8.0308235 | H9: =IF(A9="","",Proyeccion!N9) -> CARGAR 4 | I9: =IF(A9="","","Sab "&TEXT(A9,"dd/mm")&": "&FIXED(B9,0)&" cajas - descargan "&Proyeccion!D9&" - vende "&FIXED(Proyeccion!F9,0)&IF(C9>0," -> cargar "&C9&" mas hasta el "&TEXT(Proyeccion!J9,"dd/mm")&" ("&E9&"; BR hasta el "&TEXT(Proyeccion!B9-LagBR-AtrasoDias,"dd/mm")&")"," -> ok")) -> Sab 17/10: 18.754 cajas - descargan 13 - vende 17.000 -> cargar 4 mas hasta el 13/10 (Bolivia; BR hasta el 14/10)
A10: =IF(Proyeccion!J10<FechaHoy,"",Proyeccion!B10) -> 46319 | B10: =IF(A10="","",Proyeccion!I10) -> 18718 | C10: =IF(A10="","",Proyeccion!K10) -> 4 | D10: =IF(A10="","","BR "&TEXT(Proyeccion!B10-LagBR-AtrasoDias,"ddd dd/mm")&" · PY "&TEXT(Proyeccion!B10-LagPY-AtrasoDias,"ddd dd/mm")&" · BO "&TEXT(Proyeccion!B10-LagBO-AtrasoDias,"ddd dd/mm")) -> BR mié 21/10 · PY mar 20/10 · BO dom 18/10 | E10: =IF(A10="","",IF(C10>0,Proyeccion!U10,"-")) -> Bolivia | F10: =IF(A10="","","PY mie "&TEXT(Proyeccion!A10-5,"dd/mm")&" / BR jue "&TEXT(Proyeccion!A10-4,"dd/mm")) -> PY mie 14/10 / BR jue 15/10 | G10: =IF(A10="","",Proyeccion!M10) -> 8.0181176 | H10: =IF(A10="","",Proyeccion!N10) -> CARGAR 4 | I10: =IF(A10="","","Sab "&TEXT(A10,"dd/mm")&": "&FIXED(B10,0)&" cajas - descargan "&Proyeccion!D10&" - vende "&FIXED(Proyeccion!F10,0)&IF(C10>0," -> cargar "&C10&" mas hasta el "&TEXT(Proyeccion!J10,"dd/mm")&" ("&E10&"; BR hasta el "&TEXT(Proyeccion!B10-LagBR-AtrasoDias,"dd/mm")&")"," -> ok")) -> Sab 24/10: 18.718 cajas - descargan 13 - vende 17.000 -> cargar 4 mas hasta el 20/10 (Bolivia; BR hasta el 21/10)
A11: =IF(Proyeccion!J11<FechaHoy,"",Proyeccion!B11) -> 46326 | B11: =IF(A11="","",Proyeccion!I11) -> 13782 | C11: =IF(A11="","",Proyeccion!K11) -> 9 | D11: =IF(A11="","","BR "&TEXT(Proyeccion!B11-LagBR-AtrasoDias,"ddd dd/mm")&" · PY "&TEXT(Proyeccion!B11-LagPY-AtrasoDias,"ddd dd/mm")&" · BO "&TEXT(Proyeccion!B11-LagBO-AtrasoDias,"ddd dd/mm")) -> BR mié 28/10 · PY mar 27/10 · BO dom 25/10 | E11: =IF(A11="","",IF(C11>0,Proyeccion!U11,"-")) -> Bolivia | F11: =IF(A11="","","PY mie "&TEXT(Proyeccion!A11-5,"dd/mm")&" / BR jue "&TEXT(Proyeccion!A11-4,"dd/mm")) -> PY mie 21/10 / BR jue 22/10 | G11: =IF(A11="","",Proyeccion!M11) -> 8.0407059 | H11: =IF(A11="","",Proyeccion!N11) -> CARGAR 9 | I11: =IF(A11="","","Sab "&TEXT(A11,"dd/mm")&": "&FIXED(B11,0)&" cajas - descargan "&Proyeccion!D11&" - vende "&FIXED(Proyeccion!F11,0)&IF(C11>0," -> cargar "&C11&" mas hasta el "&TEXT(Proyeccion!J11,"dd/mm")&" ("&E11&"; BR hasta el "&TEXT(Proyeccion!B11-LagBR-AtrasoDias,"dd/mm")&")"," -> ok")) -> Sab 31/10: 13.782 cajas - descargan 8 - vende 17.000 -> cargar 9 mas hasta el 27/10 (Bolivia; BR hasta el 28/10)
A12: =IF(Proyeccion!J12<FechaHoy,"",Proyeccion!B12) -> 46333 | B12: =IF(A12="","",Proyeccion!I12) -> 13846 | C12: =IF(A12="","",Proyeccion!K12) -> 9 | D12: =IF(A12="","","BR "&TEXT(Proyeccion!B12-LagBR-AtrasoDias,"ddd dd/mm")&" · PY "&TEXT(Proyeccion!B12-LagPY-AtrasoDias,"ddd dd/mm")&" · BO "&TEXT(Proyeccion!B12-LagBO-AtrasoDias,"ddd dd/mm")) -> BR mié 04/11 · PY mar 03/11 · BO dom 01/11 | E12: =IF(A12="","",IF(C12>0,Proyeccion!U12,"-")) -> Bolivia | F12: =IF(A12="","","PY mie "&TEXT(Proyeccion!A12-5,"dd/mm")&" / BR jue "&TEXT(Proyeccion!A12-4,"dd/mm")) -> PY mie 28/10 / BR jue 29/10 | G12: =IF(A12="","",Proyeccion!M12) -> 8.0632941 | H12: =IF(A12="","",Proyeccion!N12) -> CARGAR 9 | I12: =IF(A12="","","Sab "&TEXT(A12,"dd/mm")&": "&FIXED(B12,0)&" cajas - descargan "&Proyeccion!D12&" - vende "&FIXED(Proyeccion!F12,0)&IF(C12>0," -> cargar "&C12&" mas hasta el "&TEXT(Proyeccion!J12,"dd/mm")&" ("&E12&"; BR hasta el "&TEXT(Proyeccion!B12-LagBR-AtrasoDias,"dd/mm")&")"," -> ok")) -> Sab 07/11: 13.846 cajas - descargan 8 - vende 17.000 -> cargar 9 mas hasta el 03/11 (Bolivia; BR hasta el 04/11)
A13: =IF(Proyeccion!J13<FechaHoy,"",Proyeccion!B13) -> 46340 | B13: =IF(A13="","",Proyeccion!I13) -> 13910 | C13: =IF(A13="","",Proyeccion!K13) -> 9 | D13: =IF(A13="","","BR "&TEXT(Proyeccion!B13-LagBR-AtrasoDias,"ddd dd/mm")&" · PY "&TEXT(Proyeccion!B13-LagPY-AtrasoDias,"ddd dd/mm")&" · BO "&TEXT(Proyeccion!B13-LagBO-AtrasoDias,"ddd dd/mm")) -> BR mié 11/11 · PY mar 10/11 · BO dom 08/11 | E13: =IF(A13="","",IF(C13>0,Proyeccion!U13,"-")) -> Bolivia | F13: =IF(A13="","","PY mie "&TEXT(Proyeccion!A13-5,"dd/mm")&" / BR jue "&TEXT(Proyeccion!A13-4,"dd/mm")) -> PY mie 04/11 / BR jue 05/11 | G13: =IF(A13="","",Proyeccion!M13) -> 8.0858824 | H13: =IF(A13="","",Proyeccion!N13) -> CARGAR 9 | I13: =IF(A13="","","Sab "&TEXT(A13,"dd/mm")&": "&FIXED(B13,0)&" cajas - descargan "&Proyeccion!D13&" - vende "&FIXED(Proyeccion!F13,0)&IF(C13>0," -> cargar "&C13&" mas hasta el "&TEXT(Proyeccion!J13,"dd/mm")&" ("&E13&"; BR hasta el "&TEXT(Proyeccion!B13-LagBR-AtrasoDias,"dd/mm")&")"," -> ok")) -> Sab 14/11: 13.910 cajas - descargan 8 - vende 17.000 -> cargar 9 mas hasta el 10/11 (Bolivia; BR hasta el 11/11)
A14: =IF(Proyeccion!J14<FechaHoy,"",Proyeccion!B14) -> 46347 | B14: =IF(A14="","",Proyeccion!I14) -> 13974 | C14: =IF(A14="","",Proyeccion!K14) -> 9 | D14: =IF(A14="","","BR "&TEXT(Proyeccion!B14-LagBR-AtrasoDias,"ddd dd/mm")&" · PY "&TEXT(Proyeccion!B14-LagPY-AtrasoDias,"ddd dd/mm")&" · BO "&TEXT(Proyeccion!B14-LagBO-AtrasoDias,"ddd dd/mm")) -> BR mié 18/11 · PY mar 17/11 · BO dom 15/11 | E14: =IF(A14="","",IF(C14>0,Proyeccion!U14,"-")) -> Bolivia | F14: =IF(A14="","","PY mie "&TEXT(Proyeccion!A14-5,"dd/mm")&" / BR jue "&TEXT(Proyeccion!A14-4,"dd/mm")) -> PY mie 11/11 / BR jue 12/11 | G14: =IF(A14="","",Proyeccion!M14) -> 8.1084706 | H14: =IF(A14="","",Proyeccion!N14) -> CARGAR 9 | I14: =IF(A14="","","Sab "&TEXT(A14,"dd/mm")&": "&FIXED(B14,0)&" cajas - descargan "&Proyeccion!D14&" - vende "&FIXED(Proyeccion!F14,0)&IF(C14>0," -> cargar "&C14&" mas hasta el "&TEXT(Proyeccion!J14,"dd/mm")&" ("&E14&"; BR hasta el "&TEXT(Proyeccion!B14-LagBR-AtrasoDias,"dd/mm")&")"," -> ok")) -> Sab 21/11: 13.974 cajas - descargan 8 - vende 17.000 -> cargar 9 mas hasta el 17/11 (Bolivia; BR hasta el 18/11)
A15: =IF(Proyeccion!J15<FechaHoy,"",Proyeccion!B15) -> 46354 | B15: =IF(A15="","",Proyeccion!I15) -> 14038 | C15: =IF(A15="","",Proyeccion!K15) -> 9 | D15: =IF(A15="","","BR "&TEXT(Proyeccion!B15-LagBR-AtrasoDias,"ddd dd/mm")&" · PY "&TEXT(Proyeccion!B15-LagPY-AtrasoDias,"ddd dd/mm")&" · BO "&TEXT(Proyeccion!B15-LagBO-AtrasoDias,"ddd dd/mm")) -> BR mié 25/11 · PY mar 24/11 · BO dom 22/11 | E15: =IF(A15="","",IF(C15>0,Proyeccion!U15,"-")) -> Bolivia | F15: =IF(A15="","","PY mie "&TEXT(Proyeccion!A15-5,"dd/mm")&" / BR jue "&TEXT(Proyeccion!A15-4,"dd/mm")) -> PY mie 18/11 / BR jue 19/11 | G15: =IF(A15="","",Proyeccion!M15) -> 8.1310588 | H15: =IF(A15="","",Proyeccion!N15) -> CARGAR 9 | I15: =IF(A15="","","Sab "&TEXT(A15,"dd/mm")&": "&FIXED(B15,0)&" cajas - descargan "&Proyeccion!D15&" - vende "&FIXED(Proyeccion!F15,0)&IF(C15>0," -> cargar "&C15&" mas hasta el "&TEXT(Proyeccion!J15,"dd/mm")&" ("&E15&"; BR hasta el "&TEXT(Proyeccion!B15-LagBR-AtrasoDias,"dd/mm")&")"," -> ok")) -> Sab 28/11: 14.038 cajas - descargan 8 - vende 17.000 -> cargar 9 mas hasta el 24/11 (Bolivia; BR hasta el 25/11)
A16: =IF(Proyeccion!J16<FechaHoy,"",Proyeccion!B16) -> 46361 | B16: =IF(A16="","",Proyeccion!I16) -> 14102 | C16: =IF(A16="","",Proyeccion!K16) -> 9 | D16: =IF(A16="","","BR "&TEXT(Proyeccion!B16-LagBR-AtrasoDias,"ddd dd/mm")&" · PY "&TEXT(Proyeccion!B16-LagPY-AtrasoDias,"ddd dd/mm")&" · BO "&TEXT(Proyeccion!B16-LagBO-AtrasoDias,"ddd dd/mm")) -> BR mié 02/12 · PY mar 01/12 · BO dom 29/11 | E16: =IF(A16="","",IF(C16>0,Proyeccion!U16,"-")) -> Bolivia | F16: =IF(A16="","","PY mie "&TEXT(Proyeccion!A16-5,"dd/mm")&" / BR jue "&TEXT(Proyeccion!A16-4,"dd/mm")) -> PY mie 25/11 / BR jue 26/11 | G16: =IF(A16="","",Proyeccion!M16) -> 8.1536471 | H16: =IF(A16="","",Proyeccion!N16) -> CARGAR 9 | I16: =IF(A16="","","Sab "&TEXT(A16,"dd/mm")&": "&FIXED(B16,0)&" cajas - descargan "&Proyeccion!D16&" - vende "&FIXED(Proyeccion!F16,0)&IF(C16>0," -> cargar "&C16&" mas hasta el "&TEXT(Proyeccion!J16,"dd/mm")&" ("&E16&"; BR hasta el "&TEXT(Proyeccion!B16-LagBR-AtrasoDias,"dd/mm")&")"," -> ok")) -> Sab 05/12: 14.102 cajas - descargan 8 - vende 17.000 -> cargar 9 mas hasta el 01/12 (Bolivia; BR hasta el 02/12)
A17: =IF(Proyeccion!J17<FechaHoy,"",Proyeccion!B17) -> 46368 | B17: =IF(A17="","",Proyeccion!I17) -> 14166 | C17: =IF(A17="","",Proyeccion!K17) -> 9 | D17: =IF(A17="","","BR "&TEXT(Proyeccion!B17-LagBR-AtrasoDias,"ddd dd/mm")&" · PY "&TEXT(Proyeccion!B17-LagPY-AtrasoDias,"ddd dd/mm")&" · BO "&TEXT(Proyeccion!B17-LagBO-AtrasoDias,"ddd dd/mm")) -> BR mié 09/12 · PY mar 08/12 · BO dom 06/12 | E17: =IF(A17="","",IF(C17>0,Proyeccion!U17,"-")) -> Bolivia | F17: =IF(A17="","","PY mie "&TEXT(Proyeccion!A17-5,"dd/mm")&" / BR jue "&TEXT(Proyeccion!A17-4,"dd/mm")) -> PY mie 02/12 / BR jue 03/12 | G17: =IF(A17="","",Proyeccion!M17) -> 8.1762353 | H17: =IF(A17="","",Proyeccion!N17) -> CARGAR 9 | I17: =IF(A17="","","Sab "&TEXT(A17,"dd/mm")&": "&FIXED(B17,0)&" cajas - descargan "&Proyeccion!D17&" - vende "&FIXED(Proyeccion!F17,0)&IF(C17>0," -> cargar "&C17&" mas hasta el "&TEXT(Proyeccion!J17,"dd/mm")&" ("&E17&"; BR hasta el "&TEXT(Proyeccion!B17-LagBR-AtrasoDias,"dd/mm")&")"," -> ok")) -> Sab 12/12: 14.166 cajas - descargan 8 - vende 17.000 -> cargar 9 mas hasta el 08/12 (Bolivia; BR hasta el 09/12)
A18: =IF(Proyeccion!J18<FechaHoy,"",Proyeccion!B18) -> 46375 | B18: =IF(A18="","",Proyeccion!I18) -> 14230 | C18: =IF(A18="","",Proyeccion!K18) -> 9 | D18: =IF(A18="","","BR "&TEXT(Proyeccion!B18-LagBR-AtrasoDias,"ddd dd/mm")&" · PY "&TEXT(Proyeccion!B18-LagPY-AtrasoDias,"ddd dd/mm")&" · BO "&TEXT(Proyeccion!B18-LagBO-AtrasoDias,"ddd dd/mm")) -> BR mié 16/12 · PY mar 15/12 · BO dom 13/12 | E18: =IF(A18="","",IF(C18>0,Proyeccion!U18,"-")) -> Bolivia | F18: =IF(A18="","","PY mie "&TEXT(Proyeccion!A18-5,"dd/mm")&" / BR jue "&TEXT(Proyeccion!A18-4,"dd/mm")) -> PY mie 09/12 / BR jue 10/12 | G18: =IF(A18="","",Proyeccion!M18) -> 8.1988235 | H18: =IF(A18="","",Proyeccion!N18) -> CARGAR 9 | I18: =IF(A18="","","Sab "&TEXT(A18,"dd/mm")&": "&FIXED(B18,0)&" cajas - descargan "&Proyeccion!D18&" - vende "&FIXED(Proyeccion!F18,0)&IF(C18>0," -> cargar "&C18&" mas hasta el "&TEXT(Proyeccion!J18,"dd/mm")&" ("&E18&"; BR hasta el "&TEXT(Proyeccion!B18-LagBR-AtrasoDias,"dd/mm")&")"," -> ok")) -> Sab 19/12: 14.230 cajas - descargan 8 - vende 17.000 -> cargar 9 mas hasta el 15/12 (Bolivia; BR hasta el 16/12)
A20: Como leerlo: "cargar N mas hasta el mie" = camiones que hay que agregar a lo ya dictado para cerrar ese sabado en el minimo; lo que cargue despues del limite descarga la semana siguiente. Los faltantes de una semana se arrastran a la siguiente (Proyeccion, columna "Pedidos anteriores").
A21: Hay SUPUESTOS de los dos origenes en Cargas: 5 camiones de Paraguay por semana (Estado = Supuesto) y 8 de Brasil los viernes en las semanas posteriores a la ultima dictada (Estado = Supuesto BR). Con ellos, "cargar N mas" es lo que falta ADEMAS del ritmo habitual; para ver toda la necesidad como en el WhatsApp, poner SupBR = 0 en Parametros. Cuando se dictan los reales, reemplazarlos.

Sheet Semaforo
A1: Semaforo semanal
A2: Una pantalla: stock al sabado y dias de cobertura por origen para esta semana y la proxima, con el estado y la accion. Los camiones que faltan todavia no tienen origen: van al que este mas justo.
A4: ="ESTA SEMANA (sabado "&TEXT(INDEX(PrSab,MATCH((FechaHoy-WEEKDAY(FechaHoy,2)+1+0),PrSemana,0)),"dd/mm")&")" -> ESTA SEMANA (sabado 03/10)
A5: Origen | B5: Stock al sabado | C5: Dias de cobertura | D5: Estado | E5: Accion
A6: Brasil | B6: =IFERROR(INDEX(PrBR,MATCH((FechaHoy-WEEKDAY(FechaHoy,2)+1+0),PrSemana,0)),"") -> 8989 | C6: =IFERROR(INDEX(PrBRd,MATCH((FechaHoy-WEEKDAY(FechaHoy,2)+1+0),PrSemana,0)),"") -> 5.1419582 | D6: =IF(B6="","",IF(B6<0,"FALTA",IF(C6<2,"CRITICO",IF(C6<CoberturaObjetivo,"JUSTO",IF(C6>VidaVerde,"EXCESO","OK"))))) -> JUSTO | E6: =IF(D6="FALTA","se queda sin fruta: cargar ya",IF(D6="CRITICO","cargar esta semana, sin falta",IF(D6="JUSTO","priorizar este origen en los pedidos",IF(D6="EXCESO","frenar cargas: riesgo de merma","")))) -> priorizar este origen en los pedidos
A7: Paraguay | B7: =IFERROR(INDEX(PrPY,MATCH((FechaHoy-WEEKDAY(FechaHoy,2)+1+0),PrSemana,0)),"") -> 12269 | C7: =IFERROR(INDEX(PrPYd,MATCH((FechaHoy-WEEKDAY(FechaHoy,2)+1+0),PrSemana,0)),"") -> 13.878959 | D7: =IF(B7="","",IF(B7<0,"FALTA",IF(C7<2,"CRITICO",IF(C7<CoberturaObjetivo,"JUSTO",IF(C7>VidaVerde,"EXCESO","OK"))))) -> OK | E7: =IF(D7="FALTA","se queda sin fruta: cargar ya",IF(D7="CRITICO","cargar esta semana, sin falta",IF(D7="JUSTO","priorizar este origen en los pedidos",IF(D7="EXCESO","frenar cargas: riesgo de merma",""))))
A8: Bolivia | B8: =IFERROR(INDEX(PrBO,MATCH((FechaHoy-WEEKDAY(FechaHoy,2)+1+0),PrSemana,0)),"") -> 1640 | C8: =IFERROR(INDEX(PrBOd,MATCH((FechaHoy-WEEKDAY(FechaHoy,2)+1+0),PrSemana,0)),"") -> 8.1524441 | D8: =IF(B8="","",IF(B8<0,"FALTA",IF(C8<2,"CRITICO",IF(C8<CoberturaObjetivo,"JUSTO",IF(C8>VidaVerde,"EXCESO","OK"))))) -> OK | E8: =IF(D8="FALTA","se queda sin fruta: cargar ya",IF(D8="CRITICO","cargar esta semana, sin falta",IF(D8="JUSTO","priorizar este origen en los pedidos",IF(D8="EXCESO","frenar cargas: riesgo de merma",""))))
A9: TOTAL | B9: =IFERROR(INDEX(PrProy,MATCH((FechaHoy-WEEKDAY(FechaHoy,2)+1+0),PrSemana,0)),"") -> 22898 | C9: =IFERROR(INDEX(PrCobertura,MATCH((FechaHoy-WEEKDAY(FechaHoy,2)+1+0),PrSemana,0)),"") -> 8.0816471 | D9: =IFERROR(INDEX(PrEstado,MATCH((FechaHoy-WEEKDAY(FechaHoy,2)+1+0),PrSemana,0)),"") -> OK | E9: =IFERROR(IF(INDEX(PrACargar,MATCH((FechaHoy-WEEKDAY(FechaHoy,2)+1+0),PrSemana,0))>0,"cargar "&INDEX(PrACargar,MATCH((FechaHoy-WEEKDAY(FechaHoy,2)+1+0),PrSemana,0))&" camion(es) mas hasta el "&TEXT(INDEX(PrLimite,MATCH((FechaHoy-WEEKDAY(FechaHoy,2)+1+0),PrSemana,0)),"ddd dd/mm")&" para cerrar en "&FIXED(MinimoSabado,0),"ok, cierra sobre "&FIXED(MinimoSabado,0)),"") -> ok, cierra sobre 22.500
A11: ="SEMANA PROXIMA (sabado "&TEXT(INDEX(PrSab,MATCH((FechaHoy-WEEKDAY(FechaHoy,2)+1+7),PrSemana,0)),"dd/mm")&")" -> SEMANA PROXIMA (sabado 10/10)
A12: Origen | B12: Stock al sabado | C12: Dias de cobertura | D12: Estado | E12: Accion
A13: Brasil | B13: =IFERROR(INDEX(PrBR,MATCH((FechaHoy-WEEKDAY(FechaHoy,2)+1+7),PrSemana,0)),"") -> 6492 | C13: =IFERROR(INDEX(PrBRd,MATCH((FechaHoy-WEEKDAY(FechaHoy,2)+1+7),PrSemana,0)),"") -> 3.7136047 | D13: =IF(B13="","",IF(B13<0,"FALTA",IF(C13<2,"CRITICO",IF(C13<CoberturaObjetivo,"JUSTO",IF(C13>VidaVerde,"EXCESO","OK"))))) -> JUSTO | E13: =IF(D13="FALTA","se queda sin fruta: cargar ya",IF(D13="CRITICO","cargar esta semana, sin falta",IF(D13="JUSTO","priorizar este origen en los pedidos",IF(D13="EXCESO","frenar cargas: riesgo de merma","")))) -> priorizar este origen en los pedidos
A14: Paraguay | B14: =IFERROR(INDEX(PrPY,MATCH((FechaHoy-WEEKDAY(FechaHoy,2)+1+7),PrSemana,0)),"") -> 11865 | C14: =IFERROR(INDEX(PrPYd,MATCH((FechaHoy-WEEKDAY(FechaHoy,2)+1+7),PrSemana,0)),"") -> 13.421946 | D14: =IF(B14="","",IF(B14<0,"FALTA",IF(C14<2,"CRITICO",IF(C14<CoberturaObjetivo,"JUSTO",IF(C14>VidaVerde,"EXCESO","OK"))))) -> OK | E14: =IF(D14="FALTA","se queda sin fruta: cargar ya",IF(D14="CRITICO","cargar esta semana, sin falta",IF(D14="JUSTO","priorizar este origen en los pedidos",IF(D14="EXCESO","frenar cargas: riesgo de merma",""))))
A15: Bolivia | B15: =IFERROR(INDEX(PrBO,MATCH((FechaHoy-WEEKDAY(FechaHoy,2)+1+7),PrSemana,0)),"") -> 433 | C15: =IFERROR(INDEX(PrBOd,MATCH((FechaHoy-WEEKDAY(FechaHoy,2)+1+7),PrSemana,0)),"") -> 2.1524441 | D15: =IF(B15="","",IF(B15<0,"FALTA",IF(C15<2,"CRITICO",IF(C15<CoberturaObjetivo,"JUSTO",IF(C15>VidaVerde,"EXCESO","OK"))))) -> JUSTO | E15: =IF(D15="FALTA","se queda sin fruta: cargar ya",IF(D15="CRITICO","cargar esta semana, sin falta",IF(D15="JUSTO","priorizar este origen en los pedidos",IF(D15="EXCESO","frenar cargas: riesgo de merma","")))) -> priorizar este origen en los pedidos
A16: TOTAL | B16: =IFERROR(INDEX(PrProy,MATCH((FechaHoy-WEEKDAY(FechaHoy,2)+1+7),PrSemana,0)),"") -> 18790 | C16: =IFERROR(INDEX(PrCobertura,MATCH((FechaHoy-WEEKDAY(FechaHoy,2)+1+7),PrSemana,0)),"") -> 8.0435294 | D16: =IFERROR(INDEX(PrEstado,MATCH((FechaHoy-WEEKDAY(FechaHoy,2)+1+7),PrSemana,0)),"") -> CARGAR 4 | E16: =IFERROR(IF(INDEX(PrACargar,MATCH((FechaHoy-WEEKDAY(FechaHoy,2)+1+7),PrSemana,0))>0,"cargar "&INDEX(PrACargar,MATCH((FechaHoy-WEEKDAY(FechaHoy,2)+1+7),PrSemana,0))&" camion(es) mas hasta el "&TEXT(INDEX(PrLimite,MATCH((FechaHoy-WEEKDAY(FechaHoy,2)+1+7),PrSemana,0)),"ddd dd/mm")&" para cerrar en "&FIXED(MinimoSabado,0),"ok, cierra sobre "&FIXED(MinimoSabado,0)),"") -> cargar 4 camion(es) mas hasta el mar 06/10 para cerrar en 22.500
A18: ="EN DOS SEMANAS (sabado "&TEXT(INDEX(PrSab,MATCH((FechaHoy-WEEKDAY(FechaHoy,2)+1+14),PrSemana,0)),"dd/mm")&")" -> EN DOS SEMANAS (sabado 17/10)
A19: Origen | B19: Stock al sabado | C19: Dias de cobertura | D19: Estado | E19: Accion
A20: Brasil | B20: =IFERROR(INDEX(PrBR,MATCH((FechaHoy-WEEKDAY(FechaHoy,2)+1+14),PrSemana,0)),"") -> 4067 | C20: =IFERROR(INDEX(PrBRd,MATCH((FechaHoy-WEEKDAY(FechaHoy,2)+1+14),PrSemana,0)),"") -> 2.3264372 | D20: =IF(B20="","",IF(B20<0,"FALTA",IF(C20<2,"CRITICO",IF(C20<CoberturaObjetivo,"JUSTO",IF(C20>VidaVerde,"EXCESO","OK"))))) -> JUSTO | E20: =IF(D20="FALTA","se queda sin fruta: cargar ya",IF(D20="CRITICO","cargar esta semana, sin falta",IF(D20="JUSTO","priorizar este origen en los pedidos",IF(D20="EXCESO","frenar cargas: riesgo de merma","")))) -> priorizar este origen en los pedidos
A21: Paraguay | B21: =IFERROR(INDEX(PrPY,MATCH((FechaHoy-WEEKDAY(FechaHoy,2)+1+14),PrSemana,0)),"") -> 11461 | C21: =IFERROR(INDEX(PrPYd,MATCH((FechaHoy-WEEKDAY(FechaHoy,2)+1+14),PrSemana,0)),"") -> 12.964932 | D21: =IF(B21="","",IF(B21<0,"FALTA",IF(C21<2,"CRITICO",IF(C21<CoberturaObjetivo,"JUSTO",IF(C21>VidaVerde,"EXCESO","OK"))))) -> OK | E21: =IF(D21="FALTA","se queda sin fruta: cargar ya",IF(D21="CRITICO","cargar esta semana, sin falta",IF(D21="JUSTO","priorizar este origen en los pedidos",IF(D21="EXCESO","frenar cargas: riesgo de merma",""))))
A22: Bolivia | B22: =IFERROR(INDEX(PrBO,MATCH((FechaHoy-WEEKDAY(FechaHoy,2)+1+14),PrSemana,0)),"") -> -774 | C22: =IFERROR(INDEX(PrBOd,MATCH((FechaHoy-WEEKDAY(FechaHoy,2)+1+14),PrSemana,0)),"") -> -3.8475559 | D22: =IF(B22="","",IF(B22<0,"FALTA",IF(C22<2,"CRITICO",IF(C22<CoberturaObjetivo,"JUSTO",IF(C22>VidaVerde,"EXCESO","OK"))))) -> FALTA | E22: =IF(D22="FALTA","se queda sin fruta: cargar ya",IF(D22="CRITICO","cargar esta semana, sin falta",IF(D22="JUSTO","priorizar este origen en los pedidos",IF(D22="EXCESO","frenar cargas: riesgo de merma","")))) -> se queda sin fruta: cargar ya
A23: TOTAL | B23: =IFERROR(INDEX(PrProy,MATCH((FechaHoy-WEEKDAY(FechaHoy,2)+1+14),PrSemana,0)),"") -> 18754 | C23: =IFERROR(INDEX(PrCobertura,MATCH((FechaHoy-WEEKDAY(FechaHoy,2)+1+14),PrSemana,0)),"") -> 8.0308235 | D23: =IFERROR(INDEX(PrEstado,MATCH((FechaHoy-WEEKDAY(FechaHoy,2)+1+14),PrSemana,0)),"") -> CARGAR 4 | E23: =IFERROR(IF(INDEX(PrACargar,MATCH((FechaHoy-WEEKDAY(FechaHoy,2)+1+14),PrSemana,0))>0,"cargar "&INDEX(PrACargar,MATCH((FechaHoy-WEEKDAY(FechaHoy,2)+1+14),PrSemana,0))&" camion(es) mas hasta el "&TEXT(INDEX(PrLimite,MATCH((FechaHoy-WEEKDAY(FechaHoy,2)+1+14),PrSemana,0)),"ddd dd/mm")&" para cerrar en "&FIXED(MinimoSabado,0),"ok, cierra sobre "&FIXED(MinimoSabado,0)),"") -> cargar 4 camion(es) mas hasta el mar 13/10 para cerrar en 22.500
A25: RIESGOS ABIERTOS
A26: =IF(COUNTIFS(CgOrigen,"BO",CgCuenta,1,CgSemana,">="&(FechaHoy-WEEKDAY(FechaHoy,2)+1))=0,"Bolivia: no hay ningun camion en camino ni dictado. Tarda 6 dias: para que entre el sabado que viene tiene que cargar antes del "&TEXT(FechaHoy-WEEKDAY(FechaHoy,2)+1+12-LagBO,"ddd dd/mm"),"Bolivia: "&COUNTIFS(CgOrigen,"BO",CgCuenta,1,CgSemana,">="&(FechaHoy-WEEKDAY(FechaHoy,2)+1))&" camion(es) en el plan") -> Bolivia: 1 camion(es) en el plan
A27: ="Paraguay: "&COUNTIFS(CgEstado,"Supuesto",CgSemana,">="&(FechaHoy-WEEKDAY(FechaHoy,2)+1),CgSemana,"<"&(FechaHoy-WEEKDAY(FechaHoy,2)+1+14))&" camiones SUPUESTOS en las proximas 2 semanas (todavia no dictados). El plan es firme cuando se dictan." -> Paraguay: 5 camiones SUPUESTOS en las proximas 2 semanas (todavia no dictados). El plan es firme cuando se dictan.
A28: ="Brasil: "&COUNTIFS(CgEstado,"Supuesto BR",CgCuenta,1)&" camiones SUPUESTOS (8 por semana los viernes) en las semanas posteriores a la ultima dictada. Se apagan en Parametros > SupBR." -> Brasil: 88 camiones SUPUESTOS (8 por semana los viernes) en las semanas posteriores a la ultima dictada. Se apagan en Parametros > SupBR.
A29: ="Dictados que Aloha aun no tiene: "&COUNTIFS(CgEstado,"Dictado",CgCuenta,1)&" camiones. Pasan a Aloha cuando se cargan en el sistema." -> Dictados que Aloha aun no tiene: 16 camiones. Pasan a Aloha cuando se cargan en el sistema.
A30: =IFERROR("Frontera lenta (P90): el sabado "&TEXT(INDEX(PrSab,MATCH(FechaHoy-WEEKDAY(FechaHoy,2)+1,PrSemana,0)),"dd/mm")&" cerraria en "&FIXED(INDEX(Escenarios!L6:L18,MATCH(FechaHoy-WEEKDAY(FechaHoy,2)+1,PrSemana,0)),0)&" cajas ("&IF(INDEX(Escenarios!G6:G18,MATCH(FechaHoy-WEEKDAY(FechaHoy,2)+1,PrSemana,0))>INDEX(Escenarios!L6:L18,MATCH(FechaHoy-WEEKDAY(FechaHoy,2)+1,PrSemana,0)),FIXED(INDEX(Escenarios!G6:G18,MATCH(FechaHoy-WEEKDAY(FechaHoy,2)+1,PrSemana,0))-INDEX(Escenarios!L6:L18,MATCH(FechaHoy-WEEKDAY(FechaHoy,2)+1,PrSemana,0)),0)&" menos que el plan","igual o mas que el plan")&") y el "&TEXT(INDEX(PrSab,MATCH(FechaHoy-WEEKDAY(FechaHoy,2)+1+7,PrSemana,0)),"dd/mm")&" en "&FIXED(INDEX(Escenarios!L6:L18,MATCH(FechaHoy-WEEKDAY(FechaHoy,2)+1+7,PrSemana,0)),0)&" (plan: "&FIXED(INDEX(Escenarios!G6:G18,MATCH(FechaHoy-WEEKDAY(FechaHoy,2)+1+7,PrSemana,0)),0)&").","") -> Frontera lenta (P90): el sabado 03/10 cerraria en 18.866 cajas (4.032 menos que el plan) y el 10/10 en 22.790 (plan: 18.790).
A31: ="Escenario de venta activo: "&Parametros!B8&" (factor "&FIXED(FactorEscenario,2)&"). Atraso extra en frontera: "&AtrasoDias&" dia(s)." -> Escenario de venta activo: Base (factor 1,00). Atraso extra en frontera: 0 dia(s).
A32: =IF(CapMadurar="","Capacidad de maduracion: sin cargar en Parametros (camaras, cajas por camara, ciclo). Hasta entonces no se controla el cuello de botella.","Capacidad de maduracion: "&FIXED(CapMadurar,0)&" cajas/semana.") -> Capacidad de maduracion: sin cargar en Parametros (camaras, cajas por camara, ciclo). Hasta entonces no se controla el cuello de botella.
A33: ="Verde en transito (cargado y sin descargar): "&FIXED(SUM(CgPipeline),0)&" cajas." -> Verde en transito (cargado y sin descargar): 7.922 cajas.

Sheet Escenarios
A1: Escenarios de venta lado a lado
A2: Misma proyeccion con la venta usada x 0,9 / x 1,0 / x 1,1 (ademas del escenario elegido en Parametros). Cada escenario arrastra sus propios camiones a cargar. Para atraso en frontera: Parametros > Atraso extra.
A5: Semana (lunes) | B5: Sabado | C5: Cajas que descargan | D5: Venta base | E5: Stock -10% | F5: A cargar -10% | G5: Stock base | H5: A cargar base | I5: Stock +10% | J5: A cargar +10% | K5: Cajas si frontera a P90 | L5: Stock frontera P90 | M5: A cargar P90 | N5: Stock sin HF 1 semana (-3 PY) | O5: Stock 1 camion rechazado (-1.000) | P5: Stock sin Bolivia 2 sem
A6: =Proyeccion!A6 -> 46286 | B6: =Proyeccion!B6 -> 46291 | C6: =Proyeccion!E6 -> 980 | D6: =Proyeccion!F6 -> 0 | E6: =ConteoTotal+C6-ROUND(D6*0.9,0) -> 27952 | F6: =IF(AND(E6<MinimoSabado,Proyeccion!J6>=FechaHoy),ROUNDUP((MinimoSabado-E6)/CajasProm,0),0) -> 0 | G6: =ConteoTotal+C6-ROUND(D6*1,0) -> 27952 | H6: =IF(AND(G6<MinimoSabado,Proyeccion!J6>=FechaHoy),ROUNDUP((MinimoSabado-G6)/CajasProm,0),0) -> 0 | I6: =ConteoTotal+C6-ROUND(D6*1.1,0) -> 27952 | J6: =IF(AND(I6<MinimoSabado,Proyeccion!J6>=FechaHoy),ROUNDUP((MinimoSabado-I6)/CajasProm,0),0) -> 0 | K6: =SUMIFS(CgCajas,CgSemanaP90,A6,CgCuenta,1) -> 980 | L6: =ConteoTotal+K6-D6 -> 27952 | M6: =IF(AND(L6<MinimoSabado,Proyeccion!J6>=FechaHoy),ROUNDUP((MinimoSabado-L6)/CajasProm,0),0) -> 0 | N6: =G6-IF(A6>=FechaHoy-WEEKDAY(FechaHoy,2)+8,3*CajasPY,0) -> 27952 | O6: =G6-IF(A6>=FechaHoy-WEEKDAY(FechaHoy,2)+8,1000,0) -> 27952 | P6: =G6-SUMIFS(CgCajas,CgOrigen,"BO",CgCuenta,1,CgSemana,">="&(FechaHoy-WEEKDAY(FechaHoy,2)+8),CgSemana,"<="&MIN(A6,FechaHoy-WEEKDAY(FechaHoy,2)+15)) -> 27952
A7: =Proyeccion!A7 -> 46293 | B7: =Proyeccion!B7 -> 46298 | C7: =Proyeccion!E7 -> 10946 | D7: =Proyeccion!F7 -> 16000 | E7: =(E6+F6*CajasProm)+C7-ROUND(D7*0.9,0) -> 24498 | F7: =IF(AND(E7<MinimoSabado,Proyeccion!J7>=FechaHoy),ROUNDUP((MinimoSabado-E7)/CajasProm,0),0) -> 0 | G7: =(G6+H6*CajasProm)+C7-ROUND(D7*1,0) -> 22898 | H7: =IF(AND(G7<MinimoSabado,Proyeccion!J7>=FechaHoy),ROUNDUP((MinimoSabado-G7)/CajasProm,0),0) -> 0 | I7: =(I6+J6*CajasProm)+C7-ROUND(D7*1.1,0) -> 21298 | J7: =IF(AND(I7<MinimoSabado,Proyeccion!J7>=FechaHoy),ROUNDUP((MinimoSabado-I7)/CajasProm,0),0) -> 2 | K7: =SUMIFS(CgCajas,CgSemanaP90,A7,CgCuenta,1) -> 6914 | L7: =(L6+M6*CajasProm)+K7-D7 -> 18866 | M7: =IF(AND(L7<MinimoSabado,Proyeccion!J7>=FechaHoy),ROUNDUP((MinimoSabado-L7)/CajasProm,0),0) -> 4 | N7: =G7-IF(A7>=FechaHoy-WEEKDAY(FechaHoy,2)+8,3*CajasPY,0) -> 22898 | O7: =G7-IF(A7>=FechaHoy-WEEKDAY(FechaHoy,2)+8,1000,0) -> 22898 | P7: =G7-SUMIFS(CgCajas,CgOrigen,"BO",CgCuenta,1,CgSemana,">="&(FechaHoy-WEEKDAY(FechaHoy,2)+8),CgSemana,"<="&MIN(A7,FechaHoy-WEEKDAY(FechaHoy,2)+15)) -> 22898
A8: =Proyeccion!A8 -> 46300 | B8: =Proyeccion!B8 -> 46305 | C8: =Proyeccion!E8 -> 12892 | D8: =Proyeccion!F8 -> 17000 | E8: =(E7+F7*CajasProm)+C8-ROUND(D8*0.9,0) -> 22090 | F8: =IF(AND(E8<MinimoSabado,Proyeccion!J8>=FechaHoy),ROUNDUP((MinimoSabado-E8)/CajasProm,0),0) -> 1 | G8: =(G7+H7*CajasProm)+C8-ROUND(D8*1,0) -> 18790 | H8: =IF(AND(G8<MinimoSabado,Proyeccion!J8>=FechaHoy),ROUNDUP((MinimoSabado-G8)/CajasProm,0),0) -> 4 | I8: =(I7+J7*CajasProm)+C8-ROUND(D8*1.1,0) -> 17490 | J8: =IF(AND(I8<MinimoSabado,Proyeccion!J8>=FechaHoy),ROUNDUP((MinimoSabado-I8)/CajasProm,0),0) -> 6 | K8: =SUMIFS(CgCajas,CgSemanaP90,A8,CgCuenta,1) -> 16924 | L8: =(L7+M7*CajasProm)+K8-D8 -> 22790 | M8: =IF(AND(L8<MinimoSabado,Proyeccion!J8>=FechaHoy),ROUNDUP((MinimoSabado-L8)/CajasProm,0),0) -> 0 | N8: =G8-IF(A8>=FechaHoy-WEEKDAY(FechaHoy,2)+8,3*CajasPY,0) -> 15850 | O8: =G8-IF(A8>=FechaHoy-WEEKDAY(FechaHoy,2)+8,1000,0) -> 17790 | P8: =G8-SUMIFS(CgCajas,CgOrigen,"BO",CgCuenta,1,CgSemana,">="&(FechaHoy-WEEKDAY(FechaHoy,2)+8),CgSemana,"<="&MIN(A8,FechaHoy-WEEKDAY(FechaHoy,2)+15)) -> 18790
A9: =Proyeccion!A9 -> 46307 | B9: =Proyeccion!B9 -> 46312 | C9: =Proyeccion!E9 -> 12964 | D9: =Proyeccion!F9 -> 17000 | E9: =(E8+F8*CajasProm)+C9-ROUND(D9*0.9,0) -> 20754 | F9: =IF(AND(E9<MinimoSabado,Proyeccion!J9>=FechaHoy),ROUNDUP((MinimoSabado-E9)/CajasProm,0),0) -> 2 | G9: =(G8+H8*CajasProm)+C9-ROUND(D9*1,0) -> 18754 | H9: =IF(AND(G9<MinimoSabado,Proyeccion!J9>=FechaHoy),ROUNDUP((MinimoSabado-G9)/CajasProm,0),0) -> 4 | I9: =(I8+J8*CajasProm)+C9-ROUND(D9*1.1,0) -> 17754 | J9: =IF(AND(I9<MinimoSabado,Proyeccion!J9>=FechaHoy),ROUNDUP((MinimoSabado-I9)/CajasProm,0),0) -> 5 | K9: =SUMIFS(CgCajas,CgSemanaP90,A9,CgCuenta,1) -> 12964 | L9: =(L8+M8*CajasProm)+K9-D9 -> 18754 | M9: =IF(AND(L9<MinimoSabado,Proyeccion!J9>=FechaHoy),ROUNDUP((MinimoSabado-L9)/CajasProm,0),0) -> 4 | N9: =G9-IF(A9>=FechaHoy-WEEKDAY(FechaHoy,2)+8,3*CajasPY,0) -> 15814 | O9: =G9-IF(A9>=FechaHoy-WEEKDAY(FechaHoy,2)+8,1000,0) -> 17754 | P9: =G9-SUMIFS(CgCajas,CgOrigen,"BO",CgCuenta,1,CgSemana,">="&(FechaHoy-WEEKDAY(FechaHoy,2)+8),CgSemana,"<="&MIN(A9,FechaHoy-WEEKDAY(FechaHoy,2)+15)) -> 18754
A10: =Proyeccion!A10 -> 46314 | B10: =Proyeccion!B10 -> 46319 | C10: =Proyeccion!E10 -> 12964 | D10: =Proyeccion!F10 -> 17000 | E10: =(E9+F9*CajasProm)+C10-ROUND(D10*0.9,0) -> 20418 | F10: =IF(AND(E10<MinimoSabado,Proyeccion!J10>=FechaHoy),ROUNDUP((MinimoSabado-E10)/CajasProm,0),0) -> 3 | G10: =(G9+H9*CajasProm)+C10-ROUND(D10*1,0) -> 18718 | H10: =IF(AND(G10<MinimoSabado,Proyeccion!J10>=FechaHoy),ROUNDUP((MinimoSabado-G10)/CajasProm,0),0) -> 4 | I10: =(I9+J9*CajasProm)+C10-ROUND(D10*1.1,0) -> 17018 | J10: =IF(AND(I10<MinimoSabado,Proyeccion!J10>=FechaHoy),ROUNDUP((MinimoSabado-I10)/CajasProm,0),0) -> 6 | K10: =SUMIFS(CgCajas,CgSemanaP90,A10,CgCuenta,1) -> 12964 | L10: =(L9+M9*CajasProm)+K10-D10 -> 18718 | M10: =IF(AND(L10<MinimoSabado,Proyeccion!J10>=FechaHoy),ROUNDUP((MinimoSabado-L10)/CajasProm,0),0) -> 4 | N10: =G10-IF(A10>=FechaHoy-WEEKDAY(FechaHoy,2)+8,3*CajasPY,0) -> 15778 | O10: =G10-IF(A10>=FechaHoy-WEEKDAY(FechaHoy,2)+8,1000,0) -> 17718 | P10: =G10-SUMIFS(CgCajas,CgOrigen,"BO",CgCuenta,1,CgSemana,">="&(FechaHoy-WEEKDAY(FechaHoy,2)+8),CgSemana,"<="&MIN(A10,FechaHoy-WEEKDAY(FechaHoy,2)+15)) -> 18718
A11: =Proyeccion!A11 -> 46321 | B11: =Proyeccion!B11 -> 46326 | C11: =Proyeccion!E11 -> 8064 | D11: =Proyeccion!F11 -> 17000 | E11: =(E10+F10*CajasProm)+C11-ROUND(D11*0.9,0) -> 16182 | F11: =IF(AND(E11<MinimoSabado,Proyeccion!J11>=FechaHoy),ROUNDUP((MinimoSabado-E11)/CajasProm,0),0) -> 7 | G11: =(G10+H10*CajasProm)+C11-ROUND(D11*1,0) -> 13782 | H11: =IF(AND(G11<MinimoSabado,Proyeccion!J11>=FechaHoy),ROUNDUP((MinimoSabado-G11)/CajasProm,0),0) -> 9 | I11: =(I10+J10*CajasProm)+C11-ROUND(D11*1.1,0) -> 12382 | J11: =IF(AND(I11<MinimoSabado,Proyeccion!J11>=FechaHoy),ROUNDUP((MinimoSabado-I11)/CajasProm,0),0) -> 11 | K11: =SUMIFS(CgCajas,CgSemanaP90,A11,CgCuenta,1) -> 8064 | L11: =(L10+M10*CajasProm)+K11-D11 -> 13782 | M11: =IF(AND(L11<MinimoSabado,Proyeccion!J11>=FechaHoy),ROUNDUP((MinimoSabado-L11)/CajasProm,0),0) -> 9 | N11: =G11-IF(A11>=FechaHoy-WEEKDAY(FechaHoy,2)+8,3*CajasPY,0) -> 10842 | O11: =G11-IF(A11>=FechaHoy-WEEKDAY(FechaHoy,2)+8,1000,0) -> 12782 | P11: =G11-SUMIFS(CgCajas,CgOrigen,"BO",CgCuenta,1,CgSemana,">="&(FechaHoy-WEEKDAY(FechaHoy,2)+8),CgSemana,"<="&MIN(A11,FechaHoy-WEEKDAY(FechaHoy,2)+15)) -> 13782
A12: =Proyeccion!A12 -> 46328 | B12: =Proyeccion!B12 -> 46333 | C12: =Proyeccion!E12 -> 8064 | D12: =Proyeccion!F12 -> 17000 | E12: =(E11+F11*CajasProm)+C12-ROUND(D12*0.9,0) -> 15946 | F12: =IF(AND(E12<MinimoSabado,Proyeccion!J12>=FechaHoy),ROUNDUP((MinimoSabado-E12)/CajasProm,0),0) -> 7 | G12: =(G11+H11*CajasProm)+C12-ROUND(D12*1,0) -> 13846 | H12: =IF(AND(G12<MinimoSabado,Proyeccion!J12>=FechaHoy),ROUNDUP((MinimoSabado-G12)/CajasProm,0),0) -> 9 | I12: =(I11+J11*CajasProm)+C12-ROUND(D12*1.1,0) -> 12746 | J12: =IF(AND(I12<MinimoSabado,Proyeccion!J12>=FechaHoy),ROUNDUP((MinimoSabado-I12)/CajasProm,0),0) -> 10 | K12: =SUMIFS(CgCajas,CgSemanaP90,A12,CgCuenta,1) -> 8064 | L12: =(L11+M11*CajasProm)+K12-D12 -> 13846 | M12: =IF(AND(L12<MinimoSabado,Proyeccion!J12>=FechaHoy),ROUNDUP((MinimoSabado-L12)/CajasProm,0),0) -> 9 | N12: =G12-IF(A12>=FechaHoy-WEEKDAY(FechaHoy,2)+8,3*CajasPY,0) -> 10906 | O12: =G12-IF(A12>=FechaHoy-WEEKDAY(FechaHoy,2)+8,1000,0) -> 12846 | P12: =G12-SUMIFS(CgCajas,CgOrigen,"BO",CgCuenta,1,CgSemana,">="&(FechaHoy-WEEKDAY(FechaHoy,2)+8),CgSemana,"<="&MIN(A12,FechaHoy-WEEKDAY(FechaHoy,2)+15)) -> 13846
A13: =Proyeccion!A13 -> 46335 | B13: =Proyeccion!B13 -> 46340 | C13: =Proyeccion!E13 -> 8064 | D13: =Proyeccion!F13 -> 17000 | E13: =(E12+F12*CajasProm)+C13-ROUND(D13*0.9,0) -> 15710 | F13: =IF(AND(E13<MinimoSabado,Proyeccion!J13>=FechaHoy),ROUNDUP((MinimoSabado-E13)/CajasProm,0),0) -> 7 | G13: =(G12+H12*CajasProm)+C13-ROUND(D13*1,0) -> 13910 | H13: =IF(AND(G13<MinimoSabado,Proyeccion!J13>=FechaHoy),ROUNDUP((MinimoSabado-G13)/CajasProm,0),0) -> 9 | I13: =(I12+J12*CajasProm)+C13-ROUND(D13*1.1,0) -> 12110 | J13: =IF(AND(I13<MinimoSabado,Proyeccion!J13>=FechaHoy),ROUNDUP((MinimoSabado-I13)/CajasProm,0),0) -> 11 | K13: =SUMIFS(CgCajas,CgSemanaP90,A13,CgCuenta,1) -> 8064 | L13: =(L12+M12*CajasProm)+K13-D13 -> 13910 | M13: =IF(AND(L13<MinimoSabado,Proyeccion!J13>=FechaHoy),ROUNDUP((MinimoSabado-L13)/CajasProm,0),0) -> 9 | N13: =G13-IF(A13>=FechaHoy-WEEKDAY(FechaHoy,2)+8,3*CajasPY,0) -> 10970 | O13: =G13-IF(A13>=FechaHoy-WEEKDAY(FechaHoy,2)+8,1000,0) -> 12910 | P13: =G13-SUMIFS(CgCajas,CgOrigen,"BO",CgCuenta,1,CgSemana,">="&(FechaHoy-WEEKDAY(FechaHoy,2)+8),CgSemana,"<="&MIN(A13,FechaHoy-WEEKDAY(FechaHoy,2)+15)) -> 13910
A14: =Proyeccion!A14 -> 46342 | B14: =Proyeccion!B14 -> 46347 | C14: =Proyeccion!E14 -> 8064 | D14: =Proyeccion!F14 -> 17000 | E14: =(E13+F13*CajasProm)+C14-ROUND(D14*0.9,0) -> 15474 | F14: =IF(AND(E14<MinimoSabado,Proyeccion!J14>=FechaHoy),ROUNDUP((MinimoSabado-E14)/CajasProm,0),0) -> 8 | G14: =(G13+H13*CajasProm)+C14-ROUND(D14*1,0) -> 13974 | H14: =IF(AND(G14<MinimoSabado,Proyeccion!J14>=FechaHoy),ROUNDUP((MinimoSabado-G14)/CajasProm,0),0) -> 9 | I14: =(I13+J13*CajasProm)+C14-ROUND(D14*1.1,0) -> 12474 | J14: =IF(AND(I14<MinimoSabado,Proyeccion!J14>=FechaHoy),ROUNDUP((MinimoSabado-I14)/CajasProm,0),0) -> 11 | K14: =SUMIFS(CgCajas,CgSemanaP90,A14,CgCuenta,1) -> 8064 | L14: =(L13+M13*CajasProm)+K14-D14 -> 13974 | M14: =IF(AND(L14<MinimoSabado,Proyeccion!J14>=FechaHoy),ROUNDUP((MinimoSabado-L14)/CajasProm,0),0) -> 9 | N14: =G14-IF(A14>=FechaHoy-WEEKDAY(FechaHoy,2)+8,3*CajasPY,0) -> 11034 | O14: =G14-IF(A14>=FechaHoy-WEEKDAY(FechaHoy,2)+8,1000,0) -> 12974 | P14: =G14-SUMIFS(CgCajas,CgOrigen,"BO",CgCuenta,1,CgSemana,">="&(FechaHoy-WEEKDAY(FechaHoy,2)+8),CgSemana,"<="&MIN(A14,FechaHoy-WEEKDAY(FechaHoy,2)+15)) -> 13974
A15: =Proyeccion!A15 -> 46349 | B15: =Proyeccion!B15 -> 46354 | C15: =Proyeccion!E15 -> 8064 | D15: =Proyeccion!F15 -> 17000 | E15: =(E14+F14*CajasProm)+C15-ROUND(D15*0.9,0) -> 16238 | F15: =IF(AND(E15<MinimoSabado,Proyeccion!J15>=FechaHoy),ROUNDUP((MinimoSabado-E15)/CajasProm,0),0) -> 7 | G15: =(G14+H14*CajasProm)+C15-ROUND(D15*1,0) -> 14038 | H15: =IF(AND(G15<MinimoSabado,Proyeccion!J15>=FechaHoy),ROUNDUP((MinimoSabado-G15)/CajasProm,0),0) -> 9 | I15: =(I14+J14*CajasProm)+C15-ROUND(D15*1.1,0) -> 12838 | J15: =IF(AND(I15<MinimoSabado,Proyeccion!J15>=FechaHoy),ROUNDUP((MinimoSabado-I15)/CajasProm,0),0) -> 10 | K15: =SUMIFS(CgCajas,CgSemanaP90,A15,CgCuenta,1) -> 8064 | L15: =(L14+M14*CajasProm)+K15-D15 -> 14038 | M15: =IF(AND(L15<MinimoSabado,Proyeccion!J15>=FechaHoy),ROUNDUP((MinimoSabado-L15)/CajasProm,0),0) -> 9 | N15: =G15-IF(A15>=FechaHoy-WEEKDAY(FechaHoy,2)+8,3*CajasPY,0) -> 11098 | O15: =G15-IF(A15>=FechaHoy-WEEKDAY(FechaHoy,2)+8,1000,0) -> 13038 | P15: =G15-SUMIFS(CgCajas,CgOrigen,"BO",CgCuenta,1,CgSemana,">="&(FechaHoy-WEEKDAY(FechaHoy,2)+8),CgSemana,"<="&MIN(A15,FechaHoy-WEEKDAY(FechaHoy,2)+15)) -> 14038
A16: =Proyeccion!A16 -> 46356 | B16: =Proyeccion!B16 -> 46361 | C16: =Proyeccion!E16 -> 8064 | D16: =Proyeccion!F16 -> 17000 | E16: =(E15+F15*CajasProm)+C16-ROUND(D16*0.9,0) -> 16002 | F16: =IF(AND(E16<MinimoSabado,Proyeccion!J16>=FechaHoy),ROUNDUP((MinimoSabado-E16)/CajasProm,0),0) -> 7 | G16: =(G15+H15*CajasProm)+C16-ROUND(D16*1,0) -> 14102 | H16: =IF(AND(G16<MinimoSabado,Proyeccion!J16>=FechaHoy),ROUNDUP((MinimoSabado-G16)/CajasProm,0),0) -> 9 | I16: =(I15+J15*CajasProm)+C16-ROUND(D16*1.1,0) -> 12202 | J16: =IF(AND(I16<MinimoSabado,Proyeccion!J16>=FechaHoy),ROUNDUP((MinimoSabado-I16)/CajasProm,0),0) -> 11 | K16: =SUMIFS(CgCajas,CgSemanaP90,A16,CgCuenta,1) -> 8064 | L16: =(L15+M15*CajasProm)+K16-D16 -> 14102 | M16: =IF(AND(L16<MinimoSabado,Proyeccion!J16>=FechaHoy),ROUNDUP((MinimoSabado-L16)/CajasProm,0),0) -> 9 | N16: =G16-IF(A16>=FechaHoy-WEEKDAY(FechaHoy,2)+8,3*CajasPY,0) -> 11162 | O16: =G16-IF(A16>=FechaHoy-WEEKDAY(FechaHoy,2)+8,1000,0) -> 13102 | P16: =G16-SUMIFS(CgCajas,CgOrigen,"BO",CgCuenta,1,CgSemana,">="&(FechaHoy-WEEKDAY(FechaHoy,2)+8),CgSemana,"<="&MIN(A16,FechaHoy-WEEKDAY(FechaHoy,2)+15)) -> 14102
A17: =Proyeccion!A17 -> 46363 | B17: =Proyeccion!B17 -> 46368 | C17: =Proyeccion!E17 -> 8064 | D17: =Proyeccion!F17 -> 17000 | E17: =(E16+F16*CajasProm)+C17-ROUND(D17*0.9,0) -> 15766 | F17: =IF(AND(E17<MinimoSabado,Proyeccion!J17>=FechaHoy),ROUNDUP((MinimoSabado-E17)/CajasProm,0),0) -> 7 | G17: =(G16+H16*CajasProm)+C17-ROUND(D17*1,0) -> 14166 | H17: =IF(AND(G17<MinimoSabado,Proyeccion!J17>=FechaHoy),ROUNDUP((MinimoSabado-G17)/CajasProm,0),0) -> 9 | I17: =(I16+J16*CajasProm)+C17-ROUND(D17*1.1,0) -> 12566 | J17: =IF(AND(I17<MinimoSabado,Proyeccion!J17>=FechaHoy),ROUNDUP((MinimoSabado-I17)/CajasProm,0),0) -> 10 | K17: =SUMIFS(CgCajas,CgSemanaP90,A17,CgCuenta,1) -> 8064 | L17: =(L16+M16*CajasProm)+K17-D17 -> 14166 | M17: =IF(AND(L17<MinimoSabado,Proyeccion!J17>=FechaHoy),ROUNDUP((MinimoSabado-L17)/CajasProm,0),0) -> 9 | N17: =G17-IF(A17>=FechaHoy-WEEKDAY(FechaHoy,2)+8,3*CajasPY,0) -> 11226 | O17: =G17-IF(A17>=FechaHoy-WEEKDAY(FechaHoy,2)+8,1000,0) -> 13166 | P17: =G17-SUMIFS(CgCajas,CgOrigen,"BO",CgCuenta,1,CgSemana,">="&(FechaHoy-WEEKDAY(FechaHoy,2)+8),CgSemana,"<="&MIN(A17,FechaHoy-WEEKDAY(FechaHoy,2)+15)) -> 14166
A18: =Proyeccion!A18 -> 46370 | B18: =Proyeccion!B18 -> 46375 | C18: =Proyeccion!E18 -> 8064 | D18: =Proyeccion!F18 -> 17000 | E18: =(E17+F17*CajasProm)+C18-ROUND(D18*0.9,0) -> 15530 | F18: =IF(AND(E18<MinimoSabado,Proyeccion!J18>=FechaHoy),ROUNDUP((MinimoSabado-E18)/CajasProm,0),0) -> 7 | G18: =(G17+H17*CajasProm)+C18-ROUND(D18*1,0) -> 14230 | H18: =IF(AND(G18<MinimoSabado,Proyeccion!J18>=FechaHoy),ROUNDUP((MinimoSabado-G18)/CajasProm,0),0) -> 9 | I18: =(I17+J17*CajasProm)+C18-ROUND(D18*1.1,0) -> 11930 | J18: =IF(AND(I18<MinimoSabado,Proyeccion!J18>=FechaHoy),ROUNDUP((MinimoSabado-I18)/CajasProm,0),0) -> 11 | K18: =SUMIFS(CgCajas,CgSemanaP90,A18,CgCuenta,1) -> 8064 | L18: =(L17+M17*CajasProm)+K18-D18 -> 14230 | M18: =IF(AND(L18<MinimoSabado,Proyeccion!J18>=FechaHoy),ROUNDUP((MinimoSabado-L18)/CajasProm,0),0) -> 9 | N18: =G18-IF(A18>=FechaHoy-WEEKDAY(FechaHoy,2)+8,3*CajasPY,0) -> 11290 | O18: =G18-IF(A18>=FechaHoy-WEEKDAY(FechaHoy,2)+8,1000,0) -> 13230 | P18: =G18-SUMIFS(CgCajas,CgOrigen,"BO",CgCuenta,1,CgSemana,">="&(FechaHoy-WEEKDAY(FechaHoy,2)+8),CgSemana,"<="&MIN(A18,FechaHoy-WEEKDAY(FechaHoy,2)+15)) -> 14230
A20: Lectura: si con -10% igual hay que cargar, el pedido es firme; si solo hace falta con +10%, es un pedido "por las dudas" que conviene decidir el miercoles con la venta real de la semana. "Frontera a P90": todos los camiones sin descarga real tardan lo que tarda el peor 10% (Parametros fila 45). Los shocks (sin HF, camion rechazado, sin Bolivia) se aplican desde la semana proxima sobre el stock base.

Sheet Capacidad
A1: Capacidad de maduracion y camaras
A2: Cajas a madurar por semana (= la venta de la semana siguiente) contra lo que las camaras de gas pueden madurar, y stock al sabado contra la capacidad fisica. Completar Parametros (camaras, cajas por camara, ciclo, capacidad fisica).
A5: Semana (lunes) | B5: Sabado | C5: Cajas que descargan | D5: Cajas a madurar (venta sem. siguiente) | E5: Capacidad de maduracion (cajas/sem) | F5: Utilizacion | G5: Cuello de botella | H5: Stock al sabado | I5: Capacidad fisica (cajas) | J5: Ocupacion camaras | K5: Estado
A6: =Proyeccion!A6 -> 46286 | B6: =Proyeccion!B6 -> 46291 | C6: =Proyeccion!E6 -> 980 | D6: =Demanda!H7 -> 16000 | E6: =IF(CapMadurar="","",CapMadurar) | F6: =IF(E6="","",D6/E6) | G6: =IF(E6="","completar Parametros",IF(D6>E6,"SI: "&FIXED(D6-E6,0)&" cajas de mas","no")) -> completar Parametros | H6: =Proyeccion!L6 -> 27952 | I6: =IF(CapFisica="","",CapFisica) | J6: =IF(I6="","",H6/I6) | K6: =IF(I6="","",IF(H6>I6,"NO ENTRA",IF(H6>0.9*I6,"al limite","ok")))
A7: =Proyeccion!A7 -> 46293 | B7: =Proyeccion!B7 -> 46298 | C7: =Proyeccion!E7 -> 10946 | D7: =Demanda!H8 -> 17000 | E7: =IF(CapMadurar="","",CapMadurar) | F7: =IF(E7="","",D7/E7) | G7: =IF(E7="","completar Parametros",IF(D7>E7,"SI: "&FIXED(D7-E7,0)&" cajas de mas","no")) -> completar Parametros | H7: =Proyeccion!L7 -> 22898 | I7: =IF(CapFisica="","",CapFisica) | J7: =IF(I7="","",H7/I7) | K7: =IF(I7="","",IF(H7>I7,"NO ENTRA",IF(H7>0.9*I7,"al limite","ok")))
A8: =Proyeccion!A8 -> 46300 | B8: =Proyeccion!B8 -> 46305 | C8: =Proyeccion!E8 -> 12892 | D8: =Demanda!H9 -> 17000 | E8: =IF(CapMadurar="","",CapMadurar) | F8: =IF(E8="","",D8/E8) | G8: =IF(E8="","completar Parametros",IF(D8>E8,"SI: "&FIXED(D8-E8,0)&" cajas de mas","no")) -> completar Parametros | H8: =Proyeccion!L8 -> 22790 | I8: =IF(CapFisica="","",CapFisica) | J8: =IF(I8="","",H8/I8) | K8: =IF(I8="","",IF(H8>I8,"NO ENTRA",IF(H8>0.9*I8,"al limite","ok")))
A9: =Proyeccion!A9 -> 46307 | B9: =Proyeccion!B9 -> 46312 | C9: =Proyeccion!E9 -> 12964 | D9: =Demanda!H10 -> 17000 | E9: =IF(CapMadurar="","",CapMadurar) | F9: =IF(E9="","",D9/E9) | G9: =IF(E9="","completar Parametros",IF(D9>E9,"SI: "&FIXED(D9-E9,0)&" cajas de mas","no")) -> completar Parametros | H9: =Proyeccion!L9 -> 22754 | I9: =IF(CapFisica="","",CapFisica) | J9: =IF(I9="","",H9/I9) | K9: =IF(I9="","",IF(H9>I9,"NO ENTRA",IF(H9>0.9*I9,"al limite","ok")))
A10: =Proyeccion!A10 -> 46314 | B10: =Proyeccion!B10 -> 46319 | C10: =Proyeccion!E10 -> 12964 | D10: =Demanda!H11 -> 17000 | E10: =IF(CapMadurar="","",CapMadurar) | F10: =IF(E10="","",D10/E10) | G10: =IF(E10="","completar Parametros",IF(D10>E10,"SI: "&FIXED(D10-E10,0)&" cajas de mas","no")) -> completar Parametros | H10: =Proyeccion!L10 -> 22718 | I10: =IF(CapFisica="","",CapFisica) | J10: =IF(I10="","",H10/I10) | K10: =IF(I10="","",IF(H10>I10,"NO ENTRA",IF(H10>0.9*I10,"al limite","ok")))
A11: =Proyeccion!A11 -> 46321 | B11: =Proyeccion!B11 -> 46326 | C11: =Proyeccion!E11 -> 8064 | D11: =Demanda!H12 -> 17000 | E11: =IF(CapMadurar="","",CapMadurar) | F11: =IF(E11="","",D11/E11) | G11: =IF(E11="","completar Parametros",IF(D11>E11,"SI: "&FIXED(D11-E11,0)&" cajas de mas","no")) -> completar Parametros | H11: =Proyeccion!L11 -> 22782 | I11: =IF(CapFisica="","",CapFisica) | J11: =IF(I11="","",H11/I11) | K11: =IF(I11="","",IF(H11>I11,"NO ENTRA",IF(H11>0.9*I11,"al limite","ok")))
A12: =Proyeccion!A12 -> 46328 | B12: =Proyeccion!B12 -> 46333 | C12: =Proyeccion!E12 -> 8064 | D12: =Demanda!H13 -> 17000 | E12: =IF(CapMadurar="","",CapMadurar) | F12: =IF(E12="","",D12/E12) | G12: =IF(E12="","completar Parametros",IF(D12>E12,"SI: "&FIXED(D12-E12,0)&" cajas de mas","no")) -> completar Parametros | H12: =Proyeccion!L12 -> 22846 | I12: =IF(CapFisica="","",CapFisica) | J12: =IF(I12="","",H12/I12) | K12: =IF(I12="","",IF(H12>I12,"NO ENTRA",IF(H12>0.9*I12,"al limite","ok")))
A13: =Proyeccion!A13 -> 46335 | B13: =Proyeccion!B13 -> 46340 | C13: =Proyeccion!E13 -> 8064 | D13: =Demanda!H14 -> 17000 | E13: =IF(CapMadurar="","",CapMadurar) | F13: =IF(E13="","",D13/E13) | G13: =IF(E13="","completar Parametros",IF(D13>E13,"SI: "&FIXED(D13-E13,0)&" cajas de mas","no")) -> completar Parametros | H13: =Proyeccion!L13 -> 22910 | I13: =IF(CapFisica="","",CapFisica) | J13: =IF(I13="","",H13/I13) | K13: =IF(I13="","",IF(H13>I13,"NO ENTRA",IF(H13>0.9*I13,"al limite","ok")))
A14: =Proyeccion!A14 -> 46342 | B14: =Proyeccion!B14 -> 46347 | C14: =Proyeccion!E14 -> 8064 | D14: =Demanda!H15 -> 17000 | E14: =IF(CapMadurar="","",CapMadurar) | F14: =IF(E14="","",D14/E14) | G14: =IF(E14="","completar Parametros",IF(D14>E14,"SI: "&FIXED(D14-E14,0)&" cajas de mas","no")) -> completar Parametros | H14: =Proyeccion!L14 -> 22974 | I14: =IF(CapFisica="","",CapFisica) | J14: =IF(I14="","",H14/I14) | K14: =IF(I14="","",IF(H14>I14,"NO ENTRA",IF(H14>0.9*I14,"al limite","ok")))
A15: =Proyeccion!A15 -> 46349 | B15: =Proyeccion!B15 -> 46354 | C15: =Proyeccion!E15 -> 8064 | D15: =Demanda!H16 -> 17000 | E15: =IF(CapMadurar="","",CapMadurar) | F15: =IF(E15="","",D15/E15) | G15: =IF(E15="","completar Parametros",IF(D15>E15,"SI: "&FIXED(D15-E15,0)&" cajas de mas","no")) -> completar Parametros | H15: =Proyeccion!L15 -> 23038 | I15: =IF(CapFisica="","",CapFisica) | J15: =IF(I15="","",H15/I15) | K15: =IF(I15="","",IF(H15>I15,"NO ENTRA",IF(H15>0.9*I15,"al limite","ok")))
A16: =Proyeccion!A16 -> 46356 | B16: =Proyeccion!B16 -> 46361 | C16: =Proyeccion!E16 -> 8064 | D16: =Demanda!H17 -> 17000 | E16: =IF(CapMadurar="","",CapMadurar) | F16: =IF(E16="","",D16/E16) | G16: =IF(E16="","completar Parametros",IF(D16>E16,"SI: "&FIXED(D16-E16,0)&" cajas de mas","no")) -> completar Parametros | H16: =Proyeccion!L16 -> 23102 | I16: =IF(CapFisica="","",CapFisica) | J16: =IF(I16="","",H16/I16) | K16: =IF(I16="","",IF(H16>I16,"NO ENTRA",IF(H16>0.9*I16,"al limite","ok")))
A17: =Proyeccion!A17 -> 46363 | B17: =Proyeccion!B17 -> 46368 | C17: =Proyeccion!E17 -> 8064 | D17: =Demanda!H18 -> 17000 | E17: =IF(CapMadurar="","",CapMadurar) | F17: =IF(E17="","",D17/E17) | G17: =IF(E17="","completar Parametros",IF(D17>E17,"SI: "&FIXED(D17-E17,0)&" cajas de mas","no")) -> completar Parametros | H17: =Proyeccion!L17 -> 23166 | I17: =IF(CapFisica="","",CapFisica) | J17: =IF(I17="","",H17/I17) | K17: =IF(I17="","",IF(H17>I17,"NO ENTRA",IF(H17>0.9*I17,"al limite","ok")))
A18: =Proyeccion!A18 -> 46370 | B18: =Proyeccion!B18 -> 46375 | C18: =Proyeccion!E18 -> 8064 | D18: =Demanda!H18 -> 17000 | E18: =IF(CapMadurar="","",CapMadurar) | F18: =IF(E18="","",D18/E18) | G18: =IF(E18="","completar Parametros",IF(D18>E18,"SI: "&FIXED(D18-E18,0)&" cajas de mas","no")) -> completar Parametros | H18: =Proyeccion!L18 -> 23230 | I18: =IF(CapFisica="","",CapFisica) | J18: =IF(I18="","",H18/I18) | K18: =IF(I18="","",IF(H18>I18,"NO ENTRA",IF(H18>0.9*I18,"al limite","ok")))
A20: "Cajas a madurar" es un PROXY: se toma la venta de la semana siguiente (lo que hay que tener maduro para vender). Referencias (multinacionales): ciclo de maduracion de 4 a 6 dias (5 el mas usado); etileno 100-150 ppm las primeras 24 h; minimo 4 camaras para escalonar entrada, gaseo y despacho; una camara de 20 pallets por cada 20 pallets extra por semana hasta ~140 pallets/semana. Un pallet = 48 cajas de 22 kg aprox.

Sheet KPIs
A1: KPIs del plan
A2: Los de arriba salen de la planilla. Abajo, la referencia de como lo miden las multinacionales de fruta y que equivale en Almar.
A4: Indicador | B4: Valor | C4: Como se calcula / lectura
A5: Stock al conteo (cajas) | B5: =ConteoTotal -> 26972 | C5: Parametros: conteo por camara, BR + PY + BO. Ecuador no entra (va por otro canal).
A6: Dias de cobertura al conteo | B6: =ConteoTotal/(INDEX(DemVenta,MATCH(FechaConteo-WEEKDAY(FechaConteo,2)+1+7,DemSemana,0))/DiasVenta) -> 10.1145 | C6: Stock / venta diaria de la semana siguiente al conteo. Multinacionales: "days on hand" o DOS.
A7: Semana actual: stock proyectado al sabado | B7: =IFERROR(INDEX(PrStock,MATCH(FechaHoy-WEEKDAY(FechaHoy,2)+1,PrSemana,0)),"") -> 22898 | C7: Proyeccion, fila de la semana de hoy, con los pedidos ya contados.
A8: Semana actual: camiones a cargar | B8: =IFERROR(INDEX(PrACargar,MATCH(FechaHoy-WEEKDAY(FechaHoy,2)+1,PrSemana,0)),"") -> 0 | C8: Lo que falta cargar antes del limite de esta semana.
A9: Semana proxima: camiones a cargar | B9: =IFERROR(INDEX(PrACargar,MATCH(FechaHoy-WEEKDAY(FechaHoy,2)+1+7,PrSemana,0)),"") -> 4 | C9: El numero que hay que tener el miercoles (PY) y el jueves (BR).
A10: Cobertura promedio proximas 4 semanas (dias) | B10: =AVERAGEIFS(PrCobertura,PrSemana,">="&(FechaHoy-WEEKDAY(FechaHoy,2)+1),PrSemana,"<"&(FechaHoy-WEEKDAY(FechaHoy,2)+1+28)) -> 8.0435294 | C10: Promedio de "Dias de cobertura" de Proyeccion. Objetivo: Parametros > cobertura objetivo.
A11: Semanas que piden cargar (prox. 4 sem) | B11: =COUNTIFS(PrACargar,">0",PrSemana,">="&(FechaHoy-WEEKDAY(FechaHoy,2)+1),PrSemana,"<"&(FechaHoy-WEEKDAY(FechaHoy,2)+1+28)) -> 3 | C11: Semanas de las proximas 4 que cierran abajo del minimo sin camiones extra. Mas alla de 2-3 semanas es normal que pidan, porque todavia no hay cargas dictadas.
A12: Camiones a cargar prox. 4 sem (ademas de lo dictado) | B12: =SUMIFS(PrACargar,PrSemana,">="&(FechaHoy-WEEKDAY(FechaHoy,2)+1),PrSemana,"<"&(FechaHoy-WEEKDAY(FechaHoy,2)+1+28)) -> 12 | C12: Suma de "Camiones a cargar" de Proyeccion en las proximas 4 semanas.
A13: Rotacion: semanas de stock al conteo | B13: =ConteoTotal/INDEX(DemVenta,MATCH(FechaConteo-WEEKDAY(FechaConteo,2)+1+7,DemSemana,0)) -> 1.68575 | C13: Stock / venta semanal. Referencia en fresco: 1 a 2 semanas de stock (26-52 vueltas al ano). Almar al 26/09: 1,6 semanas, dentro del rango pero en el borde alto.
A14: Valor del stock al conteo (USD) | B14: =ConteoBR*CostoBR+ConteoPY*CostoPY+ConteoBO*CostoBO -> 196107.57 | C14: Cajas por origen x USD/caja usado (Parametros). Capital de trabajo inmovilizado en camara.
A15: Verde en transito (cajas cargadas y no descargadas, Aloha) | B15: =SUM(CgPipeline) -> 7922 | C15: Pipeline: camiones ya cargados que todavia no descargaron (Cargas, columna "Pipeline"). Con el export de Aloha al dia es lo que viene en camino.
A16: Brasil: precio pagado vs Cepea + servicios (R$/caja) | B16: =PrecioBR_BRL-(CepeaKg*KgCaja+ServiciosCaja) -> -7.09 | C16: Negativo = Almar paga por debajo de la referencia Cepea x 22 kg + R$ 18 de servicios.
A17: Concentracion Paraguay: % camiones del mayor productor (8 sem) | B17: =IFERROR(SUMPRODUCT(MAX((Proveedores!A5:A60="PY")*Proveedores!D5:D60))/SUMIF(Proveedores!A5:A60,"PY",Proveedores!D5:D60),"") -> 0.48076923 | C17: Riesgo de dependencia: HF sola fue el 54% de los camiones PY de 2026. Multinacionales: 20-30% del programa en proveedores de contingencia precalificados (hoja MercadoPY).
A18: Concentracion Brasil: % camiones del mayor productor (8 sem) | B18: =IFERROR(SUMPRODUCT(MAX((Proveedores!A5:A60="BR")*Proveedores!D5:D60))/SUMIF(Proveedores!A5:A60,"BR",Proveedores!D5:D60),"") -> 0.1875
A19: Camiones que descargan por semana, prox. 4 sem (promedio) | B19: =AVERAGEIFS(PrCamiones,PrSemana,">="&(FechaHoy-WEEKDAY(FechaHoy,2)+1),PrSemana,"<"&(FechaHoy-WEEKDAY(FechaHoy,2)+1+28)) -> 12.5 | C19: Aloha + dictados + supuestos.
A20: Mix descargas prox. 4 sem: Brasil | B20: =IFERROR(SUMIFS(CgCajas,CgOrigen,"BR",CgCuenta,1,CgSemana,">="&(FechaHoy-WEEKDAY(FechaHoy,2)+1),CgSemana,"<"&(FechaHoy-WEEKDAY(FechaHoy,2)+1+28))/SUMIFS(CgCajas,CgCuenta,1,CgSemana,">="&(FechaHoy-WEEKDAY(FechaHoy,2)+1),CgSemana,"<"&(FechaHoy-WEEKDAY(FechaHoy,2)+1+28)),0) -> 0.60475023 | C20: Cajas por origen sobre el total de las proximas 4 semanas. Diversificacion de origen = menos riesgo (frontera, clima, TR4).
A21: Mix descargas prox. 4 sem: Paraguay | B21: =IFERROR(SUMIFS(CgCajas,CgOrigen,"PY",CgCuenta,1,CgSemana,">="&(FechaHoy-WEEKDAY(FechaHoy,2)+1),CgSemana,"<"&(FechaHoy-WEEKDAY(FechaHoy,2)+1+28))/SUMIFS(CgCajas,CgCuenta,1,CgSemana,">="&(FechaHoy-WEEKDAY(FechaHoy,2)+1),CgSemana,"<"&(FechaHoy-WEEKDAY(FechaHoy,2)+1+28)),0) -> 0.37415103
A22: Mix descargas prox. 4 sem: Bolivia | B22: =IFERROR(SUMIFS(CgCajas,CgOrigen,"BO",CgCuenta,1,CgSemana,">="&(FechaHoy-WEEKDAY(FechaHoy,2)+1),CgSemana,"<"&(FechaHoy-WEEKDAY(FechaHoy,2)+1+28))/SUMIFS(CgCajas,CgCuenta,1,CgSemana,">="&(FechaHoy-WEEKDAY(FechaHoy,2)+1),CgSemana,"<"&(FechaHoy-WEEKDAY(FechaHoy,2)+1+28)),0) -> 0.021098742
A23: Costo estimado de compra prox. 4 sem (USD) | B23: =SUMIFS(CgCosto,CgCuenta,1,CgSemana,">="&(FechaHoy-WEEKDAY(FechaHoy,2)+1),CgSemana,"<"&(FechaHoy-WEEKDAY(FechaHoy,2)+1+28)) -> 355060.64 | C23: Cajas que descargan x USD/caja usado (Parametros: precio de compra real si esta cargado, si no la referencia de aduana 2026).
A24: Camiones supuestos en el horizonte (PY + BR) | B24: =COUNTIFS(CgEstado,"Supuesto*",CgCuenta,1) -> 103 | C24: Cuantos de los camiones contados todavia son supuestos (5 PY por semana; 8 BR los viernes mas alla de lo dictado). Cuanto mas bajo, mas firme el plan. Se apagan en Parametros (SupPY / SupBR).
A25: Faltante promedio de los proveedores (MIC - descargado, Aloha 2024-26) | B25: =IFERROR(AVERAGE(Proveedores!R5:R60),"") -> -0.00095789474 | C25: Fill rate del proveedor: positivo = descargo menos de lo declarado; negativo = descargo de mas. Por productor en Proveedores.
A26: OTIF: camiones que descargaron dentro del lead time + 1 dia | B26: =IFERROR(AVERAGE(CgOTIF),"sin descargas reales todavia") -> 1 | C26: Sobre los camiones con descarga real cargada en Cargas (columna Descarga real). Se llena solo a medida que se anotan descargas.
A27: Camiones dictados que Aloha aun no tiene | B27: =COUNTIFS(CgEstado,"Dictado",CgCuenta,1) -> 16 | C27: Pasan a Aloha cuando se cargan en el sistema.
A28: Exactitud del pronostico (MAPE, semanas con venta real) | B28: =IFERROR(SUMPRODUCT((Demanda!O6:O18<>"")*ABS(Demanda!P6:P18))/COUNTIF(Demanda!O6:O18,"<>"),"sin venta real cargada") -> sin venta real cargada | C28: Promedio del desvio absoluto entre venta real (ERP) y venta usada. Multinacionales: forecast accuracy semanal; <10% es bueno para fruta.
A30: REFERENCIA MULTINACIONAL (S&OP de fruta fresca) | B30: Practica | C30: Equivalente en Almar / esta planilla
A31: Cadencia S&OP | B31: Reunion semanal (15-30 min) de demanda, abastecimiento y riesgos, con KPIs de merma y exactitud del pronostico. | C31: El WhatsApp del miercoles 12:00 (pedidos) y del viernes 19:00 (cierre): Cepea, clima, stock proyectado y camiones que faltan. Esta planilla es el soporte para probar antes de dictar.
A32: Un solo plan de demanda | B32: Un numero de venta por semana acordado entre ventas y compras, con estacionalidad (dia de la semana, semana del mes) y venta real para medir el desvio. | C32: Hoja Demanda: venta plan + factor por semana del mes + venta manual + venta real ERP + desvio.
A33: Proyeccion de inventario | B33: Stock inicial + recepciones - demanda = stock final, por semana, contra un stock de seguridad explicito; recomendacion de pedido con fecha limite por lead time. | C33: Hoja Proyeccion: cierre del sabado, minimo 22.500, camiones a cargar y fecha limite (sabado - lead time).
A34: Stock de seguridad dinamico (perecederos) | B34: Sube y baja con la venta (mas antes del fin de semana / comienzo de mes), acotado por la vida util: mas stock = mas merma. | C34: Minimo en cajas (22.500) o por dias de venta (7): Parametros. La cobertura objetivo pinta la proyeccion.
A35: Dias de cobertura (DOS / days on hand) | B35: Indicador central: stock / venta diaria. Objetivo por categoria; fruta fresca 5-10 dias segun madurez. | C35: Columnas "Dias de cobertura" (total y por origen). Almar: 7 dias = fruta que todavia no maduro (gas + camara).
A36: Lead time y ciclo de pedido por dia de la semana | B36: Cada origen con su lead time y su dia de corte; el sistema avisa antes del corte si la cobertura no llega. | C36: Lead time por origen (3/3/6), lead time real por productor (Proveedores), corte PY miercoles / BR jueves, "Cargar hasta" por semana.
A37: Capacidad de maduracion | B37: Camaras de maduracion planificadas por volumen semanal (regla: una camara de 20 pallets por cada 20 pallets extra por semana, hasta ~140 pallets/sem). | C37: Pendiente: cargar capacidad de camaras (ZAC / Coronel Raiz) como tope de recepcion semanal. FechaHoy el limite es el minimo, no el maximo.
A38: Costo total puesto en destino | B38: Precio en origen + empaque + flete + aduana + maduracion + merma esperada por carril/proveedor. | C38: Parametros: Cepea x 22 + servicios, precio pagado Almar, TC; KPI de costo de las proximas 4 semanas. Falta: flete internacional, aduana y merma por productor (calidad).
A39: Diversificacion de origen y proveedores | B39: 20-30% del programa en proveedores de contingencia precalificados; varios origenes, puertos y transportistas. | C39: Tres origenes (BR / PY / BO), 17 productores BR, 4 PY, 2 BO; el mix por origen esta en KPIs. Proveedores: capacidad semanal por productor.
A40: Scorecard de proveedores | B40: OTIF por carril, reclamos, dias en verde / color de llegada, tiempo de correccion. | C40: Proveedores: lead time real, regularidad (camiones por semana), precio. Calidad y vida verde: index_calidad (necesita 15 lotes con fecha de rompio).
A41: Merma / shrink | B41: 2-10% del costo puesto en destino segun cadena de frio y madurez; se mide y se descuenta del plan. | C41: Sin dato en el plan. Sugerencia: registrar cajas descartadas por semana en la hoja Demanda (columna nueva) y restarlas del stock.

Sheet Proveedores
A1: Proveedores: capacidad y comportamiento real
A2: Camiones desde el 02/08/2026 segun el Plan de Cargas de Aloha (8 semanas). Capacidad semanal = maximo observado (editable). Precio 2026 = promedio pagado por caja (cargas 2026.xlsx).
A4: Origen | B4: Productor (Aloha) | C4: Nombre en cargas dictadas | D4: Camiones (8 sem) | E4: Semanas con carga | F4: Prom camiones/sem | G4: Pico: max camiones en una semana | H4: CAPACIDAD semanal (prom. de las 2 mejores semanas) | I4: Lead time real (dias) | J4: Cajas/camion | K4: Transportista habitual | L4: Dias de carga habituales | M4: Precio prom 2026 (R$/caja) | N4: Camiones esta semana (Cargas) | O4: Camiones semana proxima (Cargas) | P4: Nota | Q4: Camiones 2024/2025/2026 (Aloha) | R4: Faltante % (MIC - descargado) | S4: Ultima carga (Aloha 24/09) | T4: Cupo aprox/sem 2026 | U4: Situacion
A5: BR | B5: Corupá | C5: Agrocurupa | D5: 12 | E5: 7 | F5: 1.5 | G5: 2 | H5: 2 | I5: 3.5 | J5: 1008 | K5: FG (11) / Chabat (1) | L5: vie 6, mie 4, mar 1 | M5: 37.75 | N5: =COUNTIFS(CgProductor,B5,CgSemana,FechaHoy-WEEKDAY(FechaHoy,2)+1)+IF(C5<>B5,COUNTIFS(CgProductor,C5,CgSemana,FechaHoy-WEEKDAY(FechaHoy,2)+1),0) -> 2 | O5: =COUNTIFS(CgProductor,B5,CgSemana,FechaHoy-WEEKDAY(FechaHoy,2)+1+7)+IF(C5<>B5,COUNTIFS(CgProductor,C5,CgSemana,FechaHoy-WEEKDAY(FechaHoy,2)+1+7),0) -> 1 | Q5: 47/76/46 | R5: 0.0002 | S5: 11/09/2026 | T5: 1.2 | U5: activo
A6: BR | B6: Fischer | C6: Fisher | D6: 12 | E6: 8 | F6: 1.5 | G6: 2 | H6: 2 | I6: 3.7 | J6: 1008 | K6: Amaro (8) / FG (4) | L6: vie 5, mar 4, sab 2 | M6: 37 | N6: =COUNTIFS(CgProductor,B6,CgSemana,FechaHoy-WEEKDAY(FechaHoy,2)+1)+IF(C6<>B6,COUNTIFS(CgProductor,C6,CgSemana,FechaHoy-WEEKDAY(FechaHoy,2)+1),0) -> 1 | O6: =COUNTIFS(CgProductor,B6,CgSemana,FechaHoy-WEEKDAY(FechaHoy,2)+1+7)+IF(C6<>B6,COUNTIFS(CgProductor,C6,CgSemana,FechaHoy-WEEKDAY(FechaHoy,2)+1+7),0) -> 1 | Q6: 17/164/61 | R6: 0.0005 | S6: 19/09/2026 | T6: 1.6 | U6: activo
A7: BR | B7: Cassio Hauck | C7: Cassio | D7: 10 | E7: 7 | F7: 1.2 | G7: 3 | H7: 2.5 | I7: 3.8 | J7: 936 | K7: AXT (6) / Chabat (3) | L7: vie 6, mie 2, mar 2 | M7: 38.64 | N7: =COUNTIFS(CgProductor,B7,CgSemana,FechaHoy-WEEKDAY(FechaHoy,2)+1)+IF(C7<>B7,COUNTIFS(CgProductor,C7,CgSemana,FechaHoy-WEEKDAY(FechaHoy,2)+1),0) -> 1 | O7: =COUNTIFS(CgProductor,B7,CgSemana,FechaHoy-WEEKDAY(FechaHoy,2)+1+7)+IF(C7<>B7,COUNTIFS(CgProductor,C7,CgSemana,FechaHoy-WEEKDAY(FechaHoy,2)+1+7),0) -> 1 | Q7: 13/88/96 | R7: -0.0014 | S7: 18/09/2026 | T7: 2.5 | U7: el mas regular de Brasil
A8: BR | B8: Osnildo Stein | C8: Stein | D8: 7 | E8: 5 | F8: 0.9 | G8: 2 | H8: 2 | I8: 3.9 | J8: 1008 | K8: Chabat (5) / FG (2) | L8: vie 5, mie 1, mar 1 | M8: 41.63 | N8: =COUNTIFS(CgProductor,B8,CgSemana,FechaHoy-WEEKDAY(FechaHoy,2)+1)+IF(C8<>B8,COUNTIFS(CgProductor,C8,CgSemana,FechaHoy-WEEKDAY(FechaHoy,2)+1),0) -> 1 | O8: =COUNTIFS(CgProductor,B8,CgSemana,FechaHoy-WEEKDAY(FechaHoy,2)+1+7)+IF(C8<>B8,COUNTIFS(CgProductor,C8,CgSemana,FechaHoy-WEEKDAY(FechaHoy,2)+1+7),0) -> 1 | Q8: 0/0/22 | R8: 0 | S8: 11/09/2026 | T8: 0.6 | U8: nuevo 2026
A9: BR | B9: Ivo Zimerman | C9: Ivo zimer | D9: 6 | E9: 5 | F9: 0.8 | G9: 2 | H9: 1.5 | I9: 2.8 | J9: 1008 | K9: FG (4) / Chabat (2) | L9: mie 2, vie 2, mar 1 | M9: 40.74 | N9: =COUNTIFS(CgProductor,B9,CgSemana,FechaHoy-WEEKDAY(FechaHoy,2)+1)+IF(C9<>B9,COUNTIFS(CgProductor,C9,CgSemana,FechaHoy-WEEKDAY(FechaHoy,2)+1),0) -> 1 | O9: =COUNTIFS(CgProductor,B9,CgSemana,FechaHoy-WEEKDAY(FechaHoy,2)+1+7)+IF(C9<>B9,COUNTIFS(CgProductor,C9,CgSemana,FechaHoy-WEEKDAY(FechaHoy,2)+1+7),0) -> 1 | Q9: 0/0/16 | R9: -0.0078 | S9: 18/09/2026 | T9: 0.4 | U9: activo
A10: BR | B10: Gilson | C10: Gilson | D10: 5 | E10: 5 | F10: 0.6 | G10: 1 | H10: 1 | I10: 3 | J10: 1008 | K10: FG (5) | L10: jue 1, mar 1, mie 1 | M10: 40.65 | N10: =COUNTIFS(CgProductor,B10,CgSemana,FechaHoy-WEEKDAY(FechaHoy,2)+1)+IF(C10<>B10,COUNTIFS(CgProductor,C10,CgSemana,FechaHoy-WEEKDAY(FechaHoy,2)+1),0) -> 0 | O10: =COUNTIFS(CgProductor,B10,CgSemana,FechaHoy-WEEKDAY(FechaHoy,2)+1+7)+IF(C10<>B10,COUNTIFS(CgProductor,C10,CgSemana,FechaHoy-WEEKDAY(FechaHoy,2)+1+7),0) -> 1 | Q10: 39/70/37 | R10: -0.0004 | S10: 10/09/2026 | T10: 1 | U10: activo
A11: BR | B11: Josemar Provesi | C11: Josemar | D11: 4 | E11: 4 | F11: 0.5 | G11: 1 | H11: 1 | I11: 3.2 | J11: 1008 | K11: FG (2) / Chabat (1) | L11: vie 2, sab 1, mie 1 | M11: 42.33 | N11: =COUNTIFS(CgProductor,B11,CgSemana,FechaHoy-WEEKDAY(FechaHoy,2)+1)+IF(C11<>B11,COUNTIFS(CgProductor,C11,CgSemana,FechaHoy-WEEKDAY(FechaHoy,2)+1),0) -> 0 | O11: =COUNTIFS(CgProductor,B11,CgSemana,FechaHoy-WEEKDAY(FechaHoy,2)+1+7)+IF(C11<>B11,COUNTIFS(CgProductor,C11,CgSemana,FechaHoy-WEEKDAY(FechaHoy,2)+1+7),0) -> 1 | U11: activo
A12: BR | B12: Marconi Kons | C12: Marconi | D12: 3 | E12: 3 | F12: 0.4 | G12: 1 | H12: 1 | I12: 3.7 | J12: 1008 | K12: FG (2) / Amaro (1) | L12: vie 2, sab 1 | M12: 42.16 | N12: =COUNTIFS(CgProductor,B12,CgSemana,FechaHoy-WEEKDAY(FechaHoy,2)+1)+IF(C12<>B12,COUNTIFS(CgProductor,C12,CgSemana,FechaHoy-WEEKDAY(FechaHoy,2)+1),0) -> 0 | O12: =COUNTIFS(CgProductor,B12,CgSemana,FechaHoy-WEEKDAY(FechaHoy,2)+1+7)+IF(C12<>B12,COUNTIFS(CgProductor,C12,CgSemana,FechaHoy-WEEKDAY(FechaHoy,2)+1+7),0) -> 1 | Q12: 0/0/14 | R12: -0.0001 | S12: 11/09/2026 | T12: 0.4 | U12: camion chico (834 cajas promedio historico)
A13: BR | B13: Furlani | C13: Furlani | D13: 2 | E13: 2 | F13: 0.2 | G13: 1 | H13: 1 | I13: 3 | J13: 1008 | K13: Amaro (1) / Chabat (1) | L13: mie 1, vie 1 | M13: 37.64 | N13: =COUNTIFS(CgProductor,B13,CgSemana,FechaHoy-WEEKDAY(FechaHoy,2)+1)+IF(C13<>B13,COUNTIFS(CgProductor,C13,CgSemana,FechaHoy-WEEKDAY(FechaHoy,2)+1),0) -> 0 | O13: =COUNTIFS(CgProductor,B13,CgSemana,FechaHoy-WEEKDAY(FechaHoy,2)+1+7)+IF(C13<>B13,COUNTIFS(CgProductor,C13,CgSemana,FechaHoy-WEEKDAY(FechaHoy,2)+1+7),0) -> 0 | U13: activo
A14: BR | B14: Shapo | C14: Shapo | D14: 2 | E14: 2 | F14: 0.2 | G14: 1 | H14: 1 | I14: 4.5 | J14: 1008 | K14: Chabat (1) / FG (1) | L14: vie 2 | M14: 37.8 | N14: =COUNTIFS(CgProductor,B14,CgSemana,FechaHoy-WEEKDAY(FechaHoy,2)+1)+IF(C14<>B14,COUNTIFS(CgProductor,C14,CgSemana,FechaHoy-WEEKDAY(FechaHoy,2)+1),0) -> 0 | O14: =COUNTIFS(CgProductor,B14,CgSemana,FechaHoy-WEEKDAY(FechaHoy,2)+1+7)+IF(C14<>B14,COUNTIFS(CgProductor,C14,CgSemana,FechaHoy-WEEKDAY(FechaHoy,2)+1+7),0) -> 0 | U14: activo
A15: BR | B15: Wagner Schveitzer | C15: Wagner | D15: 1 | E15: 1 | F15: 0.1 | G15: 1 | H15: 1 | I15: 4 | J15: 1008 | K15: Amaro (1) | L15: vie 1 | M15: 41.14 | N15: =COUNTIFS(CgProductor,B15,CgSemana,FechaHoy-WEEKDAY(FechaHoy,2)+1)+IF(C15<>B15,COUNTIFS(CgProductor,C15,CgSemana,FechaHoy-WEEKDAY(FechaHoy,2)+1),0) -> 0 | O15: =COUNTIFS(CgProductor,B15,CgSemana,FechaHoy-WEEKDAY(FechaHoy,2)+1+7)+IF(C15<>B15,COUNTIFS(CgProductor,C15,CgSemana,FechaHoy-WEEKDAY(FechaHoy,2)+1+7),0) -> 0 | Q15: 0/0/11 | R15: -0.0018 | S15: 14/08/2026 | T15: 0.3 | U15: activo
A16: PY | B16: Paraguay HF | C16: Paraguay HF | D16: 25 | E16: 8 | F16: 3.1 | G16: 7 | H16: 5.5 | I16: 3.4 | J16: 980 | K16: Mega Logistica (22) / G.S.C.S. PARAGUAY TTES. (3) | L16: dom 12, lun 8, mar 2 | N16: =COUNTIFS(CgProductor,B16,CgSemana,FechaHoy-WEEKDAY(FechaHoy,2)+1)+IF(C16<>B16,COUNTIFS(CgProductor,C16,CgSemana,FechaHoy-WEEKDAY(FechaHoy,2)+1),0) -> 0 | O16: =COUNTIFS(CgProductor,B16,CgSemana,FechaHoy-WEEKDAY(FechaHoy,2)+1+7)+IF(C16<>B16,COUNTIFS(CgProductor,C16,CgSemana,FechaHoy-WEEKDAY(FechaHoy,2)+1+7),0) -> 0 | P16: Paraguay carga domingo-lunes-martes y entra en la semana. | Q16: 39/16/76 | R16: -0.001 | S16: 21/09/2026 | T16: 2 | U16: 54% de los camiones PY de 2026: dependencia alta
A17: PY | B17: Paraguay AS | C17: Paraguay AS | D17: 12 | E17: 7 | F17: 1.5 | G17: 2 | H17: 2 | I17: 3.3 | J17: 980 | K17: MARSO EMPRENDIMIENTOS S.R.L. (10) | L17: lun 5, mar 5, mie 1 | N17: =COUNTIFS(CgProductor,B17,CgSemana,FechaHoy-WEEKDAY(FechaHoy,2)+1)+IF(C17<>B17,COUNTIFS(CgProductor,C17,CgSemana,FechaHoy-WEEKDAY(FechaHoy,2)+1),0) -> 1 | O17: =COUNTIFS(CgProductor,B17,CgSemana,FechaHoy-WEEKDAY(FechaHoy,2)+1+7)+IF(C17<>B17,COUNTIFS(CgProductor,C17,CgSemana,FechaHoy-WEEKDAY(FechaHoy,2)+1+7),0) -> 0 | P17: Paraguay carga domingo-lunes-martes y entra en la semana. | Q17: 0/0/11 | R17: -0.0039 | S17: 21/09/2026 | T17: 1.8 | U17: nuevo desde 11/08/2026 (Alvarito)
A18: PY | B18: Paraguay MS | C18: Paraguay MS | D18: 12 | E18: 7 | F18: 1.5 | G18: 3 | H18: 2.5 | I18: 3.6 | J18: 980 | K18: G.S.C.S. PARAGUAY TTES. (6) / Lider Express (4) | L18: lun 5, mar 5, dom 1 | N18: =COUNTIFS(CgProductor,B18,CgSemana,FechaHoy-WEEKDAY(FechaHoy,2)+1)+IF(C18<>B18,COUNTIFS(CgProductor,C18,CgSemana,FechaHoy-WEEKDAY(FechaHoy,2)+1),0) -> 1 | O18: =COUNTIFS(CgProductor,B18,CgSemana,FechaHoy-WEEKDAY(FechaHoy,2)+1+7)+IF(C18<>B18,COUNTIFS(CgProductor,C18,CgSemana,FechaHoy-WEEKDAY(FechaHoy,2)+1+7),0) -> 0 | P18: Paraguay carga domingo-lunes-martes y entra en la semana. | Q18: 84/16/22 | R18: 0.0001 | S18: 15/09/2026 | T18: 0.6 | U18: activo
A19: PY | B19: Paraguay DF | C19: Paraguay DF | D19: 3 | E19: 2 | F19: 0.4 | G19: 2 | H19: 1.5 | I19: 3 | J19: 980 | K19: Jauser (3) | L19: dom 1, lun 1, mar 1 | N19: =COUNTIFS(CgProductor,B19,CgSemana,FechaHoy-WEEKDAY(FechaHoy,2)+1)+IF(C19<>B19,COUNTIFS(CgProductor,C19,CgSemana,FechaHoy-WEEKDAY(FechaHoy,2)+1),0) -> 2 | O19: =COUNTIFS(CgProductor,B19,CgSemana,FechaHoy-WEEKDAY(FechaHoy,2)+1+7)+IF(C19<>B19,COUNTIFS(CgProductor,C19,CgSemana,FechaHoy-WEEKDAY(FechaHoy,2)+1+7),0) -> 0 | P19: Paraguay carga domingo-lunes-martes y entra en la semana. | Q19: 40/13/20 | R19: -0.0015 | S19: 14/09/2026 | T19: 0.5 | U19: transportista historico Compass
A20: BO | B20: Banexfrut | C20: Bolivia | D20: 5 | E20: 4 | F20: 0.6 | G20: 2 | H20: 1.5 | I20: 8.2 | J20: 1050 | K20: Surcentral (5) | L20: vie 3, lun 2 | N20: =COUNTIFS(CgProductor,B20,CgSemana,FechaHoy-WEEKDAY(FechaHoy,2)+1)+IF(C20<>B20,COUNTIFS(CgProductor,C20,CgSemana,FechaHoy-WEEKDAY(FechaHoy,2)+1),0) -> 1 | O20: =COUNTIFS(CgProductor,B20,CgSemana,FechaHoy-WEEKDAY(FechaHoy,2)+1+7)+IF(C20<>B20,COUNTIFS(CgProductor,C20,CgSemana,FechaHoy-WEEKDAY(FechaHoy,2)+1+7),0) -> 0 | P20: Bolivia: 6-9 dias reales de carga a descarga; 1 camion por semana en promedio. | U20: Bolivia: 1 camion por semana aprox, 6-9 dias de viaje
A21: BO | B21: Befrut | C21: Bolivia | D21: 3 | E21: 3 | F21: 0.4 | G21: 1 | H21: 1 | I21: 8.7 | J21: 1050 | K21: Sintercargas (3) | L21: mie 2, lun 1 | N21: =COUNTIFS(CgProductor,B21,CgSemana,FechaHoy-WEEKDAY(FechaHoy,2)+1)+IF(C21<>B21,COUNTIFS(CgProductor,C21,CgSemana,FechaHoy-WEEKDAY(FechaHoy,2)+1),0) -> 1 | O21: =COUNTIFS(CgProductor,B21,CgSemana,FechaHoy-WEEKDAY(FechaHoy,2)+1+7)+IF(C21<>B21,COUNTIFS(CgProductor,C21,CgSemana,FechaHoy-WEEKDAY(FechaHoy,2)+1+7),0) -> 0 | P21: Bolivia: 6-9 dias reales de carga a descarga; 1 camion por semana en promedio. | U21: Bolivia
A22: BO | B22: Bolivia | C22: Bolivia | D22: 1 | E22: 1 | F22: 0.1 | G22: 1 | H22: 1 | J22: 1050 | L22: vie 1 | N22: =COUNTIFS(CgProductor,B22,CgSemana,FechaHoy-WEEKDAY(FechaHoy,2)+1)+IF(C22<>B22,COUNTIFS(CgProductor,C22,CgSemana,FechaHoy-WEEKDAY(FechaHoy,2)+1),0) -> 1 | O22: =COUNTIFS(CgProductor,B22,CgSemana,FechaHoy-WEEKDAY(FechaHoy,2)+1+7)+IF(C22<>B22,COUNTIFS(CgProductor,C22,CgSemana,FechaHoy-WEEKDAY(FechaHoy,2)+1+7),0) -> 0 | P22: Bolivia: 6-9 dias reales de carga a descarga; 1 camion por semana en promedio. | U22: Bolivia (sin productor en Aloha)
A23: BR | B23: Valdemar | C23: Valdemar | D23: 0 | E23: 0 | J23: 982 | K23: FG | M23: 45.03 | N23: =COUNTIFS(CgProductor,B23,CgSemana,FechaHoy-WEEKDAY(FechaHoy,2)+1)+IF(C23<>B23,COUNTIFS(CgProductor,C23,CgSemana,FechaHoy-WEEKDAY(FechaHoy,2)+1),0) -> 0 | O23: =COUNTIFS(CgProductor,B23,CgSemana,FechaHoy-WEEKDAY(FechaHoy,2)+1+7)+IF(C23<>B23,COUNTIFS(CgProductor,C23,CgSemana,FechaHoy-WEEKDAY(FechaHoy,2)+1+7),0) -> 0 | P23: Sin cargas en las ultimas 8 semanas: alternativa si falla un habitual. | Q23: 81/133/33 | R23: 0.0011 | S23: 25/04/2026 | U23: inactivo desde abril 2026; fue el 2do de 2025
A24: BR | B24: Jhony Viera | C24: Jony | D24: 0 | E24: 0 | J24: 976 | K24: FG | M24: 40.58 | N24: =COUNTIFS(CgProductor,B24,CgSemana,FechaHoy-WEEKDAY(FechaHoy,2)+1)+IF(C24<>B24,COUNTIFS(CgProductor,C24,CgSemana,FechaHoy-WEEKDAY(FechaHoy,2)+1),0) -> 0 | O24: =COUNTIFS(CgProductor,B24,CgSemana,FechaHoy-WEEKDAY(FechaHoy,2)+1+7)+IF(C24<>B24,COUNTIFS(CgProductor,C24,CgSemana,FechaHoy-WEEKDAY(FechaHoy,2)+1+7),0) -> 0 | P24: Sin cargas en las ultimas 8 semanas: alternativa si falla un habitual. | Q24: 64/120/26 | R24: -0.0008 | S24: 23/03/2026 | U24: inactivo desde marzo 2026
A25: BR | B25: Jorge Marangoni | C25: Marangoni | D25: 0 | E25: 0 | J25: 1008 | K25: Chabat | M25: 39.24 | N25: =COUNTIFS(CgProductor,B25,CgSemana,FechaHoy-WEEKDAY(FechaHoy,2)+1)+IF(C25<>B25,COUNTIFS(CgProductor,C25,CgSemana,FechaHoy-WEEKDAY(FechaHoy,2)+1),0) -> 0 | O25: =COUNTIFS(CgProductor,B25,CgSemana,FechaHoy-WEEKDAY(FechaHoy,2)+1+7)+IF(C25<>B25,COUNTIFS(CgProductor,C25,CgSemana,FechaHoy-WEEKDAY(FechaHoy,2)+1+7),0) -> 0 | P25: Sin cargas en las ultimas 8 semanas: alternativa si falla un habitual. | Q25: 0/0/21 | R25: 0 | S25: 24/07/2026 | U25: sin cargas desde julio; TT 4 dias
A26: BR | B26: Banana Combinada | C26: Banana Combinada | D26: 0 | E26: 0 | J26: 996 | K26: FG | N26: =COUNTIFS(CgProductor,B26,CgSemana,FechaHoy-WEEKDAY(FechaHoy,2)+1)+IF(C26<>B26,COUNTIFS(CgProductor,C26,CgSemana,FechaHoy-WEEKDAY(FechaHoy,2)+1),0) -> 0 | O26: =COUNTIFS(CgProductor,B26,CgSemana,FechaHoy-WEEKDAY(FechaHoy,2)+1+7)+IF(C26<>B26,COUNTIFS(CgProductor,C26,CgSemana,FechaHoy-WEEKDAY(FechaHoy,2)+1+7),0) -> 0 | P26: Sin cargas en las ultimas 8 semanas: alternativa si falla un habitual. | Q26: 0/10/14 | R26: 0.0004 | S26: 26/06/2026 | U26: sin cargas desde junio; TT 4 dias
A27: PY | B27: Paraguay GM | C27: Guido / Servi Fel | D27: 0 | E27: 0 | J27: 972 | K27: Surcentral | N27: =COUNTIFS(CgProductor,B27,CgSemana,FechaHoy-WEEKDAY(FechaHoy,2)+1)+IF(C27<>B27,COUNTIFS(CgProductor,C27,CgSemana,FechaHoy-WEEKDAY(FechaHoy,2)+1),0) -> 0 | O27: =COUNTIFS(CgProductor,B27,CgSemana,FechaHoy-WEEKDAY(FechaHoy,2)+1+7)+IF(C27<>B27,COUNTIFS(CgProductor,C27,CgSemana,FechaHoy-WEEKDAY(FechaHoy,2)+1+7),0) -> 0 | P27: Sin cargas en las ultimas 8 semanas: alternativa si falla un habitual. | Q27: 25/6/11 | R27: 0.0006 | S27: 28/07/2026 | U27: sin cargar desde julio; TT 5 dias
A28: PY | B28: Paraguay EC | C28: Banana EC | D28: 0 | E28: 0 | J28: 936 | N28: =COUNTIFS(CgProductor,B28,CgSemana,FechaHoy-WEEKDAY(FechaHoy,2)+1)+IF(C28<>B28,COUNTIFS(CgProductor,C28,CgSemana,FechaHoy-WEEKDAY(FechaHoy,2)+1),0) -> 0 | O28: =COUNTIFS(CgProductor,B28,CgSemana,FechaHoy-WEEKDAY(FechaHoy,2)+1+7)+IF(C28<>B28,COUNTIFS(CgProductor,C28,CgSemana,FechaHoy-WEEKDAY(FechaHoy,2)+1+7),0) -> 0 | P28: Sin cargas en las ultimas 8 semanas: alternativa si falla un habitual. | Q28: 78/10/0 | R28: -0.0014 | S28: 10/2025 | U28: inactivo desde octubre 2025
A29: PY | B29: Paraguay SF | C29: Paraguay SF | D29: 0 | E29: 0 | J29: 980 | N29: =COUNTIFS(CgProductor,B29,CgSemana,FechaHoy-WEEKDAY(FechaHoy,2)+1)+IF(C29<>B29,COUNTIFS(CgProductor,C29,CgSemana,FechaHoy-WEEKDAY(FechaHoy,2)+1),0) -> 0 | O29: =COUNTIFS(CgProductor,B29,CgSemana,FechaHoy-WEEKDAY(FechaHoy,2)+1+7)+IF(C29<>B29,COUNTIFS(CgProductor,C29,CgSemana,FechaHoy-WEEKDAY(FechaHoy,2)+1+7),0) -> 0 | P29: Sin cargas en las ultimas 8 semanas: alternativa si falla un habitual. | Q29: 1/0/0 | R29: -0.001 | S29: 2024 | U29: un camion en 2024
A31: Rojo en "Camiones esta semana / proxima": se pidio mas de la capacidad semanal observada. La capacidad es editable (columna amarilla). Los nombres de la columna "Nombre en cargas dictadas" tienen que coincidir con los que se usan en la hoja Cargas.

Sheet MercadoPY
A1: Mercado exportador de Paraguay (Penta, ene-ago 2026)
A2: Quien mas tiene volumen si falla un proveedor habitual. Cupo semanal aprox = kg brutos / 34 semanas / 22 kg. OJO: 47% del valor 2026 figura como "No disponible" en Penta, asi que los cupos estan subestimados. USD CIF entre identificados.
A4: Exportador (razon social en aduana) | B4: Grupo (mismo productor, mas de una empresa) | C4: % del valor 2026 | D4: Millones de kg | E4: Cajas/semana aprox | F4: Relacion con Almar / nota
A5: Misionero SRL | B5: Misionero + Ecotierra | C5: 0.18 | D5: 6.42 | E5: 8600 | F5: marcas TROPICAL y CIRO
A6: Hugo Alberto Franco | B6: Franco + San Jose Obrero | C6: 0.095 | D6: 3.15 | E6: 4200 | F6: Tembiapora, Menicob: proveedor HF de Almar (54% de los camiones PY 2026)
A7: Ruben Dario Aguero | C7: 0.069 | D7: 2.97 | E7: 4000
A8: Emprendimientos Karen | C8: 0.063 | D8: 2.19 | E8: 2900
A9: Saldivar & Hijos | C9: 0.052 | D9: 1.86 | E9: 2500
A10: Agro Climatizadora San Jose | C10: 0.047 | D10: 1.68 | E10: 2250 | F10: no es San Jose Obrero
A11: Melgarejo Lopez | B11: Melgarejo + Servi-Fel | C11: 0.042 | D11: 1.57 | E11: 2100 | F11: proveedor de Nalia
A12: Ecotierra SRL | B12: Misionero + Ecotierra | C12: 0.04 | D12: 1.31 | E12: 1750 | F12: principal proveedor de Almar, marca PEPE
A13: Elvio Valdez | C13: 0.037 | D13: 1.57 | E13: 2100
A14: Velazquez Gimenez | C14: 0.035 | D14: 1.24 | E14: 1660
A15: Frutas Carolina | C15: 0.034 | D15: 1.29 | E15: 1720
A16: Samuel Riveros | C16: 0.031 | D16: 1.26 | E16: 1680
A17: Grupo Campo Flor | C17: 0.03 | D17: 1.34 | E17: 1790
A18: Servi-Fel | B18: Melgarejo + Servi-Fel | C18: 0.029 | F18: Guido (GM): proveedor de Almar sin cargas desde julio 2026
A19: Agroganadera San Jose Obrero | B19: Franco + San Jose Obrero | C19: 0.026
A20: Silvia Castillo | C20: 0.024 | F20: proveedora de Nalia
A21: Graciela Nunez | C21: 0.023
A22: Gaspar Saldivar & Nietos | C22: 0.021
A23: El Productor | C23: 0.018
A24: Fernandez Andes Schaerer Diego Fernando (persona fisica) | C24: 0.009 | D24: 0.71 | E24: 940 | F24: Paraguay DF de Almar (Diego). Puesto 23 de 2026; 61% de su fruta 2026 sale con marca PEPE. Mejor ano 2024 (~1.800 cajas/sem, puesto 14); 2025 casi nada; 2026 vuelve. Cupo observado ~1 camion/sem.
A26: RANKING AGRUPADO (3 grupos confirmados por Gonzalo + individuales) | B26: Empresas | C26: % del valor 2026 | D26: Cajas/semana aprox | E26: Nota
A27: Misionero + Ecotierra | B27: Misionero SRL + Ecotierra SRL | C27: 0.22 | D27: 10350 | E27: el grupo del principal proveedor de Almar (Ecotierra, marca PEPE); Misionero 8.600 + Ecotierra 1.750 cajas/sem
A28: Franco + San Jose Obrero | B28: Hugo Alberto Franco + Agroganadera San Jose Obrero | C28: 0.121 | D28: 4200 | E28: HF de Almar; cajas/sem solo de Franco
A29: Melgarejo + Servi-Fel | B29: Melgarejo Lopez + Servi-Fel | C29: 0.071 | D29: 2100 | E29: Guido (GM) de Almar; cajas/sem solo de Melgarejo
A30: Ruben Dario Aguero | B30: Ruben Dario Aguero | C30: 0.069 | D30: 4000
A31: Emprendimientos Karen | B31: Emprendimientos Karen | C31: 0.063 | D31: 2900
A32: Saldivar & Hijos | B32: Saldivar & Hijos | C32: 0.052 | D32: 2500
A33: Agro Climatizadora San Jose | B33: Agro Climatizadora San Jose | C33: 0.047 | D33: 2250
A34: Elvio Valdez | B34: Elvio Valdez | C34: 0.037 | D34: 2100
A35: Velazquez Gimenez | B35: Velazquez Gimenez | C35: 0.035 | D35: 1660
A36: Frutas Carolina | B36: Frutas Carolina | C36: 0.034 | D36: 1720
A37: Samuel Riveros | B37: Samuel Riveros | C37: 0.031 | D37: 1680
A38: Grupo Campo Flor | B38: Grupo Campo Flor | C38: 0.03 | D38: 1790
A39: Silvia Castillo | B39: Silvia Castillo | C39: 0.024
A40: Graciela Nunez | B40: Graciela Nunez | C40: 0.023
A41: Gaspar Saldivar & Nietos | B41: Gaspar Saldivar & Nietos | C41: 0.021
A42: El Productor | B42: El Productor | C42: 0.018
A43: Fernandez Andes Schaerer Diego Fernando (persona fisica) | B43: Fernandez Andes Schaerer Diego Fernando (persona fisica) | C43: 0.009 | D43: 940
A45: Uso: si HF (Franco) o MS no pueden cargar, los cupos de Misionero, Aguero, Karen o Saldivar cubren 2-8 camiones por semana cada uno. Los grupos son SOLO los tres que confirmo Gonzalo (19/09/2026); las demas empresas se cuentan por separado aunque se parezcan de nombre. Fuente: extractos Penta (aduana UY) trabajados en el Excel de exportadores de Paraguay (otra sesion, 28/09/2026).

Sheet Glosario
A1: Glosario y fuentes
A3: Termino | B3: Que es
A4: S&OP (Sales & Operations Planning) | B4: Proceso semanal/mensual donde ventas, compras y logistica acuerdan UN plan de demanda y de abastecimiento y revisan riesgos con KPIs.
A5: Dias de cobertura (DOS, days on hand) | B5: Stock dividido la venta diaria. Cuantos dias aguanta el stock sin que entre nada.
A6: Stock de seguridad / minimo | B6: Stock que se quiere tener al cierre para absorber atrasos y picos de venta. Aca: 22.500 cajas al sabado (o 7 dias de venta).
A7: Lead time | B7: Dias entre cargar el camion y descargarlo en Almar. BR/PY 3, BO 6 (reales por productor en Proveedores).
A8: Punto de pedido / fecha limite | B8: Ultimo dia para cargar de modo que el camion sume a esa semana: sabado menos el lead time (miercoles para BR/PY).
A9: Corte de pedido | B9: Dia en que el proveedor cierra los pedidos de la semana siguiente: Paraguay miercoles, Brasil jueves.
A10: Prorrateo de la semana del conteo | B10: La venta de la semana en que se hizo el conteo se cuenta solo por los dias que quedan hasta el sabado.
A11: Arrastre de pedidos | B11: Los camiones que faltan en una semana se suman al stock de las siguientes (se supone que se cargan).
A12: Supuesto | B12: Camion que todavia no se dicto pero que se asume por costumbre (5 PY por semana).
A13: Forecast accuracy / MAPE | B13: Promedio del desvio absoluto entre venta real y venta planificada, en %.
A14: OTIF | B14: On time in full: % de cargas que llegan el dia previsto y completas. Se puede medir con el lead time real por productor.
... A21: Fill rate proveedor / faltante | B21: Cajas descargadas sobre cajas declaradas (MIC). En el Plan de Cargas de Aloha esta como faltante %.
A23: FUENTES CONSULTADAS (28/09/2026)
A24: Blue Ridge: 11-point checklist for perishable inventory management | B24: https://blueridgeglobal.com/blog/11-point-checklist-for-perishable-inventory-management/
A25: RELEX: fresh food inventory management (safety stock dinamico, perfiles diarios de demanda) | B25: https://www.relexsolutions.com/resources/fresh-food-inventory-management/
A26: RELEX: 4 strategies for managing fresh produce in grocery retail | B26: https://www.relexsolutions.com/resources/4-strategies-for-managing-fresh-fruits-and-vegetables-in-grocery-retail/
A27: SmartSense: S&OP decisions and food waste (cadencia semanal, KPIs de merma y forecast accuracy) | B27: https://blog.smartsense.co/sop-food-waste-supply-chain
A28: Tridge: banana sourcing intelligence, total landed cost and risk | B28: https://blog.tridge.com/blog-posts/banana-sourcing-intelligence-us-import-programs-where-total-landed-cost-and-risk-really-sit
A29: Thermal Technologies: ripening room FAQs (capacidad de camaras por volumen semanal) | B29: https://thermaltechnologies.com/ripening-room-faqs/
A30: MIT Sloan: what bananas can tell us about supply chains | B30: https://mitsloan.mit.edu/ideas-made-to-matter/what-bananas-can-tell-us-about-supply-chains
A31: LIDD: a deep dive into the banana supply chain | B31: https://lidd.com/banana-supply-chain/
A32: Vena: inventory forecasting template (safety stock = Z x desvio x raiz del lead time; punto de pedido) | B32: https://www.venasolutions.com/templates/plan-budget-forecast/inventory-forecasting
A33: Umbrex: perfil de Dole plc (metricas diarias y semanales: volumen, precio, flete, merma, servicio, capital de trabajo) | B33: https://umbrex.com/resources/company-profiles/dole-plc/
A34: Umbrex: service level optimization in fresh categories (KPIs encadenados: disponibilidad, fill rate/OTIF, frescura, merma, forecast accuracy) | B34: https://umbrex.com/resources/umbrex-explainers/agriculture-food-explainers/service-level-optimization-in-fresh-categories/
A35: Fyffes: red de 40+ centros de maduracion/distribucion | B35: https://en.wikipedia.org/wiki/Fyffes
... A40: Cloud Creations: KPI guide for grocery (rotacion en fresco 26-52 vueltas/ano) | B40: https://www.cloudcreations.com/resource/kpi-guide-for-grocery-supermarkets/
