Workbook
Name Fronteras: Rangos!$H$5:$H$11
Name Productores: Rangos!$J$5:$J$69
Name Status: Rangos!$B$5:$B$14
Name Transporte: Rangos!$D$5:$D$75

Sheet Cargas
H1: --
A2: PROGRAMA DE CARGAS EN BRASIL desde 2024
O3: Detalle/descripción presentación producto
A4: Carga Sem.# | B4: Status | C4: Factura | D4: Productor | E4: Fecha de Carga | F4: Carpeta Import. | G4: AFIDI | H4: Transportista | I4: Exportador | J4: Fecha Frontera | K4: Frontera | L4: Productos | M4: Fecha Descarga | N4: TT | O4: Cajas MIC | P4: Cajas Desc | Q4: CANT. DE PALLET | R4: CANT. KILOS POR CAJA/BOLSA | S4: Código de viaje | U4: MIC | V4: PLACAS T | W4: PLACAS R | X4: Chofer | Y4: Celular | Z4: Observaciones
A5: 2 | B5: Descargado | C5: 001/24 | D5: Jaime | E5: 45300 | F5: =VLOOKUP($C5,Carpetas!$C$5:$M$2666,2,FALSE) -> BRB001 | G5: =VLOOKUP($C5,Carpetas!$C$5:$M$2666,10,FALSE) -> 148,22,17 | H5: =VLOOKUP($C5,Carpetas!$C$5:$M$2666,6,FALSE) -> Zanini | I5: =VLOOKUP($C5,Carpetas!$C$5:$M$2666,4,FALSE) -> 0 | J5: 45301 | K5: =VLOOKUP($C5,Carpetas!$C$5:$M$2666,5,FALSE) -> Rio Branco | M5: =J5+1 -> 45302 | N5: =IF(E5<>"",M5-E5,"-") -> 2 | O5: 918 | P5: 919 | S5: JM001 | U5: 4157 | V5: RLL 2A97 | W5: QHK 7710 | X5: Benhur da Rosa | Y5: =VLOOKUP(X5,Choferes!$B$2:$C$500,2,FALSE) -> +5555991366995 | Z5: MM 11/01 : DESCARGADO EN RIQUEZA NATURAL 919 CAJAS DE BRASIL FIBRA.
A6: 1 | B6: Descargado | C6: 021//24 | D6: Varios | E6: 45296 | F6: =VLOOKUP($C6,Carpetas!$C$5:$M$2666,2,FALSE) -> BRE002 | G6: =VLOOKUP($C6,Carpetas!$C$5:$M$2666,10,FALSE) -> 1481758/1411756/1411757/1471759 | H6: =VLOOKUP($C6,Carpetas!$C$5:$M$2666,6,FALSE) -> Benini | I6: =VLOOKUP($C6,Carpetas!$C$5:$M$2666,4,FALSE) -> 0 | J6: =E6+5 -> 45301 | K6: =VLOOKUP($C6,Carpetas!$C$5:$M$2666,5,FALSE) -> Rio Branco | M6: =J6+1+2 -> 45304 | N6: =IF(E6<>"",M6-E6,"-") -> 8 | O6: 1054 | U6: 58 | V6: RHB3A77 | W6: BEN2E70 | Y6: =VLOOKUP(X6,Choferes!$B$2:$C$500,2,FALSE) -> #N/A
A7: 2 | B7: Descargado | C7: 010/ | D7: Paraguay GM | E7: 45300 | F7: =VLOOKUP($C7,Carpetas!$C$5:$M$2666,2,FALSE) -> PYB005 | G7: =VLOOKUP($C7,Carpetas!$C$5:$M$2666,10,FALSE) -> 148,17,39 | H7: =VLOOKUP($C7,Carpetas!$C$5:$M$2666,6,FALSE) -> 0 | J7: 45303 | K7: =VLOOKUP($C7,Carpetas!$C$5:$M$2666,5,FALSE) -> Salto | M7: =J7+1 -> 45304 | N7: =IF(E7<>"",M7-E7,"-") -> 4 | O7: 930 | P7: 972 | S7: PY GM 003 | V7: AAGJ923 | W7: AADL399 | Y7: =VLOOKUP(X7,Choferes!$B$2:$C$500,2,FALSE) -> #N/A | Z7: se descargo en riqueza natural 972 cajas de py2 el dia 13/1/2024
A8: 2 | B8: Descargado | C8: 1183/ | D8: Paraguay EC | E8: 45301 | F8: =VLOOKUP($C8,Carpetas!$C$5:$M$2666,2,FALSE) -> PYB007 | G8: =VLOOKUP($C8,Carpetas!$C$5:$M$2666,10,FALSE) -> 148.21.72 | H8: =VLOOKUP($C8,Carpetas!$C$5:$M$2666,6,FALSE) -> 0 | J8: 45303 | K8: =VLOOKUP($C8,Carpetas!$C$5:$M$2666,5,FALSE) -> Salto | M8: =J8+1 -> 45304 | N8: =IF(E8<>"",M8-E8,"-") -> 3 | O8: 930 | P8: 930 | S8: PYEC006 | V8: AAEH166 | W8: AADU451 | Y8: =VLOOKUP(X8,Choferes!$B$2:$C$500,2,FALSE) -> #N/A | Z8: MM 15/01 : DESCARGADO EN RIQUEZA NATURAL 930 CAJAS DE PARAGUAY EXTRA.
A9: 2 | B9: Descargado | C9: 1182/ | D9: Paraguay EC | E9: 45300 | F9: =VLOOKUP($C9,Carpetas!$C$5:$M$2666,2,FALSE) -> PYB006 | G9: =VLOOKUP($C9,Carpetas!$C$5:$M$2666,10,FALSE) -> 148.21.71 | H9: =VLOOKUP($C9,Carpetas!$C$5:$M$2666,6,FALSE) -> 0 | J9: =E9+5 -> 45305 | K9: =VLOOKUP($C9,Carpetas!$C$5:$M$2666,5,FALSE) -> Salto | M9: =J9+1 -> 45306 | N9: =IF(E9<>"",M9-E9,"-") -> 6 | O9: 930 | P9: 930 | S9: PY EC 004 | V9: BOT019 | Y9: =VLOOKUP(X9,Choferes!$B$2:$C$500,2,FALSE) -> #N/A | Z9: SE DESCARGO EN RIQUEZA NATURAL 930 CAJAS DE PY EL DIA 12/1/2024
A10: 2 | B10: Descargado | C10: 001/24 | D10: Jaime | E10: 45303 | F10: =VLOOKUP($C10,Carpetas!$C$5:$M$2666,2,FALSE) -> BRB001 | G10: =VLOOKUP($C10,Carpetas!$C$5:$M$2666,10,FALSE) -> 148,22,17 | H10: =VLOOKUP($C10,Carpetas!$C$5:$M$2666,6,FALSE) -> Zanini | J10: =E10+2 -> 45305 | K10: =VLOOKUP($C10,Carpetas!$C$5:$M$2666,5,FALSE) -> Rio Branco | M10: 45307 | N10: =IF(E10<>"",M10-E10,"-") -> 4 | O10: 918 | P10: 918 | S10: JM002 | U10: 4161 | V10: RYK 8E00 | W10: RYF 1D53 | X10: Carlos Pompermaier | Y10: =VLOOKUP(X10,Choferes!$B$2:$C$500,2,FALSE) -> +5547991777362 | Z10: MM 16/01 : DESCARGADO EN RIQUEZA NATURAL 918 CAJAS DE BRASIL FBRA.
A11: 1 | B11: Descargado | C11: AL001/2024 | D11: Nordeste | E11: 45296 | F11: =VLOOKUP($C11,Carpetas!$C$5:$M$2666,2,FALSE) -> BRA001 | G11: =VLOOKUP($C11,Carpetas!$C$5:$M$2666,10,FALSE) -> 147,76,57 | H11: =VLOOKUP($C11,Carpetas!$C$5:$M$2666,6,FALSE) -> Silvio | J11: =E11+10 -> 45306 | K11: =VLOOKUP($C11,Carpetas!$C$5:$M$2666,5,FALSE) -> Rio Branco | M11: =J11+1 -> 45307 | N11: =IF(E11<>"",M11-E11,"-") -> 11 | O11: 1104 | S11: 1103 | U11: 6669 | V11: RXT 0A05 | W11: RXT 0A04 | X11: Rogerio Fagundes | Y11: =VLOOKUP(X11,Choferes!$B$2:$C$500,2,FALSE) -> +5555996711696 | Z11: SE DESCARGO EN RIQUEZA NATURAL 1103 CAJAS DE PURA VIDA EL DIA 16/1/2024. VINO EL CAMION CON FRUTA SENTIDA Y ALGUNOS PALLETS SIN FLEJES
A12: 2 | B12: Descargado | C12: 1182/ | D12: Paraguay EC | E12: 45301 | F12: =VLOOKUP($C12,Carpetas!$C$5:$M$2666,2,FALSE) -> PYB006 | G12: =VLOOKUP($C12,Carpetas!$C$5:$M$2666,10,FALSE) -> 148.21.71 | H12: =VLOOKUP($C12,Carpetas!$C$5:$M$2666,6,FALSE) -> 0 | J12: =E12+5 -> 45306 | K12: =VLOOKUP($C12,Carpetas!$C$5:$M$2666,5,FALSE) -> Salto | M12: =J12+1 -> 45307 | N12: =IF(E12<>"",M12-E12,"-") -> 6 | O12: 930 | P12: 932 | S12: PYEC005 | V12: AAAK129 | W12: CDP119 | Y12: =VLOOKUP(X12,Choferes!$B$2:$C$500,2,FALSE) -> #N/A | Z12: MM 15/01 : DESCARGADO EN RIQUEZA NATURAL 932 CAJAS DE PARAGUAY EXTRA.
A13: 2 | B13: Descargado | C13: 1185/ | D13: Paraguay EC | E13: 45302 | F13: =VLOOKUP($C13,Carpetas!$C$5:$M$2666,2,FALSE) -> PYB008 | G13: =VLOOKUP($C13,Carpetas!$C$5:$M$2666,10,FALSE) -> 148.22.46 | H13: =VLOOKUP($C13,Carpetas!$C$5:$M$2666,6,FALSE) -> 0 | J13: =E13+5 -> 45307 | K13: =VLOOKUP($C13,Carpetas!$C$5:$M$2666,5,FALSE) -> Salto | M13: =J13+1 -> 45308 | N13: =IF(E13<>"",M13-E13,"-") -> 6 | O13: 930 | P13: 933 | S13: PYEC007 | V13: AAHG850 | W13: AAHG813 | Y13: =VLOOKUP(X13,Choferes!$B$2:$C$500,2,FALSE) -> #N/A | Z13: MM 16/01 : DESCARGADO EN RIQUEZA NATURAL 933 CAJAS DE PARAGUAY EXTRA.
A14: 3 | B14: Descargado | C14: 002/24 | D14: Claudia | E14: 45306 | F14: =VLOOKUP($C14,Carpetas!$C$5:$M$2666,2,FALSE) -> BRB002 | G14: =VLOOKUP($C14,Carpetas!$C$5:$M$2666,10,FALSE) -> 148,25,12 | H14: =VLOOKUP($C14,Carpetas!$C$5:$M$2666,6,FALSE) -> Zanini | J14: =E14+2 -> 45308 | K14: =VLOOKUP($C14,Carpetas!$C$5:$M$2666,5,FALSE) -> Rio Branco | M14: =J14+1 -> 45309 | N14: =IF(E14<>"",M14-E14,"-") -> 3 | O14: 900 | P14: 900 | S14: CH002 | U14: 4167 | V14: EOE 2457 | W14: MJY 7674 | Y14: =VLOOKUP(X14,Choferes!$B$2:$C$500,2,FALSE) -> #N/A | Z14: MM 19/01 : DESCARGADO EN RIQUEZA NATURAL 900 CAJAS DE BRASIL FIBRA EXTRA.
A15: 3 | B15: Descargado | C15: 001/24 | D15: Jaime | E15: 45306 | F15: =VLOOKUP($C15,Carpetas!$C$5:$M$2666,2,FALSE) -> BRB001 | G15: =VLOOKUP($C15,Carpetas!$C$5:$M$2666,10,FALSE) -> 148,22,17 | H15: =VLOOKUP($C15,Carpetas!$C$5:$M$2666,6,FALSE) -> Zanini | J15: =E15+2 -> 45308 | K15: =VLOOKUP($C15,Carpetas!$C$5:$M$2666,5,FALSE) -> Rio Branco | M15: =J15+1 -> 45309 | N15: =IF(E15<>"",M15-E15,"-") -> 3 | O15: 918 | P15: 919 | S15: JM003 | U15: 4168 | V15: MGK 9855 | W15: EOE 2359 | Y15: =VLOOKUP(X15,Choferes!$B$2:$C$500,2,FALSE) -> #N/A | Z15: MM 19/01 : DESCARGADO EN RIQUEZA NATURAL 919 CAJAS DE BRASIL FIBRA EXTRA.
A16: 3 | B16: Descargado | C16: 001/24 | D16: Junkes | E16: 45307 | F16: =VLOOKUP($C16,Carpetas!$C$5:$M$2666,2,FALSE) -> BRB001 | G16: =VLOOKUP($C16,Carpetas!$C$5:$M$2666,10,FALSE) -> 148,22,17 | H16: =VLOOKUP($C16,Carpetas!$C$5:$M$2666,6,FALSE) -> Zanini | J16: =E16+2 -> 45309 | K16: =VLOOKUP($C16,Carpetas!$C$5:$M$2666,5,FALSE) -> Rio Branco | M16: =J16+1 -> 45310 | N16: =IF(E16<>"",M16-E16,"-") -> 3 | O16: 918 | P16: 918 | S16: JS001 | U16: 4175 | V16: RYH 3A87 | W16: RYH 2A07 | Y16: =VLOOKUP(X16,Choferes!$B$2:$C$500,2,FALSE) -> #N/A | Z16: se descargo en riqueza natural 918 cajas de brasil fibra el dia 19/1/2024
A17: 3 | B17: Descargado | C17: 1182/ | D17: Paraguay EC | E17: 45306 | F17: =VLOOKUP($C17,Carpetas!$C$5:$M$2666,2,FALSE) -> PYB006 | G17: =VLOOKUP($C17,Carpetas!$C$5:$M$2666,10,FALSE) -> 148.21.71 | H17: =VLOOKUP($C17,Carpetas!$C$5:$M$2666,6,FALSE) -> 0 | J17: 45310 | K17: =VLOOKUP($C17,Carpetas!$C$5:$M$2666,5,FALSE) -> Salto | M17: =J17+1 -> 45311 | N17: =IF(E17<>"",M17-E17,"-") -> 5 | O17: 930 | P17: 932 | S17: PYEC008 | V17: AAAG911 | W17: HFD454 | Y17: =VLOOKUP(X17,Choferes!$B$2:$C$500,2,FALSE) -> #N/A | Z17: MM 20/01: DESCARGADO EN RIQUEZA NATURAL 932 CAJAS DE PARAGUAY EXTRA,
A18: 3 | B18: Descargado | C18: 1187/ | D18: Paraguay EC | E18: 45307 | F18: =VLOOKUP($C18,Carpetas!$C$5:$M$2666,2,FALSE) -> PYB012 | G18: =VLOOKUP($C18,Carpetas!$C$5:$M$2666,10,FALSE) -> 148.26.79 | H18: =VLOOKUP($C18,Carpetas!$C$5:$M$2666,6,FALSE) -> 0 | J18: 45310 | K18: =VLOOKUP($C18,Carpetas!$C$5:$M$2666,5,FALSE) -> Salto | M18: =J18+1 -> 45311 | N18: =IF(E18<>"",M18-E18,"-") -> 4 | O18: 930 | P18: 930 | S18: PYEC009 | V18: AAIS133 | W18: AYZ125 | Y18: =VLOOKUP(X18,Choferes!$B$2:$C$500,2,FALSE) -> #N/A | Z18: MM 22/01 : DESCARGADO EN RIQUEZA NATURAL 930 CAJAS DE PARAGUAY EXTRA.
A19: 3 | B19: Descargado | C19: 307/ | D19: Paraguay MS | E19: 45307 | F19: =VLOOKUP($C19,Carpetas!$C$5:$M$2666,2,FALSE) -> PYB009 | G19: =VLOOKUP($C19,Carpetas!$C$5:$M$2666,10,FALSE) -> 148.22.30 | H19: =VLOOKUP($C19,Carpetas!$C$5:$M$2666,6,FALSE) -> 0 | J19: 45310 | K19: =VLOOKUP($C19,Carpetas!$C$5:$M$2666,5,FALSE) -> Salto | M19: =J19+1 -> 45311 | N19: =IF(E19<>"",M19-E19,"-") -> 4 | O19: 980 | V19: AACG469 | Y19: =VLOOKUP(X19,Choferes!$B$2:$C$500,2,FALSE) -> #N/A | Z19: 20/01: DESCARGADO EN RIQUEZA NATURAL 980 CAJAS DE PARAGUAY EXTRA.
A20: 3 | B20: Descargado | C20: 002/24 | D20: Claudia | E20: 45308 | F20: =VLOOKUP($C20,Carpetas!$C$5:$M$2666,2,FALSE) -> BRB002 | G20: =VLOOKUP($C20,Carpetas!$C$5:$M$2666,10,FALSE) -> 148,25,12 | H20: =VLOOKUP($C20,Carpetas!$C$5:$M$2666,6,FALSE) -> Zanini | J20: =E20+2 -> 45310 | K20: =VLOOKUP($C20,Carpetas!$C$5:$M$2666,5,FALSE) -> Rio Branco | M20: =J20+1 -> 45311 | N20: =IF(E20<>"",M20-E20,"-") -> 3 | O20: 900 | P20: 900 | S20: CH003 | U20: 4181 | V20: RKX 1F29 | W20: REA 1H91 | X20: Diego Lopes | Y20: =VLOOKUP(X20,Choferes!$B$2:$C$500,2,FALSE) -> +5542991092026 | Z20: MM 20/01 : DESCARGADO EN RIQUEZA NATURAL 900 CAJAS DE BRASIL FIBRA EXTRA.
A21: 3 | B21: Descargado | C21: 001/24 | D21: Corupá | E21: 45308 | F21: =VLOOKUP($C21,Carpetas!$C$5:$M$2666,2,FALSE) -> BRB001 | G21: =VLOOKUP($C21,Carpetas!$C$5:$M$2666,10,FALSE) -> 148,22,17 | H21: =VLOOKUP($C21,Carpetas!$C$5:$M$2666,6,FALSE) -> Zanini | J21: =E21+2 -> 45310 | K21: =VLOOKUP($C21,Carpetas!$C$5:$M$2666,5,FALSE) -> Rio Branco | M21: =J21+1 -> 45311 | N21: =IF(E21<>"",M21-E21,"-") -> 3 | O21: 918 | P21: 919 | S21: CP002 | U21: 4180 | V21: EOE 2456 | W21: EOE 2444 | X21: Edenilson S. de Almeida | Y21: =VLOOKUP(X21,Choferes!$B$2:$C$500,2,FALSE) -> +5542998101794 | Z21: MM 20/01 : DESCARGADO EN RIQUEZA NATURAL 919 CAJAS DE BRASIL COMUN.
A22: 3 | B22: Descargado | C22: 307/ | D22: Paraguay MS | E22: 45308 | F22: =VLOOKUP($C22,Carpetas!$C$5:$M$2666,2,FALSE) -> PYB009 | G22: =VLOOKUP($C22,Carpetas!$C$5:$M$2666,10,FALSE) -> 148.22.30 | H22: =VLOOKUP($C22,Carpetas!$C$5:$M$2666,6,FALSE) -> 0 | J22: 45310 | K22: =VLOOKUP($C22,Carpetas!$C$5:$M$2666,5,FALSE) -> Salto | M22: =J22+1 -> 45311 | N22: =IF(E22<>"",M22-E22,"-") -> 3 | O22: 980 | P22: 980 | S22: PYMS004 | V22: AAGO344 | W22: AAGX855 | Y22: =VLOOKUP(X22,Choferes!$B$2:$C$500,2,FALSE) -> #N/A | Z22: MM 20/01: DESCARGADO EN RIQUEZA NATURAL 980 CAJAS DE PARAGUAY EXTRA,
A23: 3 | B23: Descargado | C23: 097/ | D23: Paraguay DF | E23: 45308 | F23: =VLOOKUP($C23,Carpetas!$C$5:$M$2666,2,FALSE) -> PYB010 | G23: =VLOOKUP($C23,Carpetas!$C$5:$M$2666,10,FALSE) -> 148.22.93 | H23: =VLOOKUP($C23,Carpetas!$C$5:$M$2666,6,FALSE) -> 0 | J23: 45310 | K23: =VLOOKUP($C23,Carpetas!$C$5:$M$2666,5,FALSE) -> Salto | M23: =J23+1 -> 45311 | N23: =IF(E23<>"",M23-E23,"-") -> 3 | O23: 980 | P23: 982 | S23: PYDF001 | V23: KAZ602 | W23: HBA800 | Y23: =VLOOKUP(X23,Choferes!$B$2:$C$500,2,FALSE) -> #N/A | Z23: MM 20/01 : DESCARGADO EN RIQUEZA NATURAL 982 CAJAS DE PARAGUAY SEGUNDA.
A24: 3 | B24: Descargado | C24: 011/ | D24: Paraguay GM | E24: 45306 | F24: =VLOOKUP($C24,Carpetas!$C$5:$M$2666,2,FALSE) -> PYB011 | G24: =VLOOKUP($C24,Carpetas!$C$5:$M$2666,10,FALSE) -> 148,22,92 | H24: =VLOOKUP($C24,Carpetas!$C$5:$M$2666,6,FALSE) -> 0 | J24: 45310 | K24: =VLOOKUP($C24,Carpetas!$C$5:$M$2666,5,FALSE) -> Salto | M24: =J24+1+3 -> 45314 | N24: =IF(E24<>"",M24-E24,"-") -> 8 | O24: 972 | P24: 972 | S24: PYGM004 | V24: NBR357 | W24: NBR474 | Y24: =VLOOKUP(X24,Choferes!$B$2:$C$500,2,FALSE) -> #N/A | Z24: AL 23/01 : SE DESCARGARON EN RIQUEZA NATURAL 972 CAJAS DE PARAGUAY 2ª.
A25: 2 | B25: Descargado | C25: AL002/2024 | D25: Nordeste | E25: 45304 | F25: =VLOOKUP($C25,Carpetas!$C$5:$M$2666,2,FALSE) -> BRA002 | G25: =VLOOKUP($C25,Carpetas!$C$5:$M$2666,10,FALSE) -> 0 | H25: =VLOOKUP($C25,Carpetas!$C$5:$M$2666,6,FALSE) -> Silvio | J25: 45313 | K25: =VLOOKUP($C25,Carpetas!$C$5:$M$2666,5,FALSE) -> Rio Branco | M25: =J25+1 -> 45314 | N25: =IF(E25<>"",M25-E25,"-") -> 10 | O25: 1104 | P25: 1104 | S25: 61447 | U25: 6682 | V25: RYK 0G12 | W25: FCE 5549 | X25: Emerson Lappe | Y25: =VLOOKUP(X25,Choferes!$B$2:$C$500,2,FALSE) -> +5549999774835 | Z25: MM 25/01 : DESCARGADO EN RIQUEZA NATURAL 1104 CAJAS DE BRASIL CARTON.
A26: 3 | B26: Descargado | C26: 1188/ | D26: Paraguay EC | E26: 45308 | F26: =VLOOKUP($C26,Carpetas!$C$5:$M$2666,2,FALSE) -> PYB013 | G26: =VLOOKUP($C26,Carpetas!$C$5:$M$2666,10,FALSE) -> 148.26.81 | H26: =VLOOKUP($C26,Carpetas!$C$5:$M$2666,6,FALSE) -> 0 | J26: =E26+5 -> 45313 | K26: =VLOOKUP($C26,Carpetas!$C$5:$M$2666,5,FALSE) -> Salto | M26: =J26+1 -> 45314 | N26: =IF(E26<>"",M26-E26,"-") -> 6 | O26: 930 | P26: 933 | S26: PYEC010 | V26: AAAA288 | W26: AAAA294 | Y26: =VLOOKUP(X26,Choferes!$B$2:$C$500,2,FALSE) -> #N/A | Z26: AL 23/01 : SE DESCARGARON EN RIQUEZA NATURAL 933 CAJAS DE PARAGUAY EXTRA.
A27: 3 | B27: Descargado | C27: 001/24 | D27: Jaime | E27: 45310 | F27: =VLOOKUP($C27,Carpetas!$C$5:$M$2666,2,FALSE) -> BRB001 | G27: =VLOOKUP($C27,Carpetas!$C$5:$M$2666,10,FALSE) -> 148,22,17 | H27: =VLOOKUP($C27,Carpetas!$C$5:$M$2666,6,FALSE) -> Zanini | J27: 45313 | K27: =VLOOKUP($C27,Carpetas!$C$5:$M$2666,5,FALSE) -> Rio Branco | M27: =J27+1+1 -> 45315 | N27: =IF(E27<>"",M27-E27,"-") -> 5 | O27: 918 | P27: 919 | S27: JM004 | U27: 4187 | V27: QIW 6450 | W27: QHT 8275 | Y27: =VLOOKUP(X27,Choferes!$B$2:$C$500,2,FALSE) -> #N/A | Z27: AL 24/01 : DESCARGADO EN RIQUEZA NATURAL 919 CAJAS DE BRASIL FIBRA.
A28: 4 | B28: Descargado | C28: 003/24 | D28: Jaime | E28: 45313 | F28: =VLOOKUP($C28,Carpetas!$C$5:$M$2666,2,FALSE) -> BRB003 | G28: =VLOOKUP($C28,Carpetas!$C$5:$M$2666,10,FALSE) -> 148,30,62 | H28: =VLOOKUP($C28,Carpetas!$C$5:$M$2666,6,FALSE) -> Zanini | J28: =E28+2 -> 45315 | K28: =VLOOKUP($C28,Carpetas!$C$5:$M$2666,5,FALSE) -> Rio Branco | M28: =J28+1 -> 45316 | N28: =IF(E28<>"",M28-E28,"-") -> 3 | O28: 918 | P28: 919 | S28: JM005 | U28: 4192 | V28: FEJ 8C47 | W28: EOE 2445 | Y28: =VLOOKUP(X28,Choferes!$B$2:$C$500,2,FALSE) -> #N/A | Z28: MM 27/01 : DESCARGADO EN RIQUEZA NATURAL 919 CAJAS DE BRASIL FIBRA.
A29: 4 | B29: Descargado | C29: 002/24 | D29: Claudia | E29: 45313 | F29: =VLOOKUP($C29,Carpetas!$C$5:$M$2666,2,FALSE) -> BRB002 | G29: =VLOOKUP($C29,Carpetas!$C$5:$M$2666,10,FALSE) -> 148,25,12 | H29: =VLOOKUP($C29,Carpetas!$C$5:$M$2666,6,FALSE) -> Zanini | J29: =E29+2 -> 45315 | K29: =VLOOKUP($C29,Carpetas!$C$5:$M$2666,5,FALSE) -> Rio Branco | M29: =J29+1 -> 45316 | N29: =IF(E29<>"",M29-E29,"-") -> 3 | O29: 900 | P29: 901 | S29: CH005 | U29: 4191 | V29: RDY 1B34 | W29: RDS 5I03 | Y29: =VLOOKUP(X29,Choferes!$B$2:$C$500,2,FALSE) -> #N/A | Z29: AL 27/01: DESCARGADO EN ROQUEZA NATURAL 901CAJAS DE BRASIL FIBRA EXTRA..
A30: 4 | B30: Descargado | C30: 012/ | D30: Paraguay GM | E30: 45313 | F30: =VLOOKUP($C30,Carpetas!$C$5:$M$2666,2,FALSE) -> PYB016 | G30: =VLOOKUP($C30,Carpetas!$C$5:$M$2666,10,FALSE) -> 148,29,76 | H30: =VLOOKUP($C30,Carpetas!$C$5:$M$2666,6,FALSE) -> 0 | J30: 45315 | K30: =VLOOKUP($C30,Carpetas!$C$5:$M$2666,5,FALSE) -> Salto | M30: =J30+1 -> 45316 | N30: =IF(E30<>"",M30-E30,"-") -> 3 | O30: 980 | P30: 974 | S30: PYGM005 | V30: BHH113 | W30: OBA516 | Y30: =VLOOKUP(X30,Choferes!$B$2:$C$500,2,FALSE) -> #N/A | Z30: MM 25/01 : DESCARGADO EN RIQUEZA NATURAL 974 CAJAS DE PARAGUAY COMUN.
A31: 4 | B31: Descargado | C31: 311/ | D31: Paraguay MS | E31: 45313 | F31: =VLOOKUP($C31,Carpetas!$C$5:$M$2666,2,FALSE) -> PYB018 | G31: =VLOOKUP($C31,Carpetas!$C$5:$M$2666,10,FALSE) -> 148,29,76 | H31: =VLOOKUP($C31,Carpetas!$C$5:$M$2666,6,FALSE) -> 0 | J31: 45315 | K31: =VLOOKUP($C31,Carpetas!$C$5:$M$2666,5,FALSE) -> Salto | M31: =J31+1 -> 45316 | N31: =IF(E31<>"",M31-E31,"-") -> 3 | O31: 980 | P31: 980 | S31: PYMS005 | V31: AAIS110 | W31: OCG216 | Y31: =VLOOKUP(X31,Choferes!$B$2:$C$500,2,FALSE) -> #N/A | Z31: AL 27/01: DESCARGADO EN ROQUEZA NATURAL 980 CAJAS DE PY PEPE
A32: 4 | B32: Descargado | C32: 1190/ | D32: Paraguay EC | E32: 45313 | F32: =VLOOKUP($C32,Carpetas!$C$5:$M$2666,2,FALSE) -> PYB017 | G32: =VLOOKUP($C32,Carpetas!$C$5:$M$2666,10,FALSE) -> 148,29,76 | H32: =VLOOKUP($C32,Carpetas!$C$5:$M$2666,6,FALSE) -> 0 | J32: 45316 | K32: =VLOOKUP($C32,Carpetas!$C$5:$M$2666,5,FALSE) -> Salto | M32: =J32+1 -> 45317 | N32: =IF(E32<>"",M32-E32,"-") -> 4 | O32: 930 | P32: 933 | S32: PYEC011 | V32: ZAE495 | W32: BZR991 | Y32: =VLOOKUP(X32,Choferes!$B$2:$C$500,2,FALSE) -> #N/A | Z32: SE DESCARGO EN RIQUEZA 933 CAJAS DE PY EXTRA EL DIA 27/1/2024
A33: 4 | B33: Descargado | C33: 012/ | D33: Paraguay GM | E33: 45313 | F33: =VLOOKUP($C33,Carpetas!$C$5:$M$2666,2,FALSE) -> PYB016 | G33: =VLOOKUP($C33,Carpetas!$C$5:$M$2666,10,FALSE) -> 148,29,76 | H33: =VLOOKUP($C33,Carpetas!$C$5:$M$2666,6,FALSE) -> 0 | J33: 45316 | K33: =VLOOKUP($C33,Carpetas!$C$5:$M$2666,5,FALSE) -> Salto | M33: =J33+1 -> 45317 | N33: =IF(E33<>"",M33-E33,"-") -> 4 | O33: 980 | P33: 972 | S33: PYGM006 | V33: BFK 528 | W33: BEF 740 | Y33: =VLOOKUP(X33,Choferes!$B$2:$C$500,2,FALSE) -> #N/A | Z33: MM 27/01 : DESCARGADO EN RIQUEZA NATURAL 972 CAJAS DE PARAGUAY,
A34: 4 | B34: Descargado | C34: 004/24 | D34: Junkes | E34: 45314 | F34: =VLOOKUP($C34,Carpetas!$C$5:$M$2666,2,FALSE) -> BRB004 | G34: =VLOOKUP($C34,Carpetas!$C$5:$M$2666,10,FALSE) -> 148,30,63 | H34: =VLOOKUP($C34,Carpetas!$C$5:$M$2666,6,FALSE) -> Silvio | J34: =E34+2 -> 45316 | K34: =VLOOKUP($C34,Carpetas!$C$5:$M$2666,5,FALSE) -> Rio Branco | M34: =J34+1 -> 45317 | N34: =IF(E34<>"",M34-E34,"-") -> 3 | O34: 918 | P34: 918 | S34: JS002 | U34: 6702 | V34: MEA 9B24 | W34: INX 0372 | Y34: =VLOOKUP(X34,Choferes!$B$2:$C$500,2,FALSE) -> #N/A | Z34: MM 27/01 : DESCARGADO EN RIQUEZA NATURAL 918 CAJAS DE BRASIL FIBRA.
A35: 4 | B35: Descargado | C35: 1190/ | D35: Paraguay EC | E35: 45314 | F35: =VLOOKUP($C35,Carpetas!$C$5:$M$2666,2,FALSE) -> PYB017 | G35: =VLOOKUP($C35,Carpetas!$C$5:$M$2666,10,FALSE) -> 148,29,76 | H35: =VLOOKUP($C35,Carpetas!$C$5:$M$2666,6,FALSE) -> 0 | J35: 45316 | K35: =VLOOKUP($C35,Carpetas!$C$5:$M$2666,5,FALSE) -> Salto | M35: =J35+1 -> 45317 | N35: =IF(E35<>"",M35-E35,"-") -> 3 | O35: 930 | P35: 930 | S35: PYEC012 | V35: MBP313 | W35: OBF281 | Y35: =VLOOKUP(X35,Choferes!$B$2:$C$500,2,FALSE) -> #N/A | Z35: AL 27/01: DESCARGADO EN ROQUEZA NATURAL 930 CAJAS DE PY PEPE EXTRA.
A36: 4 | B36: Descargado | C36: 2280/ | D36: Paraguay HF | E36: 45312 | F36: =VLOOKUP($C36,Carpetas!$C$5:$M$2666,2,FALSE) -> PYB014 | G36: =VLOOKUP($C36,Carpetas!$C$5:$M$2666,10,FALSE) -> 148.27.09 | H36: =VLOOKUP($C36,Carpetas!$C$5:$M$2666,6,FALSE) -> 0 | J36: =E36+5 -> 45317 | K36: =VLOOKUP($C36,Carpetas!$C$5:$M$2666,5,FALSE) -> Salto | M36: =J36+1 -> 45318 | N36: =IF(E36<>"",M36-E36,"-") -> 6 | O36: 980 | P36: 980 | S36: PYHF001 | V36: KAO 996 | W36: ZAR 552 | Y36: =VLOOKUP(X36,Choferes!$B$2:$C$500,2,FALSE) -> #N/A | Z36: MM 27/01 : DESCARGADO EN RIQUEZA NATURAL 980 CAJAS DE PARAGUAY,
A37: 4 | B37: Descargado | C37: 002/24 | D37: Claudia | E37: 45316 | F37: =VLOOKUP($C37,Carpetas!$C$5:$M$2666,2,FALSE) -> BRB002 | G37: =VLOOKUP($C37,Carpetas!$C$5:$M$2666,10,FALSE) -> 148,25,12 | H37: =VLOOKUP($C37,Carpetas!$C$5:$M$2666,6,FALSE) -> Zanini | J37: =E37+2 -> 45318 | K37: =VLOOKUP($C37,Carpetas!$C$5:$M$2666,5,FALSE) -> Rio Branco | M37: =J37+1 -> 45319 | N37: =IF(E37<>"",M37-E37,"-") -> 3 | O37: 900 | P37: 901 | S37: CH004 | U37: 4200 | V37: RLL 2A97 | W37: QHK 7710 | Y37: =VLOOKUP(X37,Choferes!$B$2:$C$500,2,FALSE) -> #N/A | Z37: MM 27/01 : DESCARGADO EN RIQUEZA NATURAL 901 CAJAS DE BRASIL FIBRA EXTRA.
A38: 4 | B38: Descargado | C38: 312/ | D38: Paraguay MS | E38: 45315 | F38: =VLOOKUP($C38,Carpetas!$C$5:$M$2666,2,FALSE) -> PYB019 | G38: =VLOOKUP($C38,Carpetas!$C$5:$M$2666,10,FALSE) -> 148,29,76 | H38: =VLOOKUP($C38,Carpetas!$C$5:$M$2666,6,FALSE) -> 0 | J38: 45318 | K38: =VLOOKUP($C38,Carpetas!$C$5:$M$2666,5,FALSE) -> Salto | M38: 45320 | N38: =IF(E38<>"",M38-E38,"-") -> 5 | O38: 980 | P38: 980 | S38: PYMS006 | V38: AAJE676 | W38: AAJE638 | Y38: =VLOOKUP(X38,Choferes!$B$2:$C$500,2,FALSE) -> #N/A | Z38: SE DESCARGO EN RIQUEZA NATURAL 980 CAJAS DE PY EL DIA 29/1/2024
A39: 4 | B39: Descargado | C39: 101// | D39: Paraguay DF | E39: 45314 | F39: =VLOOKUP($C39,Carpetas!$C$5:$M$2666,2,FALSE) -> PYB015 | G39: =VLOOKUP($C39,Carpetas!$C$5:$M$2666,10,FALSE) -> 148,29,77 | H39: =VLOOKUP($C39,Carpetas!$C$5:$M$2666,6,FALSE) -> 0 | J39: =E39+5 -> 45319 | K39: =VLOOKUP($C39,Carpetas!$C$5:$M$2666,5,FALSE) -> Salto | M39: =J39+1 -> 45320 | N39: =IF(E39<>"",M39-E39,"-") -> 6 | O39: 980 | P39: 980 | S39: DF001 | V39: AAFL 470 | W39: BCC 343 | Y39: =VLOOKUP(X39,Choferes!$B$2:$C$500,2,FALSE) -> #N/A | Z39: MM 27/01 : DESCARGADO EN RIQUEZA NATURAL 980 CAJAS DE PARAGUAY,
A40: 3 | B40: Descargado | C40: AL003/2024 | D40: Nordeste | E40: 45310 | F40: =VLOOKUP($C40,Carpetas!$C$5:$M$2666,2,FALSE) -> BRA003 | G40: =VLOOKUP($C40,Carpetas!$C$5:$M$2666,10,FALSE) -> 0 | H40: =VLOOKUP($C40,Carpetas!$C$5:$M$2666,6,FALSE) -> Silvio | J40: 45317 | K40: =VLOOKUP($C40,Carpetas!$C$5:$M$2666,5,FALSE) -> Rio Branco | M40: 45321 | N40: =IF(E40<>"",M40-E40,"-") -> 11 | O40: 1104 | P40: 1104 | S40: 61014 | U40: 6693 | V40: RXP 2F83 | W40: MAQ 7E23 | Y40: =VLOOKUP(X40,Choferes!$B$2:$C$500,2,FALSE) -> #N/A | Z40: MM 30/01 : DESCARGADO EN RIQUEZA NATURAL 1104 CAJAS DE BRASIL CARTON.
A41: 4 | B41: Descargado | C41: 004/24 | D41: Junkes | E41: 45317 | F41: =VLOOKUP($C41,Carpetas!$C$5:$M$2666,2,FALSE) -> BRB004 | G41: =VLOOKUP($C41,Carpetas!$C$5:$M$2666,10,FALSE) -> 148,30,63 | H41: =VLOOKUP($C41,Carpetas!$C$5:$M$2666,6,FALSE) -> Silvio | J41: 45320 | K41: =VLOOKUP($C41,Carpetas!$C$5:$M$2666,5,FALSE) -> Rio Branco | M41: =J41+1 -> 45321 | N41: =IF(E41<>"",M41-E41,"-") -> 4 | O41: 918 | P41: 919 | S41: RXT0A05 | U41: 6712 | V41: RXT 0A05 | W41: RXT 0A04 | X41: Rogerio Fagundes | Y41: =VLOOKUP(X41,Choferes!$B$2:$C$500,2,FALSE) -> +5555996711696 | Z41: AL 01/02: DESCARGADO EN RIQUEZANATURAL 919 CAJAS DE BRASIL MADERA FIBRA.
A42: 4 | B42: Descargado | C42: 003/24 | D42: Jaime | E42: 45317 | F42: =VLOOKUP($C42,Carpetas!$C$5:$M$2666,2,FALSE) -> BRB003 | G42: =VLOOKUP($C42,Carpetas!$C$5:$M$2666,10,FALSE) -> 148,30,62 | H42: =VLOOKUP($C42,Carpetas!$C$5:$M$2666,6,FALSE) -> Zanini | J42: 45320 | K42: =VLOOKUP($C42,Carpetas!$C$5:$M$2666,5,FALSE) -> Rio Branco | M42: 45323 | N42: =IF(E42<>"",M42-E42,"-") -> 6 | O42: 918 | P42: 919 | S42: JM006 | U42: 4204 | V42: QJQ 3610 | W42: RLJ 4F32 | X42: Luiz Paulo R. da Silva | Y42: =VLOOKUP(X42,Choferes!$B$2:$C$500,2,FALSE) -> +5555999813455 | Z42: se descargo en riqueza natural 919 cajas de brasil fibra el dia 1/2/2024
A43: 5 | B43: Descargado | C43: 103// | D43: Paraguay DF | E43: 45320 | F43: =VLOOKUP($C43,Carpetas!$C$5:$M$2666,2,FALSE) -> PYB021 | G43: =VLOOKUP($C43,Carpetas!$C$5:$M$2666,10,FALSE) -> 148.32.37 | H43: =VLOOKUP($C43,Carpetas!$C$5:$M$2666,6,FALSE) -> 0 | J43: 45323 | K43: =VLOOKUP($C43,Carpetas!$C$5:$M$2666,5,FALSE) -> Salto | M43: =J43+1 -> 45324 | N43: =IF(E43<>"",M43-E43,"-") -> 4 | O43: 980 | S43: PYDF003 | V43: AAGJ760 | W43: AAGJ649 | Y43: =VLOOKUP(X43,Choferes!$B$2:$C$500,2,FALSE) -> #N/A | Z43: AL 02/02: DE DESCARGARON EN RIQUEZA NATURAL 981 CAJAS DE PARAGUAY MADERA PEPE.
A44: 5 | B44: Descargado | C44: 103// | D44: Paraguay DF | E44: 45320 | F44: =VLOOKUP($C44,Carpetas!$C$5:$M$2666,2,FALSE) -> PYB021 | G44: =VLOOKUP($C44,Carpetas!$C$5:$M$2666,10,FALSE) -> 148.32.37 | H44: =VLOOKUP($C44,Carpetas!$C$5:$M$2666,6,FALSE) -> 0 | J44: 45323 | K44: =VLOOKUP($C44,Carpetas!$C$5:$M$2666,5,FALSE) -> Salto | M44: =J44+1 -> 45324 | N44: =IF(E44<>"",M44-E44,"-") -> 4 | O44: 980 | P44: 980 | S44: PYDF002 | U44: 252 | V44: AAIF811 | W44: AAIF819 | Y44: =VLOOKUP(X44,Choferes!$B$2:$C$500,2,FALSE) -> #N/A | Z44: AL 02/02: DE DESCARGARON EN RIQUEZA NATURAL 980 CAJAS DE PARAGUAY MADERA PEPE.
A45: 5 | B45: Descargado | C45: 004/24 | D45: Jaime | E45: 45321 | F45: =VLOOKUP($C45,Carpetas!$C$5:$M$2666,2,FALSE) -> BRB004 | G45: =VLOOKUP($C45,Carpetas!$C$5:$M$2666,10,FALSE) -> 148,30,63 | H45: =VLOOKUP($C45,Carpetas!$C$5:$M$2666,6,FALSE) -> Silvio | J45: =E45+2 -> 45323 | K45: =VLOOKUP($C45,Carpetas!$C$5:$M$2666,5,FALSE) -> Rio Branco | M45: =J45+1 -> 45324 | N45: =IF(E45<>"",M45-E45,"-") -> 3 | O45: 918 | P45: 919 | S45: JM007 | U45: 6703 | V45: GAT 3F49 | W45: MGG 2B72 | Y45: =VLOOKUP(X45,Choferes!$B$2:$C$500,2,FALSE) -> #N/A | Z45: AL 02/02 : SE DESCARGARON EN RIQUEZA NATURAL 919 CAJA DE BANANA BR FIBRA.
A46: 5 | B46: Descargado | C46: 1191/ | D46: Paraguay EC | E46: 45321 | F46: =VLOOKUP($C46,Carpetas!$C$5:$M$2666,2,FALSE) -> PYB022 | G46: =VLOOKUP($C46,Carpetas!$C$5:$M$2666,10,FALSE) -> 148.35.32 | H46: =VLOOKUP($C46,Carpetas!$C$5:$M$2666,6,FALSE) -> 0 | J46: 45323 | K46: =VLOOKUP($C46,Carpetas!$C$5:$M$2666,5,FALSE) -> Salto | M46: =J46+1 -> 45324 | N46: =IF(E46<>"",M46-E46,"-") -> 3 | O46: 930 | P46: 930 | V46: AADH998 | W46: AADH872 | Y46: =VLOOKUP(X46,Choferes!$B$2:$C$500,2,FALSE) -> #N/A | Z46: AL 02/02 : SE DESCARGARON EN RIQUEZA NATURAL 930 CAJAS DE PY PEPE EXTRA.
A47: 5 | B47: Descargado | C47: 007/24 | D47: Claudia | E47: 45322 | F47: =VLOOKUP($C47,Carpetas!$C$5:$M$2666,2,FALSE) -> BRB005 | G47: =VLOOKUP($C47,Carpetas!$C$5:$M$2666,10,FALSE) -> 148.35.36 | H47: =VLOOKUP($C47,Carpetas!$C$5:$M$2666,6,FALSE) -> Zanini | J47: 45323 | K47: =VLOOKUP($C47,Carpetas!$C$5:$M$2666,5,FALSE) -> Rio Branco | M47: =J47+1 -> 45324 | N47: =IF(E47<>"",M47-E47,"-") -> 2 | O47: 900 | P47: 901 | S47: CH006 | U47: 4212 | V47: RYH 3A87 | W47: RYH 2A07 | X47: Nasser Machado | Y47: =VLOOKUP(X47,Choferes!$B$2:$C$500,2,FALSE) -> +5555996886269 | Z47: SE DESCARGO EN RIQUEZA NATURAL 901 CAJAS DE BR FIBRA.
A48: 5 | B48: Descargado | C48: 013/ | D48: Paraguay GM | E48: 45320 | F48: =VLOOKUP($C48,Carpetas!$C$5:$M$2666,2,FALSE) -> PYB020 | G48: =VLOOKUP($C48,Carpetas!$C$5:$M$2666,10,FALSE) -> 148,32,71 | H48: =VLOOKUP($C48,Carpetas!$C$5:$M$2666,6,FALSE) -> 0 | J48: =E48+4 -> 45324 | K48: =VLOOKUP($C48,Carpetas!$C$5:$M$2666,5,FALSE) -> Salto | M48: =J48+1 -> 45325 | N48: =IF(E48<>"",M48-E48,"-") -> 5 | O48: 972 | P48: 972 | S48: PYMG007 | V48: AAG0344 | Y48: =VLOOKUP(X48,Choferes!$B$2:$C$500,2,FALSE) -> #N/A | Z48: SE DESCARGO EN RIQUEZA NATURAL 972 CAJAS DE PY COMUN EL DIA 2/2/2024
A49: 5 | B49: Descargado | C49: 315/ | D49: Paraguay MS | E49: 45321 | F49: =VLOOKUP($C49,Carpetas!$C$5:$M$2666,2,FALSE) -> PYB023 | G49: =VLOOKUP($C49,Carpetas!$C$5:$M$2666,10,FALSE) -> 148,35,31 | H49: =VLOOKUP($C49,Carpetas!$C$5:$M$2666,6,FALSE) -> 0 | J49: 45324 | K49: =VLOOKUP($C49,Carpetas!$C$5:$M$2666,5,FALSE) -> Salto | M49: =J49+1 -> 45325 | N49: =IF(E49<>"",M49-E49,"-") -> 4 | O49: 980 | P49: 980 | S49: PYMS007 | V49: BZF483 | Y49: =VLOOKUP(X49,Choferes!$B$2:$C$500,2,FALSE) -> #N/A | Z49: SE DESCARGO EN RIQUEZA NATURAL 980 CAJAS DE PY EL DIA 3/2/2024
A50: 5 | B50: Descargado | C50: 013/ | D50: Paraguay GM | E50: 45321 | F50: =VLOOKUP($C50,Carpetas!$C$5:$M$2666,2,FALSE) -> PYB020 | G50: =VLOOKUP($C50,Carpetas!$C$5:$M$2666,10,FALSE) -> 148,32,71 | H50: =VLOOKUP($C50,Carpetas!$C$5:$M$2666,6,FALSE) -> 0 | J50: 45324 | K50: =VLOOKUP($C50,Carpetas!$C$5:$M$2666,5,FALSE) -> Salto | M50: =J50+1 -> 45325 | N50: =IF(E50<>"",M50-E50,"-") -> 4 | O50: 972 | P50: 976 | S50: PYGM008 | V50: UAJ870 | W50: NBR286 | Y50: =VLOOKUP(X50,Choferes!$B$2:$C$500,2,FALSE) -> #N/A | Z50: AL 03/02 : SE RECIBIERON EN RIQUEZA NATURAL 976 CAJAS DE BANANA PARAGUAY COMÚN (CAJA NEGRA).
A51: 5 | B51: Descargado | C51: 1191/ | D51: Paraguay EC | E51: 45322 | F51: =VLOOKUP($C51,Carpetas!$C$5:$M$2666,2,FALSE) -> PYB022 | G51: =VLOOKUP($C51,Carpetas!$C$5:$M$2666,10,FALSE) -> 148.35.32 | H51: =VLOOKUP($C51,Carpetas!$C$5:$M$2666,6,FALSE) -> 0 | J51: 45324 | K51: =VLOOKUP($C51,Carpetas!$C$5:$M$2666,5,FALSE) -> Salto | M51: =J51+1 -> 45325 | N51: =IF(E51<>"",M51-E51,"-") -> 3 | O51: 900 | P51: 934 | S51: PYEC014 | V51: AAAK129 | Y51: =VLOOKUP(X51,Choferes!$B$2:$C$500,2,FALSE) -> #N/A | Z51: SE DESCARGO EN RIQUEZA NATURAL 934 CAJAS PEPE EXTRA 04/02
A52: 3 | B52: Descargado | C52: 001/24ALM | D52: Varios | E52: 45316 | F52: =VLOOKUP($C52,Carpetas!$C$5:$M$2666,2,FALSE) -> BRE003 | G52: =VLOOKUP($C52,Carpetas!$C$5:$M$2666,10,FALSE) -> 0 | H52: =VLOOKUP($C52,Carpetas!$C$5:$M$2666,6,FALSE) -> Silvio | I52: =VLOOKUP($C52,Carpetas!$C$5:$M$2666,4,FALSE) -> 0 | J52: =E52+10 -> 45326 | K52: =VLOOKUP($C52,Carpetas!$C$5:$M$2666,5,FALSE) -> Rio Branco | M52: =J52+1+1 -> 45328 | N52: =IF(E52<>"",M52-E52,"-") -> 12 | O52: 1610 | U52: 6708 | V52: EGK 4H56 | W52: MHP 0D82 | Y52: =VLOOKUP(X52,Choferes!$B$2:$C$500,2,FALSE) -> #N/A
A53: 5 | B53: Descargado | C53: 008/24 | D53: Gilson | E53: 45323 | F53: =VLOOKUP($C53,Carpetas!$C$5:$M$2666,2,FALSE) -> BRB006 | G53: =VLOOKUP($C53,Carpetas!$C$5:$M$2666,10,FALSE) -> 148,38,32 | H53: =VLOOKUP($C53,Carpetas!$C$5:$M$2666,6,FALSE) -> Silvio | J53: =E53+2 -> 45325 | K53: =VLOOKUP($C53,Carpetas!$C$5:$M$2666,5,FALSE) -> Rio Branco | M53: =J53+1+2+1 -> 45329 | N53: =IF(E53<>"",M53-E53,"-") -> 6 | O53: 918 | P53: 919 | S53: GT001 | U53: 6723 | V53: IPA 0C32 | W53: AVA 9556 | Y53: =VLOOKUP(X53,Choferes!$B$2:$C$500,2,FALSE) -> #N/A | Z53: 08/02: SE DESCARGO EN RIQUEZA NATURAL 919 CAJAS DE BRASIL MADERA.
A54: 5 | B54: Descargado | C54: 004/24 | D54: Corupá | E54: 45322 | F54: =VLOOKUP($C54,Carpetas!$C$5:$M$2666,2,FALSE) -> BRB004 | G54: =VLOOKUP($C54,Carpetas!$C$5:$M$2666,10,FALSE) -> 148,30,63 | H54: =VLOOKUP($C54,Carpetas!$C$5:$M$2666,6,FALSE) -> Silvio | J54: 45326 | K54: =VLOOKUP($C54,Carpetas!$C$5:$M$2666,5,FALSE) -> Rio Branco | M54: =J54+1+2 -> 45329 | N54: =IF(E54<>"",M54-E54,"-") -> 7 | O54: 918 | P54: 919 | S54: CP003 | U54: 6704 | V54: MLC 7F48 | W54: MLF 4G41 | Y54: =VLOOKUP(X54,Choferes!$B$2:$C$500,2,FALSE) -> #N/A | Z54: 08/02: SE DESCARGARON EN RIQUEZA NATURAL 919 CAJAS DE BANANA BRASIL MADERA
A55: 5 | B55: Descargado | C55: 007/24 | D55: claudia | E55: 45324 | F55: =VLOOKUP($C55,Carpetas!$C$5:$M$2666,2,FALSE) -> BRB005 | G55: =VLOOKUP($C55,Carpetas!$C$5:$M$2666,10,FALSE) -> 148.35.36 | H55: =VLOOKUP($C55,Carpetas!$C$5:$M$2666,6,FALSE) -> Zanini | J55: =E55+2 -> 45326 | K55: =VLOOKUP($C55,Carpetas!$C$5:$M$2666,5,FALSE) -> Rio Branco | M55: =J55+1+2 -> 45329 | N55: =IF(E55<>"",M55-E55,"-") -> 5 | O55: 900 | P55: 901 | S55: CH007 | U55: 4214 | V55: FEJ 8C47 | W55: EOE 2445 | Y55: =VLOOKUP(X55,Choferes!$B$2:$C$500,2,FALSE) -> #N/A | Z55: 08/02: SE DESCARGO EN RIQUEZA NATURAL 901 CAJAS DE BRASIL MADERA FIBRA EXTRA.
A56: 5 | B56: Descargado | C56: AL004/2024 | D56: Nordeste | E56: 45320 | F56: =VLOOKUP($C56,Carpetas!$C$5:$M$2666,2,FALSE) -> BRA004 | G56: =VLOOKUP($C56,Carpetas!$C$5:$M$2666,10,FALSE) -> 0 | H56: =VLOOKUP($C56,Carpetas!$C$5:$M$2666,6,FALSE) -> Silvio | J56: 45328 | K56: =VLOOKUP($C56,Carpetas!$C$5:$M$2666,5,FALSE) -> Rio Branco | M56: =J56+1 -> 45329 | N56: =IF(E56<>"",M56-E56,"-") -> 9 | O56: 1104 | P56: 1104 | S56: PURA VIDA | V56: ELW 2791 | W56: MIQ 0614 | Y56: =VLOOKUP(X56,Choferes!$B$2:$C$500,2,FALSE) -> #N/A | Z56: 08/02: SE DESCARGARON EN RIQUEZA NATURAL 1104 CAJAS DE BANANA BRASIL CARTON (PURA VIDA).
A57: 5 | B57: Descargado | C57: 104/ | D57: Paraguay DF | E57: 45325 | F57: =VLOOKUP($C57,Carpetas!$C$5:$M$2666,2,FALSE) -> PYB024 | G57: =VLOOKUP($C57,Carpetas!$C$5:$M$2666,10,FALSE) -> 148,37,94 | H57: =VLOOKUP($C57,Carpetas!$C$5:$M$2666,6,FALSE) -> Jauser | J57: 45328 | K57: =VLOOKUP($C57,Carpetas!$C$5:$M$2666,5,FALSE) -> Salto | M57: =J57+1 -> 45329 | N57: =IF(E57<>"",M57-E57,"-") -> 4 | O57: 980 | P57: 983 | S57: PYDF004 | V57: AAGJ 938 | W57: AAIF650 | Y57: =VLOOKUP(X57,Choferes!$B$2:$C$500,2,FALSE) -> #N/A | Z57: 07/02 AL: SE RECIBIERON EN RIQUEZA NATURAL 983 CAJAS DE BANANA PARAGUAY PEPE.
A58: 6 | B58: Descargado | C58: 317/ | D58: Paraguay MS | E58: 45328 | F58: =VLOOKUP($C58,Carpetas!$C$5:$M$2666,2,FALSE) -> PYB026 | G58: =VLOOKUP($C58,Carpetas!$C$5:$M$2666,10,FALSE) -> 148,38,93 | H58: =VLOOKUP($C58,Carpetas!$C$5:$M$2666,6,FALSE) -> Jauser | J58: =E58+2 -> 45330 | K58: =VLOOKUP($C58,Carpetas!$C$5:$M$2666,5,FALSE) -> Salto | M58: =J58+1 -> 45331 | N58: =IF(E58<>"",M58-E58,"-") -> 3 | O58: 980 | P58: 980 | S58: PYMS007 | U58: 1892 | V58: AAIR364 | W58: AAAP975 | Y58: =VLOOKUP(X58,Choferes!$B$2:$C$500,2,FALSE) -> #N/A | Z58: 09/02: SE DESCARGARON EN RIQUEZA NATURAL 980 CAJAS DE PY PEPE( -3 QUEMADAS). 977.
A59: 5 | B59: Descargado | C59: AL005/2024 | D59: Nordeste | E59: 45322 | F59: =VLOOKUP($C59,Carpetas!$C$5:$M$2666,2,FALSE) -> BRA004 | G59: =VLOOKUP($C59,Carpetas!$C$5:$M$2666,10,FALSE) -> 0 | H59: =VLOOKUP($C59,Carpetas!$C$5:$M$2666,6,FALSE) -> Silvio | J59: 45329 | K59: =VLOOKUP($C59,Carpetas!$C$5:$M$2666,5,FALSE) -> Rio Branco | M59: 45332 | N59: =IF(E59<>"",M59-E59,"-") -> 10 | O59: 1103 | S59: PURA VIDA | U59: 6722 | V59: SEB 0B64 | W59: MLA 8D93 | Y59: =VLOOKUP(X59,Choferes!$B$2:$C$500,2,FALSE) -> #N/A | Z59: 10/02: SE DESCARGARON EN RIQUEZA NATURAL 1103 CAJAS DE BANANA PURAVIDA,
A60: 5 | B60: Descargado | C60: AL006/2024 | D60: Nordeste | E60: 45324 | F60: =VLOOKUP($C60,Carpetas!$C$5:$M$2666,2,FALSE) -> BRA005 | G60: =VLOOKUP($C60,Carpetas!$C$5:$M$2666,10,FALSE) -> 148,36,69 | H60: =VLOOKUP($C60,Carpetas!$C$5:$M$2666,6,FALSE) -> Silvio | J60: 45330 | K60: =VLOOKUP($C60,Carpetas!$C$5:$M$2666,5,FALSE) -> Rio Branco | M60: 45332 | N60: =IF(E60<>"",M60-E60,"-") -> 8 | O60: 1104 | P60: 1104 | S60: PURA VIDA | U60: 6729 | V60: PXD 0G96 | W60: MHP 0E22 | Y60: =VLOOKUP(X60,Choferes!$B$2:$C$500,2,FALSE) -> #N/A | Z60: 10/02:SE DESCARGO ENRIQUEZA NATURAL 1104 CAJAS DE PURA VIDA
A61: 6 | B61: Descargado | C61: 003/24 | D61: Junkes | E61: 45328 | F61: =VLOOKUP($C61,Carpetas!$C$5:$M$2666,2,FALSE) -> BRB003 | G61: =VLOOKUP($C61,Carpetas!$C$5:$M$2666,10,FALSE) -> 148,30,62 | H61: =VLOOKUP($C61,Carpetas!$C$5:$M$2666,6,FALSE) -> Zanini | J61: =E61+2 -> 45330 | K61: =VLOOKUP($C61,Carpetas!$C$5:$M$2666,5,FALSE) -> Rio Branco | M61: 45332 | N61: =IF(E61<>"",M61-E61,"-") -> 4 | O61: 918 | P61: 919 | S61: JS004 | U61: 4222 | V61: RAB 2900 | W61: QTM 6394 | Y61: =VLOOKUP(X61,Choferes!$B$2:$C$500,2,FALSE) -> #N/A | Z61: 10/02: DESCARGAN EN RIQUEZA NATURAL 919 CAJAS DE BANANA BRASIL FIBRA.
A62: 6 | B62: Descargado | C62: 317/ | D62: Paraguay MS | E62: 45328 | F62: =VLOOKUP($C62,Carpetas!$C$5:$M$2666,2,FALSE) -> PYB026 | G62: =VLOOKUP($C62,Carpetas!$C$5:$M$2666,10,FALSE) -> 148,38,93 | H62: =VLOOKUP($C62,Carpetas!$C$5:$M$2666,6,FALSE) -> Jauser | J62: 45331 | K62: =VLOOKUP($C62,Carpetas!$C$5:$M$2666,5,FALSE) -> Salto | M62: =J62+1 -> 45332 | N62: =IF(E62<>"",M62-E62,"-") -> 4 | O62: 980 | P62: 981 | S62: PY*MS008 | V62: BGN714 | W62: AYU645 | Y62: =VLOOKUP(X62,Choferes!$B$2:$C$500,2,FALSE) -> #N/A | Z62: SE DESCARGO EN RIQUEZA NATURAL 981 CAJAS DE PY EL DIA 10/2/2024
A63: 6 | B63: Descargado | C63: 007/24 | D63: claudia | E63: 45329 | F63: =VLOOKUP($C63,Carpetas!$C$5:$M$2666,2,FALSE) -> BRB005 | G63: =VLOOKUP($C63,Carpetas!$C$5:$M$2666,10,FALSE) -> 148.35.36 | H63: =VLOOKUP($C63,Carpetas!$C$5:$M$2666,6,FALSE) -> Zanini | J63: =E63+2 -> 45331 | K63: =VLOOKUP($C63,Carpetas!$C$5:$M$2666,5,FALSE) -> Rio Branco | M63: =J63+1 -> 45332 | N63: =IF(E63<>"",M63-E63,"-") -> 3 | O63: 900 | P63: 901 | S63: CH*008 | U63: 4221 | V63: RXZ 2J78 | W63: RYF 7H56 | Y63: =VLOOKUP(X63,Choferes!$B$2:$C$500,2,FALSE) -> #N/A | Z63: SE DESCARGO EN RIQUEZA NATURAL 901 CAJAS DE BRASIL FIBRA EL DIA 10/2/2024
A64: 6 | B64: Descargado | C64: 318/ | D64: Paraguay MS | E64: 45329 | F64: =VLOOKUP($C64,Carpetas!$C$5:$M$2666,2,FALSE) -> PYB028 | G64: =VLOOKUP($C64,Carpetas!$C$5:$M$2666,10,FALSE) -> 148,40,48 | H64: =VLOOKUP($C64,Carpetas!$C$5:$M$2666,6,FALSE) -> 0 | J64: =E64+2 -> 45331 | K64: =VLOOKUP($C64,Carpetas!$C$5:$M$2666,5,FALSE) -> Salto | M64: =J64+1 -> 45332 | N64: =IF(E64<>"",M64-E64,"-") -> 3 | O64: 980 | P64: 981 | S64: PY*MS009 | V64: BHH13 | W64: OBA516 | Y64: =VLOOKUP(X64,Choferes!$B$2:$C$500,2,FALSE) -> #N/A | Z64: SE DESCARGO EN RIQUEZA NATURAL 981 CAJAS DE PY EL DIA 10/2/2024
A65: 6 | B65: Cancelado | C65: xx | D65: Paraguay DF | E65: 45330 | F65: =VLOOKUP($C65,Carpetas!$C$5:$M$2666,2,FALSE) -> BRB | G65: =VLOOKUP($C65,Carpetas!$C$5:$M$2666,9,FALSE) -> #REF! | H65: =VLOOKUP($C65,Carpetas!$C$5:$M$2666,5,FALSE) -> xx | J65: =E65+2 -> 45332 | K65: =VLOOKUP($C65,Carpetas!$C$5:$M$2666,4,FALSE) -> 0 | M65: =J65+1 -> 45333 | N65: =IF(E65<>"",M65-E65,"-") -> 3 | O65: 918 | Y65: =VLOOKUP(X65,Choferes!$B$2:$C$500,2,FALSE) -> #N/A
A66: 6 | B66: Cancelado | C66: xx | D66: Paraguay DF | E66: 45330 | F66: =VLOOKUP($C66,Carpetas!$C$5:$M$2666,2,FALSE) -> BRB | G66: =VLOOKUP($C66,Carpetas!$C$5:$M$2666,9,FALSE) -> #REF! | H66: =VLOOKUP($C66,Carpetas!$C$5:$M$2666,5,FALSE) -> xx | J66: =E66+2 -> 45332 | K66: =VLOOKUP($C66,Carpetas!$C$5:$M$2666,4,FALSE) -> 0 | M66: =J66+1 -> 45333 | N66: =IF(E66<>"",M66-E66,"-") -> 3 | O66: 918 | Y66: =VLOOKUP(X66,Choferes!$B$2:$C$500,2,FALSE) -> #N/A
A67: 6 | B67: Descargado | C67: 014/ | D67: Paraguay GM | E67: 45329 | F67: =VLOOKUP($C67,Carpetas!$C$5:$M$2666,2,FALSE) -> PYB025 | G67: =VLOOKUP($C67,Carpetas!$C$5:$M$2666,10,FALSE) -> 148,38,94 | H67: =VLOOKUP($C67,Carpetas!$C$5:$M$2666,6,FALSE) -> Jauser | J67: 45332 | K67: =VLOOKUP($C67,Carpetas!$C$5:$M$2666,5,FALSE) -> Salto | M67: 45334 | N67: =IF(E67<>"",M67-E67,"-") -> 5 | O67: 972 | P67: 974 | Y67: =VLOOKUP(X67,Choferes!$B$2:$C$500,2,FALSE) -> #N/A | Z67: SE DESCARGO EN RIQUEZA NATURAL 974 CAJAS DE PY COMUN EL DIA 11/02/2024
A68: 6 | B68: Descargado | C68: 015// | D68: Paraguay GM | E68: 45330 | F68: =VLOOKUP($C68,Carpetas!$C$5:$M$2666,2,FALSE) -> PYB029 | G68: =VLOOKUP($C68,Carpetas!$C$5:$M$2666,10,FALSE) -> 148,42,59 | H68: =VLOOKUP($C68,Carpetas!$C$5:$M$2666,6,FALSE) -> Tahan | J68: =E68+2 -> 45332 | K68: =VLOOKUP($C68,Carpetas!$C$5:$M$2666,5,FALSE) -> Salto | M68: 45334 | N68: =IF(E68<>"",M68-E68,"-") -> 4 | O68: 972 | P68: 972 | W68: l | Y68: =VLOOKUP(X68,Choferes!$B$2:$C$500,2,FALSE) -> #N/A | Z68: SE DESCARGO EN RIQUEZA NATURAL 972 CAJAS DE PY EL DIA 14/2/2024
A69: 6 | B69: Descargado | C69: 1194/ | D69: Paraguay EC | E69: 45330 | F69: =VLOOKUP($C69,Carpetas!$C$5:$M$2666,2,FALSE) -> PYB027 | G69: =VLOOKUP($C69,Carpetas!$C$5:$M$2666,10,FALSE) -> 148,39,83 | H69: =VLOOKUP($C69,Carpetas!$C$5:$M$2666,6,FALSE) -> 0 | J69: 45332 | K69: =VLOOKUP($C69,Carpetas!$C$5:$M$2666,5,FALSE) -> Salto | M69: 45334 | N69: =IF(E69<>"",M69-E69,"-") -> 4 | O69: 930 | P69: 931 | Y69: =VLOOKUP(X69,Choferes!$B$2:$C$500,2,FALSE) -> #N/A | Z69: SE DESCARGO EN RIQUEZA NATURAL 931 CAJAS DE PY EL DIA 11/02/2024
A70: 6 | B70: Descargado | C70: 1194/ | D70: Paraguay EC | E70: 45331 | F70: =VLOOKUP($C70,Carpetas!$C$5:$M$2666,2,FALSE) -> PYB027 | G70: =VLOOKUP($C70,Carpetas!$C$5:$M$2666,10,FALSE) -> 148,39,83 | H70: =VLOOKUP($C70,Carpetas!$C$5:$M$2666,6,FALSE) -> 0 | J70: 45332 | K70: =VLOOKUP($C70,Carpetas!$C$5:$M$2666,5,FALSE) -> Salto | M70: 45334 | N70: =IF(E70<>"",M70-E70,"-") -> 3 | O70: 930 | P70: 930 | Y70: =VLOOKUP(X70,Choferes!$B$2:$C$500,2,FALSE) -> #N/A | Z70: SE DESCARGO EN RIQUEZA NATURAL 930 CAJAS DE PY EL DIA 11/02/2024
A71: 7 | B71: Descargado | C71: 107// | D71: Paraguay DF | E71: 45334 | F71: =VLOOKUP($C71,Carpetas!$C$5:$M$2666,2,FALSE) -> PYB030 | G71: =VLOOKUP($C71,Carpetas!$C$5:$M$2666,10,FALSE) -> 145,45,55 | H71: =VLOOKUP($C71,Carpetas!$C$5:$M$2666,6,FALSE) -> Tahan | J71: 45337 | K71: =VLOOKUP($C71,Carpetas!$C$5:$M$2666,5,FALSE) -> Salto | M71: =J71+1 -> 45338 | N71: =IF(E71<>"",M71-E71,"-") -> 4 | O71: 980 | P71: 981 | S71: PYDF005 | V71: BFK528 | W71: BEF740 | Y71: =VLOOKUP(X71,Choferes!$B$2:$C$500,2,FALSE) -> #N/A | Z71: 16/02: SE RECIBIERON EN RIQUEZA NATURAL 981 CAJAS DE BANANA PARAGUAY PEPE.
A72: 7 | B72: Descargado | C72: 2288/ | D72: Paraguay HF | E72: 45334 | F72: =VLOOKUP($C72,Carpetas!$C$5:$M$2666,2,FALSE) -> PYB031 | G72: =VLOOKUP($C72,Carpetas!$C$5:$M$2666,10,FALSE) -> 148.45.31 | H72: =VLOOKUP($C72,Carpetas!$C$5:$M$2666,6,FALSE) -> 0 | J72: 45337 | K72: =VLOOKUP($C72,Carpetas!$C$5:$M$2666,5,FALSE) -> Salto | M72: =J72+1 -> 45338 | N72: =IF(E72<>"",M72-E72,"-") -> 4 | O72: 980 | P72: 982 | S72: PYHF002 | V72: BGX855 | W72: UAB514 | Y72: =VLOOKUP(X72,Choferes!$B$2:$C$500,2,FALSE) -> #N/A | Z72: 16/02: SE DESCARGARON EN RIQUEZA NATURAL 982 CAJAS DE BANANA PARAGUAY PEPE.
A73: 7 | B73: Descargado | C73: 014/ | D73: Paraguay GM | E73: 45334 | F73: =VLOOKUP($C73,Carpetas!$C$5:$M$2666,2,FALSE) -> PYB025 | G73: =VLOOKUP($C73,Carpetas!$C$5:$M$2666,10,FALSE) -> 148,38,94 | H73: =VLOOKUP($C73,Carpetas!$C$5:$M$2666,6,FALSE) -> Jauser | J73: 45337 | K73: =VLOOKUP($C73,Carpetas!$C$5:$M$2666,5,FALSE) -> Salto | M73: =J73+1 -> 45338 | N73: =IF(E73<>"",M73-E73,"-") -> 4 | O73: 980 | P73: 972 | S73: PYGM010 | V73: AAIF811 | W73: AAIF819 | Y73: =VLOOKUP(X73,Choferes!$B$2:$C$500,2,FALSE) -> #N/A | Z73: 16/02: SE DESCARGARON EN RIQUEZA NATURAL 972 CAJAS DE BANANA PARAGUAY COMUN (CAJA NEGRA).
A74: 6 | B74: Descargado | C74: 008/24 | D74: Gilson | E74: 45330 | F74: =VLOOKUP($C74,Carpetas!$C$5:$M$2666,2,FALSE) -> BRB006 | G74: =VLOOKUP($C74,Carpetas!$C$5:$M$2666,10,FALSE) -> 148,38,32 | H74: =VLOOKUP($C74,Carpetas!$C$5:$M$2666,6,FALSE) -> Silvio | J74: 45336 | K74: =VLOOKUP($C74,Carpetas!$C$5:$M$2666,5,FALSE) -> Rio Branco | M74: 45339 | N74: =IF(E74<>"",M74-E74,"-") -> 9 | O74: 918 | U74: 6824 | V74: MDI 4739 | W74: MIY 3F53 | Y74: =VLOOKUP(X74,Choferes!$B$2:$C$500,2,FALSE) -> #N/A | Z74: 17/02: SE RECIBIERON EN RIQUEZA NATURAL 919 CAJAS DE BANANA BRASIL MADERA.
A75: 6 | B75: Descargado | C75: 007/24 | D75: claudia | E75: 45331 | F75: =VLOOKUP($C75,Carpetas!$C$5:$M$2666,2,FALSE) -> BRB005 | G75: =VLOOKUP($C75,Carpetas!$C$5:$M$2666,10,FALSE) -> 148.35.36 | H75: =VLOOKUP($C75,Carpetas!$C$5:$M$2666,6,FALSE) -> Zanini | J75: 45336 | K75: =VLOOKUP($C75,Carpetas!$C$5:$M$2666,5,FALSE) -> Rio Branco | M75: 45339 | N75: =IF(E75<>"",M75-E75,"-") -> 8 | O75: 900 | P75: 901 | S75: CH009 | U75: 4228 | V75: MMH 8790 | W75: FFW 3337 | Y75: =VLOOKUP(X75,Choferes!$B$2:$C$500,2,FALSE) -> #N/A | Z75: 17/02: SE DESCARGARON EN RIQUEZA NATURAL 901 CAJAS DE BANANA BR_FIBRA EXTRA.
A76: 6 | B76: Descargado | C76: 001-AMR-2024 | D76: Varios | E76: 45331 | F76: =VLOOKUP($C76,Carpetas!$C$5:$M$2666,2,FALSE) -> BRE004 | G76: =VLOOKUP($C76,Carpetas!$C$5:$M$2666,10,FALSE) -> 1483959-1483960-1483907 | H76: =VLOOKUP($C76,Carpetas!$C$5:$M$2666,6,FALSE) -> 0 | I76: =VLOOKUP($C76,Carpetas!$C$5:$M$2666,4,FALSE) -> 0 | J76: 45336 | K76: =VLOOKUP($C76,Carpetas!$C$5:$M$2666,5,FALSE) -> Rio Branco | M76: 45339 | N76: =IF(E76<>"",M76-E76,"-") -> 8 | O76: 1428 | V76: RHVOG74 | Y76: =VLOOKUP(X76,Choferes!$B$2:$C$500,2,FALSE) -> #N/A
A77: 6 | B77: Descargado | C77: AL009/2024 | D77: Nordeste | E77: 45331 | F77: =VLOOKUP($C77,Carpetas!$C$5:$M$2666,2,FALSE) -> BRA006 | G77: =VLOOKUP($C77,Carpetas!$C$5:$M$2666,10,FALSE) -> 148,40,49 | H77: =VLOOKUP($C77,Carpetas!$C$5:$M$2666,6,FALSE) -> Silvio | J77: 45336 | K77: =VLOOKUP($C77,Carpetas!$C$5:$M$2666,5,FALSE) -> Rio Branco | M77: 45339 | N77: =IF(E77<>"",M77-E77,"-") -> 8 | O77: 1104 | P77: 1104 | S77: PURA VIDA | U77: 6737 | V77: BEZ 3B58 | W77: BEZ 3B59 | Y77: =VLOOKUP(X77,Choferes!$B$2:$C$500,2,FALSE) -> #N/A | Z77: 17/02: SE DESCARGARON EN RIQUEZA NATURAL 1104 CAJAS DE BANANA PURA VIDA.
A78: 7 | B78: Descargado | C78: 008/24 | D78: Corupá | E78: 45336 | F78: =VLOOKUP($C78,Carpetas!$C$5:$M$2666,2,FALSE) -> BRB006 | G78: =VLOOKUP($C78,Carpetas!$C$5:$M$2666,10,FALSE) -> 148,38,32 | H78: =VLOOKUP($C78,Carpetas!$C$5:$M$2666,6,FALSE) -> Silvio | J78: 45336 | K78: =VLOOKUP($C78,Carpetas!$C$5:$M$2666,5,FALSE) -> Rio Branco | M78: 45339 | N78: =IF(E78<>"",M78-E78,"-") -> 3 | O78: 918 | P78: 919 | U78: 6725 | V78: RYK 0G12 | W78: FCE 5549 | Y78: =VLOOKUP(X78,Choferes!$B$2:$C$500,2,FALSE) -> #N/A | Z78: SE DESCARGO EN RIQUEZA NATURAL 919 CAJAS DE BRASIL EL DIA 17/2/2024. VINO CON FRUTA SENTIDA
A79: 6 | B79: Descargado | C79: AL007/2024 | D79: Nordeste | E79: 45329 | F79: =VLOOKUP($C79,Carpetas!$C$5:$M$2666,2,FALSE) -> BRA006 | G79: =VLOOKUP($C79,Carpetas!$C$5:$M$2666,10,FALSE) -> 148,40,49 | H79: =VLOOKUP($C79,Carpetas!$C$5:$M$2666,6,FALSE) -> Silvio | J79: 45337 | K79: =VLOOKUP($C79,Carpetas!$C$5:$M$2666,5,FALSE) -> Rio Branco | M79: 45339 | N79: =IF(E79<>"",M79-E79,"-") -> 10 | O79: 1104 | P79: 1104 | S79: PURA VIDA | U79: 6730 | V79: QJQ 1895 | W79: MKW 8297 | Y79: =VLOOKUP(X79,Choferes!$B$2:$C$500,2,FALSE) -> #N/A | Z79: SE DESCARGO EN RIQUEZA NATURAL 1104 CAJAS DE PURA VIDA EL DIA 17/2/2024
A80: 6 | B80: Descargado | C80: AL008/2024 | D80: Nordeste | E80: 45330 | F80: =VLOOKUP($C80,Carpetas!$C$5:$M$2666,2,FALSE) -> BRA006 | G80: =VLOOKUP($C80,Carpetas!$C$5:$M$2666,10,FALSE) -> 148,40,49 | H80: =VLOOKUP($C80,Carpetas!$C$5:$M$2666,6,FALSE) -> Silvio | J80: 45338 | K80: =VLOOKUP($C80,Carpetas!$C$5:$M$2666,5,FALSE) -> Rio Branco | M80: =J80+1 -> 45339 | N80: =IF(E80<>"",M80-E80,"-") -> 9 | O80: 1104 | P80: 1104 | S80: PURA VIDA | U80: 6734 | V80: MLR 9979 | W80: MEY 0446 | Y80: =VLOOKUP(X80,Choferes!$B$2:$C$500,2,FALSE) -> #N/A | Z80: SE DESCARGO EN RIQUEZA NATURAL 1104 CAJAS DE PURA VIDA EL DIA 17/2/2024
A81: 7 | B81: Descargado | C81: 321/ | D81: Paraguay MS | E81: 45335 | F81: =VLOOKUP($C81,Carpetas!$C$5:$M$2666,2,FALSE) -> PYB033 | G81: =VLOOKUP($C81,Carpetas!$C$5:$M$2666,10,FALSE) -> 148.45.61 | H81: =VLOOKUP($C81,Carpetas!$C$5:$M$2666,6,FALSE) -> 0 | J81: 45338 | K81: =VLOOKUP($C81,Carpetas!$C$5:$M$2666,5,FALSE) -> Salto | M81: =J81+1 -> 45339 | N81: =IF(E81<>"",M81-E81,"-") -> 4 | O81: 980 | P81: 980 | S81: PYMS011 | V81: AAIS110 | W81: OCG216 | Y81: =VLOOKUP(X81,Choferes!$B$2:$C$500,2,FALSE) -> #N/A | Z81: SE DESCARGO EN RIQUEZA NATURAL 980 CAJAS DE PARAGUAY EL DIA 17/2/2024
A82: 7 | B82: Descargado | C82: 016/ | D82: Paraguay GM | E82: 45335 | F82: =VLOOKUP($C82,Carpetas!$C$5:$M$2666,2,FALSE) -> PYB034 | G82: =VLOOKUP($C82,Carpetas!$C$5:$M$2666,10,FALSE) -> 0 | H82: =VLOOKUP($C82,Carpetas!$C$5:$M$2666,6,FALSE) -> 0 | J82: 45338 | K82: =VLOOKUP($C82,Carpetas!$C$5:$M$2666,5,FALSE) -> Salto | M82: =J82+1 -> 45339 | N82: =IF(E82<>"",M82-E82,"-") -> 4 | O82: 972 | P82: 972 | S82: PYGM011 | V82: AAGO344 | W82: AAGX855 | Y82: =VLOOKUP(X82,Choferes!$B$2:$C$500,2,FALSE) -> #N/A | Z82: 17/02: SE RECIBIERON EN RIQUEZA NATURAL 972 CAJAS DE BANANA PY COMUN (CAJA NEGRA).
A83: 7 | B83: Descargado | C83: 003/24 | D83: Jaime | E83: 45336 | F83: =VLOOKUP($C83,Carpetas!$C$5:$M$2666,2,FALSE) -> BRB003 | G83: =VLOOKUP($C83,Carpetas!$C$5:$M$2666,10,FALSE) -> 148,30,62 | H83: =VLOOKUP($C83,Carpetas!$C$5:$M$2666,6,FALSE) -> Zanini | J83: 45338 | K83: =VLOOKUP($C83,Carpetas!$C$5:$M$2666,5,FALSE) -> Rio Branco | M83: =J83+1 -> 45339 | N83: =IF(E83<>"",M83-E83,"-") -> 3 | O83: 918 | P83: 918 | S83: JM008 | U83: 4234 | V83: QHP 4989 | W83: QHT 8855 | Y83: =VLOOKUP(X83,Choferes!$B$2:$C$500,2,FALSE) -> #N/A | Z83: SE DESCARGO EN RIQUEZA NATURAL 918 CAJAS DE BRASIL EL DIA 17/2/2024
A84: 7 | B84: Descargado | C84: 321/ | D84: Paraguay MS | E84: 45336 | F84: =VLOOKUP($C84,Carpetas!$C$5:$M$2666,2,FALSE) -> PYB033 | G84: =VLOOKUP($C84,Carpetas!$C$5:$M$2666,10,FALSE) -> 148.45.61 | H84: =VLOOKUP($C84,Carpetas!$C$5:$M$2666,6,FALSE) -> 0 | J84: 45338 | K84: =VLOOKUP($C84,Carpetas!$C$5:$M$2666,5,FALSE) -> Salto | M84: =J84+1 -> 45339 | N84: =IF(E84<>"",M84-E84,"-") -> 3 | O84: 980 | P84: 980 | S84: PYMS010 | V84: BEB467 | W84: BFH182 | Y84: =VLOOKUP(X84,Choferes!$B$2:$C$500,2,FALSE) -> #N/A | Z84: SE DESCARGO EN RIQUEZA NATURAL 980 CAJAS DE PARAGUAY EL DIA 17/2/2024
A85: 7 | B85: Descargado | C85: 1195/ | D85: Paraguay EC | E85: 45335 | F85: =VLOOKUP($C85,Carpetas!$C$5:$M$2666,2,FALSE) -> PYB032 | G85: =VLOOKUP($C85,Carpetas!$C$5:$M$2666,10,FALSE) -> 148,45,62 | H85: =VLOOKUP($C85,Carpetas!$C$5:$M$2666,6,FALSE) -> 0 | J85: 45338 | K85: =VLOOKUP($C85,Carpetas!$C$5:$M$2666,5,FALSE) -> Salto | M85: 45341 | N85: =IF(E85<>"",M85-E85,"-") -> 6 | O85: 930 | P85: 931 | S85: PYEC017 | V85: AADH798 | W85: AADH872 | Y85: =VLOOKUP(X85,Choferes!$B$2:$C$500,2,FALSE) -> #N/A | Z85: 19/02: SE RECIBIERON EN RIQUEZA NATURAL 931 CAJAS DE BANANA PY PEPE.
A86: 7 | B86: Descargado | C86: 1195/ | D86: Paraguay EC | E86: 45336 | F86: =VLOOKUP($C86,Carpetas!$C$5:$M$2666,2,FALSE) -> PYB032 | G86: =VLOOKUP($C86,Carpetas!$C$5:$M$2666,10,FALSE) -> 148,45,62 | H86: =VLOOKUP($C86,Carpetas!$C$5:$M$2666,6,FALSE) -> 0 | J86: 45339 | K86: =VLOOKUP($C86,Carpetas!$C$5:$M$2666,5,FALSE) -> Salto | M86: 45341 | N86: =IF(E86<>"",M86-E86,"-") -> 5 | O86: 930 | P86: 930 | S86: PYEC018 | V86: AACZ181 | W86: BZR991 | Y86: =VLOOKUP(X86,Choferes!$B$2:$C$500,2,FALSE) -> #N/A | Z86: 20/02: SE RECIBIERON EN RIQUEZA NATURAL 930 CAJAS DE BANANA PY PEPE.
A87: 7 | B87: Cancelado | C87: xx | D87: Paraguay HF | E87: 45335 | F87: =VLOOKUP($C87,Carpetas!$C$5:$M$2666,2,FALSE) -> BRB | G87: =VLOOKUP($C87,Carpetas!$C$5:$M$2666,9,FALSE) -> #REF! | H87: =VLOOKUP($C87,Carpetas!$C$5:$M$2666,5,FALSE) -> xx | J87: =E87+5 -> 45340 | K87: =VLOOKUP($C87,Carpetas!$C$5:$M$2666,4,FALSE) -> 0 | M87: =J87+1 -> 45341 | N87: =IF(E87<>"",M87-E87,"-") -> 6 | O87: 918 | Y87: =VLOOKUP(X87,Choferes!$B$2:$C$500,2,FALSE) -> #N/A
A88: 7 | B88: Cancelado | C88: xx | D88: Bolivia Tuli | E88: 45335 | F88: =VLOOKUP($C88,Carpetas!$C$5:$M$2666,2,FALSE) -> BRB | G88: =VLOOKUP($C88,Carpetas!$C$5:$M$2666,9,FALSE) -> #REF! | H88: =VLOOKUP($C88,Carpetas!$C$5:$M$2666,5,FALSE) -> xx | J88: =E88+5 -> 45340 | K88: =VLOOKUP($C88,Carpetas!$C$5:$M$2666,4,FALSE) -> 0 | M88: =J88+1 -> 45341 | N88: =IF(E88<>"",M88-E88,"-") -> 6 | O88: 1104 | Y88: =VLOOKUP(X88,Choferes!$B$2:$C$500,2,FALSE) -> #N/A
A89: 7 | B89: Cancelado | C89: xx | D89: Bolivia Tuli | E89: 45335 | F89: =VLOOKUP($C89,Carpetas!$C$5:$M$2666,2,FALSE) -> BRB | G89: =VLOOKUP($C89,Carpetas!$C$5:$M$2666,9,FALSE) -> #REF! | H89: =VLOOKUP($C89,Carpetas!$C$5:$M$2666,5,FALSE) -> xx | J89: =E89+5 -> 45340 | K89: =VLOOKUP($C89,Carpetas!$C$5:$M$2666,4,FALSE) -> 0 | M89: =J89+1 -> 45341 | N89: =IF(E89<>"",M89-E89,"-") -> 6 | O89: 1104 | Y89: =VLOOKUP(X89,Choferes!$B$2:$C$500,2,FALSE) -> #N/A
A90: 7 | B90: Cancelado | C90: xx | D90: Bolivia Tuli | E90: 45335 | F90: =VLOOKUP($C90,Carpetas!$C$5:$M$2666,2,FALSE) -> BRB | G90: =VLOOKUP($C90,Carpetas!$C$5:$M$2666,9,FALSE) -> #REF! | H90: =VLOOKUP($C90,Carpetas!$C$5:$M$2666,5,FALSE) -> xx | J90: =E90+5 -> 45340 | K90: =VLOOKUP($C90,Carpetas!$C$5:$M$2666,4,FALSE) -> 0 | M90: =J90+1 -> 45341 | N90: =IF(E90<>"",M90-E90,"-") -> 6 | O90: 1104 | Y90: =VLOOKUP(X90,Choferes!$B$2:$C$500,2,FALSE) -> #N/A
A91: 7 | B91: Descargado | C91: 008/24 | D91: Gilson | E91: 45338 | F91: =VLOOKUP($C91,Carpetas!$C$5:$M$2666,2,FALSE) -> BRB006 | G91: =VLOOKUP($C91,Carpetas!$C$5:$M$2666,10,FALSE) -> 148,38,32 | H91: =VLOOKUP($C91,Carpetas!$C$5:$M$2666,6,FALSE) -> Silvio | J91: 45341 | K91: =VLOOKUP($C91,Carpetas!$C$5:$M$2666,5,FALSE) -> Rio Branco | M91: =J91+1 -> 45342 | N91: =IF(E91<>"",M91-E91,"-") -> 4 | O91: 918 | P91: 919 | U91: 6726 | V91: RHU 1A06 | W91: RHU 1A07 | Y91: =VLOOKUP(X91,Choferes!$B$2:$C$500,2,FALSE) -> #N/A | Z91: se descargo en riqueza natural 919 cajas de brasil el dia 22/2/2024
A92: 7 | B92: Descargado | C92: 022//24 | D92: Varios | E92: 45336 | F92: =VLOOKUP($C92,Carpetas!$C$5:$M$2666,2,FALSE) -> BRE005 | G92: =VLOOKUP($C92,Carpetas!$C$5:$M$2666,10,FALSE) -> 1484483/1484482 | H92: =VLOOKUP($C92,Carpetas!$C$5:$M$2666,6,FALSE) -> 0 | I92: =VLOOKUP($C92,Carpetas!$C$5:$M$2666,4,FALSE) -> 0 | J92: =E92+2 -> 45338 | K92: =VLOOKUP($C92,Carpetas!$C$5:$M$2666,5,FALSE) -> Rio Branco | M92: 45344 | N92: =IF(E92<>"",M92-E92,"-") -> 8 | O92: 1032 | U92: 59 | V92: RHB 4E47 | W92: RHB 4E46 | Y92: =VLOOKUP(X92,Choferes!$B$2:$C$500,2,FALSE) -> #N/A
A93: 7 | B93: Descargado | C93: 010/24 | D93: Claudia | E93: 45338 | F93: =VLOOKUP($C93,Carpetas!$C$5:$M$2666,2,FALSE) -> BRB007 | G93: =VLOOKUP($C93,Carpetas!$C$5:$M$2666,10,FALSE) -> 148.48.32 | H93: =VLOOKUP($C93,Carpetas!$C$5:$M$2666,6,FALSE) -> Zanini | J93: 45342 | K93: =VLOOKUP($C93,Carpetas!$C$5:$M$2666,5,FALSE) -> Rio Branco | M93: 45345 | N93: =IF(E93<>"",M93-E93,"-") -> 7 | O93: 900 | P93: 900 | S93: CH011 | U93: 4242 | V93: QJV 4800 | W93: QJM 1037 | Y93: =VLOOKUP(X93,Choferes!$B$2:$C$500,2,FALSE) -> #N/A | Z93: 23/02: SE DESCARGARON EN RIQUEZA NATURAL 900 CAJAS DE BANANA BR. FIBRA EXTRA.
A94: 8 | B94: Descargado | C94: 1010/ | D94: Paraguay HF | E94: 45341 | F94: =VLOOKUP($C94,Carpetas!$C$5:$M$2666,2,FALSE) -> PYB039 | G94: =VLOOKUP($C94,Carpetas!$C$5:$M$2666,10,FALSE) -> 148,51,09 | H94: =VLOOKUP($C94,Carpetas!$C$5:$M$2666,6,FALSE) -> 0 | J94: 45343 | K94: =VLOOKUP($C94,Carpetas!$C$5:$M$2666,5,FALSE) -> Salto | M94: =J94+1+1 -> 45345 | N94: =IF(E94<>"",M94-E94,"-") -> 4 | O94: 980 | P94: 980 | S94: PY HF 004 | V94: AAMG947 | W94: AAOE593 | Y94: =VLOOKUP(X94,Choferes!$B$2:$C$500,2,FALSE) -> #N/A | Z94: SE DESCARGO EN RIQUEZA NATURAL 980 CAJAS DE PARAGAUY EL DIA 23/2/2024
A95: 8 | B95: Descargado | C95: 2292/ | D95: Paraguay HF | E95: 45341 | F95: =VLOOKUP($C95,Carpetas!$C$5:$M$2666,2,FALSE) -> PYB035 | G95: =VLOOKUP($C95,Carpetas!$C$5:$M$2666,10,FALSE) -> 148.49.41 | H95: =VLOOKUP($C95,Carpetas!$C$5:$M$2666,6,FALSE) -> 0 | J95: 45343 | K95: =VLOOKUP($C95,Carpetas!$C$5:$M$2666,5,FALSE) -> Salto | M95: =J95+1+1 -> 45345 | N95: =IF(E95<>"",M95-E95,"-") -> 4 | O95: 980 | P95: 982 | S95: PY HF 003 | V95: AAAH194 | W95: AOZ214 | Y95: =VLOOKUP(X95,Choferes!$B$2:$C$500,2,FALSE) -> #N/A | Z95: SE DESCARGO EN RIQUEZA NATURAL 982 CAJAS DE PARAGUAY EL DIA 23/2/2024
A96: 8 | B96: Descargado | C96: 111/ | D96: Paraguay DF | E96: 45340 | F96: =VLOOKUP($C96,Carpetas!$C$5:$M$2666,2,FALSE) -> PYB038 | G96: =VLOOKUP($C96,Carpetas!$C$5:$M$2666,10,FALSE) -> 0 | H96: =VLOOKUP($C96,Carpetas!$C$5:$M$2666,6,FALSE) -> 0 | J96: 45344 | K96: =VLOOKUP($C96,Carpetas!$C$5:$M$2666,5,FALSE) -> Salto | M96: =J96+1 -> 45345 | N96: =IF(E96<>"",M96-E96,"-") -> 5 | O96: 980 | P96: 982 | S96: PY DF 006 | V96: BZF483 | W96: BHX180 | Y96: =VLOOKUP(X96,Choferes!$B$2:$C$500,2,FALSE) -> #N/A | Z96: SE DESCARGO ENR IQUEZA NATURAL 982 CAJAS DE PARAGUAY COMUN EL DIA 23/2/2024
A97: 8 | B97: Descargado | C97: 322/ | D97: Paraguay MS | E97: 45341 | F97: =VLOOKUP($C97,Carpetas!$C$5:$M$2666,2,FALSE) -> PYB040 | G97: =VLOOKUP($C97,Carpetas!$C$5:$M$2666,10,FALSE) -> 148.49.09 | H97: =VLOOKUP($C97,Carpetas!$C$5:$M$2666,6,FALSE) -> 0 | J97: 45344 | K97: =VLOOKUP($C97,Carpetas!$C$5:$M$2666,5,FALSE) -> Salto | M97: =J97+1 -> 45345 | N97: =IF(E97<>"",M97-E97,"-") -> 4 | O97: 980 | P97: 982 | S97: PY MS 012 | V97: AACG315 | W97: AAIF902 | Y97: =VLOOKUP(X97,Choferes!$B$2:$C$500,2,FALSE) -> #N/A | Z97: 23/02: E RECIBIERON EN RIQUEZA NATURAL 982 CAJAS DE BANANA PY PEPE.
A98: 8 | B98: Descargado | C98: 010/24 | D98: Claudia | E98: 45341 | F98: =VLOOKUP($C98,Carpetas!$C$5:$M$2666,2,FALSE) -> BRB007 | G98: =VLOOKUP($C98,Carpetas!$C$5:$M$2666,10,FALSE) -> 148.48.32 | H98: =VLOOKUP($C98,Carpetas!$C$5:$M$2666,6,FALSE) -> Zanini | J98: =E98+2 -> 45343 | K98: =VLOOKUP($C98,Carpetas!$C$5:$M$2666,5,FALSE) -> Rio Branco | M98: 45346 | N98: =IF(E98<>"",M98-E98,"-") -> 5 | O98: 900 | P98: 900 | S98: CH012 | U98: 4244 | V98: OKD 3060 | W98: QJJ 7228 | Y98: =VLOOKUP(X98,Choferes!$B$2:$C$500,2,FALSE) -> #N/A | Z98: SE DESCARGO EN RIQUEZA NATURAL 900 CAJAS DE BRASIL FIBRA EXTRA EL DIA 24/2/2024
A99: 8 | B99: Descargado | C99: 1197/ | D99: Paraguay EC | E99: 45342 | F99: =VLOOKUP($C99,Carpetas!$C$5:$M$2666,2,FALSE) -> PYB037 | G99: =VLOOKUP($C99,Carpetas!$C$5:$M$2666,10,FALSE) -> 0 | H99: =VLOOKUP($C99,Carpetas!$C$5:$M$2666,6,FALSE) -> 0 | J99: 45345 | K99: =VLOOKUP($C99,Carpetas!$C$5:$M$2666,5,FALSE) -> Salto | M99: =J99+1 -> 45346 | N99: =IF(E99<>"",M99-E99,"-") -> 4 | O99: 930 | P99: 930 | S99: PYEC019 | V99: HEA985 | W99: OBF281 | Y99: =VLOOKUP(X99,Choferes!$B$2:$C$500,2,FALSE) -> #N/A | Z99: 24/02: SE DESCARGARON EN RIQUEZA NATURAL 930 CAJAS DE BANANA PY PEPE.
A100: 8 | B100: Descargado | C100: 322/ | D100: Paraguay MS | E100: 45342 | F100: =VLOOKUP($C100,Carpetas!$C$5:$M$2666,2,FALSE) -> PYB040 | G100: =VLOOKUP($C100,Carpetas!$C$5:$M$2666,10,FALSE) -> 148.49.09 | H100: =VLOOKUP($C100,Carpetas!$C$5:$M$2666,6,FALSE) -> 0 | J100: 45345 | K100: =VLOOKUP($C100,Carpetas!$C$5:$M$2666,5,FALSE) -> Salto | M100: =J100+1 -> 45346 | N100: =IF(E100<>"",M100-E100,"-") -> 4 | O100: 980 | P100: 982 | S100: PYMS13 | V100: AAGJ923 | W100: AADL399 | Y100: =VLOOKUP(X100,Choferes!$B$2:$C$500,2,FALSE) -> #N/A | Z100: 24/02: SE DESCARGARON EN RIQUEZA NATURAL 982 CAJAS DE BANANA PY PEPE.
...

Sheet Carpetas
B2: CARPETAS DE IMPORTACIÓN - CONTROL DE CARGAS y SALDOS
C4: Fatura | D4: Carpeta | E4: Export | F4: Producto | G4: Frontera | H4: Transp. | I4: Qtde | J4: Cargado | K4: Saldo | L4: Afidi | M4: DUA
B5: 44208 | C5: 2994/ | D5: BRA001 | E5: Agricola Famosa | G5: Rio Branco | H5: Silvio | I5: 1152 | J5: =SUMIF(Cargas!#REF!,C5,Cargas!#REF!) -> #REF! | K5: =IF(ABS(I5-J5)<20,0,I5-J5) -> #REF! | L5: 139.16.59 | M5: 6588
B6: 44208 | C6: 2995/ | D6: BRA001 | E6: Agricola Famosa | G6: Rio Branco | H6: Silvio | I6: 1152 | J6: =SUMIF(Cargas!#REF!,C6,Cargas!#REF!) -> #REF! | K6: =IF(ABS(I6-J6)<20,0,I6-J6) -> #REF! | L6: 139.16.58 | M6: 6588
B7: 44208 | C7: 3055/ | D7: BRA001 | E7: Agricola Famosa | G7: Rio Branco | H7: Silvio | I7: 1152 | J7: =SUMIF(Cargas!#REF!,C7,Cargas!#REF!) -> #REF! | K7: =IF(ABS(I7-J7)<20,0,I7-J7) -> #REF! | L7: 139.16.57 | M7: 6588
B8: 44209 | C8: 3115/ | D8: BRA002 | E8: Agricola Famosa | G8: Rio Branco | H8: Silvio | I8: 1152 | J8: =SUMIF(Cargas!#REF!,C8,Cargas!#REF!) -> #REF! | K8: =IF(ABS(I8-J8)<20,0,I8-J8) -> #REF! | L8: 139.20.23 | M8: 10198
B9: 44209 | C9: 3116/ | D9: BRA003 | E9: Agricola Famosa | G9: Rio Branco | H9: Miro | I9: 1152 | J9: =SUMIF(Cargas!#REF!,C9,Cargas!#REF!) -> #REF! | K9: =IF(ABS(I9-J9)<20,0,I9-J9) -> #REF! | L9: 139.20.24 | M9: 10227
B10: 44221 | C10: 3179/ | D10: BRA004 | E10: Agricola Famosa | G10: Rio Branco | H10: Silvio | I10: 1152 | J10: =SUMIF(Cargas!#REF!,C10,Cargas!#REF!) -> #REF! | K10: =IF(ABS(I10-J10)<20,0,I10-J10) -> #REF! | L10: 139.25.59 | M10: 15413
B11: 44221 | C11: 3331/ | D11: BRA004 | E11: Agricola Famosa | G11: Rio Branco | H11: Silvio | I11: 1152 | J11: =SUMIF(Cargas!#REF!,C11,Cargas!#REF!) -> #REF! | K11: =IF(ABS(I11-J11)<20,0,I11-J11) -> #REF! | L11: 139.25.60 | M11: 15413
B12: 44224 | C12: 3332/ | D12: BRA005 | E12: Agricola Famosa | G12: Rio Branco | H12: Silvio | I12: 1152 | J12: =SUMIF(Cargas!#REF!,C12,Cargas!#REF!) -> #REF! | K12: =IF(ABS(I12-J12)<20,0,I12-J12) -> #REF! | L12: 139.28.29 | M12: 19843
B13: 44231 | C13: 3384/ | D13: BRA005 | E13: Agricola Famosa | G13: Rio Branco | H13: Silvio | I13: 1152 | J13: =SUMIF(Cargas!#REF!,C13,Cargas!#REF!) -> #REF! | K13: =IF(ABS(I13-J13)<20,0,I13-J13) -> #REF! | L13: 139.28.29 | M13: 19843
B14: 44238 | C14: 3385/ | D14: BRA005 | E14: Agricola Famosa | G14: Rio Branco | H14: Silvio | I14: 1152 | J14: =SUMIF(Cargas!#REF!,C14,Cargas!#REF!) -> #REF! | K14: =IF(ABS(I14-J14)<20,0,I14-J14) -> #REF! | L14: 139.28.29 | M14: 19843
B15: 44232 | C15: 3494/ | D15: BRA006 | E15: Agricola Famosa | G15: Rio Branco | H15: Silvio | I15: 1152 | J15: 1152 | K15: =IF(ABS(I15-J15)<20,0,I15-J15) -> 0 | L15: 139.31.58 | M15: 23337
B16: 44232 | C16: 3495/ | D16: BRA006 | E16: Agricola Famosa | G16: Rio Branco | H16: Silvio | I16: 1152 | J16: 1152 | K16: =IF(ABS(I16-J16)<20,0,I16-J16) -> 0 | L16: 139.31.58 | M16: 23337
B17: 44233 | C17: 3556/ | D17: BRA006 | E17: Agricola Famosa | G17: Rio Branco | H17: Silvio | I17: 1152 | J17: 1152 | K17: =IF(ABS(I17-J17)<20,0,I17-J17) -> 0 | L17: 139.31.58 | M17: 23337
B18: 44238 | C18: 3557/ | D18: BRA007 | E18: Agricola Famosa | G18: Rio Branco | H18: Silvio | I18: 1152 | J18: 1152 | K18: =IF(ABS(I18-J18)<20,0,I18-J18) -> 0 | L18: 139.31.59 | M18: 25865
B19: 44239 | C19: 3558/ | D19: BRA007 | E19: Agricola Famosa | G19: Rio Branco | H19: Silvio | I19: 1152 | J19: 1152 | K19: =IF(ABS(I19-J19)<20,0,I19-J19) -> 0 | L19: 139.31.59 | M19: 25865
B20: 44240 | C20: 3653/ | D20: BRA008 | E20: Agricola Famosa | G20: Rio Branco | H20: Miro | I20: 1152 | J20: 1152 | K20: =IF(ABS(I20-J20)<20,0,I20-J20) -> 0 | L20: 139.31.60 | M20: 26759
B21: 44248 | C21: 3707/21 | D21: BRA009 | E21: Agricola Famosa | G21: Rio Branco | H21: Miro | I21: 1152 | J21: 1152 | K21: =IF(ABS(I21-J21)<20,0,I21-J21) -> 0 | L21: 139.42.43 | M21: 32433
B22: 44248 | C22: 3657/21 | D22: BRA010 | E22: Agricola Famosa | G22: Rio Branco | H22: Silvio | I22: 1152 | J22: 1152 | K22: =IF(ABS(I22-J22)<20,0,I22-J22) -> 0 | L22: 139.42.42 | M22: 30518
B23: 44248 | C23: 3696/21 | D23: BRA010 | E23: Agricola Famosa | G23: Rio Branco | H23: Silvio | I23: 1152 | J23: 1152 | K23: =IF(ABS(I23-J23)<20,0,I23-J23) -> 0 | L23: 139.42.42 | M23: 30518
B24: 44254 | C24: 3731/21 | D24: BRA011 | E24: Agricola Famosa | G24: Rio Branco | H24: Silvio | I24: 1152 | J24: 1152 | K24: =IF(ABS(I24-J24)<20,0,I24-J24) -> 0 | L24: 139.48.43 | M24: 35198
B25: 44254 | C25: 3762/21 | D25: BRA011 | E25: Agricola Famosa | G25: Rio Branco | H25: Silvio | I25: 1152 | J25: 1152 | K25: =IF(ABS(I25-J25)<20,0,I25-J25) -> 0 | L25: 139.48.43 | M25: 35198
B26: 44254 | C26: 3763/21 | D26: BRA011 | E26: Agricola Famosa | G26: Rio Branco | H26: Silvio | I26: 1152 | J26: 1152 | K26: =IF(ABS(I26-J26)<20,0,I26-J26) -> 0 | L26: 139.48.43 | M26: 35198
... B37: 44281 | C37: 3925/ | D37: BRA018 | E37: Agricola Famosa | G37: Rio Branco | H37: Miro | I37: 1152 | J37: 1152 | K37: =IF(ABS(I37-J37)<20,0,I37-J37) -> 0 | L37: 139.66.98 | M37: 54196
B38: 44281 | C38: 3957/ | D38: BRA019 | E38: Agricola Famosa | G38: Rio Branco | H38: silvio | I38: 1152 | J38: 1152 | K38: =IF(ABS(I38-J38)<20,0,I38-J38) -> 0 | M38: 55368
B39: 44281 | C39: 3958/ | D39: BRA019 | E39: Agricola Famosa | G39: Rio Branco | H39: Silvio | I39: 1152 | J39: 1152 | K39: =IF(ABS(I39-J39)<20,0,I39-J39) -> 0 | M39: 55368
B40: 44281 | C40: 3959/ | D40: BRA020 | E40: Agricola Famosa | G40: Rio Branco | H40: Miro | I40: 1152 | J40: 1152 | K40: =IF(ABS(I40-J40)<20,0,I40-J40) -> 0 | M40: 60105
B41: 44295 | C41: 3989/ | D41: BRA021 | E41: Agricola Famosa | G41: Rio Branco | H41: Silvio | I41: 1152 | J41: 1152 | K41: =IF(ABS(I41-J41)<20,0,I41-J41) -> 0 | L41: 139.76.37 | M41: 61348
B42: 44295 | C42: 3990/ | D42: BRA021 | E42: Agricola Famosa | G42: Rio Branco | H42: Silvio | I42: 1152 | J42: 1152 | K42: =IF(ABS(I42-J42)<20,0,I42-J42) -> 0 | L42: 139.76.37 | M42: 61348
B43: 44295 | C43: 3991/ | D43: BRA021 | E43: Agricola Famosa | G43: Rio Branco | H43: Silvio | I43: 1152 | J43: 1152 | K43: =IF(ABS(I43-J43)<20,0,I43-J43) -> 0 | L43: 139.76.37 | M43: 61348
B44: 44295 | C44: 4019/ | D44: BRA021 | E44: Agricola Famosa | G44: Rio Branco | H44: Silvio | I44: 1152 | J44: 1152 | K44: =IF(ABS(I44-J44)<20,0,I44-J44) -> 0 | L44: 139.76.37 | M44: 61348
B45: 44302 | C45: 4026/ | D45: BRA022 | E45: Agricola Famosa | G45: Rio Branco | H45: Silvio | I45: 1152 | J45: 1152 | K45: =IF(ABS(I45-J45)<20,0,I45-J45) -> 0 | L45: 139.81.67 | M45: 65972
B46: 44567 | C46: 3410/ | D46: BRA001 | E46: Agricola Famosa | G46: Rio Branco | H46: Silvio | I46: 1104 | J46: =SUMIF(Cargas!$C$5:$C$3470,C46,Cargas!$O$5:$O$3470) -> 0 | K46: =IF(ABS(I46-J46)<20,0,I46-J46) -> 1104 | L46: 141.95.81 | M46: xx
B47: 44302 | C47: 4051/ | D47: BRA022 | E47: Agricola Famosa | G47: Rio Branco | H47: Silvio | I47: 1152 | J47: 1152 | K47: =IF(ABS(I47-J47)<20,0,I47-J47) -> 0 | L47: 139.81.67 | M47: 65972
B48: 44302 | C48: 4052/ | D48: BRA022 | E48: Agricola Famosa | G48: Rio Branco | H48: Silvio | I48: 1152 | J48: 1152 | K48: =IF(ABS(I48-J48)<20,0,I48-J48) -> 0 | L48: 139.81.67 | M48: 69925
B49: 44307 | C49: 4053/ | D49: BRA023 | E49: Agricola Famosa | G49: Rio Branco | H49: Silvio | I49: 1152 | J49: 1152 | K49: =IF(ABS(I49-J49)<20,0,I49-J49) -> 0 | L49: 139.85.73 | M49: 69925
B50: 44307 | C50: 4054/ | D50: BRA023 | E50: Agricola Famosa | G50: Rio Branco | H50: Silvio | I50: 1152 | J50: 1152 | K50: =IF(ABS(I50-J50)<20,0,I50-J50) -> 0 | L50: 139.85.73 | M50: 69925
B51: 44307 | C51: 4055/ | D51: BRA023 | E51: Agricola Famosa | G51: Rio Branco | H51: Silvio | I51: 1152 | J51: 1152 | K51: =IF(ABS(I51-J51)<20,0,I51-J51) -> 0 | L51: 139.85.73 | M51: 69925
B52: 44307 | C52: 4069/ | D52: BRA023 | E52: Agricola Famosa | G52: Rio Branco | H52: Silvio | I52: 1152 | J52: 1152 | K52: =IF(ABS(I52-J52)<20,0,I52-J52) -> 0 | L52: 139.85.73 | M52: 69925
B53: 44313 | C53: 4070/ | D53: BRA024 | E53: Agricola Famosa | G53: Rio Branco | H53: Silvio | I53: 1152 | J53: 1152 | K53: =IF(ABS(I53-J53)<20,0,I53-J53) -> 0 | L53: 139.91.47 | M53: 74321
B54: 44316 | C54: 4071/ | D54: BRA024 | E54: Agricola Famosa | G54: Rio Branco | H54: Silvio | I54: 1152 | J54: 1152 | K54: =IF(ABS(I54-J54)<20,0,I54-J54) -> 0 | L54: 139.91.47 | M54: 74321
B55: 44316 | C55: 4072/ | D55: BRA024 | E55: Agricola Famosa | G55: Rio Branco | H55: Silvio | I55: 1152 | J55: 1152 | K55: =IF(ABS(I55-J55)<20,0,I55-J55) -> 0 | L55: 139.91.47 | M55: 74321
B56: 44316 | C56: 4073/ | D56: BRA024 | E56: Agricola Famosa | G56: Rio Branco | H56: Silvio | I56: 1152 | J56: 1152 | K56: =IF(ABS(I56-J56)<20,0,I56-J56) -> 0 | L56: 139.91.47 | M56: 74321
B57: 44321 | C57: 4074/ | D57: BRA025 | E57: Agricola Famosa | G57: Rio Branco | H57: Silvio | I57: 1152 | J57: =SUMIF(Cargas!#REF!,C57,Cargas!#REF!) -> #REF! | K57: =IF(ABS(I57-J57)<20,0,I57-J57) -> #REF! | L57: 139.97.69 | M57: 77799
B58: 44326 | C58: 4088/ | D58: BRA025 | E58: Agricola Famosa | G58: Rio Branco | H58: Silvio | I58: 1152 | J58: =SUMIF(Cargas!#REF!,C58,Cargas!#REF!) -> #REF! | K58: =IF(ABS(I58-J58)<20,0,I58-J58) -> #REF! | L58: 139.97.69 | M58: 77799
B59: 44323 | C59: 4087/ | D59: BRA025 | E59: Agricola Famosa | G59: Rio Branco | H59: Silvio | I59: 1152 | J59: =SUMIF(Cargas!#REF!,C59,Cargas!#REF!) -> #REF! | K59: =IF(ABS(I59-J59)<20,0,I59-J59) -> #REF! | L59: 139.97.69 | M59: 77799
B60: 44322 | C60: 4075/ | D60: BRA025 | E60: Agricola Famosa | G60: Rio Branco | H60: Silvio | I60: 1152 | J60: =SUMIF(Cargas!#REF!,C60,Cargas!#REF!) -> #REF! | K60: =IF(ABS(I60-J60)<20,0,I60-J60) -> #REF! | L60: 139.97.69 | M60: 77799
B61: 44330 | C61: 4090/ | D61: BRA026 | E61: Agricola Famosa | G61: Rio Branco | H61: Silvio | I61: 1152 | J61: =SUMIF(Cargas!#REF!,C61,Cargas!#REF!) -> #REF! | K61: =IF(ABS(I61-J61)<20,0,I61-J61) -> #REF! | L61: 140.06.22 | M61: 84742
B62: 44333 | C62: 4099/ | D62: BRA026 | E62: Agricola Famosa | G62: Rio Branco | H62: Silvio | I62: 1152 | J62: =SUMIF(Cargas!#REF!,C62,Cargas!#REF!) -> #REF! | K62: =IF(ABS(I62-J62)<20,0,I62-J62) -> #REF! | L62: 140.06.22 | M62: 84742
B63: 44328 | C63: 4089/ | D63: BRA026 | E63: Agricola Famosa | G63: Rio Branco | H63: Silvio | I63: 1152 | J63: =SUMIF(Cargas!#REF!,C63,Cargas!#REF!) -> #REF! | K63: =IF(ABS(I63-J63)<20,0,I63-J63) -> #REF! | L63: 140.06.22 | M63: 84742
B64: 44328 | C64: 4100/ | D64: BRA027 | E64: Agricola Famosa | G64: Rio Branco | H64: Silvio | I64: 1152 | J64: =SUMIF(Cargas!#REF!,C64,Cargas!#REF!) -> #REF! | K64: =IF(ABS(I64-J64)<20,0,I64-J64) -> #REF! | L64: 140.10.03 | M64: 86720
B65: 44328 | C65: 4101/ | D65: BRA027 | E65: Agricola Famosa | G65: Rio Branco | H65: Silvio | I65: 1152 | J65: =SUMIF(Cargas!#REF!,C65,Cargas!#REF!) -> #REF! | K65: =IF(ABS(I65-J65)<20,0,I65-J65) -> #REF! | L65: 140.10.03 | M65: 86720
B66: 44328 | C66: 4106/ | D66: BRA027 | E66: Agricola Famosa | G66: Rio Branco | H66: Silvio | I66: 1152 | J66: =SUMIF(Cargas!#REF!,C66,Cargas!#REF!) -> #REF! | K66: =IF(ABS(I66-J66)<20,0,I66-J66) -> #REF! | L66: 140.10.03 | M66: 86720
B67: 44344 | C67: 4108/ | D67: BRA028 | E67: Agricola Famosa | G67: Rio Branco | H67: Silvio | I67: 1152 | J67: =SUMIF(Cargas!#REF!,C67,Cargas!#REF!) -> #REF! | K67: =IF(ABS(I67-J67)<20,0,I67-J67) -> #REF! | L67: 140.16.58 | M67: 92871
B68: 44343 | C68: 4107/ | D68: BRA028 | E68: Agricola Famosa | G68: Rio Branco | H68: Silvio | I68: 1152 | J68: =SUMIF(Cargas!#REF!,C68,Cargas!#REF!) -> #REF! | K68: =IF(ABS(I68-J68)<20,0,I68-J68) -> #REF! | L68: 140.16.58 | M68: 92871
... B81: 44376 | C81: 028/ | D81: BRA034 | E81: Agricola Famosa | G81: Rio Branco | H81: Silvio | I81: 1152 | J81: =SUMIF(Cargas!#REF!,C81,Cargas!#REF!) -> #REF! | K81: =IF(ABS(I81-J81)<20,0,I81-J81) -> #REF! | L81: 140.40.68 | M81: 114271
B82: 44378 | C82: 043/ | D82: BRA034 | E82: Agricola Famosa | G82: Rio Branco | H82: Silvio | I82: 1152 | J82: =SUMIF(Cargas!$C$5:$C$3470,C82,Cargas!$O$5:$O$3470) -> 0 | K82: =IF(ABS(I82-J82)<20,0,I82-J82) -> 1152 | L82: 140.40.68 | M82: 114271
B83: 44380 | C83: 059/ | D83: BRA034 | E83: Agricola Famosa | G83: Rio Branco | H83: Silvio | I83: 1152 | J83: =SUMIF(Cargas!$C$5:$C$3470,C83,Cargas!$O$5:$O$3470) -> 0 | K83: =IF(ABS(I83-J83)<20,0,I83-J83) -> 1152 | L83: 140.40.68 | M83: 114271
B84: 44380 | C84: 052/ | D84: BRA034 | E84: Agricola Famosa | G84: Rio Branco | H84: Silvio | I84: 1152 | J84: =SUMIF(Cargas!$C$5:$C$3470,C84,Cargas!$O$5:$O$3470) -> 0 | K84: =IF(ABS(I84-J84)<20,0,I84-J84) -> 1152 | L84: 140.40.68 | M84: 114271
B85: 44383 | C85: 060/ | D85: BRA035 | E85: Agricola Famosa | G85: Rio Branco | H85: Silvio | I85: 1152 | J85: =SUMIF(Cargas!$C$5:$C$3470,C85,Cargas!$O$5:$O$3470) -> 0 | K85: =IF(ABS(I85-J85)<20,0,I85-J85) -> 1152 | L85: 140.47.92 | M85: 118798
B86: 44385 | C86: 067/ | D86: BRA035 | E86: Agricola Famosa | G86: Rio Branco | H86: Silvio | I86: 1152 | J86: =SUMIF(Cargas!$C$5:$C$3470,C86,Cargas!$O$5:$O$3470) -> 0 | K86: =IF(ABS(I86-J86)<20,0,I86-J86) -> 1152 | L86: 140.47.92 | M86: 118798
B87: 44387 | C87: 070/ | D87: BRA035 | E87: Agricola Famosa | G87: Rio Branco | H87: Silvio | I87: 1152 | J87: =SUMIF(Cargas!$C$5:$C$3470,C87,Cargas!$O$5:$O$3470) -> 0 | K87: =IF(ABS(I87-J87)<20,0,I87-J87) -> 1152 | L87: 140.47.92 | M87: 118798
B88: 44393 | C88: 103/ | D88: BRA036 | E88: Agricola Famosa | G88: Rio Branco | H88: Silvio | I88: 1104 | J88: =SUMIF(Cargas!$C$5:$C$3470,C88,Cargas!$O$5:$O$3470) -> 0 | K88: =IF(ABS(I88-J88)<20,0,I88-J88) -> 1104 | L88: 140.48.71 | M88: 124975
B89: 44393 | C89: 095/ | D89: BRA036 | E89: Agricola Famosa | G89: Rio Branco | H89: Silvio | I89: 1104 | J89: =SUMIF(Cargas!$C$5:$C$3470,C89,Cargas!$O$5:$O$3470) -> 0 | K89: =IF(ABS(I89-J89)<20,0,I89-J89) -> 1104 | L89: 140.48.71 | M89: 124975
B90: 44396 | C90: 113/ | D90: BRA036 | E90: Agricola Famosa | G90: Rio Branco | H90: Silvio | I90: 1104 | J90: =SUMIF(Cargas!$C$5:$C$3470,C90,Cargas!$O$5:$O$3470) -> 0 | K90: =IF(ABS(I90-J90)<20,0,I90-J90) -> 1104 | L90: 140.48.71 | M90: 124975
B91: 44400 | C91: 128/ | D91: BRA037 | E91: Agricola Famosa | G91: Rio Branco | H91: Silvio | I91: 1104 | J91: =SUMIF(Cargas!$C$5:$C$3470,C91,Cargas!$O$5:$O$3470) -> 0 | K91: =IF(ABS(I91-J91)<20,0,I91-J91) -> 1104 | L91: 140.54.39 | M91: 130806
B92: 44400 | C92: 129/ | D92: BRA037 | E92: Agricola Famosa | G92: Rio Branco | H92: Silvio | I92: 1104 | J92: =SUMIF(Cargas!$C$5:$C$3470,C92,Cargas!$O$5:$O$3470) -> 0 | K92: =IF(ABS(I92-J92)<20,0,I92-J92) -> 1104 | L92: 140.54.39 | M92: 130806
B93: 44401 | C93: 137/ | D93: BRA037 | E93: Agricola Famosa | G93: Rio Branco | H93: Silvio | I93: 1104 | J93: =SUMIF(Cargas!$C$5:$C$3470,C93,Cargas!$O$5:$O$3470) -> 0 | K93: =IF(ABS(I93-J93)<20,0,I93-J93) -> 1104 | L93: 140.54.39 | M93: 130806
... B157: 44529 | C157: 2617/ | D157: BRA055 | E157: Agricola Famosa | G157: Chuy | H157: Silvio | I157: 1104 | J157: =SUMIF(Cargas!$C$5:$C$3470,C157,Cargas!$O$5:$O$3470) -> 0 | K157: =IF(ABS(I157-J157)<20,0,I157-J157) -> 1104 | L157: 141.63.07 | M157: 217607
B158: 44937 | C158: 2846/ | D158: BRA001 | E158: Agricola Famosa | G158: Rio Branco | H158: Silvio | I158: 1104 | J158: 1104 | K158: =IF(ABS(I158-J158)<20,0,I158-J158) -> 0 | L158: 144.99.50
B159: 44937 | C159: 2858/ | D159: BRA001 | E159: Agricola Famosa | G159: Rio Branco | H159: Silvio | I159: 1104 | J159: 1104 | K159: =IF(ABS(I159-J159)<20,0,I159-J159) -> 0 | L159: 144.99.50 | M159: 9854
B160: 44573 | C160: 3542/ | D160: BRA002 | E160: Agricola Famosa | G160: Rio Branco | H160: Silvio | I160: 1104 | J160: =SUMIF(Cargas!$C$5:$C$3470,C160,Cargas!$O$5:$O$3470) -> 0 | K160: =IF(ABS(I160-J160)<20,0,I160-J160) -> 1104 | L160: 141.99.89 | M160: 10892
B161: 44573 | C161: 3545/ | D161: BRA002 | E161: Agricola Famosa | G161: Rio Branco | H161: Silvio | I161: 1104 | J161: =SUMIF(Cargas!$C$5:$C$3470,C161,Cargas!$O$5:$O$3470) -> 0 | K161: =IF(ABS(I161-J161)<20,0,I161-J161) -> 1104 | L161: 141.99.89 | M161: 10892
B162: 44945 | C162: 2936/ | D162: BRA002 | E162: Agricola Famosa | G162: Rio Branco | H162: Silvio | I162: 1104 | J162: 1104 | K162: =IF(ABS(I162-J162)<20,0,I162-J162) -> 0 | L162: 145.06.30 | M162: 9854
B163: 44945 | C163: 2950/ | D163: BRA002 | E163: Agricola Famosa | G163: Rio Branco | H163: Silvio | I163: 1104 | J163: 1104 | K163: =IF(ABS(I163-J163)<20,0,I163-J163) -> 0 | L163: 145.06.30 | M163: 13783
B164: 44580 | C164: 3626/ | D164: BRA003 | E164: Agricola Famosa | G164: Rio Branco | H164: Silvio | I164: 1104 | J164: =SUMIF(Cargas!$C$5:$C$3470,C164,Cargas!$O$5:$O$3470) -> 0 | K164: =IF(ABS(I164-J164)<20,0,I164-J164) -> 1104 | L164: 142.05.31 | M164: 13966
B165: 44582 | C165: 3629 | D165: BRA003 | E165: Agricola Famosa | G165: Rio Branco | H165: Silvio | I165: 1104 | J165: =SUMIF(Cargas!$C$5:$C$3470,C165,Cargas!$O$5:$O$3470) -> 0 | K165: =IF(ABS(I165-J165)<20,0,I165-J165) -> 1104 | L165: 142.05.31 | M165: 13966
B166: 44953 | C166: 3029/ | D166: BRA003 | E166: Agricola Famosa | G166: Rio Branco | H166: Silvio | I166: 1104 | J166: 1104 | K166: =IF(ABS(I166-J166)<20,0,I166-J166) -> 0 | L166: 145.06.32 | M166: 19370
B167: 44589 | C167: 3775/ | D167: BRA004 | E167: Agricola Famosa | G167: Rio Branco | H167: Silvio | I167: 1104 | J167: =SUMIF(Cargas!$C$5:$C$3470,C167,Cargas!$O$5:$O$3470) -> 0 | K167: =IF(ABS(I167-J167)<20,0,I167-J167) -> 1104 | L167: 142.08.41 | M167: 20129
B168: 44589 | C168: 3765/ | D168: BRA004 | E168: Agricola Famosa | G168: Rio Branco | H168: Silvio | I168: 1104 | J168: =SUMIF(Cargas!$C$5:$C$3470,C168,Cargas!$O$5:$O$3470) -> 0 | K168: =IF(ABS(I168-J168)<20,0,I168-J168) -> 1104 | L168: 142.08.41 | M168: 20129
B169: 44959 | C169: 3126// | D169: BRA004 | E169: Agricola Famosa | G169: Rio Branco | H169: Silvio | I169: 1104 | J169: 1104 | K169: =IF(ABS(I169-J169)<20,0,I169-J169) -> 0 | L169: 145.13.38 | M169: 23027
B170: 44960 | C170: 3130/ | D170: BRA004 | E170: Agricola Famosa | G170: Rio Branco | H170: Silvio | I170: 1104 | J170: 1104 | K170: =IF(ABS(I170-J170)<20,0,I170-J170) -> 0 | L170: 145.13.38 | M170: 23027
B171: 44596 | C171: 3908/ | D171: BRA005 | E171: Agricola Famosa | G171: Rio Branco | H171: Silvio | I171: 1104 | J171: =SUMIF(Cargas!$C$5:$C$3470,C171,Cargas!$O$5:$O$3470) -> 0 | K171: =IF(ABS(I171-J171)<20,0,I171-J171) -> 1104 | L171: 142.13.98 | M171: 23390
B172: 44596 | C172: 3910/ | D172: BRA005 | E172: Agricola Famosa | G172: Rio Branco | H172: Silvio | I172: 1104 | J172: =SUMIF(Cargas!$C$5:$C$3470,C172,Cargas!$O$5:$O$3470) -> 0 | K172: =IF(ABS(I172-J172)<20,0,I172-J172) -> 1104 | L172: 142.13.98 | M172: 23390
B173: 44968 | C173: 3257/ | D173: BRA005 | E173: Agricola Famosa | G173: Rio Branco | H173: Silvio | I173: 1104 | J173: 1104 | K173: =IF(ABS(I173-J173)<20,0,I173-J173) -> 0 | L173: 145,20,04 | M173: 29590
B174: 44603 | C174: 4081/ | D174: BRA006 | E174: Agricola Famosa | G174: Rio Branco | H174: Silvio | I174: 1104 | J174: =SUMIF(Cargas!$C$5:$C$3470,C174,Cargas!$O$5:$O$3470) -> 0 | K174: =IF(ABS(I174-J174)<20,0,I174-J174) -> 1104 | L174: 142.21.60 | M174: 27952
B175: 44603 | C175: 4198/ | D175: BRA006 | E175: Agricola Famosa | G175: Rio Branco | H175: Silvio | I175: 1104 | J175: =SUMIF(Cargas!$C$5:$C$3470,C175,Cargas!$O$5:$O$3470) -> 0 | K175: =IF(ABS(I175-J175)<20,0,I175-J175) -> 1104 | L175: 142.21.60 | M175: 27952
B176: 44610 | C176: 4199/ | D176: BRA007 | E176: Agricola Famosa | G176: Rio Branco | H176: Silvio | I176: 1104 | J176: =SUMIF(Cargas!$C$5:$C$3470,C176,Cargas!$O$5:$O$3470) -> 0 | K176: =IF(ABS(I176-J176)<20,0,I176-J176) -> 1104 | L176: 142.23.89 | M176: xx
B177: 44610 | C177: 4201/ | D177: BRA007 | E177: Agricola Famosa | G177: Rio Branco | H177: Silvio | I177: 1104 | J177: =SUMIF(Cargas!$C$5:$C$3470,C177,Cargas!$O$5:$O$3470) -> 0 | K177: =IF(ABS(I177-J177)<20,0,I177-J177) -> 1104 | L177: 142.23.89 | M177: xx
B178: 44617 | C178: 4328/ | D178: BRA008 | E178: Agricola Famosa | G178: Rio Branco | H178: Silvio | I178: 1104 | J178: 1104 | K178: =IF(ABS(I178-J178)<20,0,I178-J178) -> 0 | L178: 142.30.35 | M178: 38148
B179: 44624 | C179: 4412/ | D179: BRA009 | E179: Agricola Famosa | G179: Rio Branco | H179: Silvio | I179: 1104 | J179: =SUMIF(Cargas!$C$5:$C$3471,C179,Cargas!$O$5:$O$3471) -> 0 | K179: =IF(ABS(I179-J179)<20,0,I179-J179) -> 1104 | L179: 142.39.83 | M179: 44229
B180: 44633 | C180: 4474/ | D180: BRA010 | E180: Agricola Famosa | G180: Rio Branco | H180: Silvio | I180: 1104 | J180: =SUMIF(Cargas!$C$5:$C$3471,C180,Cargas!$O$5:$O$3471) -> 0 | K180: =IF(ABS(I180-J180)<20,0,I180-J180) -> 1104 | L180: 142.33.76 | M180: 50501
B181: 44635 | C181: 4510/ | D181: BRA011 | E181: Agricola Famosa | G181: Rio Branco | H181: Silvio | I181: 1104 | J181: =SUMIF(Cargas!$C$5:$C$3471,C181,Cargas!$O$5:$O$3471) -> 0 | K181: =IF(ABS(I181-J181)<20,0,I181-J181) -> 1104 | L181: 142.44.10 | M181: 54045
B182: 44642 | C182: 4552/ | D182: BRA012 | E182: Agricola Famosa | G182: Rio Branco | H182: Silvio | I182: 1104 | J182: =SUMIF(Cargas!$C$5:$C$3471,C182,Cargas!$O$5:$O$3471) -> 0 | K182: =IF(ABS(I182-J182)<20,0,I182-J182) -> 1104 | L182: 142.50.28 | M182: 59152
B183: 44652 | C183: 4586/ | D183: BRA013 | E183: Agricola Famosa | G183: Rio Branco | H183: Silvio | I183: 1104 | J183: =SUMIF(Cargas!$C$5:$C$3471,C183,Cargas!$O$5:$O$3471) -> 0 | K183: =IF(ABS(I183-J183)<20,0,I183-J183) -> 1104 | L183: 142.58.18 | M183: 63648
B184: 44657 | C184: 4621/ | D184: BRA014 | E184: Agricola Famosa | G184: Rio Branco | H184: Silvio | I184: 1104 | J184: =SUMIF(Cargas!$C$5:$C$3471,C184,Cargas!$O$5:$O$3471) -> 0 | K184: =IF(ABS(I184-J184)<20,0,I184-J184) -> 1104 | L184: 142.59.00 | M184: xx
B185: 44664 | C185: 4671/ | D185: BRA015 | E185: Agricola Famosa | G185: Rio Branco | H185: Silvio | I185: 1104 | J185: =SUMIF(Cargas!$C$5:$C$3471,C185,Cargas!$O$5:$O$3471) -> 0 | K185: =IF(ABS(I185-J185)<20,0,I185-J185) -> 1104 | L185: 142.66.34 | M185: 71633
B186: 44674 | C186: 4685/ | D186: BRA016 | E186: Agricola Famosa | G186: Rio Branco | H186: Silvio | I186: 1104 | J186: =SUMIF(Cargas!$C$5:$C$3471,C186,Cargas!$O$5:$O$3471) -> 0 | K186: =IF(ABS(I186-J186)<20,0,I186-J186) -> 1104 | L186: 142.71.27 | M186: 74993
B187: 44674 | C187: 4684/ | D187: BRA016 | E187: Agricola Famosa | G187: Rio Branco | H187: Silvio | I187: 1104 | J187: =SUMIF(Cargas!$C$5:$C$3471,C187,Cargas!$O$5:$O$3471) -> 0 | K187: =IF(ABS(I187-J187)<20,0,I187-J187) -> 1104 | L187: 142.71.27 | M187: 74993
...

Sheet Choferes
B1: Chofer | C1: celular
B3: Adailton Chinkevicz | C3: +5542999594310
B4: Adair Rosseto | C4: +5542999841559
B5: Adão da Silveira | C5: +5549989007917
B6: Adilso Martello | C6: +5549999288403
B7: Adilson Barboza | C7: +5555999696955
B8: Adilson Beitum | C8: +554199367107
B9: Adilson Caceres | C9: +5555996177111
B10: Adilson Denis Duarte | C10: +5548992106401
B11: Adriano Becker de Souza | C11: +5555999703929
B12: Agnaldo Mariano Noelves | C12: +5527997171235
B13: Ailton Rodrigues Ibarra | C13: +5555984262559
... B361: UILIAN DE PAULA DOS SANTOS | C361: +55 53 8474-9701
B362: WESLEY SILVA MARTINS
B363: ALEX SANDRO BILHALVA
B364: Franco Camacho | C364: +598 91 694 331
B365: ANDERSON NEITZKE SOAREZ | C365: +55 53 8406-9723
B366: JOSE CLAUDIO FERNANDES ROCHA | C366: +55 73 8177-8043
B367: Gilberto Toledo | C367: +55 55 9999-0960
B368: LUCIANO FORTEZA | C368: +55 55 9979-8055
B369: Alan Adacheski | C369: +55 41 9687-3997
B370: WINSTON PORTO | C370: +55 53 9972-5431
B371: Anderson Braz | C371: +55 55 9674-9281
B372: GUILHERME MOTTA | C372: +55 53 8485-1806
B373: MARCOS ALVES COSTA | C373: +55 49 8411-6446
B374: OSNI RAPCINSKE | C374: +55 49 8816-0696
B375: Sidnei Surdi | C375: +55 49 9984-6132
... B387: Bruno Senosiain Carmona | C387: +55 53 99990-3654
Y1201: =PROCV('Choferes'!B3:C400

Sheet Rangos
B2: Listas para validación de datos
B4: Status List | D4: Transporte | E4: Cajas x Viaje | F4: INCOTERMS | H4: Fronteras | J4: Productores | K4: Iniciales
B5: Solicitado | J5: Ulgo | K5: HG
B6: Destruida | D6: CMCN | E6: 936 | F6: DAP | H6: Montevideo | J6: Exoticos PY
B7: Confirmado | D7: Amaro | E7: 1008 | F7: DAP | H7: Salto | J7: Claudia | K7: CH
B8: Cancelado | D8: Balbiani | E8: 1040 | F8: FCA | H8: Chuy | J8: Gilson | K8: GT
B9: Cargado | D9: Cigliuti | E9: 936 | F9: FCA | H9: Río Branco | J9: Jaime | K9: JM
B10: Frontera | D10: Cordenonsi | E10: 936 | F10: DAP | H10: Rivera | J10: Papa | K10: PA
B11: Liberado | D11: El Palomar | E11: 1000 | F11: DAP | H11: xx | J11: Boniato | K11: BO
B12: Arribado | D12: Pradera | E12: 918 | F12: FCA | J12: Sidnei | K12: SR
B13: Puerto | D13: Transzanini | E13: 918 | J13: Benini | K13: BN
B14: Descargado | D14: Gral | E14: 918 | F14: DAP | J14: Valdemar | K14: VH
D15: Aotrans | J15: Valdemar Ita | K15: VA
J17: Adriano | K17: AD
D18: Sergio Nava | E18: 918 | J18: Varios | K18: VA
D19: Marvel | J19: Nordeste | K19: ND
D20: K2 | E20: 918 | F20: DAP | J20: Corupá | K20: CP
D21: Costa Rica | E21: 918 | F21: DAP | J21: Jhony Viera | K21: JV
D22: Schwanck | E22: 918 | F22: DAP | J22: Muller | K22: MU
J23: Sergio | K23: SG
J24: Vitor | K24: VM
J25: Marconi Kons | K25: MK
J26: Ivo Zimerman | K26: IZ
J27: Banana MG | K27: MG
J28: A Confirmar
J29: Paraguay | K29: PY
J30: Paraguay EC | K30: PYE
J31: Paraguay OP | K31: PYO
J32: Paraguay MS | K32: PYM
J33: Paraguay GM | K33: GM
D34: Silvio | E34: 918 | F34: DAP | J34: Paraguay DF | K34: DF
J35: Jorge Marangoni | K35: JM
D36: Tottal Brasil | E36: 918 | F36: DAP | J36: Paraguay HF | K36: HF
J37: Paraguay SF | K37: SF
D38: Trans America | E38: 918 | F38: DAP | J38: Bolivia Tuli | K38: BT
J39: João Claudio Winter | K39: JW
J40: Osnildo Stein | K40: ST
J41: Zapellini | K41: ZP
J42: Fischer | K42: FH
J43: Tureck | K43: TK
J44: Chicolandia
J45: Josemar Provesi | K45: JP
J46: Cebolla | K46: CE
J47: Abacaxi | K47: AB
J48: AgroBianvirc | K48: BRSP
D49: Transitex | E49: 1008 | F49: DAP | J49: Varios | K49: VA
D50: Ruiz | E50: 1008 | F50: FCA | J50: Cobalchini | K50: CB
D51: Viana | E51: 1008 | F51: FCA | J51: Junkes | K51: JS
J52: Wagner Schveitzer | K52: WC
J53: Banana Combinada
D54: Realeza | E54: 918 | F54: FCA | J54: BAHIA | K54: BA
J55: Banana SP | K55: BRSP
J56: Bahia + Exoticos | K56: BA
J57: Marnei Meurer | K57: MM
J58: Cassio Hauck
J59: Paraguay AS
J60: Shapo | K60: SH
J65: Aldo Corupa | K65: AC
J66: Alexandre Wilbert | K66: AW
J67: Vinicios Bonkoski | K67: VB
J68: Furlani | K68: FU
D69: Azzolini | E69: 918 | F69: DAP | J69: xx | K69: xx
D71: VI-MA | E71: 918 | F71: DAP | J71: Airton Curuca
D72: Coopecarga | E72: 918 | F72: DAP
D73: Chabat | E73: 918
D74: Transporte Carneiro | E74: 918
D75: xx | E75: 1000
